Workbook

Sheet Summary
A1: NET CASH FLOW -MEGP-ACCUMULATED
A2: Project | B2: Downpayment | C2: Total Without Downpayment | D2: Total With Downpayment | E2: Diff | F2: Diff %
A3: Green Square | B3: 200 | C3: ='Net Cash Flow -Without DP'!C52 -> 375.44753 | D3: ='Net Cash Flow -With DP'!C52 -> 375.44753 | E3: =D3-C3 -> 0 | F3: =E3/C3 -> 0 | G3: =SUM('Offers DP'!C9:C16) -> 800 | H3: =G3-800 -> 0 | I3: =H3/6 -> 0
A4: L'avenir | B4: 200 | C4: ='Net Cash Flow -Without DP'!C53 -> 595.29293 | D4: ='Net Cash Flow -With DP'!C53 -> 595.29293 | E4: =D4-C4 -> 0 | F4: =E4/C4 -> 0 | G4: =SUM('Offers DP'!D9:D16) -> 850 | H4: =G4-850 -> 0 | I4: =H4/6 -> 0
A5: NPV Total CASH-IN FLOW JALOUR | C5: =SUM(C3:C4) -> 970.74046 | D5: =SUM(D3:D4) -> 970.74046 | E5: =SUM(E3:E4) -> 0 | F5: =E5/C5 -> 0
A7: NPV NET CASH FLOW -MEGP-ACCUMULATED
A8: Project | B8: Downpayment | C8: Total Without Downpayment | D8: Total With Downpayment | E8: Diff | F8: Diff %
A9: Green Square | B9: =B3 -> 200 | C9: ='Net Cash Flow -Without DP'!C58 -> 241.24144 | D9: ='Net Cash Flow -With DP'!C58 -> 215.31139 | E9: =D9-C9 -> -25.930043 | F9: =E9/C9 -> -0.10748586
A10: L'avenir | B10: =B4 -> 200 | C10: ='Net Cash Flow -Without DP'!C59 -> 328.55309 | D10: ='Net Cash Flow -With DP'!C59 -> 307.53237 | E10: =D10-C10 -> -21.020716 | F10: =E10/C10 -> -0.063979665
A11: NPV Total CASH-IN FLOW JALOUR | C11: =SUM(C9:C10) -> 569.79452 | D11: =SUM(D9:D10) -> 522.84376 | E11: =SUM(E9:E10) -> -46.950759 | F11: =E11/C11 -> -0.082399457

Sheet Green Square Summary
A1: Green Square EL-Mostakbal City -Summary
A2: Land Area: | B2: m² | C2: 14470 | D2: Construction Start: | E2: 13 | F2: Month
A3: footprint % : | C3: =C4/C2 -> 0.3 | D3: Construction Duration : | E3: 36 | F3: Month
A4: footprint : | B4: m² | C4: 4341 | D4: Project Delivery : | E4: =E3+E2-1 -> 48 | F4: Month
A5: Height: | C5: G+2
A6: Retail: | B6: m² | C6: 4341 | D6: Sales Start: | E6: 7 | F6: Month
A7: Offices: | B7: m² | C7: 8682 | D7: Maximum Cash Shortage : | E7: =MIN(C49:AT49) -> -102.5 | F7: MEGP
A8: Total BUA: | B8: m² | C8: 13023
A9: RETAINED %: | C9: 0.2
A10: Downpayment | C10: =Summary!B3 -> 200
C11: MEGP | D11: NPV-With DP | E11: NPV-With DP
A12: CASH INFLOW JALOUR | C12: =SUM(C13:C14) -> 1267.3007 | D12: ='Net Cash Flow -With DP'!C22 -> 807.95087 | E12: ='Net Cash Flow -Without DP'!C22 -> 833.88091
A13: COMMERCIAL | C13: =C32-C36 -> 523.76878
A14: ADMIN | C14: =C33-C37 -> 743.53191
C16: MEGP | D16: NPV-With DP | E16: NPV-With DP
A17: CASH OUTFLOW JALOUR | C17: =SUM(C18:C20) -> -891.85316 | D17: =-'Net Cash Flow -With DP'!C34 -> -592.63947 | E17: =-'Net Cash Flow -Without DP'!C34 -> -592.63947
A18: Construction Cost | C18: =-'Cash Out Detail'!C28/1000000 -> -697.16
A19: Sales Commission | B19: 0.04 | C19: =-'Cash Out Detail'!C33/1000000 -> -90.11916
A20: SGA& Others Cost | B20: 0.15 | C20: =-'Cash Out Detail'!C38/1000000 -> -104.574
C22: MEGP | D22: NPV-With DP | E22: NPV-Without DP | F22: Diff
A23: NET CASH FLOW JALOUR -MEGP | C23: =C12+C17 -> 375.44753 | D23: =Summary!D9 -> 215.31139 | E23: =Summary!C9 -> 241.24144 | F23: =D23-E23 -> -25.930043
A27: Total Sales 100% | C27: =SUM(C28:C29) -> 2816.2238
A28: COMMERCIAL | C28: =C32*100/80 -> 1163.9306
A29: ADMIN | C29: =C33*100/80 -> 1652.2931
A31: Total Sales 80% | C31: =SUM(C32:C33) -> 2252.979
A32: COMMERCIAL | C32: ='Green Square'!D24/1000 -> 931.1445
A33: ADMIN | C33: ='Green Square'!D25/1000 -> 1321.8345
A35: ALAHLY - SABBOUR % | B35: 0.35 | C35: =SUM(C36:C37) -> 985.67831
A36: COMMERCIAL | C36: =C28*B35 -> 407.37572
A37: ADMIN | C37: =C29*B35 -> 578.30259
C44: ='Net Cash Flow -With DP'!D3 -> M 3 | D44: ='Net Cash Flow -With DP'!E3 -> M 6 | E44: ='Net Cash Flow -With DP'!F3 -> M 9 | F44: ='Net Cash Flow -With DP'!G3 -> M 12 | G44: ='Net Cash Flow -With DP'!H3 -> M 15 | H44: ='Net Cash Flow -With DP'!I3 -> M 18 | I44: ='Net Cash Flow -With DP'!J3 -> M 21 | J44: ='Net Cash Flow -With DP'!K3 -> M 24 | ... AT44: ='Net Cash Flow -With DP'!AU3 -> 0
A45: Total Collections MEGP | C45: ='Net Cash Flow -With DP'!D4 -> 0 | D45: ='Net Cash Flow -With DP'!E4 -> 0 | E45: ='Net Cash Flow -With DP'!F4 -> 15.139238 | F45: ='Net Cash Flow -With DP'!G4 -> 30.278475 | G45: ='Net Cash Flow -With DP'!H4 -> 46.512006 | H45: ='Net Cash Flow -With DP'!I4 -> 62.745537 | I45: ='Net Cash Flow -With DP'!J4 -> 62.3657 | J45: ='Net Cash Flow -With DP'!K4 -> 63.473559 | ... AT45: ='Net Cash Flow -With DP'!AU4 -> 0
A46: ALAHLY - SABBOUR Payments MEGP | C46: =-'Net Cash Flow -With DP'!D10 -> -91.25 | D46: =-'Net Cash Flow -With DP'!E10 -> -11.25 | E46: =-'Net Cash Flow -With DP'!F10 -> -11.25 | F46: =-'Net Cash Flow -With DP'!G10 -> -11.25 | G46: =-'Net Cash Flow -With DP'!H10 -> -22.5 | H46: =-'Net Cash Flow -With DP'!I10 -> -22.5 | I46: =-'Net Cash Flow -With DP'!J10 -> -22.5 | J46: =-'Net Cash Flow -With DP'!K10 -> -22.5 | ... AT46: =-'Net Cash Flow -With DP'!AU10 -> 0
A47: CASH OUT FLOW CAPEX -MEGP | C47: =-'Net Cash Flow -With DP'!D28 -> 0 | D47: =-'Net Cash Flow -With DP'!E28 -> 0 | E47: =-'Net Cash Flow -With DP'!F28 -> 0 | F47: =-'Net Cash Flow -With DP'!G28 -> 0 | G47: =-'Net Cash Flow -With DP'!H28 -> -23 | H47: =-'Net Cash Flow -With DP'!I28 -> -30.36 | I47: =-'Net Cash Flow -With DP'!J28 -> -58.11139 | J47: =-'Net Cash Flow -With DP'!K28 -> -42.47139 | ... AT47: =-'Net Cash Flow -With DP'!AU28 -> 0
A48: Net Cash Flow | C48: =SUM(C45:C47) -> -91.25 | D48: =SUM(D45:D47) -> -11.25 | E48: =SUM(E45:E47) -> 3.8892375 | F48: =SUM(F45:F47) -> 19.028475 | G48: =SUM(G45:G47) -> 1.0120062 | H48: =SUM(H45:H47) -> 9.8855375 | I48: =SUM(I45:I47) -> -18.24569 | J48: =SUM(J45:J47) -> -1.4978306 | ... AT48: =SUM(AT45:AT47) -> 0
A49: Net Cash Flow-Accum | C49: =C48 -> -91.25 | D49: =C49+D48 -> -102.5 | E49: =D49+E48 -> -98.610763 | F49: =E49+F48 -> -79.582288 | G49: =F49+G48 -> -78.570281 | H49: =G49+H48 -> -68.684744 | I49: =H49+I48 -> -86.930434 | J49: =I49+J48 -> -88.428264 | K49: =J49+K48 -> -81.730676 | ... AT49: =AS49+AT48 -> 375.44753

Sheet L'avenir Summary
A1: L'avenir EL-Mostakbal City -Summary
A2: Land Area: | B2: m² | C2: 14910 | D2: Construction Start: | E2: 19 | F2: Month
A3: footprint % : | C3: =C4/C2 -> 0.3 | D3: Construction Duration : | E3: 36 | F3: Month
A4: footprint : | B4: m² | C4: 4473 | D4: Project Delivery : | E4: =E3+E2-1 -> 54 | F4: Month
A5: Height: | C5: G+2
A6: Retail: | B6: m² | C6: =C4 -> 4473 | D6: Sales Start: | E6: 13 | F6: Month
A7: Offices: | B7: m² | C7: 8946 | D7: Maximum Cash Shortage : | E7: =MIN(C49:AT49) -> -102.01806 | F7: MEGP
A8: Total BUA: | B8: m² | C8: =C7+C6 -> 13419
A9: RETAINED %: | C9: 0.2
A10: Downpayment | C10: =Summary!B4 -> 200
C11: MEGP | D11: NPV-With DP | E11: NPV-With DP
A12: CASH INFLOW JALOUR | C12: =SUM(C13:C14) -> 1503.9764 | D12: ='Net Cash Flow -With DP'!C23 -> 872.63711 | E12: ='Net Cash Flow -Without DP'!C23 -> 893.65783
A13: COMMERCIAL | C13: =C32-C36 -> 605.74205
A14: ADMIN | C14: =C33-C37 -> 898.23431
C16: MEGP | D16: NPV-With DP | E16: NPV-With DP
A17: CASH OUTFLOW JALOUR | C17: =SUM(C18:C20) -> -862.28343 | D17: =-'Net Cash Flow -With DP'!C35 -> -565.10474 | E17: =-'Net Cash Flow -Without DP'!C35 -> -565.10474
A18: Construction Cost | C18: =-'Cash Out Detail'!C29/1000000 -> -650.76
A19: Sales Commission | B19: 0.04 | C19: =-'Cash Out Detail'!C34/1000000 -> -106.94943
A20: SGA& Others Cost | B20: 0.15 | C20: =-'Cash Out Detail'!C39/1000000 -> -104.574
C22: MEGP | D22: NPV-With DP | E22: NPV-Without DP | F22: Diff
A23: NET CASH FLOW JALOUR -MEGP | C23: =C12+C17 -> 641.69293 | D23: =Summary!D10 -> 307.53237 | E23: =Summary!C10 -> 328.55309 | F23: =D23-E23 -> -21.020716
A27: Total Sales 100% | C27: =SUM(C28:C29) -> 3342.1697
A28: COMMERCIAL | C28: =C32*100/80 -> 1346.0934
A29: ADMIN | C29: =C33*100/80 -> 1996.0763
A31: Total Sales 80% | C31: =SUM(C32:C33) -> 2673.7357
A32: COMMERCIAL | C32: ='L''avenir'!D24/1000 -> 1076.8747
A33: ADMIN | C33: ='L''avenir'!D25/1000 -> 1596.861
A35: ALAHLY - SABBOUR % | B35: 0.35 | C35: =SUM(C36:C37) -> 1169.7594
A36: COMMERCIAL | C36: =C28*B35 -> 471.1327
A37: ADMIN | C37: =C29*B35 -> 698.62669
C44: ='Net Cash Flow -With DP'!D3 -> M 3 | D44: ='Net Cash Flow -With DP'!E3 -> M 6 | E44: ='Net Cash Flow -With DP'!F3 -> M 9 | F44: ='Net Cash Flow -With DP'!G3 -> M 12 | G44: ='Net Cash Flow -With DP'!H3 -> M 15 | H44: ='Net Cash Flow -With DP'!I3 -> M 18 | I44: ='Net Cash Flow -With DP'!J3 -> M 21 | J44: ='Net Cash Flow -With DP'!K3 -> M 24 | ... AT44: ='Net Cash Flow -With DP'!AU3 -> 0
A45: Total Collections MEGP | C45: ='Net Cash Flow -With DP'!D5 -> 0 | D45: ='Net Cash Flow -With DP'!E5 -> 0 | E45: ='Net Cash Flow -With DP'!F5 -> 0 | F45: ='Net Cash Flow -With DP'!G5 -> 0 | G45: ='Net Cash Flow -With DP'!H5 -> 18.11565 | H45: ='Net Cash Flow -With DP'!I5 -> 36.2313 | I45: ='Net Cash Flow -With DP'!J5 -> 58.260825 | J45: ='Net Cash Flow -With DP'!K5 -> 69.01839 | ... AT45: ='Net Cash Flow -With DP'!AU5 -> 0
A46: ALAHLY - SABBOUR Payments MEGP | C46: =-'Net Cash Flow -With DP'!D11 -> 0 | D46: =-'Net Cash Flow -With DP'!E11 -> 0 | E46: =-'Net Cash Flow -With DP'!F11 -> 0 | F46: =-'Net Cash Flow -With DP'!G11 -> -85 | G46: =-'Net Cash Flow -With DP'!H11 -> -22.5 | H46: =-'Net Cash Flow -With DP'!I11 -> -22.5 | I46: =-'Net Cash Flow -With DP'!J11 -> -22.5 | J46: =-'Net Cash Flow -With DP'!K11 -> -22.5 | ... AT46: =-'Net Cash Flow -With DP'!AU11 -> 0
A47: CASH OUT FLOW CAPEX -MEGP | C47: =-'Net Cash Flow -With DP'!D29 -> 0 | D47: =-'Net Cash Flow -With DP'!E29 -> 0 | E47: =-'Net Cash Flow -With DP'!F29 -> 0 | F47: =-'Net Cash Flow -With DP'!G29 -> 0 | G47: =-'Net Cash Flow -With DP'!H29 -> 0 | H47: =-'Net Cash Flow -With DP'!I29 -> 0 | I47: =-'Net Cash Flow -With DP'!J29 -> -23 | J47: =-'Net Cash Flow -With DP'!K29 -> -30.36 | ... AT47: =-'Net Cash Flow -With DP'!AU29 -> 0
A48: Net Cash Flow | C48: =SUM(C45:C47) -> 0 | D48: =SUM(D45:D47) -> 0 | E48: =SUM(E45:E47) -> 0 | F48: =SUM(F45:F47) -> -85 | G48: =SUM(G45:G47) -> -4.38435 | H48: =SUM(H45:H47) -> 13.7313 | I48: =SUM(I45:I47) -> 12.760825 | J48: =SUM(J45:J47) -> 16.15839 | ... AT48: =SUM(AT45:AT47) -> 0
A49: Net Cash Flow-Accum | C49: =C48 -> 0 | D49: =C49+D48 -> 0 | E49: =D49+E48 -> 0 | F49: =E49+F48 -> -85 | G49: =F49+G48 -> -89.38435 | H49: =G49+H48 -> -75.65305 | I49: =H49+I48 -> -62.892225 | J49: =I49+J48 -> -46.733835 | K49: =J49+K48 -> -85.13881 | ... AT49: =AS49+AT48 -> 595.29293

Sheet Offers
C2: GREEN SQUARE | D2: L'AVENIR | E2: NOTES
B3: LANDLORD % | C3: 0.35 | D3: 0.35
B4: MIN. GUARANTEED | C4: 800 M | D4: 850 M
B5: PAYMENT PERIOD | C5: 6 | D5: 6
B6: YEAR 1 (M) | C6: 50 | D6: 0 | E6: OR 35% OF COLLECTIONS WHICHEVER HIGHER
B7: YEAR 2 (M) | C7: 100 | D7: 100 | E7: OR 35% OF COLLECTIONS WHICHEVER HIGHER
B8: YEAR 3 (M) | C8: 150 | D8: 200 | E8: OR 35% OF COLLECTIONS WHICHEVER HIGHER
B9: YEAR 4 (M) | C9: 200 | D9: 250 | E9: OR 35% OF COLLECTIONS WHICHEVER HIGHER
B10: YEAR 5 (M) | C10: 200 | D10: 200 | E10: OR 35% OF COLLECTIONS WHICHEVER HIGHER
B11: YEAR 6 (M) | C11: 100 | D11: 100 | E11: OR 35% OF COLLECTIONS WHICHEVER HIGHER
B12: YEAR 7 (M) | C12: 0 | D12: 0 | E12: OR 35% OF COLLECTIONS WHICHEVER HIGHER
B13: EXCESS AMOUNT (YRS) | C13: 8 | D13: 8
B14: PROJECT DELIVERY | C14: 48 MONTHS | D14: 54 MONTHS
B16: DEVELOPER % | C16: 0.65 | D16: 0.65
B17: DESIGN | C17: ☑ | D17: ☑
B18: PERMITS | C18: ☑ | D18: ☑
B19: CONSTRUCTION | C19: ☑ | D19: ☑
B20: FINISHING | C20: CORE & SHELL | D20: CORE & SHELL
B21: MARKETING | C21: ☑ | D21: ☑
B22: SALES | C22: ☑ | D22: ☑
B23: COLLECTION | C23: ☑ | D23: ☑
B24: PROJECT NAME | C24: UNDER: JALOUR | D24: UNDER: JALOUR
B25: OPERATION, MANAGEMENT, MAINT. | C25: UNDER: JALOUR | D25: UNDER: JALOUR | E25: OR FACILITY MANAGEMENT COMPANY ASSIGNED BY JALOUR

Sheet Offers DP
B1: NPV Diff with vs without downpayments | C1: =Summary!E9 -> -25.930043 | D1: =Summary!E10 -> -21.020716
B2: NPV with DP | C2: =Summary!D9 -> 215.31139 | D2: =Summary!D10 -> 307.53237
C3: =SUM(C9:C16) -> 800 | D3: =SUM(D9:D16) -> 850 | F3: =C3-800 -> 0 | G3: =D3-850 -> 0
B4: MEGP | C4: GREEN SQUARE | D4: L'AVENIR | E4: NOTES | F4: =F3/6 -> 0 | G4: =G3/6 -> 0
B5: Landlord Share of Collections | C5: 0.35 | D5: 0.35
B6: Minimum Guaranteed Amount | C6: 800 | D6: 850
B7: Payment Period | C7: 6 | D7: 6
B8: Downpayment % | C8: 0.1 | D8: 0.1
B9: Downpayment Amount (m) | C9: =C8*C6 -> 80 | D9: =D8*D6 -> 85
B10: Year 1 (m) | C10: 45 | D10: 0 | E10: OR 35% OF COLLECTIONS WHICHEVER HIGHER
B11: Year 2 (m) | C11: 90 | D11: 90 | E11: OR 35% OF COLLECTIONS WHICHEVER HIGHER
B12: Year 3 (m) | C12: 135 | D12: 180 | E12: OR 35% OF COLLECTIONS WHICHEVER HIGHER
B13: Year 4 (m) | C13: 180 | D13: 225 | E13: OR 35% OF COLLECTIONS WHICHEVER HIGHER
B14: Year 5 (m) | C14: 180 | D14: 180 | E14: OR 35% OF COLLECTIONS WHICHEVER HIGHER
B15: Year 6 (m) | C15: 90 | D15: 90 | E15: OR 35% OF COLLECTIONS WHICHEVER HIGHER
B16: Year 7 (m) | C16: 0 | D16: 0 | E16: OR 35% OF COLLECTIONS WHICHEVER HIGHER
B17: Settlement of excess over guarantee | C17: 8 | D17: 8
B18: PROJECT DELIVERY | C18: 48 MONTHS | D18: 54 MONTHS
C20: GREEN SQUARE | D20: L'AVENIR
B21: Developer Share of Collections | C21: 0.65 | D21: 0.65
B22: Design | C22: Jalour | D22: Jalour
B23: Permits & License | C23: Jalour | D23: Jalour
B24: Construction | C24: Jalour | D24: Jalour
B25: Finishing Standard | C25: CORE & SHELL | D25: CORE & SHELL
B26: Marketing, Sales and Collections | C26: Jalour | D26: Jalour
B27: Project Branding | C27: Jalour | D27: Jalour
B28: Operation, Management& Maintenance | C28: Jalour /FM co. | D28: Jalour /FM co.
B29: Project Delivery | C29: 48 MONTHS | D29: 54 MONTHS | E29: OR FACILITY MANAGEMENT COMPANY ASSIGNED BY JALOUR

Sheet Sheet2

Sheet Net Cash Flow -With DP
B1: Cash Available for Operation after - 20% RETAINED UNITS
B2: Total Collections MEGP
B3: Project | C3: Total Sales | D3: M 3 | E3: M 6 | F3: M 9 | G3: M 12 | H3: M 15 | I3: M 18 | J3: M 21 | K3: M 24 | L3: M 27 | M3: M 30 | N3: M 33 | O3: M 36 | P3: M 39 | Q3: M 42 | R3: M 45 | S3: M 48 | T3: M 51 | U3: M 54 | V3: M 57 | W3: M 60 | X3: M 63 | Y3: M 66 | Z3: M 69 | AA3: M 72 | AB3: M 75 | AC3: M 78 | AD3: M 81 | AE3: M 84 | AF3: M 87 | AG3: M 90 | AH3: M 93 | AI3: M 96 | AJ3: M 99 | AK3: M 102 | AL3: M 105 | AM3: M 108 | AN3: M 111 | AO3: M 114 | AP3: M 117 | AQ3: M 120 | AR3: M 123 | AS3: M 126 | AT3: M 129
B4: Green Square | C4: =SUM(D4:ZZ4) -> 2252.979 | D4: ='Cash In Flow Summary'!D4 -> 0 | E4: ='Cash In Flow Summary'!E4 -> 0 | F4: ='Cash In Flow Summary'!F4 -> 15.139238 | G4: ='Cash In Flow Summary'!G4 -> 30.278475 | H4: ='Cash In Flow Summary'!H4 -> 46.512006 | I4: ='Cash In Flow Summary'!I4 -> 62.745537 | J4: ='Cash In Flow Summary'!J4 -> 62.3657 | K4: ='Cash In Flow Summary'!K4 -> 63.473559 | ... AT4: ='Cash In Flow Summary'!AT4 -> 0
B5: L'avenir | C5: =SUM(D5:ZZ5) -> 2673.7357 | D5: ='Cash In Flow Summary'!D5 -> 0 | E5: ='Cash In Flow Summary'!E5 -> 0 | F5: ='Cash In Flow Summary'!F5 -> 0 | G5: ='Cash In Flow Summary'!G5 -> 0 | H5: ='Cash In Flow Summary'!H5 -> 18.11565 | I5: ='Cash In Flow Summary'!I5 -> 36.2313 | J5: ='Cash In Flow Summary'!J5 -> 58.260825 | K5: ='Cash In Flow Summary'!K5 -> 69.01839 | ... AT5: ='Cash In Flow Summary'!AT5 -> 0
C6: =SUM(C4:C5) -> 4926.7148 | D6: =SUM(D4:D5) -> 0 | E6: =SUM(E4:E5) -> 0 | F6: =SUM(F4:F5) -> 15.139238 | G6: =SUM(G4:G5) -> 30.278475 | H6: =SUM(H4:H5) -> 64.627656 | I6: =SUM(I4:I5) -> 98.976838 | J6: =SUM(J4:J5) -> 120.62653 | ... AT6: =SUM(AT4:AT5) -> 0
B8: ALAHLY - SABBOUR Payments MEGP
B9: Project | C9: Total Sales | D9: M 3 | E9: M 6 | F9: M 9 | G9: M 12 | H9: M 15 | I9: M 18 | J9: M 21 | K9: M 24 | L9: M 27 | M9: M 30 | N9: M 33 | O9: M 36 | P9: M 39 | Q9: M 42 | R9: M 45 | S9: M 48 | T9: M 51 | U9: M 54 | V9: M 57 | W9: M 60 | X9: M 63 | Y9: M 66 | Z9: M 69 | AA9: M 72 | AB9: M 75 | AC9: M 78 | AD9: M 81 | AE9: M 84 | AF9: M 87 | AG9: M 90 | AH9: M 93 | AI9: M 96 | AJ9: M 99 | AK9: M 102 | AL9: M 105 | AM9: M 108 | AN9: M 111 | AO9: M 114 | AP9: M 117 | AQ9: M 120 | AR9: M 123 | AS9: M 126 | AT9: M 129
B10: Green Square | C10: =SUM(D10:ZZ10) -> 985.67831 | D10: ='Offers DP'!$C$10/4+'Offers DP'!C9 -> 91.25 | E10: ='Offers DP'!$C$10/4 -> 11.25 | F10: ='Offers DP'!$C$10/4 -> 11.25 | G10: ='Offers DP'!$C$10/4 -> 11.25 | H10: ='Offers DP'!$C$11/4 -> 22.5 | I10: ='Offers DP'!$C$11/4 -> 22.5 | J10: ='Offers DP'!$C$11/4 -> 22.5 | K10: ='Offers DP'!$C$11/4 -> 22.5 | L10: ='Offers DP'!$C$12/4 -> 33.75 | M10: ='Offers DP'!$C$12/4 -> 33.75 | N10: ='Offers DP'!$C$12/4 -> 33.75 | O10: ='Offers DP'!$C$12/4 -> 33.75 | P10: ='Offers DP'!$C$13/4 -> 45 | Q10: ='Offers DP'!$C$13/4 -> 45 | R10: ='Offers DP'!$C$13/4 -> 45 | S10: ='Offers DP'!$C$13/4 -> 45 | T10: ='Offers DP'!$C$14/4 -> 45 | U10: ='Offers DP'!$C$14/4 -> 45 | V10: ='Offers DP'!$C$14/4 -> 45 | W10: ='Offers DP'!$C$14/4 -> 45 | X10: ='Offers DP'!$C$15/4 -> 22.5 | Y10: ='Offers DP'!$C$15/4 -> 22.5 | Z10: ='Offers DP'!$C$15/4 -> 22.5 | AA10: ='Offers DP'!$C$15/4 -> 22.5 | AB10: ='Offers DP'!$C$16/4 -> 0 | AC10: ='Offers DP'!$C$16/4 -> 0 | AD10: ='Offers DP'!$C$16/4 -> 0 | AE10: ='Offers DP'!$C$16/4 -> 0 | AF10: =-SUM(D10:AE10)+SUM('Cash In Flow Summary'!D37:AE37)+'Cash In Flow Summary'!AF37 -> 107.75821 | AG10: ='Cash In Flow Summary'!AG37 -> 10.976512 | AH10: ='Cash In Flow Summary'!AH37 -> 10.976512 | AI10: ='Cash In Flow Summary'!AI37 -> 10.976512 | AJ10: ='Cash In Flow Summary'!AJ37 -> 10.976512 | AK10: ='Cash In Flow Summary'!AK37 -> 10.020984 | AL10: ='Cash In Flow Summary'!AL37 -> 10.020984 | AM10: ='Cash In Flow Summary'!AM37 -> 8.198555 | AN10: ='Cash In Flow Summary'!AN37 -> 4.2114483 | ... AT10: ='Cash In Flow Summary'!AT37 -> 0
B11: L'avenir | C11: =SUM(D11:ZZ11) -> 1169.7594 | D11: ='Offers DP'!$D$10/4 -> 0 | E11: ='Offers DP'!$D$10/4 -> 0 | F11: ='Offers DP'!$D$10/4 -> 0 | G11: ='Offers DP'!$D$10/4++'Offers DP'!D9 -> 85 | H11: ='Offers DP'!$D$11/4 -> 22.5 | I11: ='Offers DP'!$D$11/4 -> 22.5 | J11: ='Offers DP'!$D$11/4 -> 22.5 | K11: ='Offers DP'!$D$11/4 -> 22.5 | L11: ='Offers DP'!$D$12/4 -> 45 | M11: ='Offers DP'!$D$12/4 -> 45 | N11: ='Offers DP'!$D$12/4 -> 45 | O11: ='Offers DP'!$D$12/4 -> 45 | P11: ='Offers DP'!$D$13/4 -> 56.25 | Q11: ='Offers DP'!$D$13/4 -> 56.25 | R11: ='Offers DP'!$D$13/4 -> 56.25 | S11: ='Offers DP'!$D$13/4 -> 56.25 | T11: ='Offers DP'!$D$14/4 -> 45 | U11: ='Offers DP'!$D$14/4 -> 45 | V11: ='Offers DP'!$D$14/4 -> 45 | W11: ='Offers DP'!$D$14/4 -> 45 | X11: ='Offers DP'!$D$15/4 -> 22.5 | Y11: ='Offers DP'!$D$15/4 -> 22.5 | Z11: ='Offers DP'!$D$15/4 -> 22.5 | AA11: ='Offers DP'!$D$15/4 -> 22.5 | AB11: ='Offers DP'!$D$16/4 -> 0 | AC11: ='Offers DP'!$D$16/4 -> 0 | AD11: ='Offers DP'!$D$16/4 -> 0 | AE11: ='Offers DP'!$D$16/4 -> 0 | AF11: =-SUM(D11:AE11)+SUM('Cash In Flow Summary'!D38:AE38)+'Cash In Flow Summary'!AF38 -> 241.19161 | AG11: ='Cash In Flow Summary'!AG38 -> 16.107226 | AH11: ='Cash In Flow Summary'!AH38 -> 14.419368 | AI11: ='Cash In Flow Summary'!AI38 -> 12.731509 | AJ11: ='Cash In Flow Summary'!AJ38 -> 10.011366 | AK11: ='Cash In Flow Summary'!AK38 -> 8.4360314 | AL11: ='Cash In Flow Summary'!AL38 -> 7.3515619 | AM11: ='Cash In Flow Summary'!AM38 -> 3.1702388 | AN11: ='Cash In Flow Summary'!AN38 -> 3.1702388 | ... AT11: ='Cash In Flow Summary'!AT38 -> 0
C12: =SUM(C10:C11) -> 2155.4377 | D12: =SUM(D10:D11) -> 91.25 | E12: =SUM(E10:E11) -> 11.25 | F12: =SUM(F10:F11) -> 11.25 | G12: =SUM(G10:G11) -> 96.25 | H12: =SUM(H10:H11) -> 45 | I12: =SUM(I10:I11) -> 45 | J12: =SUM(J10:J11) -> 45 | ... AT12: =SUM(AT10:AT11) -> 0
B14: Cash Available for Operation -MEGP
B15: Project | C15: Total Sales | D15: M 3 | E15: M 6 | F15: M 9 | G15: M 12 | H15: M 15 | I15: M 18 | J15: M 21 | K15: M 24 | L15: M 27 | M15: M 30 | N15: M 33 | O15: M 36 | P15: M 39 | Q15: M 42 | R15: M 45 | S15: M 48 | T15: M 51 | U15: M 54 | V15: M 57 | W15: M 60 | X15: M 63 | Y15: M 66 | Z15: M 69 | AA15: M 72 | AB15: M 75 | AC15: M 78 | AD15: M 81 | AE15: M 84 | AF15: M 87 | AG15: M 90 | AH15: M 93 | AI15: M 96 | AJ15: M 99 | AK15: M 102 | AL15: M 105 | AM15: M 108 | AN15: M 111 | AO15: M 114 | AP15: M 117 | AQ15: M 120 | AR15: M 123 | AS15: M 126 | AT15: M 129
B16: Green Square | C16: =SUM(D16:ZZ16) -> 1267.3007 | D16: =D4-D10 -> -91.25 | E16: =E4-E10 -> -11.25 | F16: =F4-F10 -> 3.8892375 | G16: =G4-G10 -> 19.028475 | H16: =H4-H10 -> 24.012006 | I16: =I4-I10 -> 40.245537 | J16: =J4-J10 -> 39.8657 | K16: =K4-K10 -> 40.973559 | ... AT16: =AT4-AT10 -> 0
B17: L'avenir | C17: =SUM(D17:ZZ17) -> 1503.9764 | D17: =D5-D11 -> 0 | E17: =E5-E11 -> 0 | F17: =F5-F11 -> 0 | G17: =G5-G11 -> -85 | H17: =H5-H11 -> -4.38435 | I17: =I5-I11 -> 13.7313 | J17: =J5-J11 -> 35.760825 | K17: =K5-K11 -> 46.51839 | ... AT17: =AT5-AT11 -> 0
B18: Total | C18: =SUM(C16:C17) -> 2771.277 | D18: =SUM(D16:D17) -> -91.25 | E18: =SUM(E16:E17) -> -11.25 | F18: =SUM(F16:F17) -> 3.8892375 | G18: =SUM(G16:G17) -> -65.971525 | H18: =SUM(H16:H17) -> 19.627656 | I18: =SUM(I16:I17) -> 53.976838 | J18: =SUM(J16:J17) -> 75.626525 | ... AT18: =SUM(AT16:AT17) -> 0
B20: NPV Cash Available for Operation -MEGP
B21: Project | C21: Total Sales | D21: M 3 | E21: M 6 | F21: M 9 | G21: M 12 | H21: M 15 | I21: M 18 | J21: M 21 | K21: M 24 | L21: M 27 | M21: M 30 | N21: M 33 | O21: M 36 | P21: M 39 | Q21: M 42 | R21: M 45 | S21: M 48 | T21: M 51 | U21: M 54 | V21: M 57 | W21: M 60 | X21: M 63 | Y21: M 66 | Z21: M 69 | AA21: M 72 | AB21: M 75 | AC21: M 78 | AD21: M 81 | AE21: M 84 | AF21: M 87 | AG21: M 90 | AH21: M 93 | AI21: M 96 | AJ21: M 99 | AK21: M 102 | AL21: M 105 | AM21: M 108 | AN21: M 111 | AO21: M 114 | AP21: M 117 | AQ21: M 120 | AR21: M 123 | AS21: M 126 | AT21: M 129
B22: Green Square | C22: =SUM(D22:AT22) -> 807.95087 | D22: =+D16/((1+'Green Square'!$C$72)^'Green Square'!E$73) -> -88.309344 | E22: =+E16/((1+'Green Square'!$C$72)^'Green Square'!F$73) -> -10.53659 | F22: =+F16/((1+'Green Square'!$C$72)^'Green Square'!G$73) -> 3.5252168 | G22: =+G16/((1+'Green Square'!$C$72)^'Green Square'!H$73) -> 16.691645 | H22: =+H16/((1+'Green Square'!$C$72)^'Green Square'!I$73) -> 20.384374 | I22: =+I16/((1+'Green Square'!$C$72)^'Green Square'!J$73) -> 33.064385 | J22: =+J16/((1+'Green Square'!$C$72)^'Green Square'!K$73) -> 31.696835 | K22: =+K16/((1+'Green Square'!$C$72)^'Green Square'!L$73) -> 31.527823 | ... AT22: =+AT16/((1+'Green Square'!$C$72)^'Green Square'!AU$73) -> 0
B23: L'avenir | C23: =SUM(D23:AT23) -> 872.63711 | D23: =+D17/((1+'Green Square'!$C$72)^'Green Square'!E$73) -> 0 | E23: =+E17/((1+'Green Square'!$C$72)^'Green Square'!F$73) -> 0 | F23: =+F17/((1+'Green Square'!$C$72)^'Green Square'!G$73) -> 0 | G23: =+G17/((1+'Green Square'!$C$72)^'Green Square'!H$73) -> -74.561404 | H23: =+H17/((1+'Green Square'!$C$72)^'Green Square'!I$73) -> -3.721981 | I23: =+I17/((1+'Green Square'!$C$72)^'Green Square'!J$73) -> 11.281176 | J23: =+J17/((1+'Green Square'!$C$72)^'Green Square'!K$73) -> 28.433089 | K23: =+K17/((1+'Green Square'!$C$72)^'Green Square'!L$73) -> 35.794391 | ... AT23: =+AT17/((1+'Green Square'!$C$72)^'Green Square'!AU$73) -> 0
B24: Total | C24: =SUM(C22:C23) -> 1680.588 | D24: =SUM(D22:D23) -> -88.309344 | E24: =SUM(E22:E23) -> -10.53659 | F24: =SUM(F22:F23) -> 3.5252168 | G24: =SUM(G22:G23) -> -57.869759 | H24: =SUM(H22:H23) -> 16.662393 | I24: =SUM(I22:I23) -> 44.345562 | J24: =SUM(J22:J23) -> 60.129924 | ... AT24: =SUM(AT22:AT23) -> 0
B26: CASH OUT FLOW CAPEX -MEGP
B27: Project | C27: Total Sales | D27: M 3 | E27: M 6 | F27: M 9 | G27: M 12 | H27: M 15 | I27: M 18 | J27: M 21 | K27: M 24 | L27: M 27 | M27: M 30 | N27: M 33 | O27: M 36 | P27: M 39 | Q27: M 42 | R27: M 45 | S27: M 48 | T27: M 51 | U27: M 54 | V27: M 57 | W27: M 60 | X27: M 63 | Y27: M 66 | Z27: M 69 | AA27: M 72 | AB27: M 75 | AC27: M 78 | AD27: M 81 | AE27: M 84 | AF27: M 87 | AG27: M 90 | AH27: M 93 | AI27: M 96 | AJ27: M 99 | AK27: M 102 | AL27: M 105 | AM27: M 108 | AN27: M 111 | AO27: M 114 | AP27: M 117 | AQ27: M 120 | AR27: M 123 | AS27: M 126 | AT27: M 129
B28: Green Square | C28: =SUM(H28:AAD28) -> 891.85316 | H28: =SUM('Cash Out Detail'!P43:R43)/1000000 -> 23 | I28: =SUM('Cash Out Detail'!S43:U43)/1000000 -> 30.36 | J28: =SUM('Cash Out Detail'!V43:X43)/1000000 -> 58.11139 | K28: =SUM('Cash Out Detail'!Y43:AA43)/1000000 -> 42.47139 | L28: =SUM('Cash Out Detail'!AB43:AD43)/1000000 -> 39.88126 | M28: =SUM('Cash Out Detail'!AE43:AG43)/1000000 -> 39.88126 | N28: =SUM('Cash Out Detail'!AH43:AJ43)/1000000 -> 13.06101 | O28: =SUM('Cash Out Detail'!AK43:AM43)/1000000 -> 13.06101 | P28: =SUM('Cash Out Detail'!AN43:AP43)/1000000 -> 145.69804 | Q28: =SUM('Cash Out Detail'!AQ43:AS43)/1000000 -> 147.2608 | R28: =SUM('Cash Out Detail'!AT43:AV43)/1000000 -> 197.8608 | S28: =SUM('Cash Out Detail'!AW43:AY43)/1000000 -> 141.2062 | T28: =SUM('Cash Out Detail'!AZ43:BB43)/1000000 -> 0 | U28: =SUM('Cash Out Detail'!BC43:BE43)/1000000 -> 0 | V28: =SUM('Cash Out Detail'!BF43:BH43)/1000000 -> 0 | W28: =SUM('Cash Out Detail'!BI43:BK43)/1000000 -> 0 | X28: =SUM('Cash Out Detail'!BL43:BN43)/1000000 -> 0 | Y28: =SUM('Cash Out Detail'!BO43:BQ43)/1000000 -> 0
B29: L'avenir | C29: =SUM(H29:AAD29) -> 908.68343 | H29: =SUM('Cash Out Detail'!P44:R44)/1000000 -> 0 | I29: =SUM('Cash Out Detail'!S44:U44)/1000000 -> 0 | J29: =SUM('Cash Out Detail'!V44:X44)/1000000 -> 23 | K29: =SUM('Cash Out Detail'!Y44:AA44)/1000000 -> 30.36 | L29: =SUM('Cash Out Detail'!AB44:AD44)/1000000 -> 60.49252 | M29: =SUM('Cash Out Detail'!AE44:AG44)/1000000 -> 44.85252 | N29: =SUM('Cash Out Detail'!AH44:AJ44)/1000000 -> 42.79494 | O29: =SUM('Cash Out Detail'!AK44:AM44)/1000000 -> 37.56153 | P29: =SUM('Cash Out Detail'!AN44:AP44)/1000000 -> 14.00412 | Q29: =SUM('Cash Out Detail'!AQ44:AS44)/1000000 -> 13.46736 | R29: =SUM('Cash Out Detail'!AT44:AV44)/1000000 -> 145.54446 | S29: =SUM('Cash Out Detail'!AW44:AY44)/1000000 -> 145.54446 | T29: =SUM('Cash Out Detail'!AZ44:BB44)/1000000 -> 196.83032 | U29: =SUM('Cash Out Detail'!BC44:BE44)/1000000 -> 142.78032 | V29: =SUM('Cash Out Detail'!BF44:BH44)/1000000 -> 5.72544 | W29: =SUM('Cash Out Detail'!BI44:BK44)/1000000 -> 5.72544 | X29: =SUM('Cash Out Detail'!BL44:BN44)/1000000 -> 0 | Y29: =SUM('Cash Out Detail'!BO44:BQ44)/1000000 -> 0
B30: Total | C30: =SUM(C28:C29) -> 1800.5366 | D30: =SUM(H28:H29) -> 23 | E30: =SUM(I28:I29) -> 30.36 | F30: =SUM(J28:J29) -> 81.11139 | G30: =SUM(K28:K29) -> 72.83139 | H30: =SUM(L28:L29) -> 100.37378 | I30: =SUM(M28:M29) -> 84.73378 | J30: =SUM(N28:N29) -> 55.85595 | K30: =SUM(O28:O29) -> 50.62254 | ... AT30: =SUM(AX28:AX29) -> 0
B32: NPV CASH OUT FLOW CAPEX -MEGP | D32: 32.971612 | E32: 38.802329 | F32: 49.131115 | G32: 33.8285 | H32: 31.104567 | I32: 30.10218 | J32: 10.384684 | K32: 11.152308 | L32: 109.66076 | M32: 0.00010424973 | N32: 131.53864 | O32: 90.817418 | P32: 0 | Q32: 0 | R32: 0 | S32: 0 | T32: 0
B33: Project | C33: Total Sales | D33: M 3 | E33: M 6 | F33: M 9 | G33: M 12 | H33: M 15 | I33: M 18 | J33: M 21 | K33: M 24 | L33: M 27 | M33: M 30 | N33: M 33 | O33: M 36 | P33: M 39 | Q33: M 42 | R33: M 45 | S33: M 48 | T33: M 51 | U33: M 54 | V33: M 57 | W33: M 60 | X33: M 63 | Y33: M 66 | Z33: M 69 | AA33: M 72 | AB33: M 75 | AC33: M 78 | AD33: M 81 | AE33: M 84 | AF33: M 87 | AG33: M 90 | AH33: M 93 | AI33: M 96 | AJ33: M 99 | AK33: M 102 | AL33: M 105 | AM33: M 108 | AN33: M 111 | AO33: M 114 | AP33: M 117 | AQ33: M 120 | AR33: M 123 | AS33: M 126 | AT33: M 129
B34: Green Square | C34: =SUM(D34:ZZ34) -> 592.63947 | D34: =+D28/((1+'Green Square'!$C$72)^'Green Square'!E$73) -> 0 | E34: =+E28/((1+'Green Square'!$C$72)^'Green Square'!F$73) -> 0 | F34: =+F28/((1+'Green Square'!$C$72)^'Green Square'!G$73) -> 0 | G34: =+G28/((1+'Green Square'!$C$72)^'Green Square'!H$73) -> 0 | H34: =+H28/((1+'Green Square'!$C$72)^'Green Square'!I$73) -> 19.525258 | I34: =+I28/((1+'Green Square'!$C$72)^'Green Square'!J$73) -> 24.942759 | J34: =+J28/((1+'Green Square'!$C$72)^'Green Square'!K$73) -> 46.203808 | K34: =+K28/((1+'Green Square'!$C$72)^'Green Square'!L$73) -> 32.680355 | ... AA34: =+AA28/((1+'Green Square'!$C$72)^'Green Square'!AB$73) -> 0 | AB34: =+AF28/((1+'Green Square'!$C$72)^'Green Square'!AC$73) -> 0 | AC34: =+AG28/((1+'Green Square'!$C$72)^'Green Square'!AD$73) -> 0 | AD34: =+AH28/((1+'Green Square'!$C$72)^'Green Square'!AE$73) -> 0 | AE34: =+AI28/((1+'Green Square'!$C$72)^'Green Square'!AF$73) -> 0 | AF34: =+AJ28/((1+'Green Square'!$C$72)^'Green Square'!AG$73) -> 0 | AG34: =+AK28/((1+'Green Square'!$C$72)^'Green Square'!AH$73) -> 0 | AH34: =+AL28/((1+'Green Square'!$C$72)^'Green Square'!AI$73) -> 0 | AI34: =+AM28/((1+'Green Square'!$C$72)^'Green Square'!AJ$73) -> 0 | ... AT34: =+AX28/((1+'Green Square'!$C$72)^'Green Square'!AU$73) -> 0
B35: L'avenir | C35: =SUM(D35:ZZ35) -> 565.10474 | D35: =+D29/((1+'Green Square'!$C$72)^'Green Square'!E$73) -> 0 | E35: =+E29/((1+'Green Square'!$C$72)^'Green Square'!F$73) -> 0 | F35: =+F29/((1+'Green Square'!$C$72)^'Green Square'!G$73) -> 0 | G35: =+G29/((1+'Green Square'!$C$72)^'Green Square'!H$73) -> 0 | H35: =+H29/((1+'Green Square'!$C$72)^'Green Square'!I$73) -> 0 | I35: =+I29/((1+'Green Square'!$C$72)^'Green Square'!J$73) -> 0 | J35: =+J29/((1+'Green Square'!$C$72)^'Green Square'!K$73) -> 18.287079 | K35: =+K29/((1+'Green Square'!$C$72)^'Green Square'!L$73) -> 23.361034 | ... AA35: =+AA29/((1+'Green Square'!$C$72)^'Green Square'!AB$73) -> 0 | AB35: =+AF29/((1+'Green Square'!$C$72)^'Green Square'!AC$73) -> 0 | AC35: =+AG29/((1+'Green Square'!$C$72)^'Green Square'!AD$73) -> 0 | AD35: =+AH29/((1+'Green Square'!$C$72)^'Green Square'!AE$73) -> 0 | AE35: =+AI29/((1+'Green Square'!$C$72)^'Green Square'!AF$73) -> 0 | AF35: =+AJ29/((1+'Green Square'!$C$72)^'Green Square'!AG$73) -> 0 | AG35: =+AK29/((1+'Green Square'!$C$72)^'Green Square'!AH$73) -> 0 | AH35: =+AL29/((1+'Green Square'!$C$72)^'Green Square'!AI$73) -> 0 | AI35: =+AM29/((1+'Green Square'!$C$72)^'Green Square'!AJ$73) -> 0 | ... AT35: =+AX29/((1+'Green Square'!$C$72)^'Green Square'!AU$73) -> 0
B36: Total | C36: =SUM(C34:C35) -> 1157.7442 | D36: =SUM(D34:D35) -> 0 | E36: =SUM(E34:E35) -> 0 | F36: =SUM(F34:F35) -> 0 | G36: =SUM(G34:G35) -> 0 | H36: =SUM(H34:H35) -> 19.525258 | I36: =SUM(I34:I35) -> 24.942759 | J36: =SUM(J34:J35) -> 64.490888 | ... AT36: =SUM(AT34:AT35) -> 0
B38: NET CASH FLOW -MEGP
B39: Project | C39: Total Sales | D39: M 3 | E39: M 6 | F39: M 9 | G39: M 12 | H39: M 15 | I39: M 18 | J39: M 21 | K39: M 24 | L39: M 27 | M39: M 30 | N39: M 33 | O39: M 36 | P39: M 39 | Q39: M 42 | R39: M 45 | S39: M 48 | T39: M 51 | U39: M 54 | V39: M 57 | W39: M 60 | X39: M 63 | Y39: M 66 | Z39: M 69 | AA39: M 72 | AB39: M 75 | AC39: M 78 | AD39: M 81 | AE39: M 84 | AF39: M 87 | AG39: M 90 | AH39: M 93 | AI39: M 96 | AJ39: M 99 | AK39: M 102 | AL39: M 105 | AM39: M 108 | AN39: M 111 | AO39: M 114 | AP39: M 117 | AQ39: M 120 | AR39: M 123 | AS39: M 126 | AT39: M 129
B40: Green Square | C40: =SUM(D40:ZZ40) -> 375.44753 | D40: =D16-D28 -> -91.25 | E40: =E16-E28 -> -11.25 | F40: =F16-F28 -> 3.8892375 | G40: =G16-G28 -> 19.028475 | H40: =H16-H28 -> 1.0120062 | I40: =I16-I28 -> 9.8855375 | J40: =J16-J28 -> -18.24569 | K40: =K16-K28 -> -1.4978306 | ... AT40: =AT16-AT28 -> 0
B41: L'avenir | C41: =SUM(D41:ZZ41) -> 595.29293 | D41: =D17-D29 -> 0 | E41: =E17-E29 -> 0 | F41: =F17-F29 -> 0 | G41: =G17-G29 -> -85 | H41: =H17-H29 -> -4.38435 | I41: =I17-I29 -> 13.7313 | J41: =J17-J29 -> 12.760825 | K41: =K17-K29 -> 16.15839 | ... AT41: =AT17-AT29 -> 0
B42: Total | C42: =SUM(C40:C41) -> 970.74046 | D42: =SUM(D40:D41) -> -91.25 | E42: =SUM(E40:E41) -> -11.25 | F42: =SUM(F40:F41) -> 3.8892375 | G42: =SUM(G40:G41) -> -65.971525 | H42: =SUM(H40:H41) -> -3.3723438 | I42: =SUM(I40:I41) -> 23.616837 | J42: =SUM(J40:J41) -> -5.484865 | ... AT42: =SUM(AT40:AT41) -> 0
B44: NPV NET CASH FLOW -MEGP
B45: Project | C45: Total Sales | D45: M 3 | E45: M 6 | F45: M 9 | G45: M 12 | H45: M 15 | I45: M 18 | J45: M 21 | K45: M 24 | L45: M 27 | M45: M 30 | N45: M 33 | O45: M 36 | P45: M 39 | Q45: M 42 | R45: M 45 | S45: M 48 | T45: M 51 | U45: M 54 | V45: M 57 | W45: M 60 | X45: M 63 | Y45: M 66 | Z45: M 69 | AA45: M 72 | AB45: M 75 | AC45: M 78 | AD45: M 81 | AE45: M 84 | AF45: M 87 | AG45: M 90 | AH45: M 93 | AI45: M 96 | AJ45: M 99 | AK45: M 102 | AL45: M 105 | AM45: M 108 | AN45: M 111 | AO45: M 114 | AP45: M 117 | AQ45: M 120 | AR45: M 123 | AS45: M 126 | AT45: M 129
B46: Green Square | C46: =SUM(D46:ZZ46) -> 215.31139 | D46: =+D40/((1+'Green Square'!$C$72)^'Green Square'!E$73) -> -88.309344 | E46: =+E40/((1+'Green Square'!$C$72)^'Green Square'!F$73) -> -10.53659 | F46: =+F40/((1+'Green Square'!$C$72)^'Green Square'!G$73) -> 3.5252168 | G46: =+G40/((1+'Green Square'!$C$72)^'Green Square'!H$73) -> 16.691645 | H46: =+H40/((1+'Green Square'!$C$72)^'Green Square'!I$73) -> 0.85911664 | I46: =+I40/((1+'Green Square'!$C$72)^'Green Square'!J$73) -> 8.1216265 | J46: =+J40/((1+'Green Square'!$C$72)^'Green Square'!K$73) -> -14.506973 | K46: =+K40/((1+'Green Square'!$C$72)^'Green Square'!L$73) -> -1.152532 | ... AT46: =+AT40/((1+'Green Square'!$C$72)^'Green Square'!AU$73) -> 0
B47: L'avenir | C47: =SUM(D47:ZZ47) -> 307.53237 | D47: =+D41/((1+'Green Square'!$C$72)^'Green Square'!E$73) -> 0 | E47: =+E41/((1+'Green Square'!$C$72)^'Green Square'!F$73) -> 0 | F47: =+F41/((1+'Green Square'!$C$72)^'Green Square'!G$73) -> 0 | G47: =+G41/((1+'Green Square'!$C$72)^'Green Square'!H$73) -> -74.561404 | H47: =+H41/((1+'Green Square'!$C$72)^'Green Square'!I$73) -> -3.721981 | I47: =+I41/((1+'Green Square'!$C$72)^'Green Square'!J$73) -> 11.281176 | J47: =+J41/((1+'Green Square'!$C$72)^'Green Square'!K$73) -> 10.146009 | K47: =+K41/((1+'Green Square'!$C$72)^'Green Square'!L$73) -> 12.433356 | ... AT47: =+AT41/((1+'Green Square'!$C$72)^'Green Square'!AU$73) -> 0
B48: Total | C48: =SUM(C46:C47) -> 522.84376 | D48: =SUM(D46:D47) -> -88.309344 | E48: =SUM(E46:E47) -> -10.53659 | F48: =SUM(F46:F47) -> 3.5252168 | G48: =SUM(G46:G47) -> -57.869759 | H48: =SUM(H46:H47) -> -2.8628644 | I48: =SUM(I46:I47) -> 19.402803 | J48: =SUM(J46:J47) -> -4.3609635 | ... AT48: =SUM(AT46:AT47) -> 0
B50: NET CASH FLOW -MEGP-ACCUMULATED
B51: Project | C51: Total Sales | D51: M 3 | E51: M 6 | F51: M 9 | G51: M 12 | H51: M 15 | I51: M 18 | J51: M 21 | K51: M 24 | L51: M 27 | M51: M 30 | N51: M 33 | O51: M 36 | P51: M 39 | Q51: M 42 | R51: M 45 | S51: M 48 | T51: M 51 | U51: M 54 | V51: M 57 | W51: M 60 | X51: M 63 | Y51: M 66 | Z51: M 69 | AA51: M 72 | AB51: M 75 | AC51: M 78 | AD51: M 81 | AE51: M 84 | AF51: M 87 | AG51: M 90 | AH51: M 93 | AI51: M 96 | AJ51: M 99 | AK51: M 102 | AL51: M 105 | AM51: M 108 | AN51: M 111 | AO51: M 114 | AP51: M 117 | AQ51: M 120 | AR51: M 123 | AS51: M 126 | AT51: M 129
B52: Green Square | C52: =AT52 -> 375.44753 | D52: =D40 -> -91.25 | E52: =D52+E40 -> -102.5 | F52: =E52+F40 -> -98.610763 | G52: =F52+G40 -> -79.582288 | H52: =G52+H40 -> -78.570281 | I52: =H52+I40 -> -68.684744 | J52: =I52+J40 -> -86.930434 | K52: =J52+K40 -> -88.428264 | L52: =K52+L40 -> -81.730676 | ... AT52: =AS52+AT40 -> 375.44753
B53: L'avenir | C53: =AT53 -> 595.29293 | D53: =D41 -> 0 | E53: =D53+E41 -> 0 | F53: =E53+F41 -> 0 | G53: =F53+G41 -> -85 | H53: =G53+H41 -> -89.38435 | I53: =H53+I41 -> -75.65305 | J53: =I53+J41 -> -62.892225 | K53: =J53+K41 -> -46.733835 | L53: =K53+L41 -> -85.13881 | ... AT53: =AS53+AT41 -> 595.29293
B54: Total CASH-IN FLOW JALOUR | C54: =SUM(C52:C53) -> 970.74046 | D54: =SUM(D52:D53) -> -91.25 | E54: =SUM(E52:E53) -> -102.5 | F54: =SUM(F52:F53) -> -98.610763 | G54: =SUM(G52:G53) -> -164.58229 | H54: =SUM(H52:H53) -> -167.95463 | I54: =SUM(I52:I53) -> -144.33779 | J54: =SUM(J52:J53) -> -149.82266 | ... AT54: =SUM(AT52:AT53) -> 970.74046
B56: NPV NET CASH FLOW -MEGP-ACCUMULATED
B57: Project | C57: Total Sales | D57: M 3 | E57: M 6 | F57: M 9 | G57: M 12 | H57: M 15 | I57: M 18 | J57: M 21 | K57: M 24 | L57: M 27 | M57: M 30 | N57: M 33 | O57: M 36 | P57: M 39 | Q57: M 42 | R57: M 45 | S57: M 48 | T57: M 51 | U57: M 54 | V57: M 57 | W57: M 60 | X57: M 63 | Y57: M 66 | Z57: M 69 | AA57: M 72 | AB57: M 75 | AC57: M 78 | AD57: M 81 | AE57: M 84 | AF57: M 87 | AG57: M 90 | AH57: M 93 | AI57: M 96 | AJ57: M 99 | AK57: M 102 | AL57: M 105 | AM57: M 108 | AN57: M 111 | AO57: M 114 | AP57: M 117 | AQ57: M 120 | AR57: M 123 | AS57: M 126 | AT57: M 129
B58: Green Square | C58: =AT58 -> 215.31139 | D58: =D46 -> -88.309344 | E58: =D58+E46 -> -98.845935 | F58: =E58+F46 -> -95.320718 | G58: =F58+G46 -> -78.629073 | H58: =G58+H46 -> -77.769957 | I58: =H58+I46 -> -69.64833 | J58: =I58+J46 -> -84.155303 | K58: =J58+K46 -> -85.307835 | L58: =K58+L46 -> -80.320339 | ... AT58: =AS58+AT46 -> 215.31139
B59: L'avenir | C59: =AT59 -> 307.53237 | D59: =D47 -> 0 | E59: =D59+E47 -> 0 | F59: =E59+F47 -> 0 | G59: =F59+G47 -> -74.561404 | H59: =G59+H47 -> -78.283385 | I59: =H59+I47 -> -67.002208 | J59: =I59+J47 -> -56.856199 | K59: =J59+K47 -> -44.422843 | L59: =K59+L47 -> -73.02189 | ... AT59: =AS59+AT47 -> 307.53237
B60: NPV Total CASH-IN FLOW JALOUR | C60: =SUM(C58:C59) -> 522.84376 | D60: =SUM(D58:D59) -> -88.309344 | E60: =SUM(E58:E59) -> -98.845935 | F60: =SUM(F58:F59) -> -95.320718 | G60: =SUM(G58:G59) -> -153.19048 | H60: =SUM(H58:H59) -> -156.05334 | I60: =SUM(I58:I59) -> -136.65054 | J60: =SUM(J58:J59) -> -141.0115 | ... AT60: =SUM(AT58:AT59) -> 522.84376
B87: Accumulated Cash Available for Operation -MEGP
B88: Project | C88: Total Sales | D88: M 3 | E88: M 6 | F88: M 9 | G88: M 12 | H88: M 15 | I88: M 18 | J88: M 21 | K88: M 24 | L88: M 27 | M88: M 30 | N88: M 33 | O88: M 36 | P88: M 39 | Q88: M 42 | R88: M 45 | S88: M 48 | T88: M 51 | U88: M 54 | V88: M 57 | W88: M 60 | X88: M 63 | Y88: M 66 | Z88: M 69 | AA88: M 72 | AB88: M 75 | AC88: M 78 | AD88: M 81 | AE88: M 84 | AF88: M 87 | AG88: M 90 | AH88: M 93 | AI88: M 96 | AJ88: M 99 | AK88: M 102 | AL88: M 105 | AM88: M 108 | AN88: M 111 | AO88: M 114 | AP88: M 117 | AQ88: M 120 | AR88: M 123 | AS88: M 126 | AT88: M 129
B89: Green Square | C89: =AT89 -> 1267.3007 | D89: =D16 -> -91.25 | E89: =D89+E16 -> -102.5 | F89: =E89+F16 -> -98.610763 | G89: =F89+G16 -> -79.582288 | H89: =G89+H16 -> -55.570281 | I89: =H89+I16 -> -15.324744 | J89: =I89+J16 -> 24.540956 | K89: =J89+K16 -> 65.514516 | L89: =K89+L16 -> 112.09336 | ... AT89: =AS89+AT16 -> 1267.3007
B90: L'avenir | C90: =AT90 -> 1503.9764 | D90: =D17 -> 0 | E90: =D90+E17 -> 0 | F90: =E90+F17 -> 0 | G90: =F90+G17 -> -85 | H90: =G90+H17 -> -89.38435 | I90: =H90+I17 -> -75.65305 | J90: =I90+J17 -> -39.892225 | K90: =J90+K17 -> 6.626165 | L90: =K90+L17 -> 28.71371 | ... AT90: =AS90+AT17 -> 1503.9764
C91: =SUM(C89:C90) -> 2771.277 | D91: =SUM(D89:D90) -> -91.25 | E91: =SUM(E89:E90) -> -102.5 | F91: =SUM(F89:F90) -> -98.610763 | G91: =SUM(G89:G90) -> -164.58229 | H91: =SUM(H89:H90) -> -144.95463 | I91: =SUM(I89:I90) -> -90.977794 | J91: =SUM(J89:J90) -> -15.351269 | ... AT91: =SUM(AT89:AT90) -> 2771.277

Sheet Net Cash Flow -Without DP
B1: Cash Available for Operation after - 20% RETAINED UNITS
B2: Total Collections MEGP
B3: Project | C3: Total Sales | D3: M 3 | E3: M 6 | F3: M 9 | G3: M 12 | H3: M 15 | I3: M 18 | J3: M 21 | K3: M 24 | L3: M 27 | M3: M 30 | N3: M 33 | O3: M 36 | P3: M 39 | Q3: M 42 | R3: M 45 | S3: M 48 | T3: M 51 | U3: M 54 | V3: M 57 | W3: M 60 | X3: M 63 | Y3: M 66 | Z3: M 69 | AA3: M 72 | AB3: M 75 | AC3: M 78 | AD3: M 81 | AE3: M 84 | AF3: M 87 | AG3: M 90 | AH3: M 93 | AI3: M 96 | AJ3: M 99 | AK3: M 102 | AL3: M 105 | AM3: M 108 | AN3: M 111 | AO3: M 114 | AP3: M 117 | AQ3: M 120 | AR3: M 123 | AS3: M 126 | AT3: M 129
B4: Green Square | C4: =SUM(D4:ZZ4) -> 2252.979 | D4: ='Cash In Flow Summary'!D4 -> 0 | E4: ='Cash In Flow Summary'!E4 -> 0 | F4: ='Cash In Flow Summary'!F4 -> 15.139238 | G4: ='Cash In Flow Summary'!G4 -> 30.278475 | H4: ='Cash In Flow Summary'!H4 -> 46.512006 | I4: ='Cash In Flow Summary'!I4 -> 62.745537 | J4: ='Cash In Flow Summary'!J4 -> 62.3657 | K4: ='Cash In Flow Summary'!K4 -> 63.473559 | ... AT4: ='Cash In Flow Summary'!AT4 -> 0
B5: L'avenir | C5: =SUM(D5:ZZ5) -> 2673.7357 | D5: ='Cash In Flow Summary'!D5 -> 0 | E5: ='Cash In Flow Summary'!E5 -> 0 | F5: ='Cash In Flow Summary'!F5 -> 0 | G5: ='Cash In Flow Summary'!G5 -> 0 | H5: ='Cash In Flow Summary'!H5 -> 18.11565 | I5: ='Cash In Flow Summary'!I5 -> 36.2313 | J5: ='Cash In Flow Summary'!J5 -> 58.260825 | K5: ='Cash In Flow Summary'!K5 -> 69.01839 | ... AT5: ='Cash In Flow Summary'!AT5 -> 0
C6: =SUM(C4:C5) -> 4926.7148 | D6: =SUM(D4:D5) -> 0 | E6: =SUM(E4:E5) -> 0 | F6: =SUM(F4:F5) -> 15.139238 | G6: =SUM(G4:G5) -> 30.278475 | H6: =SUM(H4:H5) -> 64.627656 | I6: =SUM(I4:I5) -> 98.976838 | J6: =SUM(J4:J5) -> 120.62653 | ... AT6: =SUM(AT4:AT5) -> 0
B8: ALAHLY - SABBOUR Payments MEGP
B9: Project | C9: Total Sales | D9: M 3 | E9: M 6 | F9: M 9 | G9: M 12 | H9: M 15 | I9: M 18 | J9: M 21 | K9: M 24 | L9: M 27 | M9: M 30 | N9: M 33 | O9: M 36 | P9: M 39 | Q9: M 42 | R9: M 45 | S9: M 48 | T9: M 51 | U9: M 54 | V9: M 57 | W9: M 60 | X9: M 63 | Y9: M 66 | Z9: M 69 | AA9: M 72 | AB9: M 75 | AC9: M 78 | AD9: M 81 | AE9: M 84 | AF9: M 87 | AG9: M 90 | AH9: M 93 | AI9: M 96 | AJ9: M 99 | AK9: M 102 | AL9: M 105 | AM9: M 108 | AN9: M 111 | AO9: M 114 | AP9: M 117 | AQ9: M 120 | AR9: M 123 | AS9: M 126 | AT9: M 129
B10: Green Square | C10: =SUM(D10:ZZ10) -> 985.67831 | D10: =Offers!$C$6/4 -> 12.5 | E10: =Offers!$C$6/4 -> 12.5 | F10: =Offers!$C$6/4 -> 12.5 | G10: =Offers!$C$6/4 -> 12.5 | H10: =Offers!$C$7/4 -> 25 | I10: =Offers!$C$7/4 -> 25 | J10: =Offers!$C$7/4 -> 25 | K10: =Offers!$C$7/4 -> 25 | L10: =Offers!$C$8/4 -> 37.5 | M10: =Offers!$C$8/4 -> 37.5 | N10: =Offers!$C$8/4 -> 37.5 | O10: =Offers!$C$8/4 -> 37.5 | P10: =Offers!$C$9/4 -> 50 | Q10: =Offers!$C$9/4 -> 50 | R10: =Offers!$C$9/4 -> 50 | S10: =Offers!$C$9/4 -> 50 | T10: =Offers!$C$10/4 -> 50 | U10: =Offers!$C$10/4 -> 50 | V10: =Offers!$C$10/4 -> 50 | W10: =Offers!$C$10/4 -> 50 | X10: =Offers!$C$11/4 -> 25 | Y10: =Offers!$C$11/4 -> 25 | Z10: =Offers!$C$11/4 -> 25 | AA10: =Offers!$C$11/4 -> 25 | AB10: =Offers!$C$12/4 -> 0 | AC10: =Offers!$C$12/4 -> 0 | AD10: =Offers!$C$12/4 -> 0 | AE10: =Offers!$C$12/4 -> 0 | AF10: =-SUM(D10:AE10)+SUM('Cash In Flow Summary'!D37:AE37)+'Cash In Flow Summary'!AF37 -> 107.75821 | AG10: ='Cash In Flow Summary'!AG37 -> 10.976512 | AH10: ='Cash In Flow Summary'!AH37 -> 10.976512 | AI10: ='Cash In Flow Summary'!AI37 -> 10.976512 | AJ10: ='Cash In Flow Summary'!AJ37 -> 10.976512 | AK10: ='Cash In Flow Summary'!AK37 -> 10.020984 | AL10: ='Cash In Flow Summary'!AL37 -> 10.020984 | AM10: ='Cash In Flow Summary'!AM37 -> 8.198555 | AN10: ='Cash In Flow Summary'!AN37 -> 4.2114483 | ... AT10: ='Cash In Flow Summary'!AT37 -> 0
B11: L'avenir | C11: =SUM(D11:ZZ11) -> 1169.7594 | D11: =Offers!$D$6/4 -> 0 | E11: =Offers!$D$6/4 -> 0 | F11: =Offers!$D$6/4 -> 0 | G11: =Offers!$D$6/4 -> 0 | H11: =Offers!$D$7/4 -> 25 | I11: =Offers!$D$7/4 -> 25 | J11: =Offers!$D$7/4 -> 25 | K11: =Offers!$D$7/4 -> 25 | L11: =Offers!$D$8/4 -> 50 | M11: =Offers!$D$8/4 -> 50 | N11: =Offers!$D$8/4 -> 50 | O11: =Offers!$D$8/4 -> 50 | P11: =Offers!$D$9/4 -> 62.5 | Q11: =Offers!$D$9/4 -> 62.5 | R11: =Offers!$D$9/4 -> 62.5 | S11: =Offers!$D$9/4 -> 62.5 | T11: =Offers!$D$10/4 -> 50 | U11: =Offers!$D$10/4 -> 50 | V11: =Offers!$D$10/4 -> 50 | W11: =Offers!$D$10/4 -> 50 | X11: =Offers!$D$11/4 -> 25 | Y11: =Offers!$D$11/4 -> 25 | Z11: =Offers!$D$11/4 -> 25 | AA11: =Offers!$D$11/4 -> 25 | AB11: =Offers!$D$12/4 -> 0 | AC11: =Offers!$D$12/4 -> 0 | AD11: =Offers!$D$12/4 -> 0 | AE11: =Offers!$D$12/4 -> 0 | AF11: =-SUM(D11:AE11)+SUM('Cash In Flow Summary'!D38:AE38)+'Cash In Flow Summary'!AF38 -> 241.19161 | AG11: ='Cash In Flow Summary'!AG38 -> 16.107226 | AH11: ='Cash In Flow Summary'!AH38 -> 14.419368 | AI11: ='Cash In Flow Summary'!AI38 -> 12.731509 | AJ11: ='Cash In Flow Summary'!AJ38 -> 10.011366 | AK11: ='Cash In Flow Summary'!AK38 -> 8.4360314 | AL11: ='Cash In Flow Summary'!AL38 -> 7.3515619 | AM11: ='Cash In Flow Summary'!AM38 -> 3.1702388 | AN11: ='Cash In Flow Summary'!AN38 -> 3.1702388 | ... AT11: ='Cash In Flow Summary'!AT38 -> 0
C12: =SUM(C10:C11) -> 2155.4377 | D12: =SUM(D10:D11) -> 12.5 | E12: =SUM(E10:E11) -> 12.5 | F12: =SUM(F10:F11) -> 12.5 | G12: =SUM(G10:G11) -> 12.5 | H12: =SUM(H10:H11) -> 50 | I12: =SUM(I10:I11) -> 50 | J12: =SUM(J10:J11) -> 50 | ... AT12: =SUM(AT10:AT11) -> 0
B14: Cash Available for Operation -MEGP
B15: Project | C15: Total Sales | D15: M 3 | E15: M 6 | F15: M 9 | G15: M 12 | H15: M 15 | I15: M 18 | J15: M 21 | K15: M 24 | L15: M 27 | M15: M 30 | N15: M 33 | O15: M 36 | P15: M 39 | Q15: M 42 | R15: M 45 | S15: M 48 | T15: M 51 | U15: M 54 | V15: M 57 | W15: M 60 | X15: M 63 | Y15: M 66 | Z15: M 69 | AA15: M 72 | AB15: M 75 | AC15: M 78 | AD15: M 81 | AE15: M 84 | AF15: M 87 | AG15: M 90 | AH15: M 93 | AI15: M 96 | AJ15: M 99 | AK15: M 102 | AL15: M 105 | AM15: M 108 | AN15: M 111 | AO15: M 114 | AP15: M 117 | AQ15: M 120 | AR15: M 123 | AS15: M 126 | AT15: M 129
B16: Green Square | C16: =SUM(D16:ZZ16) -> 1267.3007 | D16: =D4-D10 -> -12.5 | E16: =E4-E10 -> -12.5 | F16: =F4-F10 -> 2.6392375 | G16: =G4-G10 -> 17.778475 | H16: =H4-H10 -> 21.512006 | I16: =I4-I10 -> 37.745537 | J16: =J4-J10 -> 37.3657 | K16: =K4-K10 -> 38.473559 | ... AT16: =AT4-AT10 -> 0
B17: L'avenir | C17: =SUM(D17:ZZ17) -> 1503.9764 | D17: =D5-D11 -> 0 | E17: =E5-E11 -> 0 | F17: =F5-F11 -> 0 | G17: =G5-G11 -> 0 | H17: =H5-H11 -> -6.88435 | I17: =I5-I11 -> 11.2313 | J17: =J5-J11 -> 33.260825 | K17: =K5-K11 -> 44.01839 | ... AT17: =AT5-AT11 -> 0
B18: Total | C18: =SUM(C16:C17) -> 2771.277 | D18: =SUM(D16:D17) -> -12.5 | E18: =SUM(E16:E17) -> -12.5 | F18: =SUM(F16:F17) -> 2.6392375 | G18: =SUM(G16:G17) -> 17.778475 | H18: =SUM(H16:H17) -> 14.627656 | I18: =SUM(I16:I17) -> 48.976838 | J18: =SUM(J16:J17) -> 70.626525 | ... AT18: =SUM(AT16:AT17) -> 0
B20: NPV Cash Available for Operation -MEGP
B21: Project | C21: Total Sales | D21: M 3 | E21: M 6 | F21: M 9 | G21: M 12 | H21: M 15 | I21: M 18 | J21: M 21 | K21: M 24 | L21: M 27 | M21: M 30 | N21: M 33 | O21: M 36 | P21: M 39 | Q21: M 42 | R21: M 45 | S21: M 48 | T21: M 51 | U21: M 54 | V21: M 57 | W21: M 60 | X21: M 63 | Y21: M 66 | Z21: M 69 | AA21: M 72 | AB21: M 75 | AC21: M 78 | AD21: M 81 | AE21: M 84 | AF21: M 87 | AG21: M 90 | AH21: M 93 | AI21: M 96 | AJ21: M 99 | AK21: M 102 | AL21: M 105 | AM21: M 108 | AN21: M 111 | AO21: M 114 | AP21: M 117 | AQ21: M 120 | AR21: M 123 | AS21: M 126 | AT21: M 129
B22: Green Square | C22: =SUM(D22:ZZ22) -> 833.88091 | D22: =+D16/((1+'Green Square'!$C$72)^'Green Square'!E$73) -> -12.09717 | E22: =+E16/((1+'Green Square'!$C$72)^'Green Square'!F$73) -> -11.707323 | F22: =+F16/((1+'Green Square'!$C$72)^'Green Square'!G$73) -> 2.3922129 | G22: =+G16/((1+'Green Square'!$C$72)^'Green Square'!H$73) -> 15.595154 | H22: =+H16/((1+'Green Square'!$C$72)^'Green Square'!I$73) -> 18.262064 | I22: =+I16/((1+'Green Square'!$C$72)^'Green Square'!J$73) -> 31.010469 | J22: =+J16/((1+'Green Square'!$C$72)^'Green Square'!K$73) -> 29.709109 | K22: =+K16/((1+'Green Square'!$C$72)^'Green Square'!L$73) -> 29.604155 | ... AT22: =+AT16/((1+'Green Square'!$C$72)^'Green Square'!AU$73) -> 0
B23: L'avenir | C23: =SUM(D23:ZZ23) -> 893.65783 | D23: =+D17/((1+'Green Square'!$C$72)^'Green Square'!E$73) -> 0 | E23: =+E17/((1+'Green Square'!$C$72)^'Green Square'!F$73) -> 0 | F23: =+F17/((1+'Green Square'!$C$72)^'Green Square'!G$73) -> 0 | G23: =+G17/((1+'Green Square'!$C$72)^'Green Square'!H$73) -> 0 | H23: =+H17/((1+'Green Square'!$C$72)^'Green Square'!I$73) -> -5.8442916 | I23: =+I17/((1+'Green Square'!$C$72)^'Green Square'!J$73) -> 9.2272598 | J23: =+J17/((1+'Green Square'!$C$72)^'Green Square'!K$73) -> 26.445363 | K23: =+K17/((1+'Green Square'!$C$72)^'Green Square'!L$73) -> 33.870722 | ... AT23: =+AT17/((1+'Green Square'!$C$72)^'Green Square'!AU$73) -> 0
B24: Total | C24: =SUM(C22:C23) -> 1727.5387 | D24: =SUM(D22:D23) -> -12.09717 | E24: =SUM(E22:E23) -> -11.707323 | F24: =SUM(F22:F23) -> 2.3922129 | G24: =SUM(G22:G23) -> 15.595154 | H24: =SUM(H22:H23) -> 12.417772 | I24: =SUM(I22:I23) -> 40.237729 | J24: =SUM(J22:J23) -> 56.154472 | ... AT24: =SUM(AT22:AT23) -> 0
B26: CASH OUT FLOW CAPEX -MEGP
B27: Project | C27: Total Sales | D27: M 3 | E27: M 6 | F27: M 9 | G27: M 12 | H27: M 15 | I27: M 18 | J27: M 21 | K27: M 24 | L27: M 27 | M27: M 30 | N27: M 33 | O27: M 36 | P27: M 39 | Q27: M 42 | R27: M 45 | S27: M 48 | T27: M 51 | U27: M 54 | V27: M 57 | W27: M 60 | X27: M 63 | Y27: M 66 | Z27: M 69 | AA27: M 72 | AB27: M 75 | AC27: M 78 | AD27: M 81 | AE27: M 84 | AF27: M 87 | AG27: M 90 | AH27: M 93 | AI27: M 96 | AJ27: M 99 | AK27: M 102 | AL27: M 105 | AM27: M 108 | AN27: M 111 | AO27: M 114 | AP27: M 117 | AQ27: M 120 | AR27: M 123 | AS27: M 126 | AT27: M 129
B28: Green Square | C28: =SUM(H28:AAD28) -> 891.85316 | H28: =SUM('Cash Out Detail'!P43:R43)/1000000 -> 23 | I28: =SUM('Cash Out Detail'!S43:U43)/1000000 -> 30.36 | J28: =SUM('Cash Out Detail'!V43:X43)/1000000 -> 58.11139 | K28: =SUM('Cash Out Detail'!Y43:AA43)/1000000 -> 42.47139 | L28: =SUM('Cash Out Detail'!AB43:AD43)/1000000 -> 39.88126 | M28: =SUM('Cash Out Detail'!AE43:AG43)/1000000 -> 39.88126 | N28: =SUM('Cash Out Detail'!AH43:AJ43)/1000000 -> 13.06101 | O28: =SUM('Cash Out Detail'!AK43:AM43)/1000000 -> 13.06101 | P28: =SUM('Cash Out Detail'!AN43:AP43)/1000000 -> 145.69804 | Q28: =SUM('Cash Out Detail'!AQ43:AS43)/1000000 -> 147.2608 | R28: =SUM('Cash Out Detail'!AT43:AV43)/1000000 -> 197.8608 | S28: =SUM('Cash Out Detail'!AW43:AY43)/1000000 -> 141.2062 | T28: =SUM('Cash Out Detail'!AZ43:BB43)/1000000 -> 0 | U28: =SUM('Cash Out Detail'!BC43:BE43)/1000000 -> 0 | V28: =SUM('Cash Out Detail'!BF43:BH43)/1000000 -> 0 | W28: =SUM('Cash Out Detail'!BI43:BK43)/1000000 -> 0 | X28: =SUM('Cash Out Detail'!BL43:BN43)/1000000 -> 0 | Y28: =SUM('Cash Out Detail'!BO43:BQ43)/1000000 -> 0
B29: L'avenir | C29: =SUM(H29:AAD29) -> 908.68343 | H29: =SUM('Cash Out Detail'!P44:R44)/1000000 -> 0 | I29: =SUM('Cash Out Detail'!S44:U44)/1000000 -> 0 | J29: =SUM('Cash Out Detail'!V44:X44)/1000000 -> 23 | K29: =SUM('Cash Out Detail'!Y44:AA44)/1000000 -> 30.36 | L29: =SUM('Cash Out Detail'!AB44:AD44)/1000000 -> 60.49252 | M29: =SUM('Cash Out Detail'!AE44:AG44)/1000000 -> 44.85252 | N29: =SUM('Cash Out Detail'!AH44:AJ44)/1000000 -> 42.79494 | O29: =SUM('Cash Out Detail'!AK44:AM44)/1000000 -> 37.56153 | P29: =SUM('Cash Out Detail'!AN44:AP44)/1000000 -> 14.00412 | Q29: =SUM('Cash Out Detail'!AQ44:AS44)/1000000 -> 13.46736 | R29: =SUM('Cash Out Detail'!AT44:AV44)/1000000 -> 145.54446 | S29: =SUM('Cash Out Detail'!AW44:AY44)/1000000 -> 145.54446 | T29: =SUM('Cash Out Detail'!AZ44:BB44)/1000000 -> 196.83032 | U29: =SUM('Cash Out Detail'!BC44:BE44)/1000000 -> 142.78032 | V29: =SUM('Cash Out Detail'!BF44:BH44)/1000000 -> 5.72544 | W29: =SUM('Cash Out Detail'!BI44:BK44)/1000000 -> 5.72544 | X29: =SUM('Cash Out Detail'!BL44:BN44)/1000000 -> 0 | Y29: =SUM('Cash Out Detail'!BO44:BQ44)/1000000 -> 0
B30: Total | C30: =SUM(C28:C29) -> 1800.5366 | D30: =SUM(H28:H29) -> 23 | E30: =SUM(I28:I29) -> 30.36 | F30: =SUM(J28:J29) -> 81.11139 | G30: =SUM(K28:K29) -> 72.83139 | H30: =SUM(L28:L29) -> 100.37378 | I30: =SUM(M28:M29) -> 84.73378 | J30: =SUM(N28:N29) -> 55.85595 | K30: =SUM(O28:O29) -> 50.62254 | ... AT30: =SUM(AX28:AX29) -> 0
B32: NPV CASH OUT FLOW CAPEX -MEGP | D32: 32.971612 | E32: 38.802329 | F32: 49.131115 | G32: 33.8285 | H32: 31.104567 | I32: 30.10218 | J32: 10.384684 | K32: 11.152308 | L32: 109.66076 | M32: 0.00010424973 | N32: 131.53864 | O32: 90.817418 | P32: 0 | Q32: 0 | R32: 0 | S32: 0 | T32: 0
B33: Project | C33: Total Sales | D33: M 3 | E33: M 6 | F33: M 9 | G33: M 12 | H33: M 15 | I33: M 18 | J33: M 21 | K33: M 24 | L33: M 27 | M33: M 30 | N33: M 33 | O33: M 36 | P33: M 39 | Q33: M 42 | R33: M 45 | S33: M 48 | T33: M 51 | U33: M 54 | V33: M 57 | W33: M 60 | X33: M 63 | Y33: M 66 | Z33: M 69 | AA33: M 72 | AB33: M 75 | AC33: M 78 | AD33: M 81 | AE33: M 84 | AF33: M 87 | AG33: M 90 | AH33: M 93 | AI33: M 96 | AJ33: M 99 | AK33: M 102 | AL33: M 105 | AM33: M 108 | AN33: M 111 | AO33: M 114 | AP33: M 117 | AQ33: M 120 | AR33: M 123 | AS33: M 126 | AT33: M 129
B34: Green Square | C34: =SUM(D34:ZZ34) -> 592.63947 | D34: =+D28/((1+'Green Square'!$C$72)^'Green Square'!E$73) -> 0 | E34: =+E28/((1+'Green Square'!$C$72)^'Green Square'!F$73) -> 0 | F34: =+F28/((1+'Green Square'!$C$72)^'Green Square'!G$73) -> 0 | G34: =+G28/((1+'Green Square'!$C$72)^'Green Square'!H$73) -> 0 | H34: =+H28/((1+'Green Square'!$C$72)^'Green Square'!I$73) -> 19.525258 | I34: =+I28/((1+'Green Square'!$C$72)^'Green Square'!J$73) -> 24.942759 | J34: =+J28/((1+'Green Square'!$C$72)^'Green Square'!K$73) -> 46.203808 | K34: =+K28/((1+'Green Square'!$C$72)^'Green Square'!L$73) -> 32.680355 | ... AA34: =+AA28/((1+'Green Square'!$C$72)^'Green Square'!AB$73) -> 0 | AB34: =+AF28/((1+'Green Square'!$C$72)^'Green Square'!AC$73) -> 0 | AC34: =+AG28/((1+'Green Square'!$C$72)^'Green Square'!AD$73) -> 0 | AD34: =+AH28/((1+'Green Square'!$C$72)^'Green Square'!AE$73) -> 0 | AE34: =+AI28/((1+'Green Square'!$C$72)^'Green Square'!AF$73) -> 0 | AF34: =+AJ28/((1+'Green Square'!$C$72)^'Green Square'!AG$73) -> 0 | AG34: =+AK28/((1+'Green Square'!$C$72)^'Green Square'!AH$73) -> 0 | AH34: =+AL28/((1+'Green Square'!$C$72)^'Green Square'!AI$73) -> 0 | AI34: =+AM28/((1+'Green Square'!$C$72)^'Green Square'!AJ$73) -> 0 | ... AT34: =+AX28/((1+'Green Square'!$C$72)^'Green Square'!AU$73) -> 0
B35: L'avenir | C35: =SUM(D35:ZZ35) -> 565.10474 | D35: =+D29/((1+'Green Square'!$C$72)^'Green Square'!E$73) -> 0 | E35: =+E29/((1+'Green Square'!$C$72)^'Green Square'!F$73) -> 0 | F35: =+F29/((1+'Green Square'!$C$72)^'Green Square'!G$73) -> 0 | G35: =+G29/((1+'Green Square'!$C$72)^'Green Square'!H$73) -> 0 | H35: =+H29/((1+'Green Square'!$C$72)^'Green Square'!I$73) -> 0 | I35: =+I29/((1+'Green Square'!$C$72)^'Green Square'!J$73) -> 0 | J35: =+J29/((1+'Green Square'!$C$72)^'Green Square'!K$73) -> 18.287079 | K35: =+K29/((1+'Green Square'!$C$72)^'Green Square'!L$73) -> 23.361034 | ... AA35: =+AA29/((1+'Green Square'!$C$72)^'Green Square'!AB$73) -> 0 | AB35: =+AF29/((1+'Green Square'!$C$72)^'Green Square'!AC$73) -> 0 | AC35: =+AG29/((1+'Green Square'!$C$72)^'Green Square'!AD$73) -> 0 | AD35: =+AH29/((1+'Green Square'!$C$72)^'Green Square'!AE$73) -> 0 | AE35: =+AI29/((1+'Green Square'!$C$72)^'Green Square'!AF$73) -> 0 | AF35: =+AJ29/((1+'Green Square'!$C$72)^'Green Square'!AG$73) -> 0 | AG35: =+AK29/((1+'Green Square'!$C$72)^'Green Square'!AH$73) -> 0 | AH35: =+AL29/((1+'Green Square'!$C$72)^'Green Square'!AI$73) -> 0 | AI35: =+AM29/((1+'Green Square'!$C$72)^'Green Square'!AJ$73) -> 0 | ... AT35: =+AX29/((1+'Green Square'!$C$72)^'Green Square'!AU$73) -> 0
B36: Total | C36: =SUM(C34:C35) -> 1157.7442 | D36: =SUM(D34:D35) -> 0 | E36: =SUM(E34:E35) -> 0 | F36: =SUM(F34:F35) -> 0 | G36: =SUM(G34:G35) -> 0 | H36: =SUM(H34:H35) -> 19.525258 | I36: =SUM(I34:I35) -> 24.942759 | J36: =SUM(J34:J35) -> 64.490888 | ... AT36: =SUM(AT34:AT35) -> 0
B38: NET CASH FLOW -MEGP
B39: Project | C39: Total Sales | D39: M 3 | E39: M 6 | F39: M 9 | G39: M 12 | H39: M 15 | I39: M 18 | J39: M 21 | K39: M 24 | L39: M 27 | M39: M 30 | N39: M 33 | O39: M 36 | P39: M 39 | Q39: M 42 | R39: M 45 | S39: M 48 | T39: M 51 | U39: M 54 | V39: M 57 | W39: M 60 | X39: M 63 | Y39: M 66 | Z39: M 69 | AA39: M 72 | AB39: M 75 | AC39: M 78 | AD39: M 81 | AE39: M 84 | AF39: M 87 | AG39: M 90 | AH39: M 93 | AI39: M 96 | AJ39: M 99 | AK39: M 102 | AL39: M 105 | AM39: M 108 | AN39: M 111 | AO39: M 114 | AP39: M 117 | AQ39: M 120 | AR39: M 123 | AS39: M 126 | AT39: M 129
B40: Green Square | C40: =SUM(D40:ZZ40) -> 375.44753 | D40: =D16-D28 -> -12.5 | E40: =E16-E28 -> -12.5 | F40: =F16-F28 -> 2.6392375 | G40: =G16-G28 -> 17.778475 | H40: =H16-H28 -> -1.4879938 | I40: =I16-I28 -> 7.3855375 | J40: =J16-J28 -> -20.74569 | K40: =K16-K28 -> -3.9978306 | ... AT40: =AT16-AT28 -> 0
B41: L'avenir | C41: =SUM(D41:ZZ41) -> 595.29293 | D41: =D17-D29 -> 0 | E41: =E17-E29 -> 0 | F41: =F17-F29 -> 0 | G41: =G17-G29 -> 0 | H41: =H17-H29 -> -6.88435 | I41: =I17-I29 -> 11.2313 | J41: =J17-J29 -> 10.260825 | K41: =K17-K29 -> 13.65839 | ... AT41: =AT17-AT29 -> 0
B42: Total | C42: =SUM(C40:C41) -> 970.74046 | D42: =SUM(D40:D41) -> -12.5 | E42: =SUM(E40:E41) -> -12.5 | F42: =SUM(F40:F41) -> 2.6392375 | G42: =SUM(G40:G41) -> 17.778475 | H42: =SUM(H40:H41) -> -8.3723438 | I42: =SUM(I40:I41) -> 18.616837 | J42: =SUM(J40:J41) -> -10.484865 | ... AT42: =SUM(AT40:AT41) -> 0
B44: NPV NET CASH FLOW -MEGP
B45: Project | C45: Total Sales | D45: M 3 | E45: M 6 | F45: M 9 | G45: M 12 | H45: M 15 | I45: M 18 | J45: M 21 | K45: M 24 | L45: M 27 | M45: M 30 | N45: M 33 | O45: M 36 | P45: M 39 | Q45: M 42 | R45: M 45 | S45: M 48 | T45: M 51 | U45: M 54 | V45: M 57 | W45: M 60 | X45: M 63 | Y45: M 66 | Z45: M 69 | AA45: M 72 | AB45: M 75 | AC45: M 78 | AD45: M 81 | AE45: M 84 | AF45: M 87 | AG45: M 90 | AH45: M 93 | AI45: M 96 | AJ45: M 99 | AK45: M 102 | AL45: M 105 | AM45: M 108 | AN45: M 111 | AO45: M 114 | AP45: M 117 | AQ45: M 120 | AR45: M 123 | AS45: M 126 | AT45: M 129
B46: Green Square | C46: =SUM(D46:ZZ46) -> 241.24144 | D46: =+D40/((1+'Green Square'!$C$72)^'Green Square'!E$73) -> -12.09717 | E46: =+E40/((1+'Green Square'!$C$72)^'Green Square'!F$73) -> -11.707323 | F46: =+F40/((1+'Green Square'!$C$72)^'Green Square'!G$73) -> 2.3922129 | G46: =+G40/((1+'Green Square'!$C$72)^'Green Square'!H$73) -> 15.595154 | H46: =+H40/((1+'Green Square'!$C$72)^'Green Square'!I$73) -> -1.263194 | I46: =+I40/((1+'Green Square'!$C$72)^'Green Square'!J$73) -> 6.0677102 | J46: =+J40/((1+'Green Square'!$C$72)^'Green Square'!K$73) -> -16.494699 | K46: =+K40/((1+'Green Square'!$C$72)^'Green Square'!L$73) -> -3.0762009 | ... AT46: =+AT40/((1+'Green Square'!$C$72)^'Green Square'!AU$73) -> 0
B47: L'avenir | C47: =SUM(D47:ZZ47) -> 328.55309 | D47: =+D41/((1+'Green Square'!$C$72)^'Green Square'!E$73) -> 0 | E47: =+E41/((1+'Green Square'!$C$72)^'Green Square'!F$73) -> 0 | F47: =+F41/((1+'Green Square'!$C$72)^'Green Square'!G$73) -> 0 | G47: =+G41/((1+'Green Square'!$C$72)^'Green Square'!H$73) -> 0 | H47: =+H41/((1+'Green Square'!$C$72)^'Green Square'!I$73) -> -5.8442916 | I47: =+I41/((1+'Green Square'!$C$72)^'Green Square'!J$73) -> 9.2272598 | J47: =+J41/((1+'Green Square'!$C$72)^'Green Square'!K$73) -> 8.1582835 | K47: =+K41/((1+'Green Square'!$C$72)^'Green Square'!L$73) -> 10.509688 | ... AT47: =+AT41/((1+'Green Square'!$C$72)^'Green Square'!AU$73) -> 0
B48: Total | C48: =SUM(C46:C47) -> 569.79452 | D48: =SUM(D46:D47) -> -12.09717 | E48: =SUM(E46:E47) -> -11.707323 | F48: =SUM(F46:F47) -> 2.3922129 | G48: =SUM(G46:G47) -> 15.595154 | H48: =SUM(H46:H47) -> -7.1074856 | I48: =SUM(I46:I47) -> 15.29497 | J48: =SUM(J46:J47) -> -8.3364155 | ... AT48: =SUM(AT46:AT47) -> 0
B50: NET CASH FLOW -MEGP-ACCUMULATED
B51: Project | C51: Total Sales | D51: M 3 | E51: M 6 | F51: M 9 | G51: M 12 | H51: M 15 | I51: M 18 | J51: M 21 | K51: M 24 | L51: M 27 | M51: M 30 | N51: M 33 | O51: M 36 | P51: M 39 | Q51: M 42 | R51: M 45 | S51: M 48 | T51: M 51 | U51: M 54 | V51: M 57 | W51: M 60 | X51: M 63 | Y51: M 66 | Z51: M 69 | AA51: M 72 | AB51: M 75 | AC51: M 78 | AD51: M 81 | AE51: M 84 | AF51: M 87 | AG51: M 90 | AH51: M 93 | AI51: M 96 | AJ51: M 99 | AK51: M 102 | AL51: M 105 | AM51: M 108 | AN51: M 111 | AO51: M 114 | AP51: M 117 | AQ51: M 120 | AR51: M 123 | AS51: M 126 | AT51: M 129
B52: Green Square | C52: =AT52 -> 375.44753 | D52: =D40 -> -12.5 | E52: =D52+E40 -> -25 | F52: =E52+F40 -> -22.360762 | G52: =F52+G40 -> -4.5822875 | H52: =G52+H40 -> -6.0702812 | I52: =H52+I40 -> 1.3152563 | J52: =I52+J40 -> -19.430434 | K52: =J52+K40 -> -23.428264 | L52: =K52+L40 -> -20.480676 | ... AT52: =AS52+AT40 -> 375.44753
B53: L'avenir | C53: =AT53 -> 595.29293 | D53: =D41 -> 0 | E53: =D53+E41 -> 0 | F53: =E53+F41 -> 0 | G53: =F53+G41 -> 0 | H53: =G53+H41 -> -6.88435 | I53: =H53+I41 -> 4.34695 | J53: =I53+J41 -> 14.607775 | K53: =J53+K41 -> 28.266165 | L53: =K53+L41 -> -15.13881 | ... AT53: =AS53+AT41 -> 595.29293
B54: Total CASH-IN FLOW JALOUR | C54: =SUM(C52:C53) -> 970.74046 | D54: =SUM(D52:D53) -> -12.5 | E54: =SUM(E52:E53) -> -25 | F54: =SUM(F52:F53) -> -22.360762 | G54: =SUM(G52:G53) -> -4.5822875 | H54: =SUM(H52:H53) -> -12.954631 | I54: =SUM(I52:I53) -> 5.6622062 | J54: =SUM(J52:J53) -> -4.8226588 | ... AT54: =SUM(AT52:AT53) -> 970.74046
B56: NPV NET CASH FLOW -MEGP-ACCUMULATED
B57: Project | C57: Total Sales | D57: M 3 | E57: M 6 | F57: M 9 | G57: M 12 | H57: M 15 | I57: M 18 | J57: M 21 | K57: M 24 | L57: M 27 | M57: M 30 | N57: M 33 | O57: M 36 | P57: M 39 | Q57: M 42 | R57: M 45 | S57: M 48 | T57: M 51 | U57: M 54 | V57: M 57 | W57: M 60 | X57: M 63 | Y57: M 66 | Z57: M 69 | AA57: M 72 | AB57: M 75 | AC57: M 78 | AD57: M 81 | AE57: M 84 | AF57: M 87 | AG57: M 90 | AH57: M 93 | AI57: M 96 | AJ57: M 99 | AK57: M 102 | AL57: M 105 | AM57: M 108 | AN57: M 111 | AO57: M 114 | AP57: M 117 | AQ57: M 120 | AR57: M 123 | AS57: M 126 | AT57: M 129
B58: Green Square | C58: =AT58 -> 241.24144 | D58: =D46 -> -12.09717 | E58: =D58+E46 -> -23.804493 | F58: =E58+F46 -> -21.41228 | G58: =F58+G46 -> -5.8171267 | H58: =G58+H46 -> -7.0803206 | I58: =H58+I46 -> -1.0126104 | J58: =I58+J46 -> -17.507309 | K58: =J58+K46 -> -20.58351 | L58: =K58+L46 -> -18.388528 | ... AT58: =AS58+AT46 -> 241.24144
B59: L'avenir | C59: =AT59 -> 328.55309 | D59: =D47 -> 0 | E59: =D59+E47 -> 0 | F59: =E59+F47 -> 0 | G59: =F59+G47 -> 0 | H59: =G59+H47 -> -5.8442916 | I59: =H59+I47 -> 3.3829682 | J59: =I59+J47 -> 11.541252 | K59: =J59+K47 -> 22.050939 | L59: =K59+L47 -> -10.27146 | ... AT59: =AS59+AT47 -> 328.55309
B60: NPV Total CASH-IN FLOW JALOUR | C60: =SUM(C58:C59) -> 569.79452 | D60: =SUM(D58:D59) -> -12.09717 | E60: =SUM(E58:E59) -> -23.804493 | F60: =SUM(F58:F59) -> -21.41228 | G60: =SUM(G58:G59) -> -5.8171267 | H60: =SUM(H58:H59) -> -12.924612 | I60: =SUM(I58:I59) -> 2.3703578 | J60: =SUM(J58:J59) -> -5.9660577 | ... AT60: =SUM(AT58:AT59) -> 569.79452
B87: Accumulated Cash Available for Operation -MEGP
B88: Project | C88: Total Sales | D88: M 3 | E88: M 6 | F88: M 9 | G88: M 12 | H88: M 15 | I88: M 18 | J88: M 21 | K88: M 24 | L88: M 27 | M88: M 30 | N88: M 33 | O88: M 36 | P88: M 39 | Q88: M 42 | R88: M 45 | S88: M 48 | T88: M 51 | U88: M 54 | V88: M 57 | W88: M 60 | X88: M 63 | Y88: M 66 | Z88: M 69 | AA88: M 72 | AB88: M 75 | AC88: M 78 | AD88: M 81 | AE88: M 84 | AF88: M 87 | AG88: M 90 | AH88: M 93 | AI88: M 96 | AJ88: M 99 | AK88: M 102 | AL88: M 105 | AM88: M 108 | AN88: M 111 | AO88: M 114 | AP88: M 117 | AQ88: M 120 | AR88: M 123 | AS88: M 126 | AT88: M 129
B89: Green Square | C89: =AT89 -> 1267.3007 | D89: =D16 -> -12.5 | E89: =D89+E16 -> -25 | F89: =E89+F16 -> -22.360762 | G89: =F89+G16 -> -4.5822875 | H89: =G89+H16 -> 16.929719 | I89: =H89+I16 -> 54.675256 | J89: =I89+J16 -> 92.040956 | K89: =J89+K16 -> 130.51452 | L89: =K89+L16 -> 173.34336 | ... AT89: =AS89+AT16 -> 1267.3007
B90: L'avenir | C90: =AT90 -> 1503.9764 | D90: =D17 -> 0 | E90: =D90+E17 -> 0 | F90: =E90+F17 -> 0 | G90: =F90+G17 -> 0 | H90: =G90+H17 -> -6.88435 | I90: =H90+I17 -> 4.34695 | J90: =I90+J17 -> 37.607775 | K90: =J90+K17 -> 81.626165 | L90: =K90+L17 -> 98.71371 | ... AT90: =AS90+AT17 -> 1503.9764
C91: =SUM(C89:C90) -> 2771.277 | D91: =SUM(D89:D90) -> -12.5 | E91: =SUM(E89:E90) -> -25 | F91: =SUM(F89:F90) -> -22.360762 | G91: =SUM(G89:G90) -> -4.5822875 | H91: =SUM(H89:H90) -> 10.045369 | I91: =SUM(I89:I90) -> 59.022206 | J91: =SUM(J89:J90) -> 129.64873 | ... AT91: =SUM(AT89:AT90) -> 2771.277

Sheet Cash In Flow Summary
B1: Sales - 20% RETAINED
B2: MEGP
B3: Project | C3: Total Sales | D3: M 3 | E3: M 6 | F3: M 9 | G3: M 12 | H3: M 15 | I3: M 18 | J3: M 21 | K3: M 24 | L3: M 27 | M3: M 30 | N3: M 33 | O3: M 36 | P3: M 39 | Q3: M 42 | R3: M 45 | S3: M 48 | T3: M 51 | U3: M 54 | V3: M 57 | W3: M 60 | X3: M 63 | Y3: M 66 | Z3: M 69 | AA3: M 72 | AB3: M 75 | AC3: M 78 | AD3: M 81 | AE3: M 84 | AF3: M 87 | AG3: M 90 | AH3: M 93 | AI3: M 96 | AJ3: M 99 | AK3: M 102 | AL3: M 105 | AM3: M 108 | AN3: M 111 | AO3: M 114 | AP3: M 117 | AQ3: M 120 | AR3: M 123 | AS3: M 126 | AT3: M 129
B4: Green Square | C4: =SUM(D4:ZZ4) -> 2252.979 | D4: ='Green Square'!E70/1000 -> 0 | E4: ='Green Square'!F70/1000 -> 0 | F4: ='Green Square'!G70/1000 -> 15.139238 | G4: ='Green Square'!H70/1000 -> 30.278475 | H4: ='Green Square'!I70/1000 -> 46.512006 | I4: ='Green Square'!J70/1000 -> 62.745537 | J4: ='Green Square'!K70/1000 -> 62.3657 | K4: ='Green Square'!L70/1000 -> 63.473559 | ... AT4: ='Green Square'!AU70/1000 -> 0
B5: L'avenir | C5: =SUM(D5:ZZ5) -> 2673.7357 | D5: ='L''avenir'!E70/1000 -> 0 | E5: ='L''avenir'!F70/1000 -> 0 | F5: ='L''avenir'!G70/1000 -> 0 | G5: ='L''avenir'!H70/1000 -> 0 | H5: ='L''avenir'!I70/1000 -> 18.11565 | I5: ='L''avenir'!J70/1000 -> 36.2313 | J5: ='L''avenir'!K70/1000 -> 58.260825 | K5: ='L''avenir'!L70/1000 -> 69.01839 | ... AT5: ='L''avenir'!AU70/1000 -> 0
C6: =SUM(C4:C5) -> 4926.7148 | D6: =SUM(D4:D5) -> 0 | E6: =SUM(E4:E5) -> 0 | F6: =SUM(F4:F5) -> 15.139238 | G6: =SUM(G4:G5) -> 30.278475 | H6: =SUM(H4:H5) -> 64.627656 | I6: =SUM(I4:I5) -> 98.976838 | J6: =SUM(J4:J5) -> 120.62653 | ... AT6: =SUM(AT4:AT5) -> 0
B8: Project | C8: Total Sales NPV | D8: M 3 | E8: M 6 | F8: M 9 | G8: M 12 | H8: M 15 | I8: M 18 | J8: M 21 | K8: M 24 | L8: M 27 | M8: M 30 | N8: M 33 | O8: M 36 | P8: M 39 | Q8: M 42 | R8: M 45 | S8: M 48 | T8: M 51 | U8: M 54 | V8: M 57 | W8: M 60 | X8: M 63 | Y8: M 66 | Z8: M 69 | AA8: M 72 | AB8: M 75 | AC8: M 78 | AD8: M 81 | AE8: M 84 | AF8: M 87 | AG8: M 90 | AH8: M 93 | AI8: M 96 | AJ8: M 99 | AK8: M 102 | AL8: M 105 | AM8: M 108 | AN8: M 111 | AO8: M 114 | AP8: M 117 | AQ8: M 120 | AR8: M 123 | AS8: M 126 | AT8: M 129
B9: Green Square | C9: =SUM(D9:ZZ9) -> 1416.8308 | D9: ='Green Square'!E71/1000 -> 0 | E9: ='Green Square'!F71/1000 -> 0 | F9: ='Green Square'!G71/1000 -> 13.722251 | G9: ='Green Square'!H71/1000 -> 26.560066 | H9: ='Green Square'!I71/1000 -> 39.48517 | I9: ='Green Square'!J71/1000 -> 51.549632 | J9: ='Green Square'!K71/1000 -> 49.586369 | K9: ='Green Square'!L71/1000 -> 48.840843 | ... AT9: ='Green Square'!AU71/1000 -> 0
B10: L'avenir | C10: =SUM(D10:ZZ10) -> 1549.3963 | D10: ='L''avenir'!E71/1000 -> 0 | E10: ='L''avenir'!F71/1000 -> 0 | F10: ='L''avenir'!G71/1000 -> 0 | G10: ='L''avenir'!H71/1000 -> 0 | H10: ='L''avenir'!I71/1000 -> 15.378814 | I10: ='L''avenir'!J71/1000 -> 29.766422 | J10: ='L''avenir'!K71/1000 -> 46.322623 | K10: ='L''avenir'!L71/1000 -> 53.10741 | ... AT10: ='L''avenir'!AU71/1000 -> 0
C11: =SUM(C9:C10) -> 2966.2271 | D11: =SUM(D9:D10) -> 0 | E11: =SUM(E9:E10) -> 0 | F11: =SUM(F9:F10) -> 13.722251 | G11: =SUM(G9:G10) -> 26.560066 | H11: =SUM(H9:H10) -> 54.863984 | I11: =SUM(I9:I10) -> 81.316054 | J11: =SUM(J9:J10) -> 95.908992 | ... AT11: =SUM(AT9:AT10) -> 0
B13: Accumulated MEGP
B14: Project | C14: Total Sales | D14: M 3 | E14: M 6 | F14: M 9 | G14: M 12 | H14: M 15 | I14: M 18 | J14: M 21 | K14: M 24 | L14: M 27 | M14: M 30 | N14: M 33 | O14: M 36 | P14: M 39 | Q14: M 42 | R14: M 45 | S14: M 48 | T14: M 51 | U14: M 54 | V14: M 57 | W14: M 60 | X14: M 63 | Y14: M 66 | Z14: M 69 | AA14: M 72 | AB14: M 75 | AC14: M 78 | AD14: M 81 | AE14: M 84 | AF14: M 87 | AG14: M 90 | AH14: M 93 | AI14: M 96 | AJ14: M 99 | AK14: M 102 | AL14: M 105 | AM14: M 108 | AN14: M 111 | AO14: M 114 | AP14: M 117 | AQ14: M 120 | AR14: M 123 | AS14: M 126 | AT14: M 129
B15: Green Square | C15: =MAX(D15:ZZ15) -> 2252.979 | D15: =D4 -> 0 | E15: =D15+E4 -> 0 | F15: =E15+F4 -> 15.139238 | G15: =F15+G4 -> 45.417713 | H15: =G15+H4 -> 91.929719 | I15: =H15+I4 -> 154.67526 | J15: =I15+J4 -> 217.04096 | K15: =J15+K4 -> 280.51452 | L15: =K15+L4 -> 360.84336 | ... AT15: =AS15+AT4 -> 2252.979
B16: L'avenir | C16: =MAX(D16:ZZ16) -> 2673.7357 | D16: =D5 -> 0 | E16: =D16+E5 -> 0 | F16: =E16+F5 -> 0 | G16: =F16+G5 -> 0 | H16: =G16+H5 -> 18.11565 | I16: =H16+I5 -> 54.34695 | J16: =I16+J5 -> 112.60778 | K16: =J16+K5 -> 181.62616 | L16: =K16+L5 -> 248.71371 | ... AT16: =AS16+AT5 -> 2673.7357
C17: =SUM(C15:C16) -> 4926.7148 | D17: =SUM(D15:D16) -> 0 | E17: =SUM(E15:E16) -> 0 | F17: =SUM(F15:F16) -> 15.139238 | G17: =SUM(G15:G16) -> 45.417713 | H17: =SUM(H15:H16) -> 110.04537 | I17: =SUM(I15:I16) -> 209.02221 | J17: =SUM(J15:J16) -> 329.64873 | ... AT17: =SUM(AT15:AT16) -> 4926.7148
B19: Project | C19: Total Sales NPV | D19: M 3 | E19: M 6 | F19: M 9 | G19: M 12 | H19: M 15 | I19: M 18 | J19: M 21 | K19: M 24 | L19: M 27 | M19: M 30 | N19: M 33 | O19: M 36 | P19: M 39 | Q19: M 42 | R19: M 45 | S19: M 48 | T19: M 51 | U19: M 54 | V19: M 57 | W19: M 60 | X19: M 63 | Y19: M 66 | Z19: M 69 | AA19: M 72 | AB19: M 75 | AC19: M 78 | AD19: M 81 | AE19: M 84 | AF19: M 87 | AG19: M 90 | AH19: M 93 | AI19: M 96 | AJ19: M 99 | AK19: M 102 | AL19: M 105 | AM19: M 108 | AN19: M 111 | AO19: M 114 | AP19: M 117 | AQ19: M 120 | AR19: M 123 | AS19: M 126 | AT19: M 129
B20: Green Square | C20: =MAX(D20:ZZ20) -> 1416.8308 | D20: =D9 -> 0 | E20: =D20+E9 -> 0 | F20: =E20+F9 -> 13.722251 | G20: =F20+G9 -> 40.282317 | H20: =G20+H9 -> 79.767487 | I20: =H20+I9 -> 131.31712 | J20: =I20+J9 -> 180.90349 | K20: =J20+K9 -> 229.74433 | L20: =K20+L9 -> 289.56285 | ... AT20: =AS20+AT9 -> 1416.8308
B21: L'avenir | C21: =MAX(D21:ZZ21) -> 1549.3963 | D21: =D10 -> 0 | E21: =D21+E10 -> 0 | F21: =E21+F10 -> 0 | G21: =F21+G10 -> 0 | H21: =G21+H10 -> 15.378814 | I21: =H21+I10 -> 45.145237 | J21: =I21+J10 -> 91.46786 | K21: =J21+K10 -> 144.57527 | L21: =K21+L10 -> 194.53338 | ... AT21: =AS21+AT10 -> 1549.3963
C22: =SUM(C20:C21) -> 2966.2271 | D22: =SUM(D20:D21) -> 0 | E22: =SUM(E20:E21) -> 0 | F22: =SUM(F20:F21) -> 13.722251 | G22: =SUM(G20:G21) -> 40.282317 | H22: =SUM(H20:H21) -> 95.146301 | I22: =SUM(I20:I21) -> 176.46236 | J22: =SUM(J20:J21) -> 272.37135 | ... AT22: =SUM(AT20:AT21) -> 2966.2271
B27: 100% Sales
B28: Project | C28: Total Sales | D28: M 3 | E28: M 6 | F28: M 9 | G28: M 12 | H28: M 15 | I28: M 18 | J28: M 21 | K28: M 24 | L28: M 27 | M28: M 30 | N28: M 33 | O28: M 36 | P28: M 39 | Q28: M 42 | R28: M 45 | S28: M 48 | T28: M 51 | U28: M 54 | V28: M 57 | W28: M 60 | X28: M 63 | Y28: M 66 | Z28: M 69 | AA28: M 72 | AB28: M 75 | AC28: M 78 | AD28: M 81 | AE28: M 84 | AF28: M 87 | AG28: M 90 | AH28: M 93 | AI28: M 96 | AJ28: M 99 | AK28: M 102 | AL28: M 105 | AM28: M 108 | AN28: M 111 | AO28: M 114 | AP28: M 117 | AQ28: M 120 | AR28: M 123 | AS28: M 126 | AT28: M 129
B29: Green Square | C29: =SUM(D29:ZZ29) -> 2816.2238 | D29: =D4*100/80 -> 0 | E29: =E4*100/80 -> 0 | F29: =F4*100/80 -> 18.924047 | G29: =G4*100/80 -> 37.848094 | H29: =H4*100/80 -> 58.140008 | I29: =I4*100/80 -> 78.431922 | J29: =J4*100/80 -> 77.957125 | K29: =K4*100/80 -> 79.341949 | ... AT29: =AT4*100/80 -> 0
B30: L'avenir | C30: =SUM(D30:ZZ30) -> 3342.1697 | D30: =D5*100/80 -> 0 | E30: =E5*100/80 -> 0 | F30: =F5*100/80 -> 0 | G30: =G5*100/80 -> 0 | H30: =H5*100/80 -> 22.644562 | I30: =I5*100/80 -> 45.289125 | J30: =J5*100/80 -> 72.826031 | K30: =K5*100/80 -> 86.272987 | ... AT30: =AT5*100/80 -> 0
C31: =SUM(C29:C30) -> 6158.3934 | D31: =SUM(D29:D30) -> 0 | E31: =SUM(E29:E30) -> 0 | F31: =SUM(F29:F30) -> 18.924047 | G31: =SUM(G29:G30) -> 37.848094 | H31: =SUM(H29:H30) -> 80.78457 | I31: =SUM(I29:I30) -> 123.72105 | J31: =SUM(J29:J30) -> 150.78316 | ... AT31: =SUM(AT29:AT30) -> 0
B35: ALAHLY - SABBOUR % | D35: 0.35
B36: Project | C36: Total Sales | D36: M 3 | E36: M 6 | F36: M 9 | G36: M 12 | H36: M 15 | I36: M 18 | J36: M 21 | K36: M 24 | L36: M 27 | M36: M 30 | N36: M 33 | O36: M 36 | P36: M 39 | Q36: M 42 | R36: M 45 | S36: M 48 | T36: M 51 | U36: M 54 | V36: M 57 | W36: M 60 | X36: M 63 | Y36: M 66 | Z36: M 69 | AA36: M 72 | AB36: M 75 | AC36: M 78 | AD36: M 81 | AE36: M 84 | AF36: M 87 | AG36: M 90 | AH36: M 93 | AI36: M 96 | AJ36: M 99 | AK36: M 102 | AL36: M 105 | AM36: M 108 | AN36: M 111 | AO36: M 114 | AP36: M 117 | AQ36: M 120 | AR36: M 123 | AS36: M 126 | AT36: M 129
B37: Green Square | C37: =SUM(D37:ZZ37) -> 985.67831 | D37: =D29*$D$35 -> 0 | E37: =E29*$D$35 -> 0 | F37: =F29*$D$35 -> 6.6234164 | G37: =G29*$D$35 -> 13.246833 | H37: =H29*$D$35 -> 20.349003 | I37: =I29*$D$35 -> 27.451173 | J37: =J29*$D$35 -> 27.284994 | K37: =K29*$D$35 -> 27.769682 | ... AT37: =AT29*$D$35 -> 0
B38: L'avenir | C38: =SUM(D38:ZZ38) -> 1169.7594 | D38: =D30*$D$35 -> 0 | E38: =E30*$D$35 -> 0 | F38: =F30*$D$35 -> 0 | G38: =G30*$D$35 -> 0 | H38: =H30*$D$35 -> 7.9255969 | I38: =I30*$D$35 -> 15.851194 | J38: =J30*$D$35 -> 25.489111 | K38: =K30*$D$35 -> 30.195546 | ... AT38: =AT30*$D$35 -> 0
C39: =SUM(C37:C38) -> 2155.4377 | D39: =SUM(D37:D38) -> 0 | E39: =SUM(E37:E38) -> 0 | F39: =SUM(F37:F38) -> 6.6234164 | G39: =SUM(G37:G38) -> 13.246833 | H39: =SUM(H37:H38) -> 28.2746 | I39: =SUM(I37:I38) -> 43.302366 | J39: =SUM(J37:J38) -> 52.774105 | ... AT39: =SUM(AT37:AT38) -> 0
B41: ALAHLY - SABBOUR ACCUM
B42: Project | C42: Total Sales | D42: M 3 | E42: M 6 | F42: M 9 | G42: M 12 | H42: M 15 | I42: M 18 | J42: M 21 | K42: M 24 | L42: M 27 | M42: M 30 | N42: M 33 | O42: M 36 | P42: M 39 | Q42: M 42 | R42: M 45 | S42: M 48 | T42: M 51 | U42: M 54 | V42: M 57 | W42: M 60 | X42: M 63 | Y42: M 66 | Z42: M 69 | AA42: M 72 | AB42: M 75 | AC42: M 78 | AD42: M 81 | AE42: M 84 | AF42: M 87 | AG42: M 90 | AH42: M 93 | AI42: M 96 | AJ42: M 99 | AK42: M 102 | AL42: M 105 | AM42: M 108 | AN42: M 111 | AO42: M 114 | AP42: M 117 | AQ42: M 120 | AR42: M 123 | AS42: M 126 | AT42: M 129
B43: Green Square | C43: =MAX(D43:ZZ43) -> 985.67831 | D43: =D37 -> 0 | E43: =D43+E37 -> 0 | F43: =E43+F37 -> 6.6234164 | G43: =F43+G37 -> 19.870249 | H43: =G43+H37 -> 40.219252 | I43: =H43+I37 -> 67.670425 | J43: =I43+J37 -> 94.955418 | K43: =J43+K37 -> 122.7251 | L43: =K43+L37 -> 157.86897 | ... AT43: =AS43+AT37 -> 985.67831
B44: L'avenir | C44: =MAX(D44:ZZ44) -> 1169.7594 | D44: =D38 -> 0 | E44: =D44+E38 -> 0 | F44: =E44+F38 -> 0 | G44: =F44+G38 -> 0 | H44: =G44+H38 -> 7.9255969 | I44: =H44+I38 -> 23.776791 | J44: =I44+J38 -> 49.265902 | K44: =J44+K38 -> 79.461447 | L44: =K44+L38 -> 108.81225 | ... AT44: =AS44+AT38 -> 1169.7594
C45: =SUM(C43:C44) -> 2155.4377 | D45: =SUM(D43:D44) -> 0 | E45: =SUM(E43:E44) -> 0 | F45: =SUM(F43:F44) -> 6.6234164 | G45: =SUM(G43:G44) -> 19.870249 | H45: =SUM(H43:H44) -> 48.144849 | I45: =SUM(I43:I44) -> 91.447215 | J45: =SUM(J43:J44) -> 144.22132 | ... AT45: =SUM(AT43:AT44) -> 2155.4377

Sheet Green Square
A1: GREEN SQUARE
B2: BUA (M²) | C2: RETAINED% | D2: Total | E2: M 3 | F2: M 6 | G2: M 9 | H2: M 12 | I2: M 15 | J2: M 18 | K2: M 21 | L2: M 24 | M2: M 27 | N2: M 30 | O2: M 33 | P2: M 36 | Q2: M 39 | R2: M 42 | S2: M 45 | T2: M 48 | U2: M 51 | V2: M 54 | W2: M 57 | X2: M 60 | Y2: M 63 | Z2: M 66 | AA2: M 69 | AB2: M 72 | AC2: M 75 | AD2: M 78 | AE2: M 81 | AF2: M 84 | AG2: M 87 | AH2: M 90 | AI2: M 93 | AJ2: M 96 | AK2: M 99 | AL2: M 102 | AM2: M 105 | AN2: M 108 | AO2: M 111 | AP2: M 114
A3: COMMERCIAL PRICE | E3: 200 | F3: 200 | G3: 225 | H3: 225 | I3: 250 | J3: 250 | K3: 275 | L3: 275 | M3: 300 | N3: 300 | O3: 300 | P3: 300 | Q3: 300 | R3: 300 | S3: 300 | T3: 300
A4: ADMIN PRICE | E4: 125 | F4: 125 | G4: 135 | H4: 135 | I4: 160 | J4: 160 | K4: 180 | L4: 180 | M4: 200 | N4: 200 | O4: 200 | P4: 200 | Q4: 200 | R4: 200 | S4: 200 | T4: 200
A5: DELIVERY DATE(month) | C5: 36 | E5: =IF(C5-3<0,0,C5-3) -> 33 | F5: =IF(E5-3<0,0,E5-3) -> 30 | G5: =IF(F5-3<0,0,F5-3) -> 27 | H5: =IF(G5-3<0,0,G5-3) -> 24 | I5: =IF(H5-3<0,0,H5-3) -> 21 | J5: =IF(I5-3<0,0,I5-3) -> 18 | K5: =IF(J5-3<0,0,J5-3) -> 15 | L5: =IF(K5-3<0,0,K5-3) -> 12 | M5: =IF(L5-3<0,0,L5-3) -> 9 | ... T5: =IF(S5-3<0,0,S5-3) -> 0
A6: TARGET SALES % COMM. | B6: 4341 | C6: 20 | G6: 10 | H6: 10 | I6: 7 | J6: 7 | K6: 7 | L6: 7 | M6: 7 | N6: 10 | O6: 10 | P6: 5 | Q6: 0 | R6: 0 | S6: 0 | T6: 0 | U6: 0 | V6: 0
A7: TARGET SALES % ADMIN | B7: 10129 | C7: 20 | G7: 15 | H7: 15 | I7: 10 | J7: 10 | K7: 5 | L7: 5 | M7: 5 | N7: 5 | O7: 5 | P7: 5 | Q7: 0 | R7: 0 | S7: 0 | T7: 0 | U7: 0 | V7: 0
A8: INSTALLMENTS (YRS) | G8: 8 | H8: 8 | I8: 8 | J8: 6 | K8: 6 | L8: 4 | M8: 4 | N8: 3 | O8: 3 | P8: 2 | Q8: 2 | R8: 2 | S8: 0 | T8: 0 | U8: 0 | V8: 0
A10: DOWN PAYMENT % | G10: 5 | H10: 5 | I10: 10 | J10: 10 | K10: 10 | L10: 10 | M10: 15 | N10: 15 | O10: 20 | P10: 20 | Q10: 20 | R10: 20 | S10: 20 | T10: 20 | U10: 20 | V10: 20
A11: 3 MONTHS % | G11: 5 | H11: 5 | I11: 10 | J11: 10 | K11: 10 | L11: 10 | M11: 15 | N11: 15 | O11: 20 | P11: 20 | Q11: 20 | R11: 20 | S11: 20 | T11: 20 | U11: 20 | V11: 20
A12: DELIVERY PAYMENT % | G12: 20 | H12: 20 | I12: 20 | J12: 20 | K12: 20 | L12: 20 | M12: 25 | N12: 25 | O12: 25 | P12: 25 | Q12: 25 | R12: 25 | S12: 25 | T12: 25 | U12: 25 | V12: 25
A14: YEAR 1 (4Q) % | G14: 10 | H14: 10 | I14: 10 | J14: 12.5 | K14: 12.5 | L14: 12.5 | M14: 15 | N14: 15 | O14: 15 | P14: 17.5 | Q14: 17.5 | R14: 17.5 | S14: 15 | T14: 15 | U14: 17.5 | V14: 17.5
A15: YEAR 2 (4Q) % | G15: 10 | H15: 10 | I15: 10 | J15: 12.5 | K15: 12.5 | L15: 12.5 | M15: 15 | N15: 15 | O15: 10 | P15: 17.5 | Q15: 17.5 | R15: 17.5 | S15: 10 | T15: 10 | U15: 17.5 | V15: 17.5
A16: YEAR 3 (4Q) % | G16: 10 | H16: 10 | I16: 10 | J16: 7 | K16: 7 | L16: 12.5 | M16: 7.5 | N16: 7.5 | O16: 10 | P16: 0 | Q16: 0 | R16: 0 | S16: 10 | T16: 10 | U16: 0 | V16: 0
A17: YEAR 4 (4Q) % | G17: 8 | H17: 8 | I17: 6 | J17: 7 | K17: 7 | L17: 12.5 | M17: 7.5 | N17: 7.5 | O17: 0 | P17: 0 | Q17: 0 | R17: 0 | S17: 0 | T17: 0 | U17: 0 | V17: 0
A18: YEAR 5 (4Q) % | G18: 8 | H18: 8 | I18: 6 | J18: 7 | K18: 7 | L18: 5 | M18: 0 | N18: 0 | O18: 0 | P18: 0 | Q18: 0 | R18: 0 | S18: 0 | T18: 0 | U18: 0 | V18: 0
A19: YEAR 6 (4Q) % | G19: 8 | H19: 8 | I19: 6 | J19: 7 | K19: 7 | L19: 5 | M19: 0 | N19: 0 | O19: 0 | P19: 0 | Q19: 0 | R19: 0 | S19: 0 | T19: 0 | U19: 0 | V19: 0
A20: YEAR 7 (4Q) % | G20: 8 | H20: 8 | I20: 6 | J20: 7 | K20: 7 | L20: 0 | M20: 0 | N20: 0 | O20: 0 | P20: 0 | Q20: 0 | R20: 0 | S20: 0 | T20: 0 | U20: 0 | V20: 0
A21: YEAR 8 (4Q) % | G21: 8 | H21: 8 | I21: 6 | J21: 0 | K21: 0 | L21: 0 | M21: 0 | N21: 0 | O21: 0 | P21: 0 | Q21: 0 | R21: 0 | S21: 0 | T21: 0 | U21: 0 | V21: 0
A24: Total Sales(COMMERCIAL) | D24: =SUM(E24:T24) -> 931144.5 | E24: =E3*$B$6*(E6/100) -> 0 | F24: =F3*$B$6*(F6/100) -> 0 | G24: =G3*$B$6*(G6/100) -> 97672.5 | H24: =H3*$B$6*(H6/100) -> 97672.5 | I24: =I3*$B$6*(I6/100) -> 75967.5 | J24: =J3*$B$6*(J6/100) -> 75967.5 | K24: =K3*$B$6*(K6/100) -> 83564.25 | L24: =L3*$B$6*(L6/100) -> 83564.25 | ... T24: =T3*$B$6*(T6/100) -> 0
A25: Total Sales (ADMIN) | D25: =SUM(E25:T25) -> 1321834.5 | E25: =E4*$B$7*(E7/100) -> 0 | F25: =F4*$B$7*(F7/100) -> 0 | G25: =G4*$B$7*(G7/100) -> 205112.25 | H25: =H4*$B$7*(H7/100) -> 205112.25 | I25: =I4*$B$7*(I7/100) -> 162064 | J25: =J4*$B$7*(J7/100) -> 162064 | K25: =K4*$B$7*(K7/100) -> 91161 | L25: =L4*$B$7*(L7/100) -> 91161 | ... T25: =T4*$B$7*(T7/100) -> 0
A26: Total Sales | D26: =SUM(D24:D25) -> 2252979 | E26: =SUM(E24:E25) -> 0 | F26: =SUM(F24:F25) -> 0 | G26: =SUM(G24:G25) -> 302784.75 | H26: =SUM(H24:H25) -> 302784.75 | I26: =SUM(I24:I25) -> 238031.5 | J26: =SUM(J24:J25) -> 238031.5 | K26: =SUM(K24:K25) -> 174725.25 | ... T26: =SUM(T24:T25) -> 0
E27: =C27+E26 -> 0 | F27: =E27+F26 -> 0 | G27: =F27+G26 -> 302784.75 | H27: =G27+H26 -> 605569.5 | I27: =H27+I26 -> 843601 | J27: =I27+J26 -> 1081632.5 | K27: =J27+K26 -> 1256357.8 | L27: =K27+L26 -> 1431083 | M27: =L27+M26 -> 1623534 | ... O27: =N27+O26 -> 2086574 | P27: =N27+P26 -> 2021459 | Q27: =O27+Q26 -> 2086574 | R27: =P27+R26 -> 2021459 | S27: =Q27+S26 -> 2086574 | T27: =R27+T26 -> 2021459
D29: Total | E29: M 3 | F29: M 6 | G29: M 9 | H29: M 12 | I29: M 15 | J29: M 18 | K29: M 21 | L29: M 24 | M29: M 27 | N29: M 30 | O29: M 33 | P29: M 36 | Q29: M 39 | R29: M 42 | S29: M 45 | T29: M 48 | U29: M 51 | V29: M 54 | W29: M 57 | X29: M 60 | Y29: M 63 | Z29: M 66 | AA29: M 69 | AB29: M 72 | AC29: M 75 | AD29: M 78 | AE29: M 81 | AF29: M 84 | AG29: M 87 | AH29: M 90 | AI29: M 93 | AJ29: M 96 | AK29: M 99 | AL29: M 102 | AM29: M 105 | AN29: M 108
A30: Bulk Payments
A31: DOWN PAYMENT (COMMERCIAL) | D31: =SUM(E31:AZ31) -> 113951.25 | E31: =E3*$B$6*(E6/100)*E10/100 -> 0 | F31: =F3*$B$6*(F6/100)*F10/100 -> 0 | G31: =G3*$B$6*(G6/100)*G10/100 -> 4883.625 | H31: =H3*$B$6*(H6/100)*H10/100 -> 4883.625 | I31: =I3*$B$6*(I6/100)*I10/100 -> 7596.75 | J31: =J3*$B$6*(J6/100)*J10/100 -> 7596.75 | K31: =K3*$B$6*(K6/100)*K10/100 -> 8356.425 | L31: =L3*$B$6*(L6/100)*L10/100 -> 8356.425 | ... V31: =V3*$B$6*(V6/100)*V10/100 -> 0
A32: DOWN PAYMENT (ADMIN) | D32: =SUM(E32:AZ32) -> 142059.23 | E32: =E4*$B$7*(E7/100)*E10/100 -> 0 | F32: =F4*$B$7*(F7/100)*F10/100 -> 0 | G32: =G4*$B$7*(G7/100)*G10/100 -> 10255.612 | H32: =H4*$B$7*(H7/100)*H10/100 -> 10255.612 | I32: =I4*$B$7*(I7/100)*I10/100 -> 16206.4 | J32: =J4*$B$7*(J7/100)*J10/100 -> 16206.4 | K32: =K4*$B$7*(K7/100)*K10/100 -> 9116.1 | L32: =L4*$B$7*(L7/100)*L10/100 -> 9116.1 | ... V32: =V4*$B$7*(V7/100)*V10/100 -> 0
A33: 3 MONTHS (COMMERCIAL) | D33: =SUM(E33:AZ33) -> 113951.25 | F33: =E31 -> 0 | G33: =F31 -> 0 | H33: =G31 -> 4883.625 | I33: =H31 -> 4883.625 | J33: =I31 -> 7596.75 | K33: =J31 -> 7596.75 | L33: =K31 -> 8356.425 | M33: =L31 -> 8356.425 | ... V33: =U31 -> 0
A34: 3 MONTHS (ADMIN) | D34: =SUM(E34:AZ34) -> 142059.23 | F34: =E32 -> 0 | G34: =F32 -> 0 | H34: =G32 -> 10255.612 | I34: =H32 -> 10255.612 | J34: =I32 -> 16206.4 | K34: =J32 -> 16206.4 | L34: =K32 -> 9116.1 | M34: =L32 -> 9116.1 | ... V34: =U32 -> 0
A35: DELIVERY PAYMENT (COMMERCIAL) | D35: =SUM(E35:AZ35) -> 207065.7 | N35: =SUM(E85:N85) -> 158229.45 | O35: =SUM(O85) -> 32557.5 | P35: =SUM(P85) -> 16278.75 | Q35: =SUM(Q85) -> 0 | R35: =SUM(R85) -> 0 | S35: =SUM(S85) -> 0 | T35: =SUM(T85) -> 0 | U35: =SUM(U85) -> 0 | V35: =SUM(V85) -> 0
A36: DELIVERY PAYMENT (ADMIN) | D36: =SUM(E36:AZ36) -> 284624.9 | N36: =SUM(E86:N86) -> 233979.9 | O36: =SUM(O86) -> 25322.5 | P36: =SUM(P86) -> 25322.5 | Q36: =SUM(Q86) -> 0 | R36: =SUM(R86) -> 0 | S36: =SUM(S86) -> 0 | T36: =SUM(T86) -> 0 | U36: =SUM(U86) -> 0 | V36: =SUM(V86) -> 0
A37: Instalments | D37: =SUM(E37:AZ37) -> 0
A38: MONTH 3 (COMMERCIAL) | D38: =SUM(E38:AZ38) -> 0 | G38: =$E$24*$E$14/100/4 -> 0 | H38: =$E$24*$E$14/100/4 -> 0 | I38: =$E$24*$E$14/100/4 -> 0 | J38: =$E$24*$E$14/100/4 -> 0 | K38: =$E$24*$E$15/100/4 -> 0 | L38: =$E$24*$E$15/100/4 -> 0 | M38: =$E$24*$E$15/100/4 -> 0 | N38: =$E$24*$E$15/100/4 -> 0 | O38: =$E$24*$E$16/100/4 -> 0 | P38: =$E$24*$E$16/100/4 -> 0 | Q38: =$E$24*$E$16/100/4 -> 0 | R38: =$E$24*$E$16/100/4 -> 0 | S38: =$E$24*$E$17/100/4 -> 0 | T38: =$E$24*$E$17/100/4 -> 0 | U38: =$E$24*$E$17/100/4 -> 0 | V38: =$E$24*$E$17/100/4 -> 0 | W38: =$E$24*$E$18/100/4 -> 0 | X38: =$E$24*$E$18/100/4 -> 0 | Y38: =$E$24*$E$18/100/4 -> 0 | Z38: =$E$24*$E$18/100/4 -> 0 | AA38: =$E$24*$E$19/100/4 -> 0 | AB38: =$E$24*$E$19/100/4 -> 0 | AC38: =$E$24*$E$19/100/4 -> 0 | AD38: =$E$24*$E$19/100/4 -> 0 | AE38: =$E$24*$E$20/100/4 -> 0 | AF38: =$E$24*$E$20/100/4 -> 0 | AG38: =$E$24*$E$20/100/4 -> 0 | AH38: =$E$24*$E$20/100/4 -> 0 | AI38: =$E$24*$E$21/100/4 -> 0 | AJ38: =$E$24*$E$21/100/4 -> 0 | AK38: =$E$24*$E$21/100/4 -> 0 | AL38: =$E$24*$E$21/100/4 -> 0
A39: MONTH 3 (ADMIN) | D39: =SUM(E39:AZ39) -> 0 | G39: =$E$25*$E$14/100/4 -> 0 | H39: =$E$25*$E$14/100/4 -> 0 | I39: =$E$25*$E$14/100/4 -> 0 | J39: =$E$25*$E$14/100/4 -> 0 | K39: =$E$25*$E$15/100/4 -> 0 | L39: =$E$25*$E$15/100/4 -> 0 | M39: =$E$25*$E$15/100/4 -> 0 | N39: =$E$25*$E$15/100/4 -> 0 | O39: =$E$25*$E$16/100/4 -> 0 | P39: =$E$25*$E$16/100/4 -> 0 | Q39: =$E$25*$E$16/100/4 -> 0 | R39: =$E$25*$E$16/100/4 -> 0 | S39: =$E$25*$E$17/100/4 -> 0 | T39: =$E$25*$E$17/100/4 -> 0 | U39: =$E$25*$E$17/100/4 -> 0 | V39: =$E$25*$E$17/100/4 -> 0 | W39: =$E$25*$E$18/100/4 -> 0 | X39: =$E$25*$E$18/100/4 -> 0 | Y39: =$E$25*$E$18/100/4 -> 0 | Z39: =$E$25*$E$18/100/4 -> 0 | AA39: =$E$25*$E$19/100/4 -> 0 | AB39: =$E$25*$E$19/100/4 -> 0 | AC39: =$E$25*$E$19/100/4 -> 0 | AD39: =$E$25*$E$19/100/4 -> 0 | AE39: =$E$25*$E$20/100/4 -> 0 | AF39: =$E$25*$E$20/100/4 -> 0 | AG39: =$E$25*$E$20/100/4 -> 0 | AH39: =$E$25*$E$20/100/4 -> 0 | AI39: =$E$25*$E$21/100/4 -> 0 | AJ39: =$E$25*$E$21/100/4 -> 0 | AK39: =$E$25*$E$21/100/4 -> 0 | AL39: =$E$25*$E$21/100/4 -> 0
A40: MONTH 6 (COMMERCIAL) | D40: =SUM(E40:AZ40) -> 0 | H40: =$F$24*$F$14/100/4 -> 0 | I40: =$F$24*$F$14/100/4 -> 0 | J40: =$F$24*$F$14/100/4 -> 0 | K40: =$F$24*$F$14/100/4 -> 0 | L40: =$F$24*$F$15/100/4 -> 0 | M40: =$F$24*$F$15/100/4 -> 0 | N40: =$F$24*$F$15/100/4 -> 0 | O40: =$F$24*$F$15/100/4 -> 0 | P40: =$F$24*$F$16/100/4 -> 0 | Q40: =$F$24*$F$16/100/4 -> 0 | R40: =$F$24*$F$16/100/4 -> 0 | S40: =$F$24*$F$16/100/4 -> 0 | T40: =$F$24*$F$17/100/4 -> 0 | U40: =$F$24*$F$17/100/4 -> 0 | V40: =$F$24*$F$17/100/4 -> 0 | W40: =$F$24*$F$17/100/4 -> 0 | X40: =$F$24*$F$18/100/4 -> 0 | Y40: =$F$24*$F$18/100/4 -> 0 | Z40: =$F$24*$F$18/100/4 -> 0 | AA40: =$F$24*$F$18/100/4 -> 0 | AB40: =$F$24*$F$19/100/4 -> 0 | AC40: =$F$24*$F$19/100/4 -> 0 | AD40: =$F$24*$F$19/100/4 -> 0 | AE40: =$F$24*$F$19/100/4 -> 0 | AF40: =$F$24*$F$20/100/4 -> 0 | AG40: =$F$24*$F$20/100/4 -> 0 | AH40: =$F$24*$F$20/100/4 -> 0 | AI40: =$F$24*$F$20/100/4 -> 0 | AJ40: =$F$24*$F$21/100/4 -> 0 | AK40: =$F$24*$F$21/100/4 -> 0 | AL40: =$F$24*$F$21/100/4 -> 0 | AM40: =$F$24*$F$21/100/4 -> 0
A41: MONTH 6 (ADMIN) | D41: =SUM(E41:AZ41) -> 0 | H41: =$F$25*$F$14/100/4 -> 0 | I41: =$F$25*$F$14/100/4 -> 0 | J41: =$F$25*$F$14/100/4 -> 0 | K41: =$F$25*$F$14/100/4 -> 0 | L41: =$F$25*$F$15/100/4 -> 0 | M41: =$F$25*$F$15/100/4 -> 0 | N41: =$F$25*$F$15/100/4 -> 0 | O41: =$F$25*$F$15/100/4 -> 0 | P41: =$F$25*$F$16/100/4 -> 0 | Q41: =$F$25*$F$16/100/4 -> 0 | R41: =$F$25*$F$16/100/4 -> 0 | S41: =$F$25*$F$16/100/4 -> 0 | T41: =$F$25*$F$17/100/4 -> 0 | U41: =$F$25*$F$17/100/4 -> 0 | V41: =$F$25*$F$17/100/4 -> 0 | W41: =$F$25*$F$17/100/4 -> 0 | X41: =$F$25*$F$18/100/4 -> 0 | Y41: =$F$25*$F$18/100/4 -> 0 | Z41: =$F$25*$F$18/100/4 -> 0 | AA41: =$F$25*$F$18/100/4 -> 0 | AB41: =$F$25*$F$19/100/4 -> 0 | AC41: =$F$25*$F$19/100/4 -> 0 | AD41: =$F$25*$F$19/100/4 -> 0 | AE41: =$F$25*$F$19/100/4 -> 0 | AF41: =$F$25*$F$20/100/4 -> 0 | AG41: =$F$25*$F$20/100/4 -> 0 | AH41: =$F$25*$F$20/100/4 -> 0 | AI41: =$F$25*$F$20/100/4 -> 0 | AJ41: =$F$25*$F$21/100/4 -> 0 | AK41: =$F$25*$F$21/100/4 -> 0 | AL41: =$F$25*$F$21/100/4 -> 0 | AM41: =$F$25*$F$21/100/4 -> 0
A42: MONTH 9 (COMMERCIAL) | D42: =SUM(E42:AZ42) -> 68370.75 | I42: =$G$24*$G$14/100/4 -> 2441.8125 | J42: =$G$24*$G$14/100/4 -> 2441.8125 | K42: =$G$24*$G$14/100/4 -> 2441.8125 | L42: =$G$24*$G$14/100/4 -> 2441.8125 | M42: =$G$24*$G$15/100/4 -> 2441.8125 | N42: =$G$24*$G$15/100/4 -> 2441.8125 | O42: =$G$24*$G$15/100/4 -> 2441.8125 | P42: =$G$24*$G$15/100/4 -> 2441.8125 | Q42: =$G$24*$G$16/100/4 -> 2441.8125 | R42: =$G$24*$G$16/100/4 -> 2441.8125 | S42: =$G$24*$G$16/100/4 -> 2441.8125 | T42: =$G$24*$G$16/100/4 -> 2441.8125 | U42: =$G$24*$G$17/100/4 -> 1953.45 | V42: =$G$24*$G$17/100/4 -> 1953.45 | W42: =$G$24*$G$17/100/4 -> 1953.45 | X42: =$G$24*$G$17/100/4 -> 1953.45 | Y42: =$G$24*$G$18/100/4 -> 1953.45 | Z42: =$G$24*$G$18/100/4 -> 1953.45 | AA42: =$G$24*$G$18/100/4 -> 1953.45 | AB42: =$G$24*$G$18/100/4 -> 1953.45 | AC42: =$G$24*$G$19/100/4 -> 1953.45 | AD42: =$G$24*$G$19/100/4 -> 1953.45 | AE42: =$G$24*$G$19/100/4 -> 1953.45 | AF42: =$G$24*$G$19/100/4 -> 1953.45 | AG42: =$G$24*$G$20/100/4 -> 1953.45 | AH42: =$G$24*$G$20/100/4 -> 1953.45 | AI42: =$G$24*$G$20/100/4 -> 1953.45 | AJ42: =$G$24*$G$20/100/4 -> 1953.45 | AK42: =$G$24*$G$21/100/4 -> 1953.45 | AL42: =$G$24*$G$21/100/4 -> 1953.45 | AM42: =$G$24*$G$21/100/4 -> 1953.45 | AN42: =$G$24*$G$21/100/4 -> 1953.45
A43: MONTH 9 (ADMIN) | D43: =SUM(E43:AZ43) -> 143578.58 | I43: =$G$25*$G$14/100/4 -> 5127.8062 | J43: =$G$25*$G$14/100/4 -> 5127.8062 | K43: =$G$25*$G$14/100/4 -> 5127.8062 | L43: =$G$25*$G$14/100/4 -> 5127.8062 | M43: =$G$25*$G$15/100/4 -> 5127.8062 | N43: =$G$25*$G$15/100/4 -> 5127.8062 | O43: =$G$25*$G$15/100/4 -> 5127.8062 | P43: =$G$25*$G$15/100/4 -> 5127.8062 | Q43: =$G$25*$G$16/100/4 -> 5127.8062 | R43: =$G$25*$G$16/100/4 -> 5127.8062 | S43: =$G$25*$G$16/100/4 -> 5127.8062 | T43: =$G$25*$G$16/100/4 -> 5127.8062 | U43: =$G$25*$G$17/100/4 -> 4102.245 | V43: =$G$25*$G$17/100/4 -> 4102.245 | W43: =$G$25*$G$17/100/4 -> 4102.245 | X43: =$G$25*$G$17/100/4 -> 4102.245 | Y43: =$G$25*$G$18/100/4 -> 4102.245 | Z43: =$G$25*$G$18/100/4 -> 4102.245 | AA43: =$G$25*$G$18/100/4 -> 4102.245 | AB43: =$G$25*$G$18/100/4 -> 4102.245 | AC43: =$G$25*$G$19/100/4 -> 4102.245 | AD43: =$G$25*$G$19/100/4 -> 4102.245 | AE43: =$G$25*$G$19/100/4 -> 4102.245 | AF43: =$G$25*$G$19/100/4 -> 4102.245 | AG43: =$G$25*$G$20/100/4 -> 4102.245 | AH43: =$G$25*$G$20/100/4 -> 4102.245 | AI43: =$G$25*$G$20/100/4 -> 4102.245 | AJ43: =$G$25*$G$20/100/4 -> 4102.245 | AK43: =$G$25*$G$21/100/4 -> 4102.245 | AL43: =$G$25*$G$21/100/4 -> 4102.245 | AM43: =$G$25*$G$21/100/4 -> 4102.245 | AN43: =$G$25*$G$21/100/4 -> 4102.245
A44: MONTH 12 (COMMERCIAL) | D44: =SUM(E44:AZ44) -> 68370.75 | J44: =$H$24*$H$14/100/4 -> 2441.8125 | K44: =$H$24*$H$14/100/4 -> 2441.8125 | L44: =$H$24*$H$14/100/4 -> 2441.8125 | M44: =$H$24*$H$14/100/4 -> 2441.8125 | N44: =$H$24*$H$15/100/4 -> 2441.8125 | O44: =$H$24*$H$15/100/4 -> 2441.8125 | P44: =$H$24*$H$15/100/4 -> 2441.8125 | Q44: =$H$24*$H$15/100/4 -> 2441.8125 | R44: =$H$24*$H$16/100/4 -> 2441.8125 | S44: =$H$24*$H$16/100/4 -> 2441.8125 | T44: =$H$24*$H$16/100/4 -> 2441.8125 | U44: =$H$24*$H$16/100/4 -> 2441.8125 | V44: =$H$24*$H$17/100/4 -> 1953.45 | W44: =$H$24*$H$17/100/4 -> 1953.45 | X44: =$H$24*$H$17/100/4 -> 1953.45 | Y44: =$H$24*$H$17/100/4 -> 1953.45 | Z44: =$H$24*$H$18/100/4 -> 1953.45 | AA44: =$H$24*$H$18/100/4 -> 1953.45 | AB44: =$H$24*$H$18/100/4 -> 1953.45 | AC44: =$H$24*$H$18/100/4 -> 1953.45 | AD44: =$H$24*$H$19/100/4 -> 1953.45 | AE44: =$H$24*$H$19/100/4 -> 1953.45 | AF44: =$H$24*$H$19/100/4 -> 1953.45 | AG44: =$H$24*$H$19/100/4 -> 1953.45 | AH44: =$H$24*$H$20/100/4 -> 1953.45 | AI44: =$H$24*$H$20/100/4 -> 1953.45 | AJ44: =$H$24*$H$20/100/4 -> 1953.45 | AK44: =$H$24*$H$20/100/4 -> 1953.45 | AL44: =$H$24*$H$21/100/4 -> 1953.45 | AM44: =$H$24*$H$21/100/4 -> 1953.45 | AN44: =$H$24*$H$21/100/4 -> 1953.45 | AO44: =$H$24*$H$21/100/4 -> 1953.45
A45: MONTH 12 (ADMIN) | D45: =SUM(E45:AZ45) -> 143578.58 | J45: =$H$25*$H$14/100/4 -> 5127.8062 | K45: =$H$25*$H$14/100/4 -> 5127.8062 | L45: =$H$25*$H$14/100/4 -> 5127.8062 | M45: =$H$25*$H$14/100/4 -> 5127.8062 | N45: =$H$25*$H$15/100/4 -> 5127.8062 | O45: =$H$25*$H$15/100/4 -> 5127.8062 | P45: =$H$25*$H$15/100/4 -> 5127.8062 | Q45: =$H$25*$H$15/100/4 -> 5127.8062 | R45: =$H$25*$H$16/100/4 -> 5127.8062 | S45: =$H$25*$H$16/100/4 -> 5127.8062 | T45: =$H$25*$H$16/100/4 -> 5127.8062 | U45: =$H$25*$H$16/100/4 -> 5127.8062 | V45: =$H$25*$H$17/100/4 -> 4102.245 | W45: =$H$25*$H$17/100/4 -> 4102.245 | X45: =$H$25*$H$17/100/4 -> 4102.245 | Y45: =$H$25*$H$17/100/4 -> 4102.245 | Z45: =$H$25*$H$18/100/4 -> 4102.245 | AA45: =$H$25*$H$18/100/4 -> 4102.245 | AB45: =$H$25*$H$18/100/4 -> 4102.245 | AC45: =$H$25*$H$18/100/4 -> 4102.245 | AD45: =$H$25*$H$19/100/4 -> 4102.245 | AE45: =$H$25*$H$19/100/4 -> 4102.245 | AF45: =$H$25*$H$19/100/4 -> 4102.245 | AG45: =$H$25*$H$19/100/4 -> 4102.245 | AH45: =$H$25*$H$20/100/4 -> 4102.245 | AI45: =$H$25*$H$20/100/4 -> 4102.245 | AJ45: =$H$25*$H$20/100/4 -> 4102.245 | AK45: =$H$25*$H$20/100/4 -> 4102.245 | AL45: =$H$25*$H$21/100/4 -> 4102.245 | AM45: =$H$25*$H$21/100/4 -> 4102.245 | AN45: =$H$25*$H$21/100/4 -> 4102.245 | AO45: =$H$25*$H$21/100/4 -> 4102.245
A46: MONTH 15 (COMMERCIAL) | D46: =SUM(E46:AZ46) -> 45580.5 | K46: =$I$24*$I$14/100/4 -> 1899.1875 | L46: =$I$24*$I$14/100/4 -> 1899.1875 | M46: =$I$24*$I$14/100/4 -> 1899.1875 | N46: =$I$24*$I$14/100/4 -> 1899.1875 | O46: =$I$24*$I$15/100/4 -> 1899.1875 | P46: =$I$24*$I$15/100/4 -> 1899.1875 | Q46: =$I$24*$I$15/100/4 -> 1899.1875 | R46: =$I$24*$I$15/100/4 -> 1899.1875 | S46: =$I$24*$I$16/100/4 -> 1899.1875 | T46: =$I$24*$I$16/100/4 -> 1899.1875 | U46: =$I$24*$I$16/100/4 -> 1899.1875 | V46: =$I$24*$I$16/100/4 -> 1899.1875 | W46: =$I$24*$I$17/100/4 -> 1139.5125 | X46: =$I$24*$I$17/100/4 -> 1139.5125 | Y46: =$I$24*$I$17/100/4 -> 1139.5125 | Z46: =$I$24*$I$17/100/4 -> 1139.5125 | AA46: =$I$24*$I$18/100/4 -> 1139.5125 | AB46: =$I$24*$I$18/100/4 -> 1139.5125 | AC46: =$I$24*$I$18/100/4 -> 1139.5125 | AD46: =$I$24*$I$18/100/4 -> 1139.5125 | AE46: =$I$24*$I$19/100/4 -> 1139.5125 | AF46: =$I$24*$I$19/100/4 -> 1139.5125 | AG46: =$I$24*$I$19/100/4 -> 1139.5125 | AH46: =$I$24*$I$19/100/4 -> 1139.5125 | AI46: =$I$24*$I$20/100/4 -> 1139.5125 | AJ46: =$I$24*$I$20/100/4 -> 1139.5125 | AK46: =$I$24*$I$20/100/4 -> 1139.5125 | AL46: =$I$24*$I$20/100/4 -> 1139.5125 | AM46: =$I$24*$I$21/100/4 -> 1139.5125 | AN46: =$I$24*$I$21/100/4 -> 1139.5125 | AO46: =$I$24*$I$21/100/4 -> 1139.5125 | AP46: =$I$24*$I$21/100/4 -> 1139.5125
A47: MONTH 15 (ADMIN) | D47: =SUM(E47:AZ47) -> 97238.4 | K47: =$I$25*$I$14/100/4 -> 4051.6 | L47: =$I$25*$I$14/100/4 -> 4051.6 | M47: =$I$25*$I$14/100/4 -> 4051.6 | N47: =$I$25*$I$14/100/4 -> 4051.6 | O47: =$I$25*$I$15/100/4 -> 4051.6 | P47: =$I$25*$I$15/100/4 -> 4051.6 | Q47: =$I$25*$I$15/100/4 -> 4051.6 | R47: =$I$25*$I$15/100/4 -> 4051.6 | S47: =$I$25*$I$16/100/4 -> 4051.6 | T47: =$I$25*$I$16/100/4 -> 4051.6 | U47: =$I$25*$I$16/100/4 -> 4051.6 | V47: =$I$25*$I$16/100/4 -> 4051.6 | W47: =$I$25*$I$17/100/4 -> 2430.96 | X47: =$I$25*$I$17/100/4 -> 2430.96 | Y47: =$I$25*$I$17/100/4 -> 2430.96 | Z47: =$I$25*$I$17/100/4 -> 2430.96 | AA47: =$I$25*$I$18/100/4 -> 2430.96 | AB47: =$I$25*$I$18/100/4 -> 2430.96 | AC47: =$I$25*$I$18/100/4 -> 2430.96 | AD47: =$I$25*$I$18/100/4 -> 2430.96 | AE47: =$I$25*$I$19/100/4 -> 2430.96 | AF47: =$I$25*$I$19/100/4 -> 2430.96 | AG47: =$I$25*$I$19/100/4 -> 2430.96 | AH47: =$I$25*$I$19/100/4 -> 2430.96 | AI47: =$I$25*$I$20/100/4 -> 2430.96 | AJ47: =$I$25*$I$20/100/4 -> 2430.96 | AK47: =$I$25*$I$20/100/4 -> 2430.96 | AL47: =$I$25*$I$20/100/4 -> 2430.96 | AM47: =$I$25*$I$21/100/4 -> 2430.96 | AN47: =$I$25*$I$21/100/4 -> 2430.96 | AO47: =$I$25*$I$21/100/4 -> 2430.96 | AP47: =$I$25*$I$21/100/4 -> 2430.96
A48: MONTH 18 (COMMERCIAL) | D48: =SUM(E48:AZ48) -> 45580.5 | L48: =$J$24*$J$14/100/4 -> 2373.9844 | M48: =$J$24*$J$14/100/4 -> 2373.9844 | N48: =$J$24*$J$14/100/4 -> 2373.9844 | O48: =$J$24*$J$14/100/4 -> 2373.9844 | P48: =$J$24*$J$15/100/4 -> 2373.9844 | Q48: =$J$24*$J$15/100/4 -> 2373.9844 | R48: =$J$24*$J$15/100/4 -> 2373.9844 | S48: =$J$24*$J$15/100/4 -> 2373.9844 | T48: =$J$24*$J$16/100/4 -> 1329.4313 | U48: =$J$24*$J$16/100/4 -> 1329.4313 | V48: =$J$24*$J$16/100/4 -> 1329.4313 | W48: =$J$24*$J$16/100/4 -> 1329.4313 | X48: =$J$24*$J$17/100/4 -> 1329.4313 | Y48: =$J$24*$J$17/100/4 -> 1329.4313 | Z48: =$J$24*$J$17/100/4 -> 1329.4313 | AA48: =$J$24*$J$17/100/4 -> 1329.4313 | AB48: =$J$24*$J$18/100/4 -> 1329.4313 | AC48: =$J$24*$J$18/100/4 -> 1329.4313 | AD48: =$J$24*$J$18/100/4 -> 1329.4313 | AE48: =$J$24*$J$18/100/4 -> 1329.4313 | AF48: =$J$24*$J$19/100/4 -> 1329.4313 | AG48: =$J$24*$J$19/100/4 -> 1329.4313 | AH48: =$J$24*$J$19/100/4 -> 1329.4313 | AI48: =$J$24*$J$19/100/4 -> 1329.4313 | AJ48: =$J$24*$J$20/100/4 -> 1329.4313 | AK48: =$J$24*$J$20/100/4 -> 1329.4313 | AL48: =$J$24*$J$20/100/4 -> 1329.4313 | AM48: =$J$24*$J$20/100/4 -> 1329.4313 | AN48: =$J$24*$J$21/100/4 -> 0 | AO48: =$J$24*$J$21/100/4 -> 0 | AP48: =$J$24*$J$21/100/4 -> 0 | AQ48: =$J$24*$J$21/100/4 -> 0
A49: MONTH 18 (ADMIN) | D49: =SUM(E49:AZ49) -> 97238.4 | L49: =$J$25*$J$14/100/4 -> 5064.5 | M49: =$J$25*$J$14/100/4 -> 5064.5 | N49: =$J$25*$J$14/100/4 -> 5064.5 | O49: =$J$25*$J$14/100/4 -> 5064.5 | P49: =$J$25*$J$15/100/4 -> 5064.5 | Q49: =$J$25*$J$15/100/4 -> 5064.5 | R49: =$J$25*$J$15/100/4 -> 5064.5 | S49: =$J$25*$J$15/100/4 -> 5064.5 | T49: =$J$25*$J$16/100/4 -> 2836.12 | U49: =$J$25*$J$16/100/4 -> 2836.12 | V49: =$J$25*$J$16/100/4 -> 2836.12 | W49: =$J$25*$J$16/100/4 -> 2836.12 | X49: =$J$25*$J$17/100/4 -> 2836.12 | Y49: =$J$25*$J$17/100/4 -> 2836.12 | Z49: =$J$25*$J$17/100/4 -> 2836.12 | AA49: =$J$25*$J$17/100/4 -> 2836.12 | AB49: =$J$25*$J$18/100/4 -> 2836.12 | AC49: =$J$25*$J$18/100/4 -> 2836.12 | AD49: =$J$25*$J$18/100/4 -> 2836.12 | AE49: =$J$25*$J$18/100/4 -> 2836.12 | AF49: =$J$25*$J$19/100/4 -> 2836.12 | AG49: =$J$25*$J$19/100/4 -> 2836.12 | AH49: =$J$25*$J$19/100/4 -> 2836.12 | AI49: =$J$25*$J$19/100/4 -> 2836.12 | AJ49: =$J$25*$J$20/100/4 -> 2836.12 | AK49: =$J$25*$J$20/100/4 -> 2836.12 | AL49: =$J$25*$J$20/100/4 -> 2836.12 | AM49: =$J$25*$J$20/100/4 -> 2836.12 | AN49: =$J$25*$J$21/100/4 -> 0 | AO49: =$J$25*$J$21/100/4 -> 0 | AP49: =$J$25*$J$21/100/4 -> 0 | AQ49: =$J$25*$J$21/100/4 -> 0 | AU49: =AS49 -> 0 | AV49: =AU49 -> 0
A50: MONTH 21 (COMMERCIAL) | D50: =SUM(E50:AZ50) -> 50138.55 | M50: =$K$24*$K$14/100/4 -> 2611.3828 | N50: =$K$24*$K$14/100/4 -> 2611.3828 | O50: =$K$24*$K$14/100/4 -> 2611.3828 | P50: =$K$24*$K$14/100/4 -> 2611.3828 | Q50: =$K$24*$K$15/100/4 -> 2611.3828 | R50: =$K$24*$K$15/100/4 -> 2611.3828 | S50: =$K$24*$K$15/100/4 -> 2611.3828 | T50: =$K$24*$K$15/100/4 -> 2611.3828 | U50: =$K$24*$K$16/100/4 -> 1462.3744 | V50: =$K$24*$K$16/100/4 -> 1462.3744 | W50: =$K$24*$K$16/100/4 -> 1462.3744 | X50: =$K$24*$K$16/100/4 -> 1462.3744 | Y50: =$K$24*$K$17/100/4 -> 1462.3744 | Z50: =$K$24*$K$17/100/4 -> 1462.3744 | AA50: =$K$24*$K$17/100/4 -> 1462.3744 | AB50: =$K$24*$K$17/100/4 -> 1462.3744 | AC50: =$K$24*$K$18/100/4 -> 1462.3744 | AD50: =$K$24*$K$18/100/4 -> 1462.3744 | AE50: =$K$24*$K$18/100/4 -> 1462.3744 | AF50: =$K$24*$K$18/100/4 -> 1462.3744 | AG50: =$K$24*$K$19/100/4 -> 1462.3744 | AH50: =$K$24*$K$19/100/4 -> 1462.3744 | AI50: =$K$24*$K$19/100/4 -> 1462.3744 | AJ50: =$K$24*$K$19/100/4 -> 1462.3744 | AK50: =$K$24*$K$20/100/4 -> 1462.3744 | AL50: =$K$24*$K$20/100/4 -> 1462.3744 | AM50: =$K$24*$K$20/100/4 -> 1462.3744 | AN50: =$K$24*$K$20/100/4 -> 1462.3744 | AO50: =$K$24*$K$21/100/4 -> 0 | AP50: =$K$24*$K$21/100/4 -> 0 | AQ50: =$K$24*$K$21/100/4 -> 0 | AR50: =$K$24*$K$21/100/4 -> 0
A51: MONTH 21 (ADMIN) | D51: =SUM(E51:AZ51) -> 54696.6 | M51: =$K$25*$K$14/100/4 -> 2848.7812 | N51: =$K$25*$K$14/100/4 -> 2848.7812 | O51: =$K$25*$K$14/100/4 -> 2848.7812 | P51: =$K$25*$K$14/100/4 -> 2848.7812 | Q51: =$K$25*$K$15/100/4 -> 2848.7812 | R51: =$K$25*$K$15/100/4 -> 2848.7812 | S51: =$K$25*$K$15/100/4 -> 2848.7812 | T51: =$K$25*$K$15/100/4 -> 2848.7812 | U51: =$K$25*$K$16/100/4 -> 1595.3175 | V51: =$K$25*$K$16/100/4 -> 1595.3175 | W51: =$K$25*$K$16/100/4 -> 1595.3175 | X51: =$K$25*$K$16/100/4 -> 1595.3175 | Y51: =$K$25*$K$17/100/4 -> 1595.3175 | Z51: =$K$25*$K$17/100/4 -> 1595.3175 | AA51: =$K$25*$K$17/100/4 -> 1595.3175 | AB51: =$K$25*$K$17/100/4 -> 1595.3175 | AC51: =$K$25*$K$18/100/4 -> 1595.3175 | AD51: =$K$25*$K$18/100/4 -> 1595.3175 | AE51: =$K$25*$K$18/100/4 -> 1595.3175 | AF51: =$K$25*$K$18/100/4 -> 1595.3175 | AG51: =$K$25*$K$19/100/4 -> 1595.3175 | AH51: =$K$25*$K$19/100/4 -> 1595.3175 | AI51: =$K$25*$K$19/100/4 -> 1595.3175 | AJ51: =$K$25*$K$19/100/4 -> 1595.3175 | AK51: =$K$25*$K$20/100/4 -> 1595.3175 | AL51: =$K$25*$K$20/100/4 -> 1595.3175 | AM51: =$K$25*$K$20/100/4 -> 1595.3175 | AN51: =$K$25*$K$20/100/4 -> 1595.3175 | AO51: =$K$25*$K$21/100/4 -> 0 | AP51: =$K$25*$K$21/100/4 -> 0 | AQ51: =$K$25*$K$21/100/4 -> 0 | AR51: =$K$25*$K$21/100/4 -> 0
A52: MONTH 24 (COMMERCIAL) | D52: =SUM(E52:AZ52) -> 50138.55 | N52: =$L$24*$L$14/100/4 -> 2611.3828 | O52: =$L$24*$L$14/100/4 -> 2611.3828 | P52: =$L$24*$L$14/100/4 -> 2611.3828 | Q52: =$L$24*$L$14/100/4 -> 2611.3828 | R52: =$L$24*$L$15/100/4 -> 2611.3828 | S52: =$L$24*$L$15/100/4 -> 2611.3828 | T52: =$L$24*$L$15/100/4 -> 2611.3828 | U52: =$L$24*$L$15/100/4 -> 2611.3828 | V52: =$L$24*$L$16/100/4 -> 2611.3828 | W52: =$L$24*$L$16/100/4 -> 2611.3828 | X52: =$L$24*$L$16/100/4 -> 2611.3828 | Y52: =$L$24*$L$16/100/4 -> 2611.3828 | Z52: =$L$24*$L$17/100/4 -> 2611.3828 | AA52: =$L$24*$L$17/100/4 -> 2611.3828 | AB52: =$L$24*$L$17/100/4 -> 2611.3828 | AC52: =$L$24*$L$17/100/4 -> 2611.3828 | AD52: =$L$24*$L$18/100/4 -> 1044.5531 | AE52: =$L$24*$L$18/100/4 -> 1044.5531 | AF52: =$L$24*$L$18/100/4 -> 1044.5531 | AG52: =$L$24*$L$18/100/4 -> 1044.5531 | AH52: =$L$24*$L$19/100/4 -> 1044.5531 | AI52: =$L$24*$L$19/100/4 -> 1044.5531 | AJ52: =$L$24*$L$19/100/4 -> 1044.5531 | AK52: =$L$24*$L$19/100/4 -> 1044.5531 | AL52: =$L$24*$L$20/100/4 -> 0 | AM52: =$L$24*$L$20/100/4 -> 0 | AN52: =$L$24*$L$20/100/4 -> 0 | AO52: =$L$24*$L$20/100/4 -> 0 | AP52: =$L$24*$L$21/100/4 -> 0 | AQ52: =$L$24*$L$21/100/4 -> 0 | AR52: =$L$24*$L$21/100/4 -> 0 | AS52: =$L$24*$L$21/100/4 -> 0 | AW52: =$L$24*$L$21/100/4 -> 0 | AX52: =AW52 -> 0 | AY52: =AX52 -> 0
A53: MONTH 24 (ADMIN) | D53: =SUM(E53:AZ53) -> 54696.6 | N53: =$L$25*$L$14/100/4 -> 2848.7812 | O53: =$L$25*$L$14/100/4 -> 2848.7812 | P53: =$L$25*$L$14/100/4 -> 2848.7812 | Q53: =$L$25*$L$14/100/4 -> 2848.7812 | R53: =$L$25*$L$15/100/4 -> 2848.7812 | S53: =$L$25*$L$15/100/4 -> 2848.7812 | T53: =$L$25*$L$15/100/4 -> 2848.7812 | U53: =$L$25*$L$15/100/4 -> 2848.7812 | V53: =$L$25*$L$16/100/4 -> 2848.7812 | W53: =$L$25*$L$16/100/4 -> 2848.7812 | X53: =$L$25*$L$16/100/4 -> 2848.7812 | Y53: =$L$25*$L$16/100/4 -> 2848.7812 | Z53: =$L$25*$L$17/100/4 -> 2848.7812 | AA53: =$L$25*$L$17/100/4 -> 2848.7812 | AB53: =$L$25*$L$17/100/4 -> 2848.7812 | AC53: =$L$25*$L$17/100/4 -> 2848.7812 | AD53: =$L$25*$L$18/100/4 -> 1139.5125 | AE53: =$L$25*$L$18/100/4 -> 1139.5125 | AF53: =$L$25*$L$18/100/4 -> 1139.5125 | AG53: =$L$25*$L$18/100/4 -> 1139.5125 | AH53: =$L$25*$L$19/100/4 -> 1139.5125 | AI53: =$L$25*$L$19/100/4 -> 1139.5125 | AJ53: =$L$25*$L$19/100/4 -> 1139.5125 | AK53: =$L$25*$L$19/100/4 -> 1139.5125 | AL53: =$L$25*$L$20/100/4 -> 0 | AM53: =$L$25*$L$20/100/4 -> 0 | AN53: =$L$25*$L$20/100/4 -> 0 | AO53: =$L$25*$L$20/100/4 -> 0 | AP53: =$L$25*$L$21/100/4 -> 0 | AQ53: =$L$25*$L$21/100/4 -> 0 | AR53: =$L$25*$L$21/100/4 -> 0 | AS53: =$L$25*$L$21/100/4 -> 0 | AW53: =$L$25*$L$21/100/4 -> 0 | AX53: =AW53 -> 0 | AY53: =AX53 -> 0
A54: MONTH 27 (COMMERCIAL) | D54: =SUM(E54:AZ54) -> 41022.45 | O54: =$M$24*$M$14/100/4 -> 3418.5375 | P54: =$M$24*$M$14/100/4 -> 3418.5375 | Q54: =$M$24*$M$14/100/4 -> 3418.5375 | R54: =$M$24*$M$14/100/4 -> 3418.5375 | S54: =$M$24*$M$15/100/4 -> 3418.5375 | T54: =$M$24*$M$15/100/4 -> 3418.5375 | U54: =$M$24*$M$15/100/4 -> 3418.5375 | V54: =$M$24*$M$15/100/4 -> 3418.5375 | W54: =$M$24*$M$16/100/4 -> 1709.2687 | X54: =$M$24*$M$16/100/4 -> 1709.2687 | Y54: =$M$24*$M$16/100/4 -> 1709.2687 | Z54: =$M$24*$M$16/100/4 -> 1709.2687 | AA54: =$M$24*$M$17/100/4 -> 1709.2687 | AB54: =$M$24*$M$17/100/4 -> 1709.2687 | AC54: =$M$24*$M$17/100/4 -> 1709.2687 | AD54: =$M$24*$M$17/100/4 -> 1709.2687 | AE54: =$M$24*$M$18/100/4 -> 0 | AF54: =$M$24*$M$18/100/4 -> 0 | AG54: =$M$24*$M$18/100/4 -> 0 | AH54: =$M$24*$M$18/100/4 -> 0 | AI54: =$M$24*$M$19/100/4 -> 0 | AJ54: =$M$24*$M$19/100/4 -> 0 | AK54: =$M$24*$M$19/100/4 -> 0 | AL54: =$M$24*$M$19/100/4 -> 0 | AM54: =$M$24*$M$20/100/4 -> 0 | AN54: =$M$24*$M$20/100/4 -> 0 | AO54: =$M$24*$M$20/100/4 -> 0 | AP54: =$M$24*$M$20/100/4 -> 0 | AQ54: =$M$24*$M$21/100/4 -> 0 | AR54: =$M$24*$M$21/100/4 -> 0 | AS54: =$M$24*$M$21/100/4 -> 0 | AT54: =$M$24*$M$21/100/4 -> 0
A55: MONTH 27 (ADMIN) | D55: =SUM(E55:AZ55) -> 45580.5 | O55: =$M$25*$M$14/100/4 -> 3798.375 | P55: =$M$25*$M$14/100/4 -> 3798.375 | Q55: =$M$25*$M$14/100/4 -> 3798.375 | R55: =$M$25*$M$14/100/4 -> 3798.375 | S55: =$M$25*$M$15/100/4 -> 3798.375 | T55: =$M$25*$M$15/100/4 -> 3798.375 | U55: =$M$25*$M$15/100/4 -> 3798.375 | V55: =$M$25*$M$15/100/4 -> 3798.375 | W55: =$M$25*$M$16/100/4 -> 1899.1875 | X55: =$M$25*$M$16/100/4 -> 1899.1875 | Y55: =$M$25*$M$16/100/4 -> 1899.1875 | Z55: =$M$25*$M$16/100/4 -> 1899.1875 | AA55: =$M$25*$M$17/100/4 -> 1899.1875 | AB55: =$M$25*$M$17/100/4 -> 1899.1875 | AC55: =$M$25*$M$17/100/4 -> 1899.1875 | AD55: =$M$25*$M$17/100/4 -> 1899.1875 | AE55: =$M$25*$M$18/100/4 -> 0 | AF55: =$M$25*$M$18/100/4 -> 0 | AG55: =$M$25*$M$18/100/4 -> 0 | AH55: =$M$25*$M$18/100/4 -> 0 | AI55: =$M$25*$M$19/100/4 -> 0 | AJ55: =$M$25*$M$19/100/4 -> 0 | AK55: =$M$25*$M$19/100/4 -> 0 | AL55: =$M$25*$M$19/100/4 -> 0 | AM55: =$M$25*$M$20/100/4 -> 0 | AN55: =$M$25*$M$20/100/4 -> 0 | AO55: =$M$25*$M$20/100/4 -> 0 | AP55: =$M$25*$M$20/100/4 -> 0 | AQ55: =$M$25*$M$21/100/4 -> 0 | AR55: =$M$25*$M$21/100/4 -> 0 | AS55: =$M$25*$M$21/100/4 -> 0 | AT55: =$M$25*$M$21/100/4 -> 0
A56: MONTH 30 (COMMERCIAL) | D56: =SUM(E56:AZ56) -> 58603.5 | P56: =$N$24*$N$14/100/4 -> 4883.625 | Q56: =$N$24*$N$14/100/4 -> 4883.625 | R56: =$N$24*$N$14/100/4 -> 4883.625 | S56: =$N$24*$N$14/100/4 -> 4883.625 | T56: =$N$24*$N$15/100/4 -> 4883.625 | U56: =$N$24*$N$15/100/4 -> 4883.625 | V56: =$N$24*$N$15/100/4 -> 4883.625 | W56: =$N$24*$N$15/100/4 -> 4883.625 | X56: =$N$24*$N$16/100/4 -> 2441.8125 | Y56: =$N$24*$N$16/100/4 -> 2441.8125 | Z56: =$N$24*$N$16/100/4 -> 2441.8125 | AA56: =$N$24*$N$16/100/4 -> 2441.8125 | AB56: =$N$24*$N$17/100/4 -> 2441.8125 | AC56: =$N$24*$N$17/100/4 -> 2441.8125 | AD56: =$N$24*$N$17/100/4 -> 2441.8125 | AE56: =$N$24*$N$17/100/4 -> 2441.8125 | AF56: =$N$24*$N$18/100/4 -> 0 | AG56: =$N$24*$N$18/100/4 -> 0 | AH56: =$N$24*$N$18/100/4 -> 0 | AI56: =$N$24*$N$18/100/4 -> 0 | AJ56: =$N$24*$N$19/100/4 -> 0 | AK56: =$N$24*$N$19/100/4 -> 0 | AL56: =$N$24*$N$19/100/4 -> 0 | AM56: =$N$24*$N$19/100/4 -> 0 | AN56: =$N$24*$N$20/100/4 -> 0 | AO56: =$N$24*$N$20/100/4 -> 0 | AP56: =$N$24*$N$20/100/4 -> 0 | AQ56: =$N$24*$N$20/100/4 -> 0 | AR56: =$N$24*$N$21/100/4 -> 0 | AS56: =$N$24*$N$21/100/4 -> 0 | AT56: =$N$24*$N$21/100/4 -> 0 | AU56: =$N$24*$N$21/100/4 -> 0 | AY56: =AW56 -> 0 | AZ56: =$N$24*$N$21/100/4 -> 0 | BA56: =AZ56 -> 0 | BB56: =BA56 -> 0
A57: MONTH 30 (ADMIN) | D57: =SUM(E57:AZ57) -> 45580.5 | P57: =$N$25*$N$14/100/4 -> 3798.375 | Q57: =$N$25*$N$14/100/4 -> 3798.375 | R57: =$N$25*$N$14/100/4 -> 3798.375 | S57: =$N$25*$N$14/100/4 -> 3798.375 | T57: =$N$25*$N$15/100/4 -> 3798.375 | U57: =$N$25*$N$15/100/4 -> 3798.375 | V57: =$N$25*$N$15/100/4 -> 3798.375 | W57: =$N$25*$N$15/100/4 -> 3798.375 | X57: =$N$25*$N$16/100/4 -> 1899.1875 | Y57: =$N$25*$N$16/100/4 -> 1899.1875 | Z57: =$N$25*$N$16/100/4 -> 1899.1875 | AA57: =$N$25*$N$16/100/4 -> 1899.1875 | AB57: =$N$25*$N$17/100/4 -> 1899.1875 | AC57: =$N$25*$N$17/100/4 -> 1899.1875 | AD57: =$N$25*$N$17/100/4 -> 1899.1875 | AE57: =$N$25*$N$17/100/4 -> 1899.1875 | AF57: =$N$25*$N$18/100/4 -> 0 | AG57: =$N$25*$N$18/100/4 -> 0 | AH57: =$N$25*$N$18/100/4 -> 0 | AI57: =$N$25*$N$18/100/4 -> 0 | AJ57: =$N$25*$N$19/100/4 -> 0 | AK57: =$N$25*$N$19/100/4 -> 0 | AL57: =$N$25*$N$19/100/4 -> 0 | AM57: =$N$25*$N$19/100/4 -> 0 | AN57: =$N$25*$N$20/100/4 -> 0 | AO57: =$N$25*$N$20/100/4 -> 0 | AP57: =$N$25*$N$20/100/4 -> 0 | AQ57: =$N$25*$N$20/100/4 -> 0 | AR57: =$N$25*$N$21/100/4 -> 0 | AS57: =$N$25*$N$21/100/4 -> 0 | AT57: =$N$25*$N$21/100/4 -> 0 | AU57: =$N$25*$N$21/100/4 -> 0 | AY57: =AW57 -> 0 | AZ57: =$N$25*$N$21/100/4 -> 0 | BA57: =AZ57 -> 0 | BB57: =BA57 -> 0
A58: MONTH 33 (COMMERCIAL) | D58: =SUM(E58:AZ58) -> 45580.5 | Q58: =$O$24*$O$14/100/4 -> 4883.625 | R58: =$O$24*$O$14/100/4 -> 4883.625 | S58: =$O$24*$O$14/100/4 -> 4883.625 | T58: =$O$24*$O$14/100/4 -> 4883.625 | U58: =$O$24*$O$15/100/4 -> 3255.75 | V58: =$O$24*$O$15/100/4 -> 3255.75 | W58: =$O$24*$O$15/100/4 -> 3255.75 | X58: =$O$24*$O$15/100/4 -> 3255.75 | Y58: =$O$24*$O$16/100/4 -> 3255.75 | Z58: =$O$24*$O$16/100/4 -> 3255.75 | AA58: =$O$24*$O$16/100/4 -> 3255.75 | AB58: =$O$24*$O$16/100/4 -> 3255.75 | AC58: =$O$24*$O$17/100/4 -> 0 | AD58: =$O$24*$O$17/100/4 -> 0 | AE58: =$O$24*$O$17/100/4 -> 0 | AF58: =$O$24*$O$17/100/4 -> 0 | AG58: =$O$24*$O$18/100/4 -> 0 | AH58: =$O$24*$O$18/100/4 -> 0 | AI58: =$O$24*$O$18/100/4 -> 0 | AJ58: =$O$24*$O$18/100/4 -> 0 | AK58: =$O$24*$O$19/100/4 -> 0 | AL58: =$O$24*$O$19/100/4 -> 0 | AM58: =$O$24*$O$19/100/4 -> 0 | AN58: =$O$24*$O$19/100/4 -> 0 | AO58: =$O$24*$O$20/100/4 -> 0 | AP58: =$O$24*$O$20/100/4 -> 0 | AQ58: =$O$24*$O$20/100/4 -> 0 | AR58: =$O$24*$O$20/100/4 -> 0 | AS58: =$O$24*$O$21/100/4 -> 0 | AT58: =$O$24*$O$21/100/4 -> 0 | AU58: =$O$24*$O$21/100/4 -> 0 | AV58: =$O$24*$O$21/100/4 -> 0
A59: MONTH 33 (ADMIN) | D59: =SUM(E59:AZ59) -> 35451.5 | Q59: =$O$25*$O$14/100/4 -> 3798.375 | R59: =$O$25*$O$14/100/4 -> 3798.375 | S59: =$O$25*$O$14/100/4 -> 3798.375 | T59: =$O$25*$O$14/100/4 -> 3798.375 | U59: =$O$25*$O$15/100/4 -> 2532.25 | V59: =$O$25*$O$15/100/4 -> 2532.25 | W59: =$O$25*$O$15/100/4 -> 2532.25 | X59: =$O$25*$O$15/100/4 -> 2532.25 | Y59: =$O$25*$O$16/100/4 -> 2532.25 | Z59: =$O$25*$O$16/100/4 -> 2532.25 | AA59: =$O$25*$O$16/100/4 -> 2532.25 | AB59: =$O$25*$O$16/100/4 -> 2532.25 | AC59: =$O$25*$O$17/100/4 -> 0 | AD59: =$O$25*$O$17/100/4 -> 0 | AE59: =$O$25*$O$17/100/4 -> 0 | AF59: =$O$25*$O$17/100/4 -> 0 | AG59: =$O$25*$O$18/100/4 -> 0 | AH59: =$O$25*$O$18/100/4 -> 0 | AI59: =$O$25*$O$18/100/4 -> 0 | AJ59: =$O$25*$O$18/100/4 -> 0 | AK59: =$O$25*$O$19/100/4 -> 0 | AL59: =$O$25*$O$19/100/4 -> 0 | AM59: =$O$25*$O$19/100/4 -> 0 | AN59: =$O$25*$O$19/100/4 -> 0 | AO59: =$O$25*$O$20/100/4 -> 0 | AP59: =$O$25*$O$20/100/4 -> 0 | AQ59: =$O$25*$O$20/100/4 -> 0 | AR59: =$O$25*$O$20/100/4 -> 0 | AS59: =$O$25*$O$21/100/4 -> 0 | AT59: =$O$25*$O$21/100/4 -> 0 | AU59: =$O$25*$O$21/100/4 -> 0 | AV59: =$O$25*$O$21/100/4 -> 0
A60: MONTH 36 (COMMERCIAL) | D60: =SUM(E60:AZ60) -> 22790.25 | R60: =$P$24*$P$14/100/4 -> 2848.7812 | S60: =$P$24*$P$14/100/4 -> 2848.7812 | T60: =$P$24*$P$14/100/4 -> 2848.7812 | U60: =$P$24*$P$14/100/4 -> 2848.7812 | V60: =$P$24*$P$15/100/4 -> 2848.7812 | W60: =$P$24*$P$15/100/4 -> 2848.7812 | X60: =$P$24*$P$15/100/4 -> 2848.7812 | Y60: =$P$24*$P$15/100/4 -> 2848.7812 | Z60: =$P$24*$P$16/100/4 -> 0 | AA60: =$P$24*$P$16/100/4 -> 0 | AB60: =$P$24*$P$16/100/4 -> 0 | AC60: =$P$24*$P$16/100/4 -> 0 | AD60: =$P$24*$P$17/100/4 -> 0 | AE60: =$P$24*$P$17/100/4 -> 0 | AF60: =$P$24*$P$17/100/4 -> 0 | AG60: =$P$24*$P$17/100/4 -> 0 | AH60: =$P$24*$P$18/100/4 -> 0 | AI60: =$P$24*$P$18/100/4 -> 0 | AJ60: =$P$24*$P$18/100/4 -> 0 | AK60: =$P$24*$P$18/100/4 -> 0 | AL60: =$P$24*$P$19/100/4 -> 0 | AM60: =$P$24*$P$19/100/4 -> 0 | AN60: =$P$24*$P$19/100/4 -> 0 | AO60: =$P$24*$P$19/100/4 -> 0 | AP60: =$P$24*$P$20/100/4 -> 0 | AQ60: =$P$24*$P$20/100/4 -> 0 | AR60: =$P$24*$P$20/100/4 -> 0 | AS60: =$P$24*$P$20/100/4 -> 0 | AT60: =$P$24*$P$21/100/4 -> 0 | AU60: =$P$24*$P$21/100/4 -> 0 | AV60: =$P$24*$P$21/100/4 -> 0 | AW60: =$P$24*$P$21/100/4 -> 0 | BA60: =$P$24*$P$20/100/4 -> 0 | BB60: =BA60 -> 0 | BC60: =$P$24*$P$21/100/4 -> 0 | BD60: =BC60 -> 0 | BE60: =BD60 -> 0
A61: MONTH 36 (ADMIN) | D61: =SUM(E61:AZ61) -> 35451.5 | R61: =$P$25*$P$14/100/4 -> 4431.4375 | S61: =$P$25*$P$14/100/4 -> 4431.4375 | T61: =$P$25*$P$14/100/4 -> 4431.4375 | U61: =$P$25*$P$14/100/4 -> 4431.4375 | V61: =$P$25*$P$15/100/4 -> 4431.4375 | W61: =$P$25*$P$15/100/4 -> 4431.4375 | X61: =$P$25*$P$15/100/4 -> 4431.4375 | Y61: =$P$25*$P$15/100/4 -> 4431.4375 | Z61: =$P$25*$P$16/100/4 -> 0 | AA61: =$P$25*$P$16/100/4 -> 0 | AB61: =$P$25*$P$16/100/4 -> 0 | AC61: =$P$25*$P$16/100/4 -> 0 | AD61: =$P$25*$P$17/100/4 -> 0 | AE61: =$P$25*$P$17/100/4 -> 0 | AF61: =$P$25*$P$17/100/4 -> 0 | AG61: =$P$25*$P$17/100/4 -> 0 | AH61: =$P$25*$P$18/100/4 -> 0 | AI61: =$P$25*$P$18/100/4 -> 0 | AJ61: =$P$25*$P$18/100/4 -> 0 | AK61: =$P$25*$P$18/100/4 -> 0 | AL61: =$P$25*$P$19/100/4 -> 0 | AM61: =$P$25*$P$19/100/4 -> 0 | AN61: =$P$25*$P$19/100/4 -> 0 | AO61: =$P$25*$P$19/100/4 -> 0 | AP61: =$P$25*$P$20/100/4 -> 0 | AQ61: =$P$25*$P$20/100/4 -> 0 | AR61: =$P$25*$P$20/100/4 -> 0 | AS61: =$P$25*$P$20/100/4 -> 0 | AT61: =$P$25*$P$21/100/4 -> 0 | AU61: =$P$25*$P$21/100/4 -> 0 | AV61: =$P$25*$P$21/100/4 -> 0 | AW61: =$P$25*$P$21/100/4 -> 0 | BA61: =$P$25*$P$20/100/4 -> 0 | BB61: =BA61 -> 0 | BC61: =$P$25*$P$21/100/4 -> 0 | BD61: =BC61 -> 0 | BE61: =BD61 -> 0
A62: MONTH 39 (COMMERCIAL) | D62: =SUM(E62:AZ62) -> 0 | S62: =$Q$24*$Q$14/100/4 -> 0 | T62: =$Q$24*$Q$14/100/4 -> 0 | U62: =$Q$24*$Q$14/100/4 -> 0 | V62: =$Q$24*$Q$14/100/4 -> 0 | W62: =$Q$24*$Q$15/100/4 -> 0 | X62: =$Q$24*$Q$15/100/4 -> 0 | Y62: =$Q$24*$Q$15/100/4 -> 0 | Z62: =$Q$24*$Q$15/100/4 -> 0 | AA62: =$Q$24*$Q$16/100/4 -> 0 | AB62: =$Q$24*$Q$16/100/4 -> 0 | AC62: =$Q$24*$Q$16/100/4 -> 0 | AD62: =$Q$24*$Q$16/100/4 -> 0 | AE62: =$Q$24*$Q$17/100/4 -> 0 | AF62: =$Q$24*$Q$17/100/4 -> 0 | AG62: =$Q$24*$Q$17/100/4 -> 0 | AH62: =$Q$24*$Q$17/100/4 -> 0 | AI62: =$Q$24*$Q$18/100/4 -> 0 | AJ62: =$Q$24*$Q$18/100/4 -> 0 | AK62: =$Q$24*$Q$18/100/4 -> 0 | AL62: =$Q$24*$Q$18/100/4 -> 0 | AM62: =$Q$24*$Q$19/100/4 -> 0 | AN62: =$Q$24*$Q$19/100/4 -> 0 | AO62: =$Q$24*$Q$19/100/4 -> 0 | AP62: =$Q$24*$Q$19/100/4 -> 0 | AQ62: =$Q$24*$Q$20/100/4 -> 0 | AR62: =$Q$24*$Q$20/100/4 -> 0 | AS62: =$Q$24*$Q$20/100/4 -> 0 | AT62: =$Q$24*$Q$20/100/4 -> 0 | AU62: =$Q$24*$Q$21/100/4 -> 0 | AV62: =$Q$24*$Q$21/100/4 -> 0 | AW62: =$Q$24*$Q$21/100/4 -> 0 | AX62: =$Q$24*$Q$21/100/4 -> 0
A63: MONTH 39 (ADMIN) | D63: =SUM(E63:AZ63) -> 0 | S63: =$Q$25*$Q$14/100/4 -> 0 | T63: =$Q$25*$Q$14/100/4 -> 0 | U63: =$Q$25*$Q$14/100/4 -> 0 | V63: =$Q$25*$Q$14/100/4 -> 0 | W63: =$Q$25*$Q$15/100/4 -> 0 | X63: =$Q$25*$Q$15/100/4 -> 0 | Y63: =$Q$25*$Q$15/100/4 -> 0 | Z63: =$Q$25*$Q$15/100/4 -> 0 | AA63: =$Q$25*$Q$16/100/4 -> 0 | AB63: =$Q$25*$Q$16/100/4 -> 0 | AC63: =$Q$25*$Q$16/100/4 -> 0 | AD63: =$Q$25*$Q$16/100/4 -> 0 | AE63: =$Q$25*$Q$17/100/4 -> 0 | AF63: =$Q$25*$Q$17/100/4 -> 0 | AG63: =$Q$25*$Q$17/100/4 -> 0 | AH63: =$Q$25*$Q$17/100/4 -> 0 | AI63: =$Q$25*$Q$18/100/4 -> 0 | AJ63: =$Q$25*$Q$18/100/4 -> 0 | AK63: =$Q$25*$Q$18/100/4 -> 0 | AL63: =$Q$25*$Q$18/100/4 -> 0 | AM63: =$Q$25*$Q$19/100/4 -> 0 | AN63: =$Q$25*$Q$19/100/4 -> 0 | AO63: =$Q$25*$Q$19/100/4 -> 0 | AP63: =$Q$25*$Q$19/100/4 -> 0 | AQ63: =$Q$25*$Q$20/100/4 -> 0 | AR63: =$Q$25*$Q$20/100/4 -> 0 | AS63: =$Q$25*$Q$20/100/4 -> 0 | AT63: =$Q$25*$Q$20/100/4 -> 0 | AU63: =$Q$25*$Q$21/100/4 -> 0 | AV63: =$Q$25*$Q$21/100/4 -> 0 | AW63: =$Q$25*$Q$21/100/4 -> 0 | AX63: =$Q$25*$Q$21/100/4 -> 0
A64: MONTH 42 (COMMERCIAL) | D64: =SUM(E64:AZ64) -> 0 | T64: =$R$24*$R$14/100/4 -> 0 | U64: =$R$24*$R$14/100/4 -> 0 | V64: =$R$24*$R$14/100/4 -> 0 | W64: =$R$24*$R$14/100/4 -> 0 | X64: =$R$24*$R$15/100/4 -> 0 | Y64: =$R$24*$R$15/100/4 -> 0 | Z64: =$R$24*$R$15/100/4 -> 0 | AA64: =$R$24*$R$15/100/4 -> 0 | AB64: =$R$24*$R$16/100/4 -> 0 | AC64: =$R$24*$R$16/100/4 -> 0 | AD64: =$R$24*$R$16/100/4 -> 0 | AE64: =$R$24*$R$16/100/4 -> 0 | AF64: =$R$24*$R$17/100/4 -> 0 | AG64: =$R$24*$R$17/100/4 -> 0 | AH64: =$R$24*$R$17/100/4 -> 0 | AI64: =$R$24*$R$17/100/4 -> 0 | AJ64: =$R$24*$R$18/100/4 -> 0 | AK64: =$R$24*$R$18/100/4 -> 0 | AL64: =$R$24*$R$18/100/4 -> 0 | AM64: =$R$24*$R$18/100/4 -> 0 | AN64: =$R$24*$R$19/100/4 -> 0 | AO64: =$R$24*$R$19/100/4 -> 0 | AP64: =$R$24*$R$19/100/4 -> 0 | AQ64: =$R$24*$R$19/100/4 -> 0 | AR64: =$R$24*$R$20/100/4 -> 0 | AS64: =$R$24*$R$20/100/4 -> 0 | AT64: =$R$24*$R$20/100/4 -> 0 | AU64: =$R$24*$R$20/100/4 -> 0 | AV64: =$R$24*$R$21/100/4 -> 0 | AW64: =$R$24*$R$21/100/4 -> 0 | AX64: =$R$24*$R$21/100/4 -> 0 | AY64: =$R$24*$R$21/100/4 -> 0 | BC64: =BA64 -> 0 | BD64: =$R$24*$R$20/100/4 -> 0 | BE64: =BD64 -> 0 | BF64: =$R$24*$R$21/100/4 -> 0 | BG64: =BF64 -> 0 | BH64: =BG64 -> 0
A65: MONTH 42 (ADMIN) | D65: =SUM(E65:AZ65) -> 0 | T65: =$R$25*$R$14/100/4 -> 0 | U65: =$R$25*$R$14/100/4 -> 0 | V65: =$R$25*$R$14/100/4 -> 0 | W65: =$R$25*$R$14/100/4 -> 0 | X65: =$R$25*$R$15/100/4 -> 0 | Y65: =$R$25*$R$15/100/4 -> 0 | Z65: =$R$25*$R$15/100/4 -> 0 | AA65: =$R$25*$R$15/100/4 -> 0 | AB65: =$R$25*$R$16/100/4 -> 0 | AC65: =$R$25*$R$16/100/4 -> 0 | AD65: =$R$25*$R$16/100/4 -> 0 | AE65: =$R$25*$R$16/100/4 -> 0 | AF65: =$R$25*$R$17/100/4 -> 0 | AG65: =$R$25*$R$17/100/4 -> 0 | AH65: =$R$25*$R$17/100/4 -> 0 | AI65: =$R$25*$R$17/100/4 -> 0 | AJ65: =$R$25*$R$18/100/4 -> 0 | AK65: =$R$25*$R$18/100/4 -> 0 | AL65: =$R$25*$R$18/100/4 -> 0 | AM65: =$R$25*$R$18/100/4 -> 0 | AN65: =$R$25*$R$19/100/4 -> 0 | AO65: =$R$25*$R$19/100/4 -> 0 | AP65: =$R$25*$R$19/100/4 -> 0 | AQ65: =$R$25*$R$19/100/4 -> 0 | AR65: =$R$25*$R$20/100/4 -> 0 | AS65: =$R$25*$R$20/100/4 -> 0 | AT65: =$R$25*$R$20/100/4 -> 0 | AU65: =$R$25*$R$20/100/4 -> 0 | AV65: =$R$25*$R$21/100/4 -> 0 | AW65: =$R$25*$R$21/100/4 -> 0 | AX65: =$R$25*$R$21/100/4 -> 0 | AY65: =$R$25*$R$21/100/4 -> 0 | BC65: =BA65 -> 0 | BD65: =$R$25*$R$20/100/4 -> 0 | BE65: =BD65 -> 0 | BF65: =$R$25*$R$21/100/4 -> 0 | BG65: =BF65 -> 0 | BH65: =BG65 -> 0
A66: MONTH 45 (COMMERCIAL) | D66: =SUM(E66:AZ66) -> 0 | U66: =$S$24*$S$14/100/4 -> 0 | V66: =$S$24*$S$14/100/4 -> 0 | W66: =$S$24*$S$14/100/4 -> 0 | X66: =$S$24*$S$14/100/4 -> 0 | Y66: =$S$24*$S$15/100/4 -> 0 | Z66: =$S$24*$S$15/100/4 -> 0 | AA66: =$S$24*$S$15/100/4 -> 0 | AB66: =$S$24*$S$15/100/4 -> 0 | AC66: =$S$24*$S$16/100/4 -> 0 | AD66: =$S$24*$S$16/100/4 -> 0 | AE66: =$S$24*$S$16/100/4 -> 0 | AF66: =$S$24*$S$16/100/4 -> 0 | AG66: =$S$24*$S$17/100/4 -> 0 | AH66: =$S$24*$S$17/100/4 -> 0 | AI66: =$S$24*$S$17/100/4 -> 0 | AJ66: =$S$24*$S$17/100/4 -> 0 | AK66: =$S$24*$S$18/100/4 -> 0 | AL66: =$S$24*$S$18/100/4 -> 0 | AM66: =$S$24*$S$18/100/4 -> 0 | AN66: =$S$24*$S$18/100/4 -> 0 | AO66: =$S$24*$S$19/100/4 -> 0 | AP66: =$S$24*$S$19/100/4 -> 0 | AQ66: =$S$24*$S$19/100/4 -> 0 | AR66: =$S$24*$S$19/100/4 -> 0 | AS66: =$S$24*$S$20/100/4 -> 0 | AT66: =$S$24*$S$20/100/4 -> 0 | AU66: =$S$24*$S$20/100/4 -> 0 | AV66: =$S$24*$S$20/100/4 -> 0 | AW66: =$S$24*$S$21/100/4 -> 0 | AX66: =$S$24*$S$21/100/4 -> 0 | AY66: =$S$24*$S$21/100/4 -> 0 | AZ66: =$S$24*$S$21/100/4 -> 0
A67: MONTH 45 (ADMIN) | D67: =SUM(E67:AZ67) -> 0 | U67: =$S$25*$S$14/100/4 -> 0 | V67: =$S$25*$S$14/100/4 -> 0 | W67: =$S$25*$S$14/100/4 -> 0 | X67: =$S$25*$S$14/100/4 -> 0 | Y67: =$S$25*$S$15/100/4 -> 0 | Z67: =$S$25*$S$15/100/4 -> 0 | AA67: =$S$25*$S$15/100/4 -> 0 | AB67: =$S$25*$S$15/100/4 -> 0 | AC67: =$S$25*$S$16/100/4 -> 0 | AD67: =$S$25*$S$16/100/4 -> 0 | AE67: =$S$25*$S$16/100/4 -> 0 | AF67: =$S$25*$S$16/100/4 -> 0 | AG67: =$S$25*$S$17/100/4 -> 0 | AH67: =$S$25*$S$17/100/4 -> 0 | AI67: =$S$25*$S$17/100/4 -> 0 | AJ67: =$S$25*$S$17/100/4 -> 0 | AK67: =$S$25*$S$18/100/4 -> 0 | AL67: =$S$25*$S$18/100/4 -> 0 | AM67: =$S$25*$S$18/100/4 -> 0 | AN67: =$S$25*$S$18/100/4 -> 0 | AO67: =$S$25*$S$19/100/4 -> 0 | AP67: =$S$25*$S$19/100/4 -> 0 | AQ67: =$S$25*$S$19/100/4 -> 0 | AR67: =$S$25*$S$19/100/4 -> 0 | AS67: =$S$25*$S$20/100/4 -> 0 | AT67: =$S$25*$S$20/100/4 -> 0 | AU67: =$S$25*$S$20/100/4 -> 0 | AV67: =$S$25*$S$20/100/4 -> 0 | AW67: =$S$25*$S$21/100/4 -> 0 | AX67: =$S$25*$S$21/100/4 -> 0 | AY67: =$S$25*$S$21/100/4 -> 0 | AZ67: =$S$25*$S$21/100/4 -> 0
A68: MONTH 48 (COMMERCIAL) | D68: =SUM(E68:AZ68) -> 0 | V68: =$T$24*$T$14/100/4 -> 0 | W68: =$T$24*$T$14/100/4 -> 0 | X68: =$T$24*$T$14/100/4 -> 0 | Y68: =$T$24*$T$14/100/4 -> 0 | Z68: =$T$24*$T$15/100/4 -> 0 | AA68: =$T$24*$T$15/100/4 -> 0 | AB68: =$T$24*$T$15/100/4 -> 0 | AC68: =$T$24*$T$15/100/4 -> 0 | AD68: =$T$24*$T$16/100/4 -> 0 | AE68: =$T$24*$T$16/100/4 -> 0 | AF68: =$T$24*$T$16/100/4 -> 0 | AG68: =$T$24*$T$16/100/4 -> 0 | AH68: =$T$24*$T$17/100/4 -> 0 | AI68: =$T$24*$T$17/100/4 -> 0 | AJ68: =$T$24*$T$17/100/4 -> 0 | AK68: =$T$24*$T$17/100/4 -> 0 | AL68: =$T$24*$T$18/100/4 -> 0 | AM68: =$T$24*$T$18/100/4 -> 0 | AN68: =$T$24*$T$18/100/4 -> 0 | AO68: =$T$24*$T$18/100/4 -> 0 | AP68: =$T$24*$T$19/100/4 -> 0 | AQ68: =$T$24*$T$19/100/4 -> 0 | AR68: =$T$24*$T$19/100/4 -> 0 | AS68: =$T$24*$T$19/100/4 -> 0 | AT68: =$T$24*$T$20/100/4 -> 0 | AU68: =$T$24*$T$20/100/4 -> 0 | AV68: =$T$24*$T$20/100/4 -> 0 | AW68: =$T$24*$T$20/100/4 -> 0 | AX68: =$T$24*$T$21/100/4 -> 0 | AY68: =$T$24*$T$21/100/4 -> 0 | AZ68: =$T$24*$T$21/100/4 -> 0 | BA68: =$T$24*$T$21/100/4 -> 0 | BE68: =$T$24*$T$19/100/4 -> 0 | BF68: =BE68 -> 0 | BG68: =$T$24*$T$20/100/4 -> 0 | BH68: =BG68 -> 0 | BI68: =$T$24*$T$21/100/4 -> 0 | BJ68: =BI68 -> 0 | BK68: =BJ68 -> 0
A69: MONTH 48 (ADMIN) | D69: =SUM(E69:AZ69) -> 0 | V69: =$T$25*$T$14/100/4 -> 0 | W69: =$T$25*$T$14/100/4 -> 0 | X69: =$T$25*$T$14/100/4 -> 0 | Y69: =$T$25*$T$14/100/4 -> 0 | Z69: =$T$25*$T$15/100/4 -> 0 | AA69: =$T$25*$T$15/100/4 -> 0 | AB69: =$T$25*$T$15/100/4 -> 0 | AC69: =$T$25*$T$15/100/4 -> 0 | AD69: =$T$25*$T$16/100/4 -> 0 | AE69: =$T$25*$T$16/100/4 -> 0 | AF69: =$T$25*$T$16/100/4 -> 0 | AG69: =$T$25*$T$16/100/4 -> 0 | AH69: =$T$25*$T$17/100/4 -> 0 | AI69: =$T$25*$T$17/100/4 -> 0 | AJ69: =$T$25*$T$17/100/4 -> 0 | AK69: =$T$25*$T$17/100/4 -> 0 | AL69: =$T$25*$T$18/100/4 -> 0 | AM69: =$T$25*$T$18/100/4 -> 0 | AN69: =$T$25*$T$18/100/4 -> 0 | AO69: =$T$25*$T$18/100/4 -> 0 | AP69: =$T$25*$T$19/100/4 -> 0 | AQ69: =$T$25*$T$19/100/4 -> 0 | AR69: =$T$25*$T$19/100/4 -> 0 | AS69: =$T$25*$T$19/100/4 -> 0 | AT69: =$T$25*$T$20/100/4 -> 0 | AU69: =$T$25*$T$20/100/4 -> 0 | AV69: =$T$25*$T$20/100/4 -> 0 | AW69: =$T$25*$T$20/100/4 -> 0 | AX69: =$T$25*$T$21/100/4 -> 0 | AY69: =$T$25*$T$21/100/4 -> 0 | AZ69: =$T$25*$T$21/100/4 -> 0 | BA69: =$T$25*$T$21/100/4 -> 0 | BE69: =$T$25*$T$19/100/4 -> 0 | BF69: =BE69 -> 0 | BG69: =$T$25*$T$20/100/4 -> 0 | BH69: =BG69 -> 0 | BI69: =$T$25*$T$21/100/4 -> 0 | BJ69: =BI69 -> 0 | BK69: =BJ69 -> 0
A70: Total colections | D70: =SUM(E70:AZ70) -> 2252979 | E70: =SUM(E31:E69) -> 0 | F70: =SUM(F31:F69) -> 0 | G70: =SUM(G31:G69) -> 15139.237 | H70: =SUM(H31:H69) -> 30278.475 | I70: =SUM(I31:I69) -> 46512.006 | J70: =SUM(J31:J69) -> 62745.537 | K70: =SUM(K31:K69) -> 62365.7 | L70: =SUM(L31:L69) -> 63473.559 | ... AQ70: =SUM(AQ31:AQ69) -> 0
A71: Total Sales NPV | D71: =SUM(E71:AS71) -> 1416830.8 | E71: =+E70/((1+$C$72)^E$73) -> 0 | F71: =+F70/((1+$C$72)^F$73) -> 0 | G71: =+G70/((1+$C$72)^G$73) -> 13722.251 | H71: =+H70/((1+$C$72)^H$73) -> 26560.066 | I71: =+I70/((1+$C$72)^I$73) -> 39485.17 | J71: =+J70/((1+$C$72)^J$73) -> 51549.632 | K71: =+K70/((1+$C$72)^K$73) -> 49586.369 | L71: =+L70/((1+$C$72)^L$73) -> 48840.843 | ... AS71: =+AS70/((1+$C$72)^AS$73) -> 0
A72: Cost Of Capital | B72: % | C72: 0.14
E73: =0.0833333333333333*3 -> 0.25 | F73: =0.25+E73 -> 0.5 | G73: =0.25+F73 -> 0.75 | H73: =0.25+G73 -> 1 | I73: =0.25+H73 -> 1.25 | J73: =0.25+I73 -> 1.5 | K73: =0.25+J73 -> 1.75 | L73: =0.25+K73 -> 2 | M73: =0.25+L73 -> 2.25 | ... AS73: =0.25+AR73 -> 10.25
A75: Total Sales Accumulated NPV | E75: =E71 -> 0 | F75: =E75+F71 -> 0 | G75: =F75+G71 -> 13722.251 | H75: =G75+H71 -> 40282.317 | I75: =H75+I71 -> 79767.487 | J75: =I75+J71 -> 131317.12 | K75: =J75+K71 -> 180903.49 | L75: =K75+L71 -> 229744.33 | M75: =L75+M71 -> 289562.85 | ... AQ75: =AP75+AQ71 -> 1416830.8
A76: Total Sales Accumulated | E76: =SUM(E77:E78) -> 0 | F76: =SUM(F77:F78) -> 0 | G76: =SUM(G77:G78) -> 15139.237 | H76: =SUM(H77:H78) -> 45417.713 | I76: =SUM(I77:I78) -> 91929.719 | J76: =SUM(J77:J78) -> 154675.26 | K76: =SUM(K77:K78) -> 217040.96 | L76: =SUM(L77:L78) -> 280514.52 | ... AS76: =SUM(AS77:AS78) -> 2252979
A77: Bulk Payments Accumulated | E77: =SUM(E31:E36) -> 0 | F77: =E77+SUM(F31:F36) -> 0 | G77: =F77+SUM(G31:G36) -> 15139.237 | H77: =G77+SUM(H31:H36) -> 45417.713 | I77: =H77+SUM(I31:I36) -> 84360.1 | J77: =I77+SUM(J31:J36) -> 131966.4 | K77: =J77+SUM(K31:K36) -> 173242.08 | L77: =K77+SUM(L31:L36) -> 208187.12 | M77: =L77+SUM(M31:M36) -> 254527.3 | ... AS77: =AR77+SUM(AS31:AS36) -> 1003711.6
A78: Instalments Accumulated | E78: =SUM(E38:E69) -> 0 | F78: =E78+SUM(F38:F69) -> 0 | G78: =F78+SUM(G38:G69) -> 0 | H78: =G78+SUM(H38:H69) -> 0 | I78: =H78+SUM(I38:I69) -> 7569.6187 | J78: =I78+SUM(J38:J69) -> 22708.856 | K78: =J78+SUM(K38:K69) -> 43798.881 | L78: =K78+SUM(L38:L69) -> 72327.391 | M78: =L78+SUM(M38:M69) -> 106316.06 | ... AS78: =AR78+SUM(AS38:AS69) -> 1249267.4
A81: NOTES:
A82: 1- LAUNCH : MONTH 3 | E82: =SUM(E14:E21)*E24/100 -> 0 | F82: =SUM(F14:F21)*F24/100 -> 0 | G82: =SUM(G14:G21)*G24/100 -> 68370.75 | H82: =SUM(H14:H21)*H24/100 -> 68370.75 | I82: =SUM(I14:I21)*I24/100 -> 45580.5 | J82: =SUM(J14:J21)*J24/100 -> 45580.5 | K82: =SUM(K14:K21)*K24/100 -> 50138.55 | L82: =SUM(L14:L21)*L24/100 -> 50138.55 | ... U82: =SUM(U14:U21)*U24/100 -> 0
A83: 2- START OF CONSTRUCTION : MONTH 12 | E83: =SUM(E14:E21)*E25/100 -> 0 | F83: =SUM(F14:F21)*F25/100 -> 0 | G83: =SUM(G14:G21)*G25/100 -> 143578.58 | H83: =SUM(H14:H21)*H25/100 -> 143578.58 | I83: =SUM(I14:I21)*I25/100 -> 97238.4 | J83: =SUM(J14:J21)*J25/100 -> 97238.4 | K83: =SUM(K14:K21)*K25/100 -> 54696.6 | L83: =SUM(L14:L21)*L25/100 -> 54696.6 | ... U83: =SUM(U14:U21)*U25/100 -> 0
A85: DELIVERY PAYMENT (COMMERCIAL) | D85: =D70-D24-D25 -> 0 | E85: =E24*E12/100 -> 0 | F85: =F24*F12/100 -> 0 | G85: =G24*G12/100 -> 19534.5 | H85: =H24*H12/100 -> 19534.5 | I85: =I24*I12/100 -> 15193.5 | J85: =J24*J12/100 -> 15193.5 | K85: =K24*K12/100 -> 16712.85 | L85: =L24*L12/100 -> 16712.85 | ... Y85: =Y24*Y12/100 -> 0
A86: DELIVERY PAYMENT (ADMIN) | E86: =E25*E12/100 -> 0 | F86: =F25*F12/100 -> 0 | G86: =G25*G12/100 -> 41022.45 | H86: =H25*H12/100 -> 41022.45 | I86: =I25*I12/100 -> 32412.8 | J86: =J25*J12/100 -> 32412.8 | K86: =K25*K12/100 -> 18232.2 | L86: =L25*L12/100 -> 18232.2 | ... Y86: =Y25*Y12/100 -> 0

Sheet L'avenir
A1: L'AVENIR
B2: BUA (M²) | C2: RETAINED% | D2: Total | E2: M 3 | F2: M 6 | G2: M 9 | H2: M 12 | I2: M 15 | J2: M 18 | K2: M 21 | L2: M 24 | M2: M 27 | N2: M 30 | O2: M 33 | P2: M 36 | Q2: M 39 | R2: M 42 | S2: M 45 | T2: M 48 | U2: M 51 | V2: M 54 | W2: M 57 | X2: M 60 | Y2: M 63 | Z2: M 66 | AA2: M 69 | AB2: M 72 | AC2: M 75 | AD2: M 78 | AE2: M 81 | AF2: M 84 | AG2: M 87 | AH2: M 90 | AI2: M 93 | AJ2: M 96 | AK2: M 99 | AL2: M 102 | AM2: M 105 | AN2: M 108
A3: COMMERCIAL PRICE | E3: 200 | F3: 200 | G3: 225 | H3: 225 | I3: 250 | J3: 250 | K3: 275 | L3: 275 | M3: 300 | N3: 300 | O3: 330 | P3: 330 | Q3: 360 | R3: 360 | S3: 360 | T3: 360
A4: ADMIN PRICE | E4: 125 | F4: 125 | G4: 135 | H4: 135 | I4: 160 | J4: 160 | K4: 180 | L4: 180 | M4: 200 | N4: 200 | O4: 220 | P4: 220 | Q4: 240 | R4: 240 | S4: 240 | T4: 240
A5: DELIVERY DATE(month) | C5: 48 | E5: =IF(C5-3<0,0,C5-3) -> 45 | F5: =IF(E5-3<0,0,E5-3) -> 42 | G5: =IF(F5-3<0,0,F5-3) -> 39 | H5: =IF(G5-3<0,0,G5-3) -> 36 | I5: =IF(H5-3<0,0,H5-3) -> 33 | J5: =IF(I5-3<0,0,I5-3) -> 30 | K5: =IF(J5-3<0,0,J5-3) -> 27 | L5: =IF(K5-3<0,0,K5-3) -> 24 | M5: =IF(L5-3<0,0,L5-3) -> 21 | ... T5: =IF(S5-3<0,0,S5-3) -> 0
A6: TARGET SALES % COMM. | B6: 4473 | C6: 20 | I6: 10 | J6: 10 | K6: 10 | L6: 7 | M6: 7 | N6: 6 | O6: 5 | P6: 5 | Q6: 5 | R6: 5 | S6: 5 | T6: 5
A7: TARGET SALES % ADMIN | B7: 10437 | C7: 20 | I7: 15 | J7: 15 | K7: 10 | L7: 5 | M7: 5 | N7: 5 | O7: 5 | P7: 5 | Q7: 5 | R7: 5 | S7: 2.5 | T7: 2.5
A8: INSTALLMENTS (YRS) | I8: 8 | J8: 8 | K8: 8 | L8: 6 | M8: 6 | N8: 6 | O8: 4 | P8: 4 | Q8: 4 | R8: 3 | S8: 3 | T8: 2
A10: DOWN PAYMENT % | I10: 5 | J10: 5 | K10: 10 | L10: 10 | M10: 10 | N10: 10 | O10: 15 | P10: 15 | Q10: 15 | R10: 15 | S10: 20 | T10: 20
A11: 3 MONTHS % | I11: 5 | J11: 5 | K11: 10 | L11: 10 | M11: 10 | N11: 10 | O11: 15 | P11: 15 | Q11: 15 | R11: 15 | S11: 20 | T11: 20
A12: DELIVERY PAYMENT % | I12: 20 | J12: 20 | K12: 20 | L12: 20 | M12: 20 | N12: 20 | O12: 25 | P12: 25 | Q12: 25 | R12: 25 | S12: 25 | T12: 25
A14: YEAR 1 (4Q) % | I14: 10 | J14: 12 | K14: 12 | L14: 12 | M14: 15 | N14: 15 | O14: 15 | P14: 15 | Q14: 15 | R14: 15 | S14: 15 | T14: 15
A15: YEAR 2 (4Q) % | I15: 10 | J15: 12 | K15: 12 | L15: 12 | M15: 15 | N15: 15 | O15: 15 | P15: 15 | Q15: 15 | R15: 15 | S15: 10 | T15: 10
A16: YEAR 3 (4Q) % | I16: 10 | J16: 12 | K16: 12 | L16: 12 | M16: 15 | N16: 15 | O16: 7.5 | P16: 7.5 | Q16: 7.5 | R16: 7.5 | S16: 10 | T16: 10
A17: YEAR 4 (4Q) % | I17: 8 | J17: 10 | K17: 8 | L17: 8 | M17: 5 | N17: 5 | O17: 7.5 | P17: 7.5 | Q17: 7.5 | R17: 7.5 | S17: 0 | T17: 0
A18: YEAR 5 (4Q) % | I18: 8 | J18: 8 | K18: 8 | L18: 8 | M18: 5 | N18: 5 | O18: 0 | P18: 0 | Q18: 0 | R18: 0 | S18: 0 | T18: 0
A19: YEAR 6 (4Q) % | I19: 8 | J19: 8 | K19: 8 | L19: 8 | M19: 5 | N19: 5 | O19: 0 | P19: 0 | Q19: 0 | R19: 0 | S19: 0 | T19: 0
A20: YEAR 7 (4Q) % | I20: 8 | J20: 8 | K20: 0 | L20: 0 | M20: 0 | N20: 0 | O20: 0 | P20: 0 | Q20: 0 | R20: 0 | S20: 0 | T20: 0
A21: YEAR 8 (4Q) % | I21: 8 | J21: 0 | K21: 0 | L21: 0 | M21: 0 | N21: 0 | O21: 0 | P21: 0 | Q21: 0 | R21: 0 | S21: 0 | T21: 0
A24: Total Sales(COMMERCIAL) | D24: =SUM(E24:T24) -> 1076874.8 | E24: =E3*$B$6*(E6/100) -> 0 | F24: =F3*$B$6*(F6/100) -> 0 | G24: =G3*$B$6*(G6/100) -> 0 | H24: =H3*$B$6*(H6/100) -> 0 | I24: =I3*$B$6*(I6/100) -> 111825 | J24: =J3*$B$6*(J6/100) -> 111825 | K24: =K3*$B$6*(K6/100) -> 123007.5 | L24: =L3*$B$6*(L6/100) -> 86105.25 | ... T24: =T3*$B$6*(T6/100) -> 80514
A25: Total Sales (ADMIN) | D25: =SUM(E25:T25) -> 1596861 | E25: =E4*$B$7*(E7/100) -> 0 | F25: =F4*$B$7*(F7/100) -> 0 | G25: =G4*$B$7*(G7/100) -> 0 | H25: =H4*$B$7*(H7/100) -> 0 | I25: =I4*$B$7*(I7/100) -> 250488 | J25: =J4*$B$7*(J7/100) -> 250488 | K25: =K4*$B$7*(K7/100) -> 187866 | L25: =L4*$B$7*(L7/100) -> 93933 | ... T25: =T4*$B$7*(T7/100) -> 62622
A26: Total Sales | D26: =SUM(D24:D25) -> 2673735.8 | E26: =SUM(E24:E25) -> 0 | F26: =SUM(F24:F25) -> 0 | G26: =SUM(G24:G25) -> 0 | H26: =SUM(H24:H25) -> 0 | I26: =SUM(I24:I25) -> 362313 | J26: =SUM(J24:J25) -> 362313 | K26: =SUM(K24:K25) -> 310873.5 | ... T26: =SUM(T24:T25) -> 143136
E27: =E26 -> 0 | F27: =E27+F26 -> 0 | G27: =E27+G26 -> 0 | H27: =G27+H26 -> 0 | I27: =H27+I26 -> 362313 | J27: =I27+J26 -> 724626 | K27: =J27+K26 -> 1035499.5 | L27: =K27+L26 -> 1215537.8 | M27: =L27+M26 -> 1413840.8 | N27: =M27+N26 -> 1598724.8 | O27: =N27+O26 -> 1787336.2 | ... T27: =S27+T26 -> 2673735.8
G28: =G26*4% -> 0 | H28: =H26*4% -> 0 | I28: =I26*4% -> 14492.52 | J28: =J26*4% -> 14492.52 | K28: =K26*4% -> 12434.94 | L28: =L26*4% -> 7201.53 | M28: =M26*4% -> 7932.12 | N28: =N26*4% -> 7395.36 | ... T28: =T26*4% -> 5725.44
D29: Total | E29: M 3 | F29: M 6 | G29: M 9 | H29: M 12 | I29: M 15 | J29: M 18 | K29: M 21 | L29: M 24 | M29: M 27 | N29: M 30 | O29: M 33 | P29: M 36 | Q29: M 39 | R29: M 42 | S29: M 45 | T29: M 48 | U29: M 51 | V29: M 54 | W29: M 57 | X29: M 60 | Y29: M 63 | Z29: M 66 | AA29: M 69 | AB29: M 72 | AC29: M 75 | AD29: M 78 | AE29: M 81 | AF29: M 84 | AG29: M 87 | AH29: M 90 | AI29: M 93 | AJ29: M 96 | AK29: M 99 | AL29: M 102 | AM29: M 105 | AN29: M 108
A30: Bulk Payments
A31: DOWN PAYMENT (COMMERCIAL) | D31: =SUM(E31:AZ31) -> 128039.62 | E31: =E3*$B$6*(E6/100)*E10/100 -> 0 | F31: =F3*$B$6*(F6/100)*F10/100 -> 0 | G31: =G3*$B$6*(G6/100)*G10/100 -> 0 | H31: =H3*$B$6*(H6/100)*H10/100 -> 0 | I31: =I3*$B$6*(I6/100)*I10/100 -> 5591.25 | J31: =J3*$B$6*(J6/100)*J10/100 -> 5591.25 | K31: =K3*$B$6*(K6/100)*K10/100 -> 12300.75 | L31: =L3*$B$6*(L6/100)*L10/100 -> 8610.525 | ... V31: =V3*$B$6*(V6/100)*V10/100 -> 0
A32: DOWN PAYMENT (ADMIN) | D32: =SUM(E32:AZ32) -> 171166.8 | E32: =E4*$B$7*(E7/100)*E10/100 -> 0 | F32: =F4*$B$7*(F7/100)*F10/100 -> 0 | G32: =G4*$B$7*(G7/100)*G10/100 -> 0 | H32: =H4*$B$7*(H7/100)*H10/100 -> 0 | I32: =I4*$B$7*(I7/100)*I10/100 -> 12524.4 | J32: =J4*$B$7*(J7/100)*J10/100 -> 12524.4 | K32: =K4*$B$7*(K7/100)*K10/100 -> 18786.6 | L32: =L4*$B$7*(L7/100)*L10/100 -> 9393.3 | ... V32: =V4*$B$7*(V7/100)*V10/100 -> 0
A33: 3 MONTHS (COMMERCIAL) | D33: =SUM(E33:AZ33) -> 128039.62 | F33: =E31 -> 0 | G33: =F31 -> 0 | H33: =G31 -> 0 | I33: =H31 -> 0 | J33: =I31 -> 5591.25 | K33: =J31 -> 5591.25 | L33: =K31 -> 12300.75 | M33: =L31 -> 8610.525 | ... V33: =U31 -> 0
A34: 3 MONTHS (ADMIN) | D34: =SUM(E34:AZ34) -> 171166.8 | F34: =E32 -> 0 | G34: =F32 -> 0 | H34: =G32 -> 0 | I34: =H32 -> 0 | J34: =I32 -> 12524.4 | K34: =J32 -> 12524.4 | L34: =K32 -> 18786.6 | M34: =L32 -> 9393.3 | ... V34: =U32 -> 0
A35: DELIVERY PAYMENT (COMMERCIAL) | D35: =SUM(E35:AZ35) -> 238858.2 | S35: =SUM(E85:S85) -> 218729.7 | T35: =SUM(T85) -> 20128.5 | U35: =SUM(U85) -> 0 | V35: =SUM(V85) -> 0 | W35: =SUM(W85) -> 0
A36: DELIVERY PAYMENT (ADMIN) | D36: =SUM(E36:AZ36) -> 349639.5 | S36: =SUM(E86:S86) -> 333984 | T36: =SUM(T86) -> 15655.5 | U36: =SUM(U86) -> 0 | V36: =SUM(V86) -> 0 | W36: =SUM(W86) -> 0
A37: Instalments | D37: =SUM(E37:AZ37) -> 0
A38: MONTH 3 (COMMERCIAL) | D38: =SUM(E38:AZ38) -> 0 | G38: =$E$24*$E$14/100/4 -> 0 | H38: =$E$24*$E$14/100/4 -> 0 | I38: =$E$24*$E$14/100/4 -> 0 | J38: =$E$24*$E$14/100/4 -> 0 | K38: =$E$24*$E$15/100/4 -> 0 | L38: =$E$24*$E$15/100/4 -> 0 | M38: =$E$24*$E$15/100/4 -> 0 | N38: =$E$24*$E$15/100/4 -> 0 | O38: =$E$24*$E$16/100/4 -> 0 | P38: =$E$24*$E$16/100/4 -> 0 | Q38: =$E$24*$E$16/100/4 -> 0 | R38: =$E$24*$E$16/100/4 -> 0 | S38: =$E$24*$E$17/100/4 -> 0 | T38: =$E$24*$E$17/100/4 -> 0 | U38: =$E$24*$E$17/100/4 -> 0 | V38: =$E$24*$E$17/100/4 -> 0 | W38: =$E$24*$E$18/100/4 -> 0 | X38: =$E$24*$E$18/100/4 -> 0 | Y38: =$E$24*$E$18/100/4 -> 0 | Z38: =$E$24*$E$18/100/4 -> 0 | AA38: =$E$24*$E$19/100/4 -> 0 | AB38: =$E$24*$E$19/100/4 -> 0 | AC38: =$E$24*$E$19/100/4 -> 0 | AD38: =$E$24*$E$19/100/4 -> 0 | AE38: =$E$24*$E$20/100/4 -> 0 | AF38: =$E$24*$E$20/100/4 -> 0 | AG38: =$E$24*$E$20/100/4 -> 0 | AH38: =$E$24*$E$20/100/4 -> 0 | AI38: =$E$24*$E$21/100/4 -> 0 | AJ38: =$E$24*$E$21/100/4 -> 0 | AK38: =$E$24*$E$21/100/4 -> 0 | AL38: =$E$24*$E$21/100/4 -> 0
A39: MONTH 3 (ADMIN) | D39: =SUM(E39:AZ39) -> 0 | G39: =$E$25*$E$14/100/4 -> 0 | H39: =$E$25*$E$14/100/4 -> 0 | I39: =$E$25*$E$14/100/4 -> 0 | J39: =$E$25*$E$14/100/4 -> 0 | K39: =$E$25*$E$15/100/4 -> 0 | L39: =$E$25*$E$15/100/4 -> 0 | M39: =$E$25*$E$15/100/4 -> 0 | N39: =$E$25*$E$15/100/4 -> 0 | O39: =$E$25*$E$16/100/4 -> 0 | P39: =$E$25*$E$16/100/4 -> 0 | Q39: =$E$25*$E$16/100/4 -> 0 | R39: =$E$25*$E$16/100/4 -> 0 | S39: =$E$25*$E$17/100/4 -> 0 | T39: =$E$25*$E$17/100/4 -> 0 | U39: =$E$25*$E$17/100/4 -> 0 | V39: =$E$25*$E$17/100/4 -> 0 | W39: =$E$25*$E$18/100/4 -> 0 | X39: =$E$25*$E$18/100/4 -> 0 | Y39: =$E$25*$E$18/100/4 -> 0 | Z39: =$E$25*$E$18/100/4 -> 0 | AA39: =$E$25*$E$19/100/4 -> 0 | AB39: =$E$25*$E$19/100/4 -> 0 | AC39: =$E$25*$E$19/100/4 -> 0 | AD39: =$E$25*$E$19/100/4 -> 0 | AE39: =$E$25*$E$20/100/4 -> 0 | AF39: =$E$25*$E$20/100/4 -> 0 | AG39: =$E$25*$E$20/100/4 -> 0 | AH39: =$E$25*$E$20/100/4 -> 0 | AI39: =$E$25*$E$21/100/4 -> 0 | AJ39: =$E$25*$E$21/100/4 -> 0 | AK39: =$E$25*$E$21/100/4 -> 0 | AL39: =$E$25*$E$21/100/4 -> 0
A40: MONTH 6 (COMMERCIAL) | D40: =SUM(E40:AZ40) -> 0 | H40: =$F$24*$F$14/100/4 -> 0 | I40: =$F$24*$F$14/100/4 -> 0 | J40: =$F$24*$F$14/100/4 -> 0 | K40: =$F$24*$F$14/100/4 -> 0 | L40: =$F$24*$F$15/100/4 -> 0 | M40: =$F$24*$F$15/100/4 -> 0 | N40: =$F$24*$F$15/100/4 -> 0 | O40: =$F$24*$F$15/100/4 -> 0 | P40: =$F$24*$F$16/100/4 -> 0 | Q40: =$F$24*$F$16/100/4 -> 0 | R40: =$F$24*$F$16/100/4 -> 0 | S40: =$F$24*$F$16/100/4 -> 0 | T40: =$F$24*$F$17/100/4 -> 0 | U40: =$F$24*$F$17/100/4 -> 0 | V40: =$F$24*$F$17/100/4 -> 0 | W40: =$F$24*$F$17/100/4 -> 0 | X40: =$F$24*$F$18/100/4 -> 0 | Y40: =$F$24*$F$18/100/4 -> 0 | Z40: =$F$24*$F$18/100/4 -> 0 | AA40: =$F$24*$F$18/100/4 -> 0 | AB40: =$F$24*$F$19/100/4 -> 0 | AC40: =$F$24*$F$19/100/4 -> 0 | AD40: =$F$24*$F$19/100/4 -> 0 | AE40: =$F$24*$F$19/100/4 -> 0 | AF40: =$F$24*$F$20/100/4 -> 0 | AG40: =$F$24*$F$20/100/4 -> 0 | AH40: =$F$24*$F$20/100/4 -> 0 | AI40: =$F$24*$F$20/100/4 -> 0 | AJ40: =$F$24*$F$21/100/4 -> 0 | AK40: =$F$24*$F$21/100/4 -> 0 | AL40: =$F$24*$F$21/100/4 -> 0 | AM40: =$F$24*$F$21/100/4 -> 0
A41: MONTH 6 (ADMIN) | D41: =SUM(E41:AZ41) -> 0 | H41: =$F$25*$F$14/100/4 -> 0 | I41: =$F$25*$F$14/100/4 -> 0 | J41: =$F$25*$F$14/100/4 -> 0 | K41: =$F$25*$F$14/100/4 -> 0 | L41: =$F$25*$F$15/100/4 -> 0 | M41: =$F$25*$F$15/100/4 -> 0 | N41: =$F$25*$F$15/100/4 -> 0 | O41: =$F$25*$F$15/100/4 -> 0 | P41: =$F$25*$F$16/100/4 -> 0 | Q41: =$F$25*$F$16/100/4 -> 0 | R41: =$F$25*$F$16/100/4 -> 0 | S41: =$F$25*$F$16/100/4 -> 0 | T41: =$F$25*$F$17/100/4 -> 0 | U41: =$F$25*$F$17/100/4 -> 0 | V41: =$F$25*$F$17/100/4 -> 0 | W41: =$F$25*$F$17/100/4 -> 0 | X41: =$F$25*$F$18/100/4 -> 0 | Y41: =$F$25*$F$18/100/4 -> 0 | Z41: =$F$25*$F$18/100/4 -> 0 | AA41: =$F$25*$F$18/100/4 -> 0 | AB41: =$F$25*$F$19/100/4 -> 0 | AC41: =$F$25*$F$19/100/4 -> 0 | AD41: =$F$25*$F$19/100/4 -> 0 | AE41: =$F$25*$F$19/100/4 -> 0 | AF41: =$F$25*$F$20/100/4 -> 0 | AG41: =$F$25*$F$20/100/4 -> 0 | AH41: =$F$25*$F$20/100/4 -> 0 | AI41: =$F$25*$F$20/100/4 -> 0 | AJ41: =$F$25*$F$21/100/4 -> 0 | AK41: =$F$25*$F$21/100/4 -> 0 | AL41: =$F$25*$F$21/100/4 -> 0 | AM41: =$F$25*$F$21/100/4 -> 0
A42: MONTH 9 (COMMERCIAL) | D42: =SUM(E42:AZ42) -> 0 | I42: =$G$24*$G$14/100/4 -> 0 | J42: =$G$24*$G$14/100/4 -> 0 | K42: =$G$24*$G$14/100/4 -> 0 | L42: =$G$24*$G$14/100/4 -> 0 | M42: =$G$24*$G$15/100/4 -> 0 | N42: =$G$24*$G$15/100/4 -> 0 | O42: =$G$24*$G$15/100/4 -> 0 | P42: =$G$24*$G$15/100/4 -> 0 | Q42: =$G$24*$G$16/100/4 -> 0 | R42: =$G$24*$G$16/100/4 -> 0 | S42: =$G$24*$G$16/100/4 -> 0 | T42: =$G$24*$G$16/100/4 -> 0 | U42: =$G$24*$G$17/100/4 -> 0 | V42: =$G$24*$G$17/100/4 -> 0 | W42: =$G$24*$G$17/100/4 -> 0 | X42: =$G$24*$G$17/100/4 -> 0 | Y42: =$G$24*$G$18/100/4 -> 0 | Z42: =$G$24*$G$18/100/4 -> 0 | AA42: =$G$24*$G$18/100/4 -> 0 | AB42: =$G$24*$G$18/100/4 -> 0 | AC42: =$G$24*$G$19/100/4 -> 0 | AD42: =$G$24*$G$19/100/4 -> 0 | AE42: =$G$24*$G$19/100/4 -> 0 | AF42: =$G$24*$G$19/100/4 -> 0 | AG42: =$G$24*$G$20/100/4 -> 0 | AH42: =$G$24*$G$20/100/4 -> 0 | AI42: =$G$24*$G$20/100/4 -> 0 | AJ42: =$G$24*$G$20/100/4 -> 0 | AK42: =$G$24*$G$21/100/4 -> 0 | AL42: =$G$24*$G$21/100/4 -> 0 | AM42: =$G$24*$G$21/100/4 -> 0 | AN42: =$G$24*$G$21/100/4 -> 0
A43: MONTH 9 (ADMIN) | D43: =SUM(E43:AZ43) -> 0 | I43: =$G$25*$G$14/100/4 -> 0 | J43: =$G$25*$G$14/100/4 -> 0 | K43: =$G$25*$G$14/100/4 -> 0 | L43: =$G$25*$G$14/100/4 -> 0 | M43: =$G$25*$G$15/100/4 -> 0 | N43: =$G$25*$G$15/100/4 -> 0 | O43: =$G$25*$G$15/100/4 -> 0 | P43: =$G$25*$G$15/100/4 -> 0 | Q43: =$G$25*$G$16/100/4 -> 0 | R43: =$G$25*$G$16/100/4 -> 0 | S43: =$G$25*$G$16/100/4 -> 0 | T43: =$G$25*$G$16/100/4 -> 0 | U43: =$G$25*$G$17/100/4 -> 0 | V43: =$G$25*$G$17/100/4 -> 0 | W43: =$G$25*$G$17/100/4 -> 0 | X43: =$G$25*$G$17/100/4 -> 0 | Y43: =$G$25*$G$18/100/4 -> 0 | Z43: =$G$25*$G$18/100/4 -> 0 | AA43: =$G$25*$G$18/100/4 -> 0 | AB43: =$G$25*$G$18/100/4 -> 0 | AC43: =$G$25*$G$19/100/4 -> 0 | AD43: =$G$25*$G$19/100/4 -> 0 | AE43: =$G$25*$G$19/100/4 -> 0 | AF43: =$G$25*$G$19/100/4 -> 0 | AG43: =$G$25*$G$20/100/4 -> 0 | AH43: =$G$25*$G$20/100/4 -> 0 | AI43: =$G$25*$G$20/100/4 -> 0 | AJ43: =$G$25*$G$20/100/4 -> 0 | AK43: =$G$25*$G$21/100/4 -> 0 | AL43: =$G$25*$G$21/100/4 -> 0 | AM43: =$G$25*$G$21/100/4 -> 0 | AN43: =$G$25*$G$21/100/4 -> 0
A44: MONTH 12 (COMMERCIAL) | D44: =SUM(E44:AZ44) -> 0 | J44: =$H$24*$H$14/100/4 -> 0 | K44: =$H$24*$H$14/100/4 -> 0 | L44: =$H$24*$H$14/100/4 -> 0 | M44: =$H$24*$H$14/100/4 -> 0 | N44: =$H$24*$H$15/100/4 -> 0 | O44: =$H$24*$H$15/100/4 -> 0 | P44: =$H$24*$H$15/100/4 -> 0 | Q44: =$H$24*$H$15/100/4 -> 0 | R44: =$H$24*$H$16/100/4 -> 0 | S44: =$H$24*$H$16/100/4 -> 0 | T44: =$H$24*$H$16/100/4 -> 0 | U44: =$H$24*$H$16/100/4 -> 0 | V44: =$H$24*$H$17/100/4 -> 0 | W44: =$H$24*$H$17/100/4 -> 0 | X44: =$H$24*$H$17/100/4 -> 0 | Y44: =$H$24*$H$17/100/4 -> 0 | Z44: =$H$24*$H$18/100/4 -> 0 | AA44: =$H$24*$H$18/100/4 -> 0 | AB44: =$H$24*$H$18/100/4 -> 0 | AC44: =$H$24*$H$18/100/4 -> 0 | AD44: =$H$24*$H$19/100/4 -> 0 | AE44: =$H$24*$H$19/100/4 -> 0 | AF44: =$H$24*$H$19/100/4 -> 0 | AG44: =$H$24*$H$19/100/4 -> 0 | AH44: =$H$24*$H$20/100/4 -> 0 | AI44: =$H$24*$H$20/100/4 -> 0 | AJ44: =$H$24*$H$20/100/4 -> 0 | AK44: =$H$24*$H$20/100/4 -> 0 | AL44: =$H$24*$H$21/100/4 -> 0 | AM44: =$H$24*$H$21/100/4 -> 0 | AN44: =$H$24*$H$21/100/4 -> 0 | AO44: =$H$24*$H$21/100/4 -> 0
A45: MONTH 12 (ADMIN) | D45: =SUM(E45:AZ45) -> 0 | J45: =$H$25*$H$14/100/4 -> 0 | K45: =$H$25*$H$14/100/4 -> 0 | L45: =$H$25*$H$14/100/4 -> 0 | M45: =$H$25*$H$14/100/4 -> 0 | N45: =$H$25*$H$15/100/4 -> 0 | O45: =$H$25*$H$15/100/4 -> 0 | P45: =$H$25*$H$15/100/4 -> 0 | Q45: =$H$25*$H$15/100/4 -> 0 | R45: =$H$25*$H$16/100/4 -> 0 | S45: =$H$25*$H$16/100/4 -> 0 | T45: =$H$25*$H$16/100/4 -> 0 | U45: =$H$25*$H$16/100/4 -> 0 | V45: =$H$25*$H$17/100/4 -> 0 | W45: =$H$25*$H$17/100/4 -> 0 | X45: =$H$25*$H$17/100/4 -> 0 | Y45: =$H$25*$H$17/100/4 -> 0 | Z45: =$H$25*$H$18/100/4 -> 0 | AA45: =$H$25*$H$18/100/4 -> 0 | AB45: =$H$25*$H$18/100/4 -> 0 | AC45: =$H$25*$H$18/100/4 -> 0 | AD45: =$H$25*$H$19/100/4 -> 0 | AE45: =$H$25*$H$19/100/4 -> 0 | AF45: =$H$25*$H$19/100/4 -> 0 | AG45: =$H$25*$H$19/100/4 -> 0 | AH45: =$H$25*$H$20/100/4 -> 0 | AI45: =$H$25*$H$20/100/4 -> 0 | AJ45: =$H$25*$H$20/100/4 -> 0 | AK45: =$H$25*$H$20/100/4 -> 0 | AL45: =$H$25*$H$21/100/4 -> 0 | AM45: =$H$25*$H$21/100/4 -> 0 | AN45: =$H$25*$H$21/100/4 -> 0 | AO45: =$H$25*$H$21/100/4 -> 0
A46: MONTH 15 (COMMERCIAL) | D46: =SUM(E46:AZ46) -> 78277.5 | K46: =$I$24*$I$14/100/4 -> 2795.625 | L46: =$I$24*$I$14/100/4 -> 2795.625 | M46: =$I$24*$I$14/100/4 -> 2795.625 | N46: =$I$24*$I$14/100/4 -> 2795.625 | O46: =$I$24*$I$15/100/4 -> 2795.625 | P46: =$I$24*$I$15/100/4 -> 2795.625 | Q46: =$I$24*$I$15/100/4 -> 2795.625 | R46: =$I$24*$I$15/100/4 -> 2795.625 | S46: =$I$24*$I$16/100/4 -> 2795.625 | T46: =$I$24*$I$16/100/4 -> 2795.625 | U46: =$I$24*$I$16/100/4 -> 2795.625 | V46: =$I$24*$I$16/100/4 -> 2795.625 | W46: =$I$24*$I$17/100/4 -> 2236.5 | X46: =$I$24*$I$17/100/4 -> 2236.5 | Y46: =$I$24*$I$17/100/4 -> 2236.5 | Z46: =$I$24*$I$17/100/4 -> 2236.5 | AA46: =$I$24*$I$18/100/4 -> 2236.5 | AB46: =$I$24*$I$18/100/4 -> 2236.5 | AC46: =$I$24*$I$18/100/4 -> 2236.5 | AD46: =$I$24*$I$18/100/4 -> 2236.5 | AE46: =$I$24*$I$19/100/4 -> 2236.5 | AF46: =$I$24*$I$19/100/4 -> 2236.5 | AG46: =$I$24*$I$19/100/4 -> 2236.5 | AH46: =$I$24*$I$19/100/4 -> 2236.5 | AI46: =$I$24*$I$20/100/4 -> 2236.5 | AJ46: =$I$24*$I$20/100/4 -> 2236.5 | AK46: =$I$24*$I$20/100/4 -> 2236.5 | AL46: =$I$24*$I$20/100/4 -> 2236.5 | AM46: =$I$24*$I$21/100/4 -> 2236.5 | AN46: =$I$24*$I$21/100/4 -> 2236.5 | AO46: =$I$24*$I$21/100/4 -> 2236.5 | AP46: =$I$24*$I$21/100/4 -> 2236.5
A47: MONTH 15 (ADMIN) | D47: =SUM(E47:AZ47) -> 175341.6 | K47: =$I$25*$I$14/100/4 -> 6262.2 | L47: =$I$25*$I$14/100/4 -> 6262.2 | M47: =$I$25*$I$14/100/4 -> 6262.2 | N47: =$I$25*$I$14/100/4 -> 6262.2 | O47: =$I$25*$I$15/100/4 -> 6262.2 | P47: =$I$25*$I$15/100/4 -> 6262.2 | Q47: =$I$25*$I$15/100/4 -> 6262.2 | R47: =$I$25*$I$15/100/4 -> 6262.2 | S47: =$I$25*$I$16/100/4 -> 6262.2 | T47: =$I$25*$I$16/100/4 -> 6262.2 | U47: =$I$25*$I$16/100/4 -> 6262.2 | V47: =$I$25*$I$16/100/4 -> 6262.2 | W47: =$I$25*$I$17/100/4 -> 5009.76 | X47: =$I$25*$I$17/100/4 -> 5009.76 | Y47: =$I$25*$I$17/100/4 -> 5009.76 | Z47: =$I$25*$I$17/100/4 -> 5009.76 | AA47: =$I$25*$I$18/100/4 -> 5009.76 | AB47: =$I$25*$I$18/100/4 -> 5009.76 | AC47: =$I$25*$I$18/100/4 -> 5009.76 | AD47: =$I$25*$I$18/100/4 -> 5009.76 | AE47: =$I$25*$I$19/100/4 -> 5009.76 | AF47: =$I$25*$I$19/100/4 -> 5009.76 | AG47: =$I$25*$I$19/100/4 -> 5009.76 | AH47: =$I$25*$I$19/100/4 -> 5009.76 | AI47: =$I$25*$I$20/100/4 -> 5009.76 | AJ47: =$I$25*$I$20/100/4 -> 5009.76 | AK47: =$I$25*$I$20/100/4 -> 5009.76 | AL47: =$I$25*$I$20/100/4 -> 5009.76 | AM47: =$I$25*$I$21/100/4 -> 5009.76 | AN47: =$I$25*$I$21/100/4 -> 5009.76 | AO47: =$I$25*$I$21/100/4 -> 5009.76 | AP47: =$I$25*$I$21/100/4 -> 5009.76
A48: MONTH 18 (COMMERCIAL) | D48: =SUM(E48:AZ48) -> 78277.5 | L48: =$J$24*$J$14/100/4 -> 3354.75 | M48: =$J$24*$J$14/100/4 -> 3354.75 | N48: =$J$24*$J$14/100/4 -> 3354.75 | O48: =$J$24*$J$14/100/4 -> 3354.75 | P48: =$J$24*$J$15/100/4 -> 3354.75 | Q48: =$J$24*$J$15/100/4 -> 3354.75 | R48: =$J$24*$J$15/100/4 -> 3354.75 | S48: =$J$24*$J$15/100/4 -> 3354.75 | T48: =$J$24*$J$16/100/4 -> 3354.75 | U48: =$J$24*$J$16/100/4 -> 3354.75 | V48: =$J$24*$J$16/100/4 -> 3354.75 | W48: =$J$24*$J$16/100/4 -> 3354.75 | X48: =$J$24*$J$17/100/4 -> 2795.625 | Y48: =$J$24*$J$17/100/4 -> 2795.625 | Z48: =$J$24*$J$17/100/4 -> 2795.625 | AA48: =$J$24*$J$17/100/4 -> 2795.625 | AB48: =$J$24*$J$18/100/4 -> 2236.5 | AC48: =$J$24*$J$18/100/4 -> 2236.5 | AD48: =$J$24*$J$18/100/4 -> 2236.5 | AE48: =$J$24*$J$18/100/4 -> 2236.5 | AF48: =$J$24*$J$19/100/4 -> 2236.5 | AG48: =$J$24*$J$19/100/4 -> 2236.5 | AH48: =$J$24*$J$19/100/4 -> 2236.5 | AI48: =$J$24*$J$19/100/4 -> 2236.5 | AJ48: =$J$24*$J$20/100/4 -> 2236.5 | AK48: =$J$24*$J$20/100/4 -> 2236.5 | AL48: =$J$24*$J$20/100/4 -> 2236.5 | AM48: =$J$24*$J$20/100/4 -> 2236.5 | AN48: =$J$24*$J$21/100/4 -> 0 | AO48: =$J$24*$J$21/100/4 -> 0 | AP48: =$J$24*$J$21/100/4 -> 0 | AQ48: =$J$24*$J$21/100/4 -> 0
A49: MONTH 18 (ADMIN) | D49: =SUM(E49:AZ49) -> 175341.6 | L49: =$J$25*$J$14/100/4 -> 7514.64 | M49: =$J$25*$J$14/100/4 -> 7514.64 | N49: =$J$25*$J$14/100/4 -> 7514.64 | O49: =$J$25*$J$14/100/4 -> 7514.64 | P49: =$J$25*$J$15/100/4 -> 7514.64 | Q49: =$J$25*$J$15/100/4 -> 7514.64 | R49: =$J$25*$J$15/100/4 -> 7514.64 | S49: =$J$25*$J$15/100/4 -> 7514.64 | T49: =$J$25*$J$16/100/4 -> 7514.64 | U49: =$J$25*$J$16/100/4 -> 7514.64 | V49: =$J$25*$J$16/100/4 -> 7514.64 | W49: =$J$25*$J$16/100/4 -> 7514.64 | X49: =$J$25*$J$17/100/4 -> 6262.2 | Y49: =$J$25*$J$17/100/4 -> 6262.2 | Z49: =$J$25*$J$17/100/4 -> 6262.2 | AA49: =$J$25*$J$17/100/4 -> 6262.2 | AB49: =$J$25*$J$18/100/4 -> 5009.76 | AC49: =$J$25*$J$18/100/4 -> 5009.76 | AD49: =$J$25*$J$18/100/4 -> 5009.76 | AE49: =$J$25*$J$18/100/4 -> 5009.76 | AF49: =$J$25*$J$19/100/4 -> 5009.76 | AG49: =$J$25*$J$19/100/4 -> 5009.76 | AH49: =$J$25*$J$19/100/4 -> 5009.76 | AI49: =$J$25*$J$19/100/4 -> 5009.76 | AJ49: =$J$25*$J$20/100/4 -> 5009.76 | AK49: =$J$25*$J$20/100/4 -> 5009.76 | AL49: =$J$25*$J$20/100/4 -> 5009.76 | AM49: =$J$25*$J$20/100/4 -> 5009.76 | AN49: =$J$25*$J$21/100/4 -> 0 | AO49: =$J$25*$J$21/100/4 -> 0 | AP49: =$J$25*$J$21/100/4 -> 0 | AQ49: =$J$25*$J$21/100/4 -> 0 | AU49: =AS49 -> 0 | AV49: =AU49 -> 0
A50: MONTH 21 (COMMERCIAL) | D50: =SUM(E50:AZ50) -> 73804.5 | M50: =$K$24*$K$14/100/4 -> 3690.225 | N50: =$K$24*$K$14/100/4 -> 3690.225 | O50: =$K$24*$K$14/100/4 -> 3690.225 | P50: =$K$24*$K$14/100/4 -> 3690.225 | Q50: =$K$24*$K$15/100/4 -> 3690.225 | R50: =$K$24*$K$15/100/4 -> 3690.225 | S50: =$K$24*$K$15/100/4 -> 3690.225 | T50: =$K$24*$K$15/100/4 -> 3690.225 | U50: =$K$24*$K$16/100/4 -> 3690.225 | V50: =$K$24*$K$16/100/4 -> 3690.225 | W50: =$K$24*$K$16/100/4 -> 3690.225 | X50: =$K$24*$K$16/100/4 -> 3690.225 | Y50: =$K$24*$K$17/100/4 -> 2460.15 | Z50: =$K$24*$K$17/100/4 -> 2460.15 | AA50: =$K$24*$K$17/100/4 -> 2460.15 | AB50: =$K$24*$K$17/100/4 -> 2460.15 | AC50: =$K$24*$K$18/100/4 -> 2460.15 | AD50: =$K$24*$K$18/100/4 -> 2460.15 | AE50: =$K$24*$K$18/100/4 -> 2460.15 | AF50: =$K$24*$K$18/100/4 -> 2460.15 | AG50: =$K$24*$K$19/100/4 -> 2460.15 | AH50: =$K$24*$K$19/100/4 -> 2460.15 | AI50: =$K$24*$K$19/100/4 -> 2460.15 | AJ50: =$K$24*$K$19/100/4 -> 2460.15 | AK50: =$K$24*$K$20/100/4 -> 0 | AL50: =$K$24*$K$20/100/4 -> 0 | AM50: =$K$24*$K$20/100/4 -> 0 | AN50: =$K$24*$K$20/100/4 -> 0 | AO50: =$K$24*$K$21/100/4 -> 0 | AP50: =$K$24*$K$21/100/4 -> 0 | AQ50: =$K$24*$K$21/100/4 -> 0 | AR50: =$K$24*$K$21/100/4 -> 0
A51: MONTH 21 (ADMIN) | D51: =SUM(E51:AZ51) -> 112719.6 | M51: =$K$25*$K$14/100/4 -> 5635.98 | N51: =$K$25*$K$14/100/4 -> 5635.98 | O51: =$K$25*$K$14/100/4 -> 5635.98 | P51: =$K$25*$K$14/100/4 -> 5635.98 | Q51: =$K$25*$K$15/100/4 -> 5635.98 | R51: =$K$25*$K$15/100/4 -> 5635.98 | S51: =$K$25*$K$15/100/4 -> 5635.98 | T51: =$K$25*$K$15/100/4 -> 5635.98 | U51: =$K$25*$K$16/100/4 -> 5635.98 | V51: =$K$25*$K$16/100/4 -> 5635.98 | W51: =$K$25*$K$16/100/4 -> 5635.98 | X51: =$K$25*$K$16/100/4 -> 5635.98 | Y51: =$K$25*$K$17/100/4 -> 3757.32 | Z51: =$K$25*$K$17/100/4 -> 3757.32 | AA51: =$K$25*$K$17/100/4 -> 3757.32 | AB51: =$K$25*$K$17/100/4 -> 3757.32 | AC51: =$K$25*$K$18/100/4 -> 3757.32 | AD51: =$K$25*$K$18/100/4 -> 3757.32 | AE51: =$K$25*$K$18/100/4 -> 3757.32 | AF51: =$K$25*$K$18/100/4 -> 3757.32 | AG51: =$K$25*$K$19/100/4 -> 3757.32 | AH51: =$K$25*$K$19/100/4 -> 3757.32 | AI51: =$K$25*$K$19/100/4 -> 3757.32 | AJ51: =$K$25*$K$19/100/4 -> 3757.32 | AK51: =$K$25*$K$20/100/4 -> 0 | AL51: =$K$25*$K$20/100/4 -> 0 | AM51: =$K$25*$K$20/100/4 -> 0 | AN51: =$K$25*$K$20/100/4 -> 0 | AO51: =$K$25*$K$21/100/4 -> 0 | AP51: =$K$25*$K$21/100/4 -> 0 | AQ51: =$K$25*$K$21/100/4 -> 0 | AR51: =$K$25*$K$21/100/4 -> 0
A52: MONTH 24 (COMMERCIAL) | D52: =SUM(E52:AZ52) -> 51663.15 | N52: =$L$24*$L$14/100/4 -> 2583.1575 | O52: =$L$24*$L$14/100/4 -> 2583.1575 | P52: =$L$24*$L$14/100/4 -> 2583.1575 | Q52: =$L$24*$L$14/100/4 -> 2583.1575 | R52: =$L$24*$L$15/100/4 -> 2583.1575 | S52: =$L$24*$L$15/100/4 -> 2583.1575 | T52: =$L$24*$L$15/100/4 -> 2583.1575 | U52: =$L$24*$L$15/100/4 -> 2583.1575 | V52: =$L$24*$L$16/100/4 -> 2583.1575 | W52: =$L$24*$L$16/100/4 -> 2583.1575 | X52: =$L$24*$L$16/100/4 -> 2583.1575 | Y52: =$L$24*$L$16/100/4 -> 2583.1575 | Z52: =$L$24*$L$17/100/4 -> 1722.105 | AA52: =$L$24*$L$17/100/4 -> 1722.105 | AB52: =$L$24*$L$17/100/4 -> 1722.105 | AC52: =$L$24*$L$17/100/4 -> 1722.105 | AD52: =$L$24*$L$18/100/4 -> 1722.105 | AE52: =$L$24*$L$18/100/4 -> 1722.105 | AF52: =$L$24*$L$18/100/4 -> 1722.105 | AG52: =$L$24*$L$18/100/4 -> 1722.105 | AH52: =$L$24*$L$19/100/4 -> 1722.105 | AI52: =$L$24*$L$19/100/4 -> 1722.105 | AJ52: =$L$24*$L$19/100/4 -> 1722.105 | AK52: =$L$24*$L$19/100/4 -> 1722.105 | AL52: =$L$24*$L$20/100/4 -> 0 | AM52: =$L$24*$L$20/100/4 -> 0 | AN52: =$L$24*$L$20/100/4 -> 0 | AO52: =$L$24*$L$20/100/4 -> 0 | AP52: =$L$24*$L$21/100/4 -> 0 | AQ52: =$L$24*$L$21/100/4 -> 0 | AR52: =$L$24*$L$21/100/4 -> 0 | AS52: =$L$24*$L$21/100/4 -> 0 | AW52: =$L$24*$L$21/100/4 -> 0 | AX52: =AW52 -> 0 | AY52: =AX52 -> 0
A53: MONTH 24 (ADMIN) | D53: =SUM(E53:AZ53) -> 56359.8 | N53: =$L$25*$L$14/100/4 -> 2817.99 | O53: =$L$25*$L$14/100/4 -> 2817.99 | P53: =$L$25*$L$14/100/4 -> 2817.99 | Q53: =$L$25*$L$14/100/4 -> 2817.99 | R53: =$L$25*$L$15/100/4 -> 2817.99 | S53: =$L$25*$L$15/100/4 -> 2817.99 | T53: =$L$25*$L$15/100/4 -> 2817.99 | U53: =$L$25*$L$15/100/4 -> 2817.99 | V53: =$L$25*$L$16/100/4 -> 2817.99 | W53: =$L$25*$L$16/100/4 -> 2817.99 | X53: =$L$25*$L$16/100/4 -> 2817.99 | Y53: =$L$25*$L$16/100/4 -> 2817.99 | Z53: =$L$25*$L$17/100/4 -> 1878.66 | AA53: =$L$25*$L$17/100/4 -> 1878.66 | AB53: =$L$25*$L$17/100/4 -> 1878.66 | AC53: =$L$25*$L$17/100/4 -> 1878.66 | AD53: =$L$25*$L$18/100/4 -> 1878.66 | AE53: =$L$25*$L$18/100/4 -> 1878.66 | AF53: =$L$25*$L$18/100/4 -> 1878.66 | AG53: =$L$25*$L$18/100/4 -> 1878.66 | AH53: =$L$25*$L$19/100/4 -> 1878.66 | AI53: =$L$25*$L$19/100/4 -> 1878.66 | AJ53: =$L$25*$L$19/100/4 -> 1878.66 | AK53: =$L$25*$L$19/100/4 -> 1878.66 | AL53: =$L$25*$L$20/100/4 -> 0 | AM53: =$L$25*$L$20/100/4 -> 0 | AN53: =$L$25*$L$20/100/4 -> 0 | AO53: =$L$25*$L$20/100/4 -> 0 | AP53: =$L$25*$L$21/100/4 -> 0 | AQ53: =$L$25*$L$21/100/4 -> 0 | AR53: =$L$25*$L$21/100/4 -> 0 | AS53: =$L$25*$L$21/100/4 -> 0 | AW53: =$L$25*$L$21/100/4 -> 0 | AX53: =AW53 -> 0 | AY53: =AX53 -> 0
A54: MONTH 27 (COMMERCIAL) | D54: =SUM(E54:AZ54) -> 56359.8 | O54: =$M$24*$M$14/100/4 -> 3522.4875 | P54: =$M$24*$M$14/100/4 -> 3522.4875 | Q54: =$M$24*$M$14/100/4 -> 3522.4875 | R54: =$M$24*$M$14/100/4 -> 3522.4875 | S54: =$M$24*$M$15/100/4 -> 3522.4875 | T54: =$M$24*$M$15/100/4 -> 3522.4875 | U54: =$M$24*$M$15/100/4 -> 3522.4875 | V54: =$M$24*$M$15/100/4 -> 3522.4875 | W54: =$M$24*$M$16/100/4 -> 3522.4875 | X54: =$M$24*$M$16/100/4 -> 3522.4875 | Y54: =$M$24*$M$16/100/4 -> 3522.4875 | Z54: =$M$24*$M$16/100/4 -> 3522.4875 | AA54: =$M$24*$M$17/100/4 -> 1174.1625 | AB54: =$M$24*$M$17/100/4 -> 1174.1625 | AC54: =$M$24*$M$17/100/4 -> 1174.1625 | AD54: =$M$24*$M$17/100/4 -> 1174.1625 | AE54: =$M$24*$M$18/100/4 -> 1174.1625 | AF54: =$M$24*$M$18/100/4 -> 1174.1625 | AG54: =$M$24*$M$18/100/4 -> 1174.1625 | AH54: =$M$24*$M$18/100/4 -> 1174.1625 | AI54: =$M$24*$M$19/100/4 -> 1174.1625 | AJ54: =$M$24*$M$19/100/4 -> 1174.1625 | AK54: =$M$24*$M$19/100/4 -> 1174.1625 | AL54: =$M$24*$M$19/100/4 -> 1174.1625 | AM54: =$M$24*$M$20/100/4 -> 0 | AN54: =$M$24*$M$20/100/4 -> 0 | AO54: =$M$24*$M$20/100/4 -> 0 | AP54: =$M$24*$M$20/100/4 -> 0 | AQ54: =$M$24*$M$21/100/4 -> 0 | AR54: =$M$24*$M$21/100/4 -> 0 | AS54: =$M$24*$M$21/100/4 -> 0 | AT54: =$M$24*$M$21/100/4 -> 0
A55: MONTH 27 (ADMIN) | D55: =SUM(E55:AZ55) -> 62622 | O55: =$M$25*$M$14/100/4 -> 3913.875 | P55: =$M$25*$M$14/100/4 -> 3913.875 | Q55: =$M$25*$M$14/100/4 -> 3913.875 | R55: =$M$25*$M$14/100/4 -> 3913.875 | S55: =$M$25*$M$15/100/4 -> 3913.875 | T55: =$M$25*$M$15/100/4 -> 3913.875 | U55: =$M$25*$M$15/100/4 -> 3913.875 | V55: =$M$25*$M$15/100/4 -> 3913.875 | W55: =$M$25*$M$16/100/4 -> 3913.875 | X55: =$M$25*$M$16/100/4 -> 3913.875 | Y55: =$M$25*$M$16/100/4 -> 3913.875 | Z55: =$M$25*$M$16/100/4 -> 3913.875 | AA55: =$M$25*$M$17/100/4 -> 1304.625 | AB55: =$M$25*$M$17/100/4 -> 1304.625 | AC55: =$M$25*$M$17/100/4 -> 1304.625 | AD55: =$M$25*$M$17/100/4 -> 1304.625 | AE55: =$M$25*$M$18/100/4 -> 1304.625 | AF55: =$M$25*$M$18/100/4 -> 1304.625 | AG55: =$M$25*$M$18/100/4 -> 1304.625 | AH55: =$M$25*$M$18/100/4 -> 1304.625 | AI55: =$M$25*$M$19/100/4 -> 1304.625 | AJ55: =$M$25*$M$19/100/4 -> 1304.625 | AK55: =$M$25*$M$19/100/4 -> 1304.625 | AL55: =$M$25*$M$19/100/4 -> 1304.625 | AM55: =$M$25*$M$20/100/4 -> 0 | AN55: =$M$25*$M$20/100/4 -> 0 | AO55: =$M$25*$M$20/100/4 -> 0 | AP55: =$M$25*$M$20/100/4 -> 0 | AQ55: =$M$25*$M$21/100/4 -> 0 | AR55: =$M$25*$M$21/100/4 -> 0 | AS55: =$M$25*$M$21/100/4 -> 0 | AT55: =$M$25*$M$21/100/4 -> 0
A56: MONTH 30 (COMMERCIAL) | D56: =SUM(E56:AZ56) -> 48308.4 | P56: =$N$24*$N$14/100/4 -> 3019.275 | Q56: =$N$24*$N$14/100/4 -> 3019.275 | R56: =$N$24*$N$14/100/4 -> 3019.275 | S56: =$N$24*$N$14/100/4 -> 3019.275 | T56: =$N$24*$N$15/100/4 -> 3019.275 | U56: =$N$24*$N$15/100/4 -> 3019.275 | V56: =$N$24*$N$15/100/4 -> 3019.275 | W56: =$N$24*$N$15/100/4 -> 3019.275 | X56: =$N$24*$N$16/100/4 -> 3019.275 | Y56: =$N$24*$N$16/100/4 -> 3019.275 | Z56: =$N$24*$N$16/100/4 -> 3019.275 | AA56: =$N$24*$N$16/100/4 -> 3019.275 | AB56: =$N$24*$N$17/100/4 -> 1006.425 | AC56: =$N$24*$N$17/100/4 -> 1006.425 | AD56: =$N$24*$N$17/100/4 -> 1006.425 | AE56: =$N$24*$N$17/100/4 -> 1006.425 | AF56: =$N$24*$N$18/100/4 -> 1006.425 | AG56: =$N$24*$N$18/100/4 -> 1006.425 | AH56: =$N$24*$N$18/100/4 -> 1006.425 | AI56: =$N$24*$N$18/100/4 -> 1006.425 | AJ56: =$N$24*$N$19/100/4 -> 1006.425 | AK56: =$N$24*$N$19/100/4 -> 1006.425 | AL56: =$N$24*$N$19/100/4 -> 1006.425 | AM56: =$N$24*$N$19/100/4 -> 1006.425 | AN56: =$N$24*$N$20/100/4 -> 0 | AO56: =$N$24*$N$20/100/4 -> 0 | AP56: =$N$24*$N$20/100/4 -> 0 | AQ56: =$N$24*$N$20/100/4 -> 0 | AR56: =$N$24*$N$21/100/4 -> 0 | AS56: =$N$24*$N$21/100/4 -> 0 | AT56: =$N$24*$N$21/100/4 -> 0 | AU56: =$N$24*$N$21/100/4 -> 0 | AY56: =AW56 -> 0 | AZ56: =$N$24*$N$21/100/4 -> 0 | BA56: =AZ56 -> 0 | BB56: =BA56 -> 0
A57: MONTH 30 (ADMIN) | D57: =SUM(E57:AZ57) -> 62622 | P57: =$N$25*$N$14/100/4 -> 3913.875 | Q57: =$N$25*$N$14/100/4 -> 3913.875 | R57: =$N$25*$N$14/100/4 -> 3913.875 | S57: =$N$25*$N$14/100/4 -> 3913.875 | T57: =$N$25*$N$15/100/4 -> 3913.875 | U57: =$N$25*$N$15/100/4 -> 3913.875 | V57: =$N$25*$N$15/100/4 -> 3913.875 | W57: =$N$25*$N$15/100/4 -> 3913.875 | X57: =$N$25*$N$16/100/4 -> 3913.875 | Y57: =$N$25*$N$16/100/4 -> 3913.875 | Z57: =$N$25*$N$16/100/4 -> 3913.875 | AA57: =$N$25*$N$16/100/4 -> 3913.875 | AB57: =$N$25*$N$17/100/4 -> 1304.625 | AC57: =$N$25*$N$17/100/4 -> 1304.625 | AD57: =$N$25*$N$17/100/4 -> 1304.625 | AE57: =$N$25*$N$17/100/4 -> 1304.625 | AF57: =$N$25*$N$18/100/4 -> 1304.625 | AG57: =$N$25*$N$18/100/4 -> 1304.625 | AH57: =$N$25*$N$18/100/4 -> 1304.625 | AI57: =$N$25*$N$18/100/4 -> 1304.625 | AJ57: =$N$25*$N$19/100/4 -> 1304.625 | AK57: =$N$25*$N$19/100/4 -> 1304.625 | AL57: =$N$25*$N$19/100/4 -> 1304.625 | AM57: =$N$25*$N$19/100/4 -> 1304.625 | AN57: =$N$25*$N$20/100/4 -> 0 | AO57: =$N$25*$N$20/100/4 -> 0 | AP57: =$N$25*$N$20/100/4 -> 0 | AQ57: =$N$25*$N$20/100/4 -> 0 | AR57: =$N$25*$N$21/100/4 -> 0 | AS57: =$N$25*$N$21/100/4 -> 0 | AT57: =$N$25*$N$21/100/4 -> 0 | AU57: =$N$25*$N$21/100/4 -> 0 | AY57: =AW57 -> 0 | AZ57: =$N$25*$N$21/100/4 -> 0 | BA57: =AZ57 -> 0 | BB57: =BA57 -> 0
A58: MONTH 33 (COMMERCIAL) | D58: =SUM(E58:AZ58) -> 33212.025 | Q58: =$O$24*$O$14/100/4 -> 2767.6687 | R58: =$O$24*$O$14/100/4 -> 2767.6687 | S58: =$O$24*$O$14/100/4 -> 2767.6687 | T58: =$O$24*$O$14/100/4 -> 2767.6687 | U58: =$O$24*$O$15/100/4 -> 2767.6687 | V58: =$O$24*$O$15/100/4 -> 2767.6687 | W58: =$O$24*$O$15/100/4 -> 2767.6687 | X58: =$O$24*$O$15/100/4 -> 2767.6687 | Y58: =$O$24*$O$16/100/4 -> 1383.8344 | Z58: =$O$24*$O$16/100/4 -> 1383.8344 | AA58: =$O$24*$O$16/100/4 -> 1383.8344 | AB58: =$O$24*$O$16/100/4 -> 1383.8344 | AC58: =$O$24*$O$17/100/4 -> 1383.8344 | AD58: =$O$24*$O$17/100/4 -> 1383.8344 | AE58: =$O$24*$O$17/100/4 -> 1383.8344 | AF58: =$O$24*$O$17/100/4 -> 1383.8344 | AG58: =$O$24*$O$18/100/4 -> 0 | AH58: =$O$24*$O$18/100/4 -> 0 | AI58: =$O$24*$O$18/100/4 -> 0 | AJ58: =$O$24*$O$18/100/4 -> 0 | AK58: =$O$24*$O$19/100/4 -> 0 | AL58: =$O$24*$O$19/100/4 -> 0 | AM58: =$O$24*$O$19/100/4 -> 0 | AN58: =$O$24*$O$19/100/4 -> 0 | AO58: =$O$24*$O$20/100/4 -> 0 | AP58: =$O$24*$O$20/100/4 -> 0 | AQ58: =$O$24*$O$20/100/4 -> 0 | AR58: =$O$24*$O$20/100/4 -> 0 | AS58: =$O$24*$O$21/100/4 -> 0 | AT58: =$O$24*$O$21/100/4 -> 0 | AU58: =$O$24*$O$21/100/4 -> 0 | AV58: =$O$24*$O$21/100/4 -> 0
A59: MONTH 33 (ADMIN) | D59: =SUM(E59:AZ59) -> 51663.15 | Q59: =$O$25*$O$14/100/4 -> 4305.2625 | R59: =$O$25*$O$14/100/4 -> 4305.2625 | S59: =$O$25*$O$14/100/4 -> 4305.2625 | T59: =$O$25*$O$14/100/4 -> 4305.2625 | U59: =$O$25*$O$15/100/4 -> 4305.2625 | V59: =$O$25*$O$15/100/4 -> 4305.2625 | W59: =$O$25*$O$15/100/4 -> 4305.2625 | X59: =$O$25*$O$15/100/4 -> 4305.2625 | Y59: =$O$25*$O$16/100/4 -> 2152.6312 | Z59: =$O$25*$O$16/100/4 -> 2152.6312 | AA59: =$O$25*$O$16/100/4 -> 2152.6312 | AB59: =$O$25*$O$16/100/4 -> 2152.6312 | AC59: =$O$25*$O$17/100/4 -> 2152.6312 | AD59: =$O$25*$O$17/100/4 -> 2152.6312 | AE59: =$O$25*$O$17/100/4 -> 2152.6312 | AF59: =$O$25*$O$17/100/4 -> 2152.6312 | AG59: =$O$25*$O$18/100/4 -> 0 | AH59: =$O$25*$O$18/100/4 -> 0 | AI59: =$O$25*$O$18/100/4 -> 0 | AJ59: =$O$25*$O$18/100/4 -> 0 | AK59: =$O$25*$O$19/100/4 -> 0 | AL59: =$O$25*$O$19/100/4 -> 0 | AM59: =$O$25*$O$19/100/4 -> 0 | AN59: =$O$25*$O$19/100/4 -> 0 | AO59: =$O$25*$O$20/100/4 -> 0 | AP59: =$O$25*$O$20/100/4 -> 0 | AQ59: =$O$25*$O$20/100/4 -> 0 | AR59: =$O$25*$O$20/100/4 -> 0 | AS59: =$O$25*$O$21/100/4 -> 0 | AT59: =$O$25*$O$21/100/4 -> 0 | AU59: =$O$25*$O$21/100/4 -> 0 | AV59: =$O$25*$O$21/100/4 -> 0
A60: MONTH 36 (COMMERCIAL) | D60: =SUM(E60:AZ60) -> 33212.025 | R60: =$P$24*$P$14/100/4 -> 2767.6687 | S60: =$P$24*$P$14/100/4 -> 2767.6687 | T60: =$P$24*$P$14/100/4 -> 2767.6687 | U60: =$P$24*$P$14/100/4 -> 2767.6687 | V60: =$P$24*$P$15/100/4 -> 2767.6687 | W60: =$P$24*$P$15/100/4 -> 2767.6687 | X60: =$P$24*$P$15/100/4 -> 2767.6687 | Y60: =$P$24*$P$15/100/4 -> 2767.6687 | Z60: =$P$24*$P$16/100/4 -> 1383.8344 | AA60: =$P$24*$P$16/100/4 -> 1383.8344 | AB60: =$P$24*$P$16/100/4 -> 1383.8344 | AC60: =$P$24*$P$16/100/4 -> 1383.8344 | AD60: =$P$24*$P$17/100/4 -> 1383.8344 | AE60: =$P$24*$P$17/100/4 -> 1383.8344 | AF60: =$P$24*$P$17/100/4 -> 1383.8344 | AG60: =$P$24*$P$17/100/4 -> 1383.8344 | AH60: =$P$24*$P$18/100/4 -> 0 | AI60: =$P$24*$P$18/100/4 -> 0 | AJ60: =$P$24*$P$18/100/4 -> 0 | AK60: =$P$24*$P$18/100/4 -> 0 | AL60: =$P$24*$P$19/100/4 -> 0 | AM60: =$P$24*$P$19/100/4 -> 0 | AN60: =$P$24*$P$19/100/4 -> 0 | AO60: =$P$24*$P$19/100/4 -> 0 | AP60: =$P$24*$P$20/100/4 -> 0 | AQ60: =$P$24*$P$20/100/4 -> 0 | AR60: =$P$24*$P$20/100/4 -> 0 | AS60: =$P$24*$P$20/100/4 -> 0 | AT60: =$P$24*$P$21/100/4 -> 0 | AU60: =$P$24*$P$21/100/4 -> 0 | AV60: =$P$24*$P$21/100/4 -> 0 | AW60: =$P$24*$P$21/100/4 -> 0 | BA60: =$P$24*$P$20/100/4 -> 0 | BB60: =BA60 -> 0 | BC60: =$P$24*$P$21/100/4 -> 0 | BD60: =BC60 -> 0 | BE60: =BD60 -> 0
A61: MONTH 36 (ADMIN) | D61: =SUM(E61:AZ61) -> 51663.15 | R61: =$P$25*$P$14/100/4 -> 4305.2625 | S61: =$P$25*$P$14/100/4 -> 4305.2625 | T61: =$P$25*$P$14/100/4 -> 4305.2625 | U61: =$P$25*$P$14/100/4 -> 4305.2625 | V61: =$P$25*$P$15/100/4 -> 4305.2625 | W61: =$P$25*$P$15/100/4 -> 4305.2625 | X61: =$P$25*$P$15/100/4 -> 4305.2625 | Y61: =$P$25*$P$15/100/4 -> 4305.2625 | Z61: =$P$25*$P$16/100/4 -> 2152.6312 | AA61: =$P$25*$P$16/100/4 -> 2152.6312 | AB61: =$P$25*$P$16/100/4 -> 2152.6312 | AC61: =$P$25*$P$16/100/4 -> 2152.6312 | AD61: =$P$25*$P$17/100/4 -> 2152.6312 | AE61: =$P$25*$P$17/100/4 -> 2152.6312 | AF61: =$P$25*$P$17/100/4 -> 2152.6312 | AG61: =$P$25*$P$17/100/4 -> 2152.6312 | AH61: =$P$25*$P$18/100/4 -> 0 | AI61: =$P$25*$P$18/100/4 -> 0 | AJ61: =$P$25*$P$18/100/4 -> 0 | AK61: =$P$25*$P$18/100/4 -> 0 | AL61: =$P$25*$P$19/100/4 -> 0 | AM61: =$P$25*$P$19/100/4 -> 0 | AN61: =$P$25*$P$19/100/4 -> 0 | AO61: =$P$25*$P$19/100/4 -> 0 | AP61: =$P$25*$P$20/100/4 -> 0 | AQ61: =$P$25*$P$20/100/4 -> 0 | AR61: =$P$25*$P$20/100/4 -> 0 | AS61: =$P$25*$P$20/100/4 -> 0 | AT61: =$P$25*$P$21/100/4 -> 0 | AU61: =$P$25*$P$21/100/4 -> 0 | AV61: =$P$25*$P$21/100/4 -> 0 | AW61: =$P$25*$P$21/100/4 -> 0 | BA61: =$P$25*$P$20/100/4 -> 0 | BB61: =BA61 -> 0 | BC61: =$P$25*$P$21/100/4 -> 0 | BD61: =BC61 -> 0 | BE61: =BD61 -> 0
A62: MONTH 39 (COMMERCIAL) | D62: =SUM(E62:AZ62) -> 36231.3 | S62: =$Q$24*$Q$14/100/4 -> 3019.275 | T62: =$Q$24*$Q$14/100/4 -> 3019.275 | U62: =$Q$24*$Q$14/100/4 -> 3019.275 | V62: =$Q$24*$Q$14/100/4 -> 3019.275 | W62: =$Q$24*$Q$15/100/4 -> 3019.275 | X62: =$Q$24*$Q$15/100/4 -> 3019.275 | Y62: =$Q$24*$Q$15/100/4 -> 3019.275 | Z62: =$Q$24*$Q$15/100/4 -> 3019.275 | AA62: =$Q$24*$Q$16/100/4 -> 1509.6375 | AB62: =$Q$24*$Q$16/100/4 -> 1509.6375 | AC62: =$Q$24*$Q$16/100/4 -> 1509.6375 | AD62: =$Q$24*$Q$16/100/4 -> 1509.6375 | AE62: =$Q$24*$Q$17/100/4 -> 1509.6375 | AF62: =$Q$24*$Q$17/100/4 -> 1509.6375 | AG62: =$Q$24*$Q$17/100/4 -> 1509.6375 | AH62: =$Q$24*$Q$17/100/4 -> 1509.6375 | AI62: =$Q$24*$Q$18/100/4 -> 0 | AJ62: =$Q$24*$Q$18/100/4 -> 0 | AK62: =$Q$24*$Q$18/100/4 -> 0 | AL62: =$Q$24*$Q$18/100/4 -> 0 | AM62: =$Q$24*$Q$19/100/4 -> 0 | AN62: =$Q$24*$Q$19/100/4 -> 0 | AO62: =$Q$24*$Q$19/100/4 -> 0 | AP62: =$Q$24*$Q$19/100/4 -> 0 | AQ62: =$Q$24*$Q$20/100/4 -> 0 | AR62: =$Q$24*$Q$20/100/4 -> 0 | AS62: =$Q$24*$Q$20/100/4 -> 0 | AT62: =$Q$24*$Q$20/100/4 -> 0 | AU62: =$Q$24*$Q$21/100/4 -> 0 | AV62: =$Q$24*$Q$21/100/4 -> 0 | AW62: =$Q$24*$Q$21/100/4 -> 0 | AX62: =$Q$24*$Q$21/100/4 -> 0
A63: MONTH 39 (ADMIN) | D63: =SUM(E63:AZ63) -> 56359.8 | S63: =$Q$25*$Q$14/100/4 -> 4696.65 | T63: =$Q$25*$Q$14/100/4 -> 4696.65 | U63: =$Q$25*$Q$14/100/4 -> 4696.65 | V63: =$Q$25*$Q$14/100/4 -> 4696.65 | W63: =$Q$25*$Q$15/100/4 -> 4696.65 | X63: =$Q$25*$Q$15/100/4 -> 4696.65 | Y63: =$Q$25*$Q$15/100/4 -> 4696.65 | Z63: =$Q$25*$Q$15/100/4 -> 4696.65 | AA63: =$Q$25*$Q$16/100/4 -> 2348.325 | AB63: =$Q$25*$Q$16/100/4 -> 2348.325 | AC63: =$Q$25*$Q$16/100/4 -> 2348.325 | AD63: =$Q$25*$Q$16/100/4 -> 2348.325 | AE63: =$Q$25*$Q$17/100/4 -> 2348.325 | AF63: =$Q$25*$Q$17/100/4 -> 2348.325 | AG63: =$Q$25*$Q$17/100/4 -> 2348.325 | AH63: =$Q$25*$Q$17/100/4 -> 2348.325 | AI63: =$Q$25*$Q$18/100/4 -> 0 | AJ63: =$Q$25*$Q$18/100/4 -> 0 | AK63: =$Q$25*$Q$18/100/4 -> 0 | AL63: =$Q$25*$Q$18/100/4 -> 0 | AM63: =$Q$25*$Q$19/100/4 -> 0 | AN63: =$Q$25*$Q$19/100/4 -> 0 | AO63: =$Q$25*$Q$19/100/4 -> 0 | AP63: =$Q$25*$Q$19/100/4 -> 0 | AQ63: =$Q$25*$Q$20/100/4 -> 0 | AR63: =$Q$25*$Q$20/100/4 -> 0 | AS63: =$Q$25*$Q$20/100/4 -> 0 | AT63: =$Q$25*$Q$20/100/4 -> 0 | AU63: =$Q$25*$Q$21/100/4 -> 0 | AV63: =$Q$25*$Q$21/100/4 -> 0 | AW63: =$Q$25*$Q$21/100/4 -> 0 | AX63: =$Q$25*$Q$21/100/4 -> 0
A64: MONTH 42 (COMMERCIAL) | D64: =SUM(E64:AZ64) -> 36231.3 | T64: =$R$24*$R$14/100/4 -> 3019.275 | U64: =$R$24*$R$14/100/4 -> 3019.275 | V64: =$R$24*$R$14/100/4 -> 3019.275 | W64: =$R$24*$R$14/100/4 -> 3019.275 | X64: =$R$24*$R$15/100/4 -> 3019.275 | Y64: =$R$24*$R$15/100/4 -> 3019.275 | Z64: =$R$24*$R$15/100/4 -> 3019.275 | AA64: =$R$24*$R$15/100/4 -> 3019.275 | AB64: =$R$24*$R$16/100/4 -> 1509.6375 | AC64: =$R$24*$R$16/100/4 -> 1509.6375 | AD64: =$R$24*$R$16/100/4 -> 1509.6375 | AE64: =$R$24*$R$16/100/4 -> 1509.6375 | AF64: =$R$24*$R$17/100/4 -> 1509.6375 | AG64: =$R$24*$R$17/100/4 -> 1509.6375 | AH64: =$R$24*$R$17/100/4 -> 1509.6375 | AI64: =$R$24*$R$17/100/4 -> 1509.6375 | AJ64: =$R$24*$R$18/100/4 -> 0 | AK64: =$R$24*$R$18/100/4 -> 0 | AL64: =$R$24*$R$18/100/4 -> 0 | AM64: =$R$24*$R$18/100/4 -> 0 | AN64: =$R$24*$R$19/100/4 -> 0 | AO64: =$R$24*$R$19/100/4 -> 0 | AP64: =$R$24*$R$19/100/4 -> 0 | AQ64: =$R$24*$R$19/100/4 -> 0 | AR64: =$R$24*$R$20/100/4 -> 0 | AS64: =$R$24*$R$20/100/4 -> 0 | AT64: =$R$24*$R$20/100/4 -> 0 | AU64: =$R$24*$R$20/100/4 -> 0 | AV64: =$R$24*$R$21/100/4 -> 0 | AW64: =$R$24*$R$21/100/4 -> 0 | AX64: =$R$24*$R$21/100/4 -> 0 | AY64: =$R$24*$R$21/100/4 -> 0 | BC64: =BA64 -> 0 | BD64: =$R$24*$R$20/100/4 -> 0 | BE64: =BD64 -> 0 | BF64: =$R$24*$R$21/100/4 -> 0 | BG64: =BF64 -> 0 | BH64: =BG64 -> 0
A65: MONTH 42 (ADMIN) | D65: =SUM(E65:AZ65) -> 56359.8 | T65: =$R$25*$R$14/100/4 -> 4696.65 | U65: =$R$25*$R$14/100/4 -> 4696.65 | V65: =$R$25*$R$14/100/4 -> 4696.65 | W65: =$R$25*$R$14/100/4 -> 4696.65 | X65: =$R$25*$R$15/100/4 -> 4696.65 | Y65: =$R$25*$R$15/100/4 -> 4696.65 | Z65: =$R$25*$R$15/100/4 -> 4696.65 | AA65: =$R$25*$R$15/100/4 -> 4696.65 | AB65: =$R$25*$R$16/100/4 -> 2348.325 | AC65: =$R$25*$R$16/100/4 -> 2348.325 | AD65: =$R$25*$R$16/100/4 -> 2348.325 | AE65: =$R$25*$R$16/100/4 -> 2348.325 | AF65: =$R$25*$R$17/100/4 -> 2348.325 | AG65: =$R$25*$R$17/100/4 -> 2348.325 | AH65: =$R$25*$R$17/100/4 -> 2348.325 | AI65: =$R$25*$R$17/100/4 -> 2348.325 | AJ65: =$R$25*$R$18/100/4 -> 0 | AK65: =$R$25*$R$18/100/4 -> 0 | AL65: =$R$25*$R$18/100/4 -> 0 | AM65: =$R$25*$R$18/100/4 -> 0 | AN65: =$R$25*$R$19/100/4 -> 0 | AO65: =$R$25*$R$19/100/4 -> 0 | AP65: =$R$25*$R$19/100/4 -> 0 | AQ65: =$R$25*$R$19/100/4 -> 0 | AR65: =$R$25*$R$20/100/4 -> 0 | AS65: =$R$25*$R$20/100/4 -> 0 | AT65: =$R$25*$R$20/100/4 -> 0 | AU65: =$R$25*$R$20/100/4 -> 0 | AV65: =$R$25*$R$21/100/4 -> 0 | AW65: =$R$25*$R$21/100/4 -> 0 | AX65: =$R$25*$R$21/100/4 -> 0 | AY65: =$R$25*$R$21/100/4 -> 0 | BC65: =BA65 -> 0 | BD65: =$R$25*$R$20/100/4 -> 0 | BE65: =BD65 -> 0 | BF65: =$R$25*$R$21/100/4 -> 0 | BG65: =BF65 -> 0 | BH65: =BG65 -> 0
A66: MONTH 45 (COMMERCIAL) | D66: =SUM(E66:AZ66) -> 28179.9 | U66: =$S$24*$S$14/100/4 -> 3019.275 | V66: =$S$24*$S$14/100/4 -> 3019.275 | W66: =$S$24*$S$14/100/4 -> 3019.275 | X66: =$S$24*$S$14/100/4 -> 3019.275 | Y66: =$S$24*$S$15/100/4 -> 2012.85 | Z66: =$S$24*$S$15/100/4 -> 2012.85 | AA66: =$S$24*$S$15/100/4 -> 2012.85 | AB66: =$S$24*$S$15/100/4 -> 2012.85 | AC66: =$S$24*$S$16/100/4 -> 2012.85 | AD66: =$S$24*$S$16/100/4 -> 2012.85 | AE66: =$S$24*$S$16/100/4 -> 2012.85 | AF66: =$S$24*$S$16/100/4 -> 2012.85 | AG66: =$S$24*$S$17/100/4 -> 0 | AH66: =$S$24*$S$17/100/4 -> 0 | AI66: =$S$24*$S$17/100/4 -> 0 | AJ66: =$S$24*$S$17/100/4 -> 0 | AK66: =$S$24*$S$18/100/4 -> 0 | AL66: =$S$24*$S$18/100/4 -> 0 | AM66: =$S$24*$S$18/100/4 -> 0 | AN66: =$S$24*$S$18/100/4 -> 0 | AO66: =$S$24*$S$19/100/4 -> 0 | AP66: =$S$24*$S$19/100/4 -> 0 | AQ66: =$S$24*$S$19/100/4 -> 0 | AR66: =$S$24*$S$19/100/4 -> 0 | AS66: =$S$24*$S$20/100/4 -> 0 | AT66: =$S$24*$S$20/100/4 -> 0 | AU66: =$S$24*$S$20/100/4 -> 0 | AV66: =$S$24*$S$20/100/4 -> 0 | AW66: =$S$24*$S$21/100/4 -> 0 | AX66: =$S$24*$S$21/100/4 -> 0 | AY66: =$S$24*$S$21/100/4 -> 0 | AZ66: =$S$24*$S$21/100/4 -> 0
A67: MONTH 45 (ADMIN) | D67: =SUM(E67:AZ67) -> 21917.7 | U67: =$S$25*$S$14/100/4 -> 2348.325 | V67: =$S$25*$S$14/100/4 -> 2348.325 | W67: =$S$25*$S$14/100/4 -> 2348.325 | X67: =$S$25*$S$14/100/4 -> 2348.325 | Y67: =$S$25*$S$15/100/4 -> 1565.55 | Z67: =$S$25*$S$15/100/4 -> 1565.55 | AA67: =$S$25*$S$15/100/4 -> 1565.55 | AB67: =$S$25*$S$15/100/4 -> 1565.55 | AC67: =$S$25*$S$16/100/4 -> 1565.55 | AD67: =$S$25*$S$16/100/4 -> 1565.55 | AE67: =$S$25*$S$16/100/4 -> 1565.55 | AF67: =$S$25*$S$16/100/4 -> 1565.55 | AG67: =$S$25*$S$17/100/4 -> 0 | AH67: =$S$25*$S$17/100/4 -> 0 | AI67: =$S$25*$S$17/100/4 -> 0 | AJ67: =$S$25*$S$17/100/4 -> 0 | AK67: =$S$25*$S$18/100/4 -> 0 | AL67: =$S$25*$S$18/100/4 -> 0 | AM67: =$S$25*$S$18/100/4 -> 0 | AN67: =$S$25*$S$18/100/4 -> 0 | AO67: =$S$25*$S$19/100/4 -> 0 | AP67: =$S$25*$S$19/100/4 -> 0 | AQ67: =$S$25*$S$19/100/4 -> 0 | AR67: =$S$25*$S$19/100/4 -> 0 | AS67: =$S$25*$S$20/100/4 -> 0 | AT67: =$S$25*$S$20/100/4 -> 0 | AU67: =$S$25*$S$20/100/4 -> 0 | AV67: =$S$25*$S$20/100/4 -> 0 | AW67: =$S$25*$S$21/100/4 -> 0 | AX67: =$S$25*$S$21/100/4 -> 0 | AY67: =$S$25*$S$21/100/4 -> 0 | AZ67: =$S$25*$S$21/100/4 -> 0
A68: MONTH 48 (COMMERCIAL) | D68: =SUM(E68:AZ68) -> 28179.9 | V68: =$T$24*$T$14/100/4 -> 3019.275 | W68: =$T$24*$T$14/100/4 -> 3019.275 | X68: =$T$24*$T$14/100/4 -> 3019.275 | Y68: =$T$24*$T$14/100/4 -> 3019.275 | Z68: =$T$24*$T$15/100/4 -> 2012.85 | AA68: =$T$24*$T$15/100/4 -> 2012.85 | AB68: =$T$24*$T$15/100/4 -> 2012.85 | AC68: =$T$24*$T$15/100/4 -> 2012.85 | AD68: =$T$24*$T$16/100/4 -> 2012.85 | AE68: =$T$24*$T$16/100/4 -> 2012.85 | AF68: =$T$24*$T$16/100/4 -> 2012.85 | AG68: =$T$24*$T$16/100/4 -> 2012.85 | AH68: =$T$24*$T$17/100/4 -> 0 | AI68: =$T$24*$T$17/100/4 -> 0 | AJ68: =$T$24*$T$17/100/4 -> 0 | AK68: =$T$24*$T$17/100/4 -> 0 | AL68: =$T$24*$T$18/100/4 -> 0 | AM68: =$T$24*$T$18/100/4 -> 0 | AN68: =$T$24*$T$18/100/4 -> 0 | AO68: =$T$24*$T$18/100/4 -> 0 | AP68: =$T$24*$T$19/100/4 -> 0 | AQ68: =$T$24*$T$19/100/4 -> 0 | AR68: =$T$24*$T$19/100/4 -> 0 | AS68: =$T$24*$T$19/100/4 -> 0 | AT68: =$T$24*$T$20/100/4 -> 0 | AU68: =$T$24*$T$20/100/4 -> 0 | AV68: =$T$24*$T$20/100/4 -> 0 | AW68: =$T$24*$T$20/100/4 -> 0 | AX68: =$T$24*$T$21/100/4 -> 0 | AY68: =$T$24*$T$21/100/4 -> 0 | AZ68: =$T$24*$T$21/100/4 -> 0 | BA68: =$T$24*$T$21/100/4 -> 0 | BE68: =$T$24*$T$19/100/4 -> 0 | BF68: =BE68 -> 0 | BG68: =$T$24*$T$20/100/4 -> 0 | BH68: =BG68 -> 0 | BI68: =$T$24*$T$21/100/4 -> 0 | BJ68: =BI68 -> 0 | BK68: =BJ68 -> 0
A69: MONTH 48 (ADMIN) | D69: =SUM(E69:AZ69) -> 21917.7 | V69: =$T$25*$T$14/100/4 -> 2348.325 | W69: =$T$25*$T$14/100/4 -> 2348.325 | X69: =$T$25*$T$14/100/4 -> 2348.325 | Y69: =$T$25*$T$14/100/4 -> 2348.325 | Z69: =$T$25*$T$15/100/4 -> 1565.55 | AA69: =$T$25*$T$15/100/4 -> 1565.55 | AB69: =$T$25*$T$15/100/4 -> 1565.55 | AC69: =$T$25*$T$15/100/4 -> 1565.55 | AD69: =$T$25*$T$16/100/4 -> 1565.55 | AE69: =$T$25*$T$16/100/4 -> 1565.55 | AF69: =$T$25*$T$16/100/4 -> 1565.55 | AG69: =$T$25*$T$16/100/4 -> 1565.55 | AH69: =$T$25*$T$17/100/4 -> 0 | AI69: =$T$25*$T$17/100/4 -> 0 | AJ69: =$T$25*$T$17/100/4 -> 0 | AK69: =$T$25*$T$17/100/4 -> 0 | AL69: =$T$25*$T$18/100/4 -> 0 | AM69: =$T$25*$T$18/100/4 -> 0 | AN69: =$T$25*$T$18/100/4 -> 0 | AO69: =$T$25*$T$18/100/4 -> 0 | AP69: =$T$25*$T$19/100/4 -> 0 | AQ69: =$T$25*$T$19/100/4 -> 0 | AR69: =$T$25*$T$19/100/4 -> 0 | AS69: =$T$25*$T$19/100/4 -> 0 | AT69: =$T$25*$T$20/100/4 -> 0 | AU69: =$T$25*$T$20/100/4 -> 0 | AV69: =$T$25*$T$20/100/4 -> 0 | AW69: =$T$25*$T$20/100/4 -> 0 | AX69: =$T$25*$T$21/100/4 -> 0 | AY69: =$T$25*$T$21/100/4 -> 0 | AZ69: =$T$25*$T$21/100/4 -> 0 | BA69: =$T$25*$T$21/100/4 -> 0 | BE69: =$T$25*$T$19/100/4 -> 0 | BF69: =BE69 -> 0 | BG69: =$T$25*$T$20/100/4 -> 0 | BH69: =BG69 -> 0 | BI69: =$T$25*$T$21/100/4 -> 0 | BJ69: =BI69 -> 0 | BK69: =BJ69 -> 0
A70: Total Collections | D70: =SUM(E70:AZ70) -> 2673735.8 | E70: =SUM(E31:E69) -> 0 | F70: =SUM(F31:F69) -> 0 | G70: =SUM(G31:G69) -> 0 | H70: =SUM(H31:H69) -> 0 | I70: =SUM(I31:I69) -> 18115.65 | J70: =SUM(J31:J69) -> 36231.3 | K70: =SUM(K31:K69) -> 58260.825 | L70: =SUM(L31:L69) -> 69018.39 | ... AQ70: =SUM(AQ31:AQ69) -> 0
A71: Total Sales NPV | D71: =SUM(E71:AS71) -> 1549396.3 | E71: =+E70/((1+$C$72)^E$73) -> 0 | F71: =+F70/((1+$C$72)^F$73) -> 0 | G71: =+G70/((1+$C$72)^G$73) -> 0 | H71: =+H70/((1+$C$72)^H$73) -> 0 | I71: =+I70/((1+$C$72)^I$73) -> 15378.814 | J71: =+J70/((1+$C$72)^J$73) -> 29766.422 | K71: =+K70/((1+$C$72)^K$73) -> 46322.623 | L71: =+L70/((1+$C$72)^L$73) -> 53107.41 | ... AS71: =+AS70/((1+$C$72)^AS$73) -> 0
A72: Cost Of Capital | B72: % | C72: 0.14
E73: =0.0833333333333333*3 -> 0.25 | F73: =0.25+E73 -> 0.5 | G73: =0.25+F73 -> 0.75 | H73: =0.25+G73 -> 1 | I73: =0.25+H73 -> 1.25 | J73: =0.25+I73 -> 1.5 | K73: =0.25+J73 -> 1.75 | L73: =0.25+K73 -> 2 | M73: =0.25+L73 -> 2.25 | ... AS73: =0.25+AR73 -> 10.25
A75: Total Sales Accumulated NPV | E75: =E71 -> 0 | F75: =E75+F71 -> 0 | G75: =F75+G71 -> 0 | H75: =G75+H71 -> 0 | I75: =H75+I71 -> 15378.814 | J75: =I75+J71 -> 45145.237 | K75: =J75+K71 -> 91467.86 | L75: =K75+L71 -> 144575.27 | M75: =L75+M71 -> 194533.38 | ... AQ75: =AP75+AQ71 -> 1549396.3
A76: Total Sales Accumulated | E76: =SUM(E77:E78) -> 0 | F76: =SUM(F77:F78) -> 0 | G76: =SUM(G77:G78) -> 0 | H76: =SUM(H77:H78) -> 0 | I76: =SUM(I77:I78) -> 18115.65 | J76: =SUM(J77:J78) -> 54346.95 | K76: =SUM(K77:K78) -> 112607.77 | L76: =SUM(L77:L78) -> 181626.17 | ... AS76: =SUM(AS77:AS78) -> 2673735.8
A77: Bulk Payments Accumulated | E77: =SUM(E31:E36) -> 0 | F77: =E77+SUM(F31:F36) -> 0 | G77: =F77+SUM(G31:G36) -> 0 | H77: =G77+SUM(H31:H36) -> 0 | I77: =H77+SUM(I31:I36) -> 18115.65 | J77: =I77+SUM(J31:J36) -> 54346.95 | K77: =J77+SUM(K31:K36) -> 103549.95 | L77: =K77+SUM(L31:L36) -> 152641.12 | M77: =L77+SUM(M31:M36) -> 190475.25 | ... AS77: =AR77+SUM(AS31:AS36) -> 1186910.6
A78: Instalments Accumulated | E78: =SUM(E38:E69) -> 0 | F78: =E78+SUM(F38:F69) -> 0 | G78: =F78+SUM(G38:G69) -> 0 | H78: =G78+SUM(H38:H69) -> 0 | I78: =H78+SUM(I38:I69) -> 0 | J78: =I78+SUM(J38:J69) -> 0 | K78: =J78+SUM(K38:K69) -> 9057.825 | L78: =K78+SUM(L38:L69) -> 28985.04 | M78: =L78+SUM(M38:M69) -> 58238.46 | ... AS78: =AR78+SUM(AS38:AS69) -> 1486825.2
A81: NOTES:
A82: 1- LAUNCH : MONTH 9
A83: 2- START OF CONSTRUCTION : MONTH 24
A85: DELIVERY PAYMENT (COMMERCIAL) | D85: =D70-D24-D25 -> 0 | E85: =E24*E12/100 -> 0 | F85: =F24*F12/100 -> 0 | G85: =G24*G12/100 -> 0 | H85: =H24*H12/100 -> 0 | I85: =I24*I12/100 -> 22365 | J85: =J24*J12/100 -> 22365 | K85: =K24*K12/100 -> 24601.5 | L85: =L24*L12/100 -> 17221.05 | ... Y85: =Y24*Y12/100 -> 0
A86: DELIVERY PAYMENT (ADMIN) | E86: =E25*E12/100 -> 0 | F86: =F25*F12/100 -> 0 | G86: =G25*G12/100 -> 0 | H86: =H25*H12/100 -> 0 | I86: =I25*I12/100 -> 50097.6 | J86: =J25*J12/100 -> 50097.6 | K86: =K25*K12/100 -> 37573.2 | L86: =L25*L12/100 -> 18786.6 | ... Y86: =Y25*Y12/100 -> 0

Sheet Cash Out Detail
A1: Cash Out — Construction Spend by Stage
A2: Stage costs are spread evenly (straight-line) across each stage's duration. Figures pull automatically from the Stage Schedule & Costs sheet.
A4: No. | B4: Stage | D4: 1 | E4: 2 | F4: 3 | G4: 4 | H4: 5 | I4: 6 | J4: 7 | K4: 8 | L4: 9 | M4: 10 | N4: 11 | O4: 12 | P4: 13 | Q4: 14 | R4: 15 | S4: 16 | T4: 17 | U4: 18 | V4: 19 | W4: 20 | X4: 21 | Y4: 22 | Z4: 23 | AA4: 24 | AB4: 25 | AC4: 26 | AD4: 27 | AE4: 28 | AF4: 29 | AG4: 30 | AH4: 31 | AI4: 32 | AJ4: 33 | AK4: 34 | AL4: 35 | AM4: 36 | AN4: 37 | AO4: 38 | AP4: 39 | AQ4: 40 | AR4: 41 | AS4: 42 | AT4: 43 | AU4: 44 | AV4: 45 | AW4: 46 | AX4: 47 | AY4: 48 | AZ4: 49 | BA4: 50 | BB4: 51 | BC4: 52 | BD4: 53 | BE4: 54 | BF4: 55 | BG4: 56 | BH4: 57 | BI4: 58 | BJ4: 59 | BK4: 60 | BL4: 61 | BM4: 62 | BN4: 63 | BO4: 64 | BP4: 65 | BQ4: 66 | BR4: 67 | BS4: 68 | BT4: 69 | BU4: 70 | BV4: 71 | BW4: 72
A5: ='Stage Schedule & Costs (2)'!A5 -> 1 | B5: ='Stage Schedule & Costs (2)'!B5&" - "&'Stage Schedule & Costs (2)'!C5 -> Excavation - Excavation | C5: =SUM(P5:BQ5) -> 2500000 | P5: =MAX(0,MIN('Stage Schedule & Costs (2)'!$F5,D$4)-MAX('Stage Schedule & Costs (2)'!$E5,D$4-1))*'Stage Schedule & Costs (2)'!$H5 -> 833333.33 | Q5: =MAX(0,MIN('Stage Schedule & Costs (2)'!$F5,E$4)-MAX('Stage Schedule & Costs (2)'!$E5,E$4-1))*'Stage Schedule & Costs (2)'!$H5 -> 833333.33 | R5: =MAX(0,MIN('Stage Schedule & Costs (2)'!$F5,F$4)-MAX('Stage Schedule & Costs (2)'!$E5,F$4-1))*'Stage Schedule & Costs (2)'!$H5 -> 833333.33 | S5: =MAX(0,MIN('Stage Schedule & Costs (2)'!$F5,G$4)-MAX('Stage Schedule & Costs (2)'!$E5,G$4-1))*'Stage Schedule & Costs (2)'!$H5 -> 0 | T5: =MAX(0,MIN('Stage Schedule & Costs (2)'!$F5,H$4)-MAX('Stage Schedule & Costs (2)'!$E5,H$4-1))*'Stage Schedule & Costs (2)'!$H5 -> 0 | U5: =MAX(0,MIN('Stage Schedule & Costs (2)'!$F5,I$4)-MAX('Stage Schedule & Costs (2)'!$E5,I$4-1))*'Stage Schedule & Costs (2)'!$H5 -> 0 | V5: =MAX(0,MIN('Stage Schedule & Costs (2)'!$F5,J$4)-MAX('Stage Schedule & Costs (2)'!$E5,J$4-1))*'Stage Schedule & Costs (2)'!$H5 -> 0 | W5: =MAX(0,MIN('Stage Schedule & Costs (2)'!$F5,K$4)-MAX('Stage Schedule & Costs (2)'!$E5,K$4-1))*'Stage Schedule & Costs (2)'!$H5 -> 0 | ... BQ5: =MAX(0,MIN('Stage Schedule & Costs (2)'!$F5,BE$4)-MAX('Stage Schedule & Costs (2)'!$E5,BE$4-1))*'Stage Schedule & Costs (2)'!$H5 -> 0
A6: ='Stage Schedule & Costs (2)'!A6 -> 2 | B6: ='Stage Schedule & Costs (2)'!B6&" - "&'Stage Schedule & Costs (2)'!C6 -> Replacement - Replacement (Backfill) | C6: =SUM(P6:BQ6) -> 3300000 | P6: =MAX(0,MIN('Stage Schedule & Costs (2)'!$F6,D$4)-MAX('Stage Schedule & Costs (2)'!$E6,D$4-1))*'Stage Schedule & Costs (2)'!$H6 -> 0 | Q6: =MAX(0,MIN('Stage Schedule & Costs (2)'!$F6,E$4)-MAX('Stage Schedule & Costs (2)'!$E6,E$4-1))*'Stage Schedule & Costs (2)'!$H6 -> 0 | R6: =MAX(0,MIN('Stage Schedule & Costs (2)'!$F6,F$4)-MAX('Stage Schedule & Costs (2)'!$E6,F$4-1))*'Stage Schedule & Costs (2)'!$H6 -> 0 | S6: =MAX(0,MIN('Stage Schedule & Costs (2)'!$F6,G$4)-MAX('Stage Schedule & Costs (2)'!$E6,G$4-1))*'Stage Schedule & Costs (2)'!$H6 -> 1100000 | T6: =MAX(0,MIN('Stage Schedule & Costs (2)'!$F6,H$4)-MAX('Stage Schedule & Costs (2)'!$E6,H$4-1))*'Stage Schedule & Costs (2)'!$H6 -> 1100000 | U6: =MAX(0,MIN('Stage Schedule & Costs (2)'!$F6,I$4)-MAX('Stage Schedule & Costs (2)'!$E6,I$4-1))*'Stage Schedule & Costs (2)'!$H6 -> 1100000 | V6: =MAX(0,MIN('Stage Schedule & Costs (2)'!$F6,J$4)-MAX('Stage Schedule & Costs (2)'!$E6,J$4-1))*'Stage Schedule & Costs (2)'!$H6 -> 0 | W6: =MAX(0,MIN('Stage Schedule & Costs (2)'!$F6,K$4)-MAX('Stage Schedule & Costs (2)'!$E6,K$4-1))*'Stage Schedule & Costs (2)'!$H6 -> 0 | ... BQ6: =MAX(0,MIN('Stage Schedule & Costs (2)'!$F6,BE$4)-MAX('Stage Schedule & Costs (2)'!$E6,BE$4-1))*'Stage Schedule & Costs (2)'!$H6 -> 0
A7: ='Stage Schedule & Costs (2)'!A7 -> 3 | B7: ='Stage Schedule & Costs (2)'!B7&" - "&'Stage Schedule & Costs (2)'!C7 -> Concrete Structure - Basement Floor | C7: =SUM(P7:BQ7) -> 5000000 | P7: =MAX(0,MIN('Stage Schedule & Costs (2)'!$F7,D$4)-MAX('Stage Schedule & Costs (2)'!$E7,D$4-1))*'Stage Schedule & Costs (2)'!$H7 -> 0 | Q7: =MAX(0,MIN('Stage Schedule & Costs (2)'!$F7,E$4)-MAX('Stage Schedule & Costs (2)'!$E7,E$4-1))*'Stage Schedule & Costs (2)'!$H7 -> 0 | R7: =MAX(0,MIN('Stage Schedule & Costs (2)'!$F7,F$4)-MAX('Stage Schedule & Costs (2)'!$E7,F$4-1))*'Stage Schedule & Costs (2)'!$H7 -> 0 | S7: =MAX(0,MIN('Stage Schedule & Costs (2)'!$F7,G$4)-MAX('Stage Schedule & Costs (2)'!$E7,G$4-1))*'Stage Schedule & Costs (2)'!$H7 -> 0 | T7: =MAX(0,MIN('Stage Schedule & Costs (2)'!$F7,H$4)-MAX('Stage Schedule & Costs (2)'!$E7,H$4-1))*'Stage Schedule & Costs (2)'!$H7 -> 0 | U7: =MAX(0,MIN('Stage Schedule & Costs (2)'!$F7,I$4)-MAX('Stage Schedule & Costs (2)'!$E7,I$4-1))*'Stage Schedule & Costs (2)'!$H7 -> 0 | V7: =MAX(0,MIN('Stage Schedule & Costs (2)'!$F7,J$4)-MAX('Stage Schedule & Costs (2)'!$E7,J$4-1))*'Stage Schedule & Costs (2)'!$H7 -> 1666666.7 | W7: =MAX(0,MIN('Stage Schedule & Costs (2)'!$F7,K$4)-MAX('Stage Schedule & Costs (2)'!$E7,K$4-1))*'Stage Schedule & Costs (2)'!$H7 -> 1666666.7 | ... BQ7: =MAX(0,MIN('Stage Schedule & Costs (2)'!$F7,BE$4)-MAX('Stage Schedule & Costs (2)'!$E7,BE$4-1))*'Stage Schedule & Costs (2)'!$H7 -> 0
A8: ='Stage Schedule & Costs (2)'!A8 -> 4 | B8: ='Stage Schedule & Costs (2)'!B8&" - "&'Stage Schedule & Costs (2)'!C8 -> - Ground Floor | C8: =SUM(P8:BQ8) -> 3300000 | P8: =MAX(0,MIN('Stage Schedule & Costs (2)'!$F8,D$4)-MAX('Stage Schedule & Costs (2)'!$E8,D$4-1))*'Stage Schedule & Costs (2)'!$H8 -> 0 | Q8: =MAX(0,MIN('Stage Schedule & Costs (2)'!$F8,E$4)-MAX('Stage Schedule & Costs (2)'!$E8,E$4-1))*'Stage Schedule & Costs (2)'!$H8 -> 0 | R8: =MAX(0,MIN('Stage Schedule & Costs (2)'!$F8,F$4)-MAX('Stage Schedule & Costs (2)'!$E8,F$4-1))*'Stage Schedule & Costs (2)'!$H8 -> 0 | S8: =MAX(0,MIN('Stage Schedule & Costs (2)'!$F8,G$4)-MAX('Stage Schedule & Costs (2)'!$E8,G$4-1))*'Stage Schedule & Costs (2)'!$H8 -> 0 | T8: =MAX(0,MIN('Stage Schedule & Costs (2)'!$F8,H$4)-MAX('Stage Schedule & Costs (2)'!$E8,H$4-1))*'Stage Schedule & Costs (2)'!$H8 -> 0 | U8: =MAX(0,MIN('Stage Schedule & Costs (2)'!$F8,I$4)-MAX('Stage Schedule & Costs (2)'!$E8,I$4-1))*'Stage Schedule & Costs (2)'!$H8 -> 0 | V8: =MAX(0,MIN('Stage Schedule & Costs (2)'!$F8,J$4)-MAX('Stage Schedule & Costs (2)'!$E8,J$4-1))*'Stage Schedule & Costs (2)'!$H8 -> 0 | W8: =MAX(0,MIN('Stage Schedule & Costs (2)'!$F8,K$4)-MAX('Stage Schedule & Costs (2)'!$E8,K$4-1))*'Stage Schedule & Costs (2)'!$H8 -> 0 | ... BQ8: =MAX(0,MIN('Stage Schedule & Costs (2)'!$F8,BE$4)-MAX('Stage Schedule & Costs (2)'!$E8,BE$4-1))*'Stage Schedule & Costs (2)'!$H8 -> 0
A9: ='Stage Schedule & Costs (2)'!A9 -> 5 | B9: ='Stage Schedule & Costs (2)'!B9&" - "&'Stage Schedule & Costs (2)'!C9 -> - 1st Floor | C9: =SUM(P9:BQ9) -> 3300000 | P9: =MAX(0,MIN('Stage Schedule & Costs (2)'!$F9,D$4)-MAX('Stage Schedule & Costs (2)'!$E9,D$4-1))*'Stage Schedule & Costs (2)'!$H9 -> 0 | Q9: =MAX(0,MIN('Stage Schedule & Costs (2)'!$F9,E$4)-MAX('Stage Schedule & Costs (2)'!$E9,E$4-1))*'Stage Schedule & Costs (2)'!$H9 -> 0 | R9: =MAX(0,MIN('Stage Schedule & Costs (2)'!$F9,F$4)-MAX('Stage Schedule & Costs (2)'!$E9,F$4-1))*'Stage Schedule & Costs (2)'!$H9 -> 0 | S9: =MAX(0,MIN('Stage Schedule & Costs (2)'!$F9,G$4)-MAX('Stage Schedule & Costs (2)'!$E9,G$4-1))*'Stage Schedule & Costs (2)'!$H9 -> 0 | T9: =MAX(0,MIN('Stage Schedule & Costs (2)'!$F9,H$4)-MAX('Stage Schedule & Costs (2)'!$E9,H$4-1))*'Stage Schedule & Costs (2)'!$H9 -> 0 | U9: =MAX(0,MIN('Stage Schedule & Costs (2)'!$F9,I$4)-MAX('Stage Schedule & Costs (2)'!$E9,I$4-1))*'Stage Schedule & Costs (2)'!$H9 -> 0 | V9: =MAX(0,MIN('Stage Schedule & Costs (2)'!$F9,J$4)-MAX('Stage Schedule & Costs (2)'!$E9,J$4-1))*'Stage Schedule & Costs (2)'!$H9 -> 0 | W9: =MAX(0,MIN('Stage Schedule & Costs (2)'!$F9,K$4)-MAX('Stage Schedule & Costs (2)'!$E9,K$4-1))*'Stage Schedule & Costs (2)'!$H9 -> 0 | ... BQ9: =MAX(0,MIN('Stage Schedule & Costs (2)'!$F9,BE$4)-MAX('Stage Schedule & Costs (2)'!$E9,BE$4-1))*'Stage Schedule & Costs (2)'!$H9 -> 0
A10: ='Stage Schedule & Costs (2)'!A10 -> 6 | B10: ='Stage Schedule & Costs (2)'!B10&" - "&'Stage Schedule & Costs (2)'!C10 -> - 2nd Floor | C10: =SUM(P10:BQ10) -> 3300000 | P10: =MAX(0,MIN('Stage Schedule & Costs (2)'!$F10,D$4)-MAX('Stage Schedule & Costs (2)'!$E10,D$4-1))*'Stage Schedule & Costs (2)'!$H10 -> 0 | Q10: =MAX(0,MIN('Stage Schedule & Costs (2)'!$F10,E$4)-MAX('Stage Schedule & Costs (2)'!$E10,E$4-1))*'Stage Schedule & Costs (2)'!$H10 -> 0 | R10: =MAX(0,MIN('Stage Schedule & Costs (2)'!$F10,F$4)-MAX('Stage Schedule & Costs (2)'!$E10,F$4-1))*'Stage Schedule & Costs (2)'!$H10 -> 0 | S10: =MAX(0,MIN('Stage Schedule & Costs (2)'!$F10,G$4)-MAX('Stage Schedule & Costs (2)'!$E10,G$4-1))*'Stage Schedule & Costs (2)'!$H10 -> 0 | T10: =MAX(0,MIN('Stage Schedule & Costs (2)'!$F10,H$4)-MAX('Stage Schedule & Costs (2)'!$E10,H$4-1))*'Stage Schedule & Costs (2)'!$H10 -> 0 | U10: =MAX(0,MIN('Stage Schedule & Costs (2)'!$F10,I$4)-MAX('Stage Schedule & Costs (2)'!$E10,I$4-1))*'Stage Schedule & Costs (2)'!$H10 -> 0 | V10: =MAX(0,MIN('Stage Schedule & Costs (2)'!$F10,J$4)-MAX('Stage Schedule & Costs (2)'!$E10,J$4-1))*'Stage Schedule & Costs (2)'!$H10 -> 0 | W10: =MAX(0,MIN('Stage Schedule & Costs (2)'!$F10,K$4)-MAX('Stage Schedule & Costs (2)'!$E10,K$4-1))*'Stage Schedule & Costs (2)'!$H10 -> 0 | ... BQ10: =MAX(0,MIN('Stage Schedule & Costs (2)'!$F10,BE$4)-MAX('Stage Schedule & Costs (2)'!$E10,BE$4-1))*'Stage Schedule & Costs (2)'!$H10 -> 0
A11: ='Stage Schedule & Costs (2)'!A11 -> 7 | B11: ='Stage Schedule & Costs (2)'!B11&" - "&'Stage Schedule & Costs (2)'!C11 -> - 3rd Floor | C11: =SUM(P11:BQ11) -> 0 | P11: =MAX(0,MIN('Stage Schedule & Costs (2)'!$F11,D$4)-MAX('Stage Schedule & Costs (2)'!$E11,D$4-1))*'Stage Schedule & Costs (2)'!$H11 -> 0 | Q11: =MAX(0,MIN('Stage Schedule & Costs (2)'!$F11,E$4)-MAX('Stage Schedule & Costs (2)'!$E11,E$4-1))*'Stage Schedule & Costs (2)'!$H11 -> 0 | R11: =MAX(0,MIN('Stage Schedule & Costs (2)'!$F11,F$4)-MAX('Stage Schedule & Costs (2)'!$E11,F$4-1))*'Stage Schedule & Costs (2)'!$H11 -> 0 | S11: =MAX(0,MIN('Stage Schedule & Costs (2)'!$F11,G$4)-MAX('Stage Schedule & Costs (2)'!$E11,G$4-1))*'Stage Schedule & Costs (2)'!$H11 -> 0 | T11: =MAX(0,MIN('Stage Schedule & Costs (2)'!$F11,H$4)-MAX('Stage Schedule & Costs (2)'!$E11,H$4-1))*'Stage Schedule & Costs (2)'!$H11 -> 0 | U11: =MAX(0,MIN('Stage Schedule & Costs (2)'!$F11,I$4)-MAX('Stage Schedule & Costs (2)'!$E11,I$4-1))*'Stage Schedule & Costs (2)'!$H11 -> 0 | V11: =MAX(0,MIN('Stage Schedule & Costs (2)'!$F11,J$4)-MAX('Stage Schedule & Costs (2)'!$E11,J$4-1))*'Stage Schedule & Costs (2)'!$H11 -> 0 | W11: =MAX(0,MIN('Stage Schedule & Costs (2)'!$F11,K$4)-MAX('Stage Schedule & Costs (2)'!$E11,K$4-1))*'Stage Schedule & Costs (2)'!$H11 -> 0 | ... BQ11: =MAX(0,MIN('Stage Schedule & Costs (2)'!$F11,BE$4)-MAX('Stage Schedule & Costs (2)'!$E11,BE$4-1))*'Stage Schedule & Costs (2)'!$H11 -> 0
A12: ='Stage Schedule & Costs (2)'!A12 -> 8 | B12: ='Stage Schedule & Costs (2)'!B12&" - "&'Stage Schedule & Costs (2)'!C12 -> Building Works - Basement Floor | C12: =SUM(P12:BQ12) -> 330000 | P12: =MAX(0,MIN('Stage Schedule & Costs (2)'!$F12,D$4)-MAX('Stage Schedule & Costs (2)'!$E12,D$4-1))*'Stage Schedule & Costs (2)'!$H12 -> 0 | Q12: =MAX(0,MIN('Stage Schedule & Costs (2)'!$F12,E$4)-MAX('Stage Schedule & Costs (2)'!$E12,E$4-1))*'Stage Schedule & Costs (2)'!$H12 -> 0 | R12: =MAX(0,MIN('Stage Schedule & Costs (2)'!$F12,F$4)-MAX('Stage Schedule & Costs (2)'!$E12,F$4-1))*'Stage Schedule & Costs (2)'!$H12 -> 0 | S12: =MAX(0,MIN('Stage Schedule & Costs (2)'!$F12,G$4)-MAX('Stage Schedule & Costs (2)'!$E12,G$4-1))*'Stage Schedule & Costs (2)'!$H12 -> 0 | T12: =MAX(0,MIN('Stage Schedule & Costs (2)'!$F12,H$4)-MAX('Stage Schedule & Costs (2)'!$E12,H$4-1))*'Stage Schedule & Costs (2)'!$H12 -> 0 | U12: =MAX(0,MIN('Stage Schedule & Costs (2)'!$F12,I$4)-MAX('Stage Schedule & Costs (2)'!$E12,I$4-1))*'Stage Schedule & Costs (2)'!$H12 -> 0 | V12: =MAX(0,MIN('Stage Schedule & Costs (2)'!$F12,J$4)-MAX('Stage Schedule & Costs (2)'!$E12,J$4-1))*'Stage Schedule & Costs (2)'!$H12 -> 0 | W12: =MAX(0,MIN('Stage Schedule & Costs (2)'!$F12,K$4)-MAX('Stage Schedule & Costs (2)'!$E12,K$4-1))*'Stage Schedule & Costs (2)'!$H12 -> 0 | ... BQ12: =MAX(0,MIN('Stage Schedule & Costs (2)'!$F12,BE$4)-MAX('Stage Schedule & Costs (2)'!$E12,BE$4-1))*'Stage Schedule & Costs (2)'!$H12 -> 0
A13: ='Stage Schedule & Costs (2)'!A13 -> 9 | B13: ='Stage Schedule & Costs (2)'!B13&" - "&'Stage Schedule & Costs (2)'!C13 -> - Ground Floor | C13: =SUM(P13:BQ13) -> 330000 | P13: =MAX(0,MIN('Stage Schedule & Costs (2)'!$F13,D$4)-MAX('Stage Schedule & Costs (2)'!$E13,D$4-1))*'Stage Schedule & Costs (2)'!$H13 -> 0 | Q13: =MAX(0,MIN('Stage Schedule & Costs (2)'!$F13,E$4)-MAX('Stage Schedule & Costs (2)'!$E13,E$4-1))*'Stage Schedule & Costs (2)'!$H13 -> 0 | R13: =MAX(0,MIN('Stage Schedule & Costs (2)'!$F13,F$4)-MAX('Stage Schedule & Costs (2)'!$E13,F$4-1))*'Stage Schedule & Costs (2)'!$H13 -> 0 | S13: =MAX(0,MIN('Stage Schedule & Costs (2)'!$F13,G$4)-MAX('Stage Schedule & Costs (2)'!$E13,G$4-1))*'Stage Schedule & Costs (2)'!$H13 -> 0 | T13: =MAX(0,MIN('Stage Schedule & Costs (2)'!$F13,H$4)-MAX('Stage Schedule & Costs (2)'!$E13,H$4-1))*'Stage Schedule & Costs (2)'!$H13 -> 0 | U13: =MAX(0,MIN('Stage Schedule & Costs (2)'!$F13,I$4)-MAX('Stage Schedule & Costs (2)'!$E13,I$4-1))*'Stage Schedule & Costs (2)'!$H13 -> 0 | V13: =MAX(0,MIN('Stage Schedule & Costs (2)'!$F13,J$4)-MAX('Stage Schedule & Costs (2)'!$E13,J$4-1))*'Stage Schedule & Costs (2)'!$H13 -> 0 | W13: =MAX(0,MIN('Stage Schedule & Costs (2)'!$F13,K$4)-MAX('Stage Schedule & Costs (2)'!$E13,K$4-1))*'Stage Schedule & Costs (2)'!$H13 -> 0 | ... BQ13: =MAX(0,MIN('Stage Schedule & Costs (2)'!$F13,BE$4)-MAX('Stage Schedule & Costs (2)'!$E13,BE$4-1))*'Stage Schedule & Costs (2)'!$H13 -> 0
A14: ='Stage Schedule & Costs (2)'!A14 -> 10 | B14: ='Stage Schedule & Costs (2)'!B14&" - "&'Stage Schedule & Costs (2)'!C14 -> - 1st Floor | C14: =SUM(P14:BQ14) -> 330000 | P14: =MAX(0,MIN('Stage Schedule & Costs (2)'!$F14,D$4)-MAX('Stage Schedule & Costs (2)'!$E14,D$4-1))*'Stage Schedule & Costs (2)'!$H14 -> 0 | Q14: =MAX(0,MIN('Stage Schedule & Costs (2)'!$F14,E$4)-MAX('Stage Schedule & Costs (2)'!$E14,E$4-1))*'Stage Schedule & Costs (2)'!$H14 -> 0 | R14: =MAX(0,MIN('Stage Schedule & Costs (2)'!$F14,F$4)-MAX('Stage Schedule & Costs (2)'!$E14,F$4-1))*'Stage Schedule & Costs (2)'!$H14 -> 0 | S14: =MAX(0,MIN('Stage Schedule & Costs (2)'!$F14,G$4)-MAX('Stage Schedule & Costs (2)'!$E14,G$4-1))*'Stage Schedule & Costs (2)'!$H14 -> 0 | T14: =MAX(0,MIN('Stage Schedule & Costs (2)'!$F14,H$4)-MAX('Stage Schedule & Costs (2)'!$E14,H$4-1))*'Stage Schedule & Costs (2)'!$H14 -> 0 | U14: =MAX(0,MIN('Stage Schedule & Costs (2)'!$F14,I$4)-MAX('Stage Schedule & Costs (2)'!$E14,I$4-1))*'Stage Schedule & Costs (2)'!$H14 -> 0 | V14: =MAX(0,MIN('Stage Schedule & Costs (2)'!$F14,J$4)-MAX('Stage Schedule & Costs (2)'!$E14,J$4-1))*'Stage Schedule & Costs (2)'!$H14 -> 0 | W14: =MAX(0,MIN('Stage Schedule & Costs (2)'!$F14,K$4)-MAX('Stage Schedule & Costs (2)'!$E14,K$4-1))*'Stage Schedule & Costs (2)'!$H14 -> 0 | ... BQ14: =MAX(0,MIN('Stage Schedule & Costs (2)'!$F14,BE$4)-MAX('Stage Schedule & Costs (2)'!$E14,BE$4-1))*'Stage Schedule & Costs (2)'!$H14 -> 0
A15: ='Stage Schedule & Costs (2)'!A15 -> 11 | B15: ='Stage Schedule & Costs (2)'!B15&" - "&'Stage Schedule & Costs (2)'!C15 -> - 2nd Floor | C15: =SUM(P15:BQ15) -> 330000 | P15: =MAX(0,MIN('Stage Schedule & Costs (2)'!$F15,D$4)-MAX('Stage Schedule & Costs (2)'!$E15,D$4-1))*'Stage Schedule & Costs (2)'!$H15 -> 0 | Q15: =MAX(0,MIN('Stage Schedule & Costs (2)'!$F15,E$4)-MAX('Stage Schedule & Costs (2)'!$E15,E$4-1))*'Stage Schedule & Costs (2)'!$H15 -> 0 | R15: =MAX(0,MIN('Stage Schedule & Costs (2)'!$F15,F$4)-MAX('Stage Schedule & Costs (2)'!$E15,F$4-1))*'Stage Schedule & Costs (2)'!$H15 -> 0 | S15: =MAX(0,MIN('Stage Schedule & Costs (2)'!$F15,G$4)-MAX('Stage Schedule & Costs (2)'!$E15,G$4-1))*'Stage Schedule & Costs (2)'!$H15 -> 0 | T15: =MAX(0,MIN('Stage Schedule & Costs (2)'!$F15,H$4)-MAX('Stage Schedule & Costs (2)'!$E15,H$4-1))*'Stage Schedule & Costs (2)'!$H15 -> 0 | U15: =MAX(0,MIN('Stage Schedule & Costs (2)'!$F15,I$4)-MAX('Stage Schedule & Costs (2)'!$E15,I$4-1))*'Stage Schedule & Costs (2)'!$H15 -> 0 | V15: =MAX(0,MIN('Stage Schedule & Costs (2)'!$F15,J$4)-MAX('Stage Schedule & Costs (2)'!$E15,J$4-1))*'Stage Schedule & Costs (2)'!$H15 -> 0 | W15: =MAX(0,MIN('Stage Schedule & Costs (2)'!$F15,K$4)-MAX('Stage Schedule & Costs (2)'!$E15,K$4-1))*'Stage Schedule & Costs (2)'!$H15 -> 0 | ... BQ15: =MAX(0,MIN('Stage Schedule & Costs (2)'!$F15,BE$4)-MAX('Stage Schedule & Costs (2)'!$E15,BE$4-1))*'Stage Schedule & Costs (2)'!$H15 -> 0
A16: ='Stage Schedule & Costs (2)'!A16 -> 12 | B16: ='Stage Schedule & Costs (2)'!B16&" - "&'Stage Schedule & Costs (2)'!C16 -> - 3rd Floor | C16: =SUM(P16:BQ16) -> 0 | P16: =MAX(0,MIN('Stage Schedule & Costs (2)'!$F16,D$4)-MAX('Stage Schedule & Costs (2)'!$E16,D$4-1))*'Stage Schedule & Costs (2)'!$H16 -> 0 | Q16: =MAX(0,MIN('Stage Schedule & Costs (2)'!$F16,E$4)-MAX('Stage Schedule & Costs (2)'!$E16,E$4-1))*'Stage Schedule & Costs (2)'!$H16 -> 0 | R16: =MAX(0,MIN('Stage Schedule & Costs (2)'!$F16,F$4)-MAX('Stage Schedule & Costs (2)'!$E16,F$4-1))*'Stage Schedule & Costs (2)'!$H16 -> 0 | S16: =MAX(0,MIN('Stage Schedule & Costs (2)'!$F16,G$4)-MAX('Stage Schedule & Costs (2)'!$E16,G$4-1))*'Stage Schedule & Costs (2)'!$H16 -> 0 | T16: =MAX(0,MIN('Stage Schedule & Costs (2)'!$F16,H$4)-MAX('Stage Schedule & Costs (2)'!$E16,H$4-1))*'Stage Schedule & Costs (2)'!$H16 -> 0 | U16: =MAX(0,MIN('Stage Schedule & Costs (2)'!$F16,I$4)-MAX('Stage Schedule & Costs (2)'!$E16,I$4-1))*'Stage Schedule & Costs (2)'!$H16 -> 0 | V16: =MAX(0,MIN('Stage Schedule & Costs (2)'!$F16,J$4)-MAX('Stage Schedule & Costs (2)'!$E16,J$4-1))*'Stage Schedule & Costs (2)'!$H16 -> 0 | W16: =MAX(0,MIN('Stage Schedule & Costs (2)'!$F16,K$4)-MAX('Stage Schedule & Costs (2)'!$E16,K$4-1))*'Stage Schedule & Costs (2)'!$H16 -> 0 | ... BQ16: =MAX(0,MIN('Stage Schedule & Costs (2)'!$F16,BE$4)-MAX('Stage Schedule & Costs (2)'!$E16,BE$4-1))*'Stage Schedule & Costs (2)'!$H16 -> 0
... A23: ='Stage Schedule & Costs (2)'!A23 -> 19 | B23: ='Stage Schedule & Costs (2)'!B23&" - "&'Stage Schedule & Costs (2)'!C23 -> Landscape - Landscape | C23: =SUM(P23:BQ23) -> 4125000 | P23: =MAX(0,MIN('Stage Schedule & Costs (2)'!$F23,D$4)-MAX('Stage Schedule & Costs (2)'!$E23,D$4-1))*'Stage Schedule & Costs (2)'!$H23 -> 0 | Q23: =MAX(0,MIN('Stage Schedule & Costs (2)'!$F23,E$4)-MAX('Stage Schedule & Costs (2)'!$E23,E$4-1))*'Stage Schedule & Costs (2)'!$H23 -> 0 | R23: =MAX(0,MIN('Stage Schedule & Costs (2)'!$F23,F$4)-MAX('Stage Schedule & Costs (2)'!$E23,F$4-1))*'Stage Schedule & Costs (2)'!$H23 -> 0 | S23: =MAX(0,MIN('Stage Schedule & Costs (2)'!$F23,G$4)-MAX('Stage Schedule & Costs (2)'!$E23,G$4-1))*'Stage Schedule & Costs (2)'!$H23 -> 0 | T23: =MAX(0,MIN('Stage Schedule & Costs (2)'!$F23,H$4)-MAX('Stage Schedule & Costs (2)'!$E23,H$4-1))*'Stage Schedule & Costs (2)'!$H23 -> 0 | U23: =MAX(0,MIN('Stage Schedule & Costs (2)'!$F23,I$4)-MAX('Stage Schedule & Costs (2)'!$E23,I$4-1))*'Stage Schedule & Costs (2)'!$H23 -> 0 | V23: =MAX(0,MIN('Stage Schedule & Costs (2)'!$F23,J$4)-MAX('Stage Schedule & Costs (2)'!$E23,J$4-1))*'Stage Schedule & Costs (2)'!$H23 -> 0 | W23: =MAX(0,MIN('Stage Schedule & Costs (2)'!$F23,K$4)-MAX('Stage Schedule & Costs (2)'!$E23,K$4-1))*'Stage Schedule & Costs (2)'!$H23 -> 0 | ... BQ23: =MAX(0,MIN('Stage Schedule & Costs (2)'!$F23,BE$4)-MAX('Stage Schedule & Costs (2)'!$E23,BE$4-1))*'Stage Schedule & Costs (2)'!$H23 -> 0
B24: Total Monthly Spend (EGP) | C24: =SUM(P24:BQ24) -> 87145000 | P24: =SUM(P5:P23) -> 833333.33 | Q24: =SUM(Q5:Q23) -> 833333.33 | R24: =SUM(R5:R23) -> 833333.33 | S24: =SUM(S5:S23) -> 1100000 | T24: =SUM(T5:T23) -> 1100000 | U24: =SUM(U5:U23) -> 1100000 | V24: =SUM(V5:V23) -> 1666666.7 | W24: =SUM(W5:W23) -> 1666666.7 | ... BQ24: =SUM(BQ5:BQ23) -> 0
B25: Cumulative Spend (EGP) | P25: =P24 -> 833333.33 | Q25: =P25+Q24 -> 1666666.7 | R25: =Q25+R24 -> 2500000 | S25: =R25+S24 -> 3600000 | T25: =S25+T24 -> 4700000 | U25: =T25+U24 -> 5800000 | V25: =U25+V24 -> 7466666.7 | W25: =V25+W24 -> 9133333.3 | X25: =W25+X24 -> 10800000 | ... BQ25: =BP25+BQ24 -> 87145000
B27: Construction Cost
B28: Green Square | C28: =SUM(P28:BQ28) -> 697160000 | P28: =P24*8 -> 6666666.7 | Q28: =Q24*8 -> 6666666.7 | R28: =R24*8 -> 6666666.7 | S28: =S24*8 -> 8800000 | T28: =T24*8 -> 8800000 | U28: =U24*8 -> 8800000 | V28: =V24*8 -> 13333333 | W28: =W24*8 -> 13333333 | ... BW28: =BW24*8 -> 0
B29: L'avenir | C29: =SUM(AB29:CC29) -> 650760000 | V29: =P24*8 -> 6666666.7 | W29: =Q24*8 -> 6666666.7 | X29: =R24*8 -> 6666666.7 | Y29: =S24*8 -> 8800000 | Z29: =T24*8 -> 8800000 | AA29: =U24*8 -> 8800000 | AB29: =V24*8 -> 13333333 | AC29: =W24*8 -> 13333333 | ... BN29: =BH24*8 -> 0
B30: Total | C30: =SUM(C28:C29) -> 1347920000 | P30: =SUM(P28:P29) -> 6666666.7 | Q30: =SUM(Q28:Q29) -> 6666666.7 | R30: =SUM(R28:R29) -> 6666666.7 | S30: =SUM(S28:S29) -> 8800000 | T30: =SUM(T28:T29) -> 8800000 | U30: =SUM(U28:U29) -> 8800000 | V30: =SUM(V28:V29) -> 20000000 | W30: =SUM(W28:W29) -> 20000000 | ... BW30: =SUM(BW28:BW29) -> 0
B32: Sales Commission | C32: 0.04
B33: Green Square | C33: =SUM(P33:BQ33) -> 90119160 | P33: ='Green Square'!$E$26/3*$C$32*1000 -> 0 | Q33: ='Green Square'!$E$26/3*$C$32*1000 -> 0 | R33: ='Green Square'!$E$26/3*$C$32*1000 -> 0 | S33: ='Green Square'!$F$26/3*$C$32*1000 -> 0 | T33: ='Green Square'!$F$26/3*$C$32*1000 -> 0 | U33: ='Green Square'!$F$26/3*$C$32*1000 -> 0 | V33: ='Green Square'!$G$26/3*$C$32*1000 -> 4037130 | W33: ='Green Square'!$G$26/3*$C$32*1000 -> 4037130 | X33: ='Green Square'!$G$26/3*$C$32*1000 -> 4037130 | Y33: ='Green Square'!$H$26/3*$C$32*1000 -> 4037130 | Z33: ='Green Square'!$H$26/3*$C$32*1000 -> 4037130 | AA33: ='Green Square'!$H$26/3*$C$32*1000 -> 4037130 | AB33: ='Green Square'!$I$26/3*$C$32*1000 -> 3173753.3 | AC33: ='Green Square'!$I$26/3*$C$32*1000 -> 3173753.3 | AD33: ='Green Square'!$I$26/3*$C$32*1000 -> 3173753.3 | AE33: ='Green Square'!$J$26/3*$C$32*1000 -> 3173753.3 | AF33: ='Green Square'!$J$26/3*$C$32*1000 -> 3173753.3 | AG33: ='Green Square'!$J$26/3*$C$32*1000 -> 3173753.3 | AH33: ='Green Square'!$K$26/3*$C$32*1000 -> 2329670 | AI33: ='Green Square'!$K$26/3*$C$32*1000 -> 2329670 | AJ33: ='Green Square'!$K$26/3*$C$32*1000 -> 2329670 | AK33: ='Green Square'!$L$26/3*$C$32*1000 -> 2329670 | AL33: ='Green Square'!$L$26/3*$C$32*1000 -> 2329670 | AM33: ='Green Square'!$L$26/3*$C$32*1000 -> 2329670 | AN33: ='Green Square'!$M$26/3*$C$32*1000 -> 2566013.3 | AO33: ='Green Square'!$M$26/3*$C$32*1000 -> 2566013.3 | AP33: ='Green Square'!$M$26/3*$C$32*1000 -> 2566013.3 | AQ33: ='Green Square'!$N$26/3*$C$32*1000 -> 3086933.3 | AR33: ='Green Square'!$N$26/3*$C$32*1000 -> 3086933.3 | AS33: ='Green Square'!$N$26/3*$C$32*1000 -> 3086933.3 | AT33: ='Green Square'!$O$26/3*$C$32*1000 -> 3086933.3 | AU33: ='Green Square'!$O$26/3*$C$32*1000 -> 3086933.3 | AV33: ='Green Square'!$O$26/3*$C$32*1000 -> 3086933.3 | AW33: ='Green Square'!$P$26/3*$C$32*1000 -> 2218733.3 | AX33: ='Green Square'!$P$26/3*$C$32*1000 -> 2218733.3 | AY33: ='Green Square'!$P$26/3*$C$32*1000 -> 2218733.3 | AZ33: ='Green Square'!$Q$26/3*$C$32*1000 -> 0 | BA33: ='Green Square'!$Q$26/3*$C$32*1000 -> 0 | BB33: ='Green Square'!$Q$26/3*$C$32*1000 -> 0 | BC33: ='Green Square'!$R$26/3*$C$32*1000 -> 0 | BD33: ='Green Square'!$R$26/3*$C$32*1000 -> 0 | BE33: ='Green Square'!$R$26/3*$C$32*1000 -> 0 | BF33: ='Green Square'!$S$26/3*$C$32*1000 -> 0 | BG33: ='Green Square'!$S$26/3*$C$32*1000 -> 0 | BH33: ='Green Square'!$S$26/3*$C$32*1000 -> 0 | BI33: ='Green Square'!$T$26/3*$C$32*1000 -> 0 | BJ33: ='Green Square'!$T$26/3*$C$32*1000 -> 0 | BK33: ='Green Square'!$T$26/3*$C$32*1000 -> 0 | BL33: ='Green Square'!$U$26/3*$C$32*1000 -> 0 | BM33: ='Green Square'!$U$26/3*$C$32*1000 -> 0 | BN33: ='Green Square'!$U$26/3*$C$32*1000 -> 0 | BO33: ='Green Square'!$V$26/3*$C$32*1000 -> 0 | BP33: ='Green Square'!$V$26/3*$C$32*1000 -> 0 | BQ33: ='Green Square'!$V$26/3*$C$32*1000 -> 0 | BR33: ='Green Square'!$W$26/3*$C$32*1000 -> 0 | BS33: ='Green Square'!$W$26/3*$C$32*1000 -> 0 | BT33: ='Green Square'!$W$26/3*$C$32*1000 -> 0 | BU33: ='Green Square'!$X$26/3*$C$32*1000 -> 0 | BV33: ='Green Square'!$X$26/3*$C$32*1000 -> 0 | BW33: ='Green Square'!$X$26/3*$C$32*1000 -> 0
