Workbook

Sheet Summary
A1: L'avenir EL-Mostakbal City -Summary
A2: Land Area: | B2: m² | C2: 14910 | D2: Construction Start: | E2: =Assumptions!$C$12 -> 7 | F2: Month
A3: footprint % : | C3: =C4/C2 -> 0.3 | D3: Construction Duration : | E3: =Assumptions!$C$13 -> 36 | F3: Month
A4: footprint : | B4: m² | C4: 4473 | D4: Project Delivery : | E4: =E3+E2-1 -> 42 | F4: Month
A5: Height: | C5: G+2
A6: Retail: | B6: m² | C6: =C4 -> 4473 | D6: Sales Start: | E6: =Assumptions!$C$10 -> 1 | F6: Month
A7: Offices: | B7: m² | C7: 8946 | D7: Maximum Cash Shortage : | E7: =MIN(C49:AT49) -> -102.01806 | F7: MEGP
A8: Total BUA: | B8: m² | C8: =C7+C6 -> 13419
A9: RETAINED %: | C9: 0.2
A10: Downpayment | C10: =Assumptions!$C$27 -> 200
C11: MEGP | D11: NPV-With DP | E11: NPV-Without DP
A12: CASH INFLOW JALOUR | C12: =SUM(C13:C14) -> 1503.9764 | D12: ='Net Cash Flow -With DP'!C16 -> 994.8063 | E12: ='Net Cash Flow -Without DP'!C16 -> 1018.7699
A13: COMMERCIAL | C13: =C32-C36 -> 605.74205
A14: ADMIN | C14: =C33-C37 -> 898.23431
C16: MEGP | D16: NPV-With DP | E16: NPV-Without DP
A17: CASH OUTFLOW JALOUR | C17: =SUM(C18:C20) -> -862.28343 | D17: =-'Net Cash Flow -With DP'!C24 -> -644.2194 | E17: =-'Net Cash Flow -Without DP'!C24 -> -644.2194
A18: Construction Cost | C18: =-'Cash Out Detail'!C28/1000000 -> -650.76
A19: Sales Commission | B19: 0.04 | C19: =-'Cash Out Detail'!C31/1000000 -> -106.94943
A20: SGA& Others Cost | B20: 0.15 | C20: =-'Cash Out Detail'!C34/1000000 -> -104.574
C22: MEGP | D22: NPV-With DP | E22: NPV-Without DP | F22: Diff
A23: NET CASH FLOW JALOUR -MEGP | C23: =C12+C17 -> 641.69293 | D23: ='Net Cash Flow -With DP'!C40 -> 350.5869 | E23: ='Net Cash Flow -Without DP'!C40 -> 374.55052 | F23: =D23-E23 -> -23.963617
A25: Note: NPV figures are as at this project's own start (M1 = sales launch), not the shared calendar start used in the combined workbook. All time axes are shifted back 12 months.
A26: Note: 'Construction Cost', 'Sales Commission' and 'SGA' above are picked up exactly as in the original Summary sheet (see Cash Out Detail check rows).
A27: Total Sales 100% | C27: =SUM(C28:C29) -> 3342.1697
A28: COMMERCIAL | C28: =C32*100/80 -> 1346.0934
A29: ADMIN | C29: =C33*100/80 -> 1996.0763
A31: Total Sales 80% | C31: =SUM(C32:C33) -> 2673.7357
A32: COMMERCIAL | C32: ='L''avenir'!D24/1000 -> 1076.8747
A33: ADMIN | C33: ='L''avenir'!D25/1000 -> 1596.861
A35: ALAHLY - SABBOUR % | B35: 0.35 | C35: =SUM(C36:C37) -> 1169.7594
A36: COMMERCIAL | C36: =C28*B35 -> 471.1327
A37: ADMIN | C37: =C29*B35 -> 698.62669
C44: ='Net Cash Flow -With DP'!D3 -> M -9 | D44: ='Net Cash Flow -With DP'!E3 -> M -6 | E44: ='Net Cash Flow -With DP'!F3 -> M -3 | F44: ='Net Cash Flow -With DP'!G3 -> M 0 | G44: ='Net Cash Flow -With DP'!H3 -> M 3 | H44: ='Net Cash Flow -With DP'!I3 -> M 6 | I44: ='Net Cash Flow -With DP'!J3 -> M 9 | J44: ='Net Cash Flow -With DP'!K3 -> M 12 | ... AT44: ='Net Cash Flow -With DP'!AU3 -> 0
A45: Total Collections MEGP | C45: ='Net Cash Flow -With DP'!D4 -> 0 | D45: ='Net Cash Flow -With DP'!E4 -> 0 | E45: ='Net Cash Flow -With DP'!F4 -> 0 | F45: ='Net Cash Flow -With DP'!G4 -> 0 | G45: ='Net Cash Flow -With DP'!H4 -> 18.11565 | H45: ='Net Cash Flow -With DP'!I4 -> 36.2313 | I45: ='Net Cash Flow -With DP'!J4 -> 58.260825 | J45: ='Net Cash Flow -With DP'!K4 -> 69.01839 | ... AT45: ='Net Cash Flow -With DP'!AU4 -> 0
A46: ALAHLY - SABBOUR Payments MEGP | C46: =-'Net Cash Flow -With DP'!D8 -> 0 | D46: =-'Net Cash Flow -With DP'!E8 -> 0 | E46: =-'Net Cash Flow -With DP'!F8 -> 0 | F46: =-'Net Cash Flow -With DP'!G8 -> -85 | G46: =-'Net Cash Flow -With DP'!H8 -> -22.5 | H46: =-'Net Cash Flow -With DP'!I8 -> -22.5 | I46: =-'Net Cash Flow -With DP'!J8 -> -22.5 | J46: =-'Net Cash Flow -With DP'!K8 -> -22.5 | ... AT46: =-'Net Cash Flow -With DP'!AU8 -> 0
A47: CASH OUT FLOW CAPEX -MEGP | C47: =-'Net Cash Flow -With DP'!D20 -> 0 | D47: =-'Net Cash Flow -With DP'!E20 -> 0 | E47: =-'Net Cash Flow -With DP'!F20 -> 0 | F47: =-'Net Cash Flow -With DP'!G20 -> 0 | G47: =-'Net Cash Flow -With DP'!H20 -> 0 | H47: =-'Net Cash Flow -With DP'!I20 -> 0 | I47: =-'Net Cash Flow -With DP'!J20 -> -23 | J47: =-'Net Cash Flow -With DP'!K20 -> -30.36 | ... AT47: =-'Net Cash Flow -With DP'!AU20 -> 0
A48: Net Cash Flow | C48: =SUM(C45:C47) -> 0 | D48: =SUM(D45:D47) -> 0 | E48: =SUM(E45:E47) -> 0 | F48: =SUM(F45:F47) -> -85 | G48: =SUM(G45:G47) -> -4.38435 | H48: =SUM(H45:H47) -> 13.7313 | I48: =SUM(I45:I47) -> 12.760825 | J48: =SUM(J45:J47) -> 16.15839 | ... AT48: =SUM(AT45:AT47) -> 0
A49: Net Cash Flow-Accum | C49: =C48 -> 0 | D49: =C49+D48 -> 0 | E49: =D49+E48 -> 0 | F49: =E49+F48 -> -85 | G49: =F49+G48 -> -89.38435 | H49: =G49+H48 -> -75.65305 | I49: =H49+I48 -> -62.892225 | J49: =I49+J48 -> -46.733835 | K49: =J49+K48 -> -85.13881 | ... AT49: =AS49+AT48 -> 595.29293

Sheet Assumptions
A1: L'AVENIR - ASSUMPTIONS AND TIMELINE
A2: Standalone model. Month 1 (M1) is this project's own sales launch. Blue = input, black = formula or fixed reference. Cash flows are in MEGP unless stated.
A4: NPV SETTINGS
A5: Cost of capital (annual) | C5: 0.14 | D5: Carried over unchanged from the combined model, where it was a single shared input.
A6: Quarter column (month at end of quarter) | E6: M -9 | F6: M -6 | G6: M -3 | H6: M 0 | I6: M 3 | J6: M 6 | K6: M 9 | L6: M 12 | M6: M 15 | N6: M 18 | O6: M 21 | P6: M 24 | Q6: M 27 | R6: M 30 | S6: M 33 | T6: M 36 | U6: M 39 | V6: M 42 | W6: M 45 | X6: M 48 | Y6: M 51 | Z6: M 54 | AA6: M 57 | AB6: M 60 | AC6: M 63 | AD6: M 66 | AE6: M 69 | AF6: M 72 | AG6: M 75 | AH6: M 78 | AI6: M 81 | AJ6: M 84 | AK6: M 87 | AL6: M 90 | AM6: M 93 | AN6: M 96 | AO6: M 99 | AP6: M 102 | AQ6: M 105 | AR6: M 108 | AS6: M 111
A7: Discount period (years from the start of M1) | E7: =(3-$C$15)/12 -> -0.75 | F7: =0.25+E7 -> -0.5 | G7: =0.25+F7 -> -0.25 | H7: =0.25+G7 -> 0 | I7: =0.25+H7 -> 0.25 | J7: =0.25+I7 -> 0.5 | K7: =0.25+J7 -> 0.75 | L7: =0.25+K7 -> 1 | M7: =0.25+L7 -> 1.25 | ... AS7: =0.25+AR7 -> 9.25
A9: TIMELINE (months counted from this project's own M1)
A10: Sales start (launch) month | C10: 1 | D10: M1 = launch. Equals original Sales Start less the calendar offset below.
A11: Construction start offset from launch (months) | C11: 6 | D11: Gap kept from the original model: construction start less sales start on the shared calendar.
A12: Construction start month | C12: =$C$10+$C$11 -> 7 | D12: Drives the stage schedule on 'Cash Out Detail'.
A13: Construction duration (months) | C13: 36
A14: Project delivery month (end of construction) | C14: =$C$12+$C$13-1 -> 42
A15: Calendar offset removed from the shared timeline (months) | C15: 12 | D15: Equals original Sales Start month less 1. Structural: it re-labels the axis and the discount months; do not overwrite.
A16: Original Sales Start month (shared calendar, for reference) | C16: 13
A17: Original Construction Start month (shared calendar, for reference) | C17: 19
A18: Unit handover month, original shared calendar (project sheet C5) | C18: 48
A19: Unit handover month, own timeline | C19: =$C$18-$C$15 -> 36 | D19: Feeds project sheet C5 (months-to-delivery row).
A21: COST SCALING (as picked up by the original Cash Out Detail)
A22: Construction cost multiple of the base stage schedule | C22: 8 | D22: Base 'Stage Schedule & Costs (2)' is the NURV build cost; this project is a multiple of it.
A23: Additional size multiple | C23: 1 | D23: None for this project (1.0).
A24: Combined multiple (information) | C24: =$C$22*$C$23 -> 8
A26: OTHER
A27: Downpayment shown on Summary (MEGP) | C27: 200 | D27: Was 'Summary'!B3:B5 on the combined sheet.

Sheet L'avenir
A1: L'AVENIR
B2: BUA (M²) | C2: RETAINED% | D2: Total | E2: M -9 | F2: M -6 | G2: M -3 | H2: M 0 | I2: M 3 | J2: M 6 | K2: M 9 | L2: M 12 | M2: M 15 | N2: M 18 | O2: M 21 | P2: M 24 | Q2: M 27 | R2: M 30 | S2: M 33 | T2: M 36 | U2: M 39 | V2: M 42 | W2: M 45 | X2: M 48 | Y2: M 51 | Z2: M 54 | AA2: M 57 | AB2: M 60 | AC2: M 63 | AD2: M 66 | AE2: M 69 | AF2: M 72 | AG2: M 75 | AH2: M 78 | AI2: M 81 | AJ2: M 84 | AK2: M 87 | AL2: M 90 | AM2: M 93 | AN2: M 96
A3: COMMERCIAL PRICE | E3: 200 | F3: 200 | G3: 225 | H3: 225 | I3: 250 | J3: 250 | K3: 275 | L3: 275 | M3: 300 | N3: 300 | O3: 330 | P3: 330 | Q3: 360 | R3: 360 | S3: 360 | T3: 360
A4: ADMIN PRICE | E4: 125 | F4: 125 | G4: 135 | H4: 135 | I4: 160 | J4: 160 | K4: 180 | L4: 180 | M4: 200 | N4: 200 | O4: 220 | P4: 220 | Q4: 240 | R4: 240 | S4: 240 | T4: 240
A5: DELIVERY DATE(month) | C5: =Assumptions!$C$19 -> 36 | E5: =IF(C5-3<0,0,C5-3) -> 33 | F5: =IF(E5-3<0,0,E5-3) -> 30 | G5: =IF(F5-3<0,0,F5-3) -> 27 | H5: =IF(G5-3<0,0,G5-3) -> 24 | I5: =IF(H5-3<0,0,H5-3) -> 21 | J5: =IF(I5-3<0,0,I5-3) -> 18 | K5: =IF(J5-3<0,0,J5-3) -> 15 | L5: =IF(K5-3<0,0,K5-3) -> 12 | M5: =IF(L5-3<0,0,L5-3) -> 9 | ... T5: =IF(S5-3<0,0,S5-3) -> 0
A6: TARGET SALES % COMM. | B6: 4473 | C6: 20 | I6: 10 | J6: 10 | K6: 10 | L6: 7 | M6: 7 | N6: 6 | O6: 5 | P6: 5 | Q6: 5 | R6: 5 | S6: 5 | T6: 5
A7: TARGET SALES % ADMIN | B7: 10437 | C7: 20 | I7: 15 | J7: 15 | K7: 10 | L7: 5 | M7: 5 | N7: 5 | O7: 5 | P7: 5 | Q7: 5 | R7: 5 | S7: 2.5 | T7: 2.5
A8: INSTALLMENTS (YRS) | I8: 8 | J8: 8 | K8: 8 | L8: 6 | M8: 6 | N8: 6 | O8: 4 | P8: 4 | Q8: 4 | R8: 3 | S8: 3 | T8: 2
A10: DOWN PAYMENT % | I10: 5 | J10: 5 | K10: 10 | L10: 10 | M10: 10 | N10: 10 | O10: 15 | P10: 15 | Q10: 15 | R10: 15 | S10: 20 | T10: 20
A11: 3 MONTHS % | I11: 5 | J11: 5 | K11: 10 | L11: 10 | M11: 10 | N11: 10 | O11: 15 | P11: 15 | Q11: 15 | R11: 15 | S11: 20 | T11: 20
A12: DELIVERY PAYMENT % | I12: 20 | J12: 20 | K12: 20 | L12: 20 | M12: 20 | N12: 20 | O12: 25 | P12: 25 | Q12: 25 | R12: 25 | S12: 25 | T12: 25
A14: YEAR 1 (4Q) % | I14: 10 | J14: 12 | K14: 12 | L14: 12 | M14: 15 | N14: 15 | O14: 15 | P14: 15 | Q14: 15 | R14: 15 | S14: 15 | T14: 15
A15: YEAR 2 (4Q) % | I15: 10 | J15: 12 | K15: 12 | L15: 12 | M15: 15 | N15: 15 | O15: 15 | P15: 15 | Q15: 15 | R15: 15 | S15: 10 | T15: 10
A16: YEAR 3 (4Q) % | I16: 10 | J16: 12 | K16: 12 | L16: 12 | M16: 15 | N16: 15 | O16: 7.5 | P16: 7.5 | Q16: 7.5 | R16: 7.5 | S16: 10 | T16: 10
A17: YEAR 4 (4Q) % | I17: 8 | J17: 10 | K17: 8 | L17: 8 | M17: 5 | N17: 5 | O17: 7.5 | P17: 7.5 | Q17: 7.5 | R17: 7.5 | S17: 0 | T17: 0
A18: YEAR 5 (4Q) % | I18: 8 | J18: 8 | K18: 8 | L18: 8 | M18: 5 | N18: 5 | O18: 0 | P18: 0 | Q18: 0 | R18: 0 | S18: 0 | T18: 0
A19: YEAR 6 (4Q) % | I19: 8 | J19: 8 | K19: 8 | L19: 8 | M19: 5 | N19: 5 | O19: 0 | P19: 0 | Q19: 0 | R19: 0 | S19: 0 | T19: 0
A20: YEAR 7 (4Q) % | I20: 8 | J20: 8 | K20: 0 | L20: 0 | M20: 0 | N20: 0 | O20: 0 | P20: 0 | Q20: 0 | R20: 0 | S20: 0 | T20: 0
A21: YEAR 8 (4Q) % | I21: 8 | J21: 0 | K21: 0 | L21: 0 | M21: 0 | N21: 0 | O21: 0 | P21: 0 | Q21: 0 | R21: 0 | S21: 0 | T21: 0
A24: Total Sales(COMMERCIAL) | D24: =SUM(E24:T24) -> 1076874.8 | E24: =E3*$B$6*(E6/100) -> 0 | F24: =F3*$B$6*(F6/100) -> 0 | G24: =G3*$B$6*(G6/100) -> 0 | H24: =H3*$B$6*(H6/100) -> 0 | I24: =I3*$B$6*(I6/100) -> 111825 | J24: =J3*$B$6*(J6/100) -> 111825 | K24: =K3*$B$6*(K6/100) -> 123007.5 | L24: =L3*$B$6*(L6/100) -> 86105.25 | ... T24: =T3*$B$6*(T6/100) -> 80514
A25: Total Sales (ADMIN) | D25: =SUM(E25:T25) -> 1596861 | E25: =E4*$B$7*(E7/100) -> 0 | F25: =F4*$B$7*(F7/100) -> 0 | G25: =G4*$B$7*(G7/100) -> 0 | H25: =H4*$B$7*(H7/100) -> 0 | I25: =I4*$B$7*(I7/100) -> 250488 | J25: =J4*$B$7*(J7/100) -> 250488 | K25: =K4*$B$7*(K7/100) -> 187866 | L25: =L4*$B$7*(L7/100) -> 93933 | ... T25: =T4*$B$7*(T7/100) -> 62622
A26: Total Sales | D26: =SUM(D24:D25) -> 2673735.8 | E26: =SUM(E24:E25) -> 0 | F26: =SUM(F24:F25) -> 0 | G26: =SUM(G24:G25) -> 0 | H26: =SUM(H24:H25) -> 0 | I26: =SUM(I24:I25) -> 362313 | J26: =SUM(J24:J25) -> 362313 | K26: =SUM(K24:K25) -> 310873.5 | ... T26: =SUM(T24:T25) -> 143136
E27: =E26 -> 0 | F27: =E27+F26 -> 0 | G27: =E27+G26 -> 0 | H27: =G27+H26 -> 0 | I27: =H27+I26 -> 362313 | J27: =I27+J26 -> 724626 | K27: =J27+K26 -> 1035499.5 | L27: =K27+L26 -> 1215537.8 | M27: =L27+M26 -> 1413840.8 | N27: =M27+N26 -> 1598724.8 | O27: =N27+O26 -> 1787336.2 | ... T27: =S27+T26 -> 2673735.8
G28: =G26*4% -> 0 | H28: =H26*4% -> 0 | I28: =I26*4% -> 14492.52 | J28: =J26*4% -> 14492.52 | K28: =K26*4% -> 12434.94 | L28: =L26*4% -> 7201.53 | M28: =M26*4% -> 7932.12 | N28: =N26*4% -> 7395.36 | ... T28: =T26*4% -> 5725.44
D29: Total | E29: M -9 | F29: M -6 | G29: M -3 | H29: M 0 | I29: M 3 | J29: M 6 | K29: M 9 | L29: M 12 | M29: M 15 | N29: M 18 | O29: M 21 | P29: M 24 | Q29: M 27 | R29: M 30 | S29: M 33 | T29: M 36 | U29: M 39 | V29: M 42 | W29: M 45 | X29: M 48 | Y29: M 51 | Z29: M 54 | AA29: M 57 | AB29: M 60 | AC29: M 63 | AD29: M 66 | AE29: M 69 | AF29: M 72 | AG29: M 75 | AH29: M 78 | AI29: M 81 | AJ29: M 84 | AK29: M 87 | AL29: M 90 | AM29: M 93 | AN29: M 96
A30: Bulk Payments
A31: DOWN PAYMENT (COMMERCIAL) | D31: =SUM(E31:AZ31) -> 128039.62 | E31: =E3*$B$6*(E6/100)*E10/100 -> 0 | F31: =F3*$B$6*(F6/100)*F10/100 -> 0 | G31: =G3*$B$6*(G6/100)*G10/100 -> 0 | H31: =H3*$B$6*(H6/100)*H10/100 -> 0 | I31: =I3*$B$6*(I6/100)*I10/100 -> 5591.25 | J31: =J3*$B$6*(J6/100)*J10/100 -> 5591.25 | K31: =K3*$B$6*(K6/100)*K10/100 -> 12300.75 | L31: =L3*$B$6*(L6/100)*L10/100 -> 8610.525 | ... V31: =V3*$B$6*(V6/100)*V10/100 -> 0
A32: DOWN PAYMENT (ADMIN) | D32: =SUM(E32:AZ32) -> 171166.8 | E32: =E4*$B$7*(E7/100)*E10/100 -> 0 | F32: =F4*$B$7*(F7/100)*F10/100 -> 0 | G32: =G4*$B$7*(G7/100)*G10/100 -> 0 | H32: =H4*$B$7*(H7/100)*H10/100 -> 0 | I32: =I4*$B$7*(I7/100)*I10/100 -> 12524.4 | J32: =J4*$B$7*(J7/100)*J10/100 -> 12524.4 | K32: =K4*$B$7*(K7/100)*K10/100 -> 18786.6 | L32: =L4*$B$7*(L7/100)*L10/100 -> 9393.3 | ... V32: =V4*$B$7*(V7/100)*V10/100 -> 0
A33: 3 MONTHS (COMMERCIAL) | D33: =SUM(E33:AZ33) -> 128039.62 | F33: =E31 -> 0 | G33: =F31 -> 0 | H33: =G31 -> 0 | I33: =H31 -> 0 | J33: =I31 -> 5591.25 | K33: =J31 -> 5591.25 | L33: =K31 -> 12300.75 | M33: =L31 -> 8610.525 | ... V33: =U31 -> 0
A34: 3 MONTHS (ADMIN) | D34: =SUM(E34:AZ34) -> 171166.8 | F34: =E32 -> 0 | G34: =F32 -> 0 | H34: =G32 -> 0 | I34: =H32 -> 0 | J34: =I32 -> 12524.4 | K34: =J32 -> 12524.4 | L34: =K32 -> 18786.6 | M34: =L32 -> 9393.3 | ... V34: =U32 -> 0
A35: DELIVERY PAYMENT (COMMERCIAL) | D35: =SUM(E35:AZ35) -> 238858.2 | S35: =SUM(E85:S85) -> 218729.7 | T35: =SUM(T85) -> 20128.5 | U35: =SUM(U85) -> 0 | V35: =SUM(V85) -> 0 | W35: =SUM(W85) -> 0
A36: DELIVERY PAYMENT (ADMIN) | D36: =SUM(E36:AZ36) -> 349639.5 | S36: =SUM(E86:S86) -> 333984 | T36: =SUM(T86) -> 15655.5 | U36: =SUM(U86) -> 0 | V36: =SUM(V86) -> 0 | W36: =SUM(W86) -> 0
A37: Instalments | D37: =SUM(E37:AZ37) -> 0
A38: MONTH -9 (COMMERCIAL) | D38: =SUM(E38:AZ38) -> 0 | G38: =$E$24*$E$14/100/4 -> 0 | H38: =$E$24*$E$14/100/4 -> 0 | I38: =$E$24*$E$14/100/4 -> 0 | J38: =$E$24*$E$14/100/4 -> 0 | K38: =$E$24*$E$15/100/4 -> 0 | L38: =$E$24*$E$15/100/4 -> 0 | M38: =$E$24*$E$15/100/4 -> 0 | N38: =$E$24*$E$15/100/4 -> 0 | O38: =$E$24*$E$16/100/4 -> 0 | P38: =$E$24*$E$16/100/4 -> 0 | Q38: =$E$24*$E$16/100/4 -> 0 | R38: =$E$24*$E$16/100/4 -> 0 | S38: =$E$24*$E$17/100/4 -> 0 | T38: =$E$24*$E$17/100/4 -> 0 | U38: =$E$24*$E$17/100/4 -> 0 | V38: =$E$24*$E$17/100/4 -> 0 | W38: =$E$24*$E$18/100/4 -> 0 | X38: =$E$24*$E$18/100/4 -> 0 | Y38: =$E$24*$E$18/100/4 -> 0 | Z38: =$E$24*$E$18/100/4 -> 0 | AA38: =$E$24*$E$19/100/4 -> 0 | AB38: =$E$24*$E$19/100/4 -> 0 | AC38: =$E$24*$E$19/100/4 -> 0 | AD38: =$E$24*$E$19/100/4 -> 0 | AE38: =$E$24*$E$20/100/4 -> 0 | AF38: =$E$24*$E$20/100/4 -> 0 | AG38: =$E$24*$E$20/100/4 -> 0 | AH38: =$E$24*$E$20/100/4 -> 0 | AI38: =$E$24*$E$21/100/4 -> 0 | AJ38: =$E$24*$E$21/100/4 -> 0 | AK38: =$E$24*$E$21/100/4 -> 0 | AL38: =$E$24*$E$21/100/4 -> 0
A39: MONTH -9 (ADMIN) | D39: =SUM(E39:AZ39) -> 0 | G39: =$E$25*$E$14/100/4 -> 0 | H39: =$E$25*$E$14/100/4 -> 0 | I39: =$E$25*$E$14/100/4 -> 0 | J39: =$E$25*$E$14/100/4 -> 0 | K39: =$E$25*$E$15/100/4 -> 0 | L39: =$E$25*$E$15/100/4 -> 0 | M39: =$E$25*$E$15/100/4 -> 0 | N39: =$E$25*$E$15/100/4 -> 0 | O39: =$E$25*$E$16/100/4 -> 0 | P39: =$E$25*$E$16/100/4 -> 0 | Q39: =$E$25*$E$16/100/4 -> 0 | R39: =$E$25*$E$16/100/4 -> 0 | S39: =$E$25*$E$17/100/4 -> 0 | T39: =$E$25*$E$17/100/4 -> 0 | U39: =$E$25*$E$17/100/4 -> 0 | V39: =$E$25*$E$17/100/4 -> 0 | W39: =$E$25*$E$18/100/4 -> 0 | X39: =$E$25*$E$18/100/4 -> 0 | Y39: =$E$25*$E$18/100/4 -> 0 | Z39: =$E$25*$E$18/100/4 -> 0 | AA39: =$E$25*$E$19/100/4 -> 0 | AB39: =$E$25*$E$19/100/4 -> 0 | AC39: =$E$25*$E$19/100/4 -> 0 | AD39: =$E$25*$E$19/100/4 -> 0 | AE39: =$E$25*$E$20/100/4 -> 0 | AF39: =$E$25*$E$20/100/4 -> 0 | AG39: =$E$25*$E$20/100/4 -> 0 | AH39: =$E$25*$E$20/100/4 -> 0 | AI39: =$E$25*$E$21/100/4 -> 0 | AJ39: =$E$25*$E$21/100/4 -> 0 | AK39: =$E$25*$E$21/100/4 -> 0 | AL39: =$E$25*$E$21/100/4 -> 0
A40: MONTH -6 (COMMERCIAL) | D40: =SUM(E40:AZ40) -> 0 | H40: =$F$24*$F$14/100/4 -> 0 | I40: =$F$24*$F$14/100/4 -> 0 | J40: =$F$24*$F$14/100/4 -> 0 | K40: =$F$24*$F$14/100/4 -> 0 | L40: =$F$24*$F$15/100/4 -> 0 | M40: =$F$24*$F$15/100/4 -> 0 | N40: =$F$24*$F$15/100/4 -> 0 | O40: =$F$24*$F$15/100/4 -> 0 | P40: =$F$24*$F$16/100/4 -> 0 | Q40: =$F$24*$F$16/100/4 -> 0 | R40: =$F$24*$F$16/100/4 -> 0 | S40: =$F$24*$F$16/100/4 -> 0 | T40: =$F$24*$F$17/100/4 -> 0 | U40: =$F$24*$F$17/100/4 -> 0 | V40: =$F$24*$F$17/100/4 -> 0 | W40: =$F$24*$F$17/100/4 -> 0 | X40: =$F$24*$F$18/100/4 -> 0 | Y40: =$F$24*$F$18/100/4 -> 0 | Z40: =$F$24*$F$18/100/4 -> 0 | AA40: =$F$24*$F$18/100/4 -> 0 | AB40: =$F$24*$F$19/100/4 -> 0 | AC40: =$F$24*$F$19/100/4 -> 0 | AD40: =$F$24*$F$19/100/4 -> 0 | AE40: =$F$24*$F$19/100/4 -> 0 | AF40: =$F$24*$F$20/100/4 -> 0 | AG40: =$F$24*$F$20/100/4 -> 0 | AH40: =$F$24*$F$20/100/4 -> 0 | AI40: =$F$24*$F$20/100/4 -> 0 | AJ40: =$F$24*$F$21/100/4 -> 0 | AK40: =$F$24*$F$21/100/4 -> 0 | AL40: =$F$24*$F$21/100/4 -> 0 | AM40: =$F$24*$F$21/100/4 -> 0
A41: MONTH -6 (ADMIN) | D41: =SUM(E41:AZ41) -> 0 | H41: =$F$25*$F$14/100/4 -> 0 | I41: =$F$25*$F$14/100/4 -> 0 | J41: =$F$25*$F$14/100/4 -> 0 | K41: =$F$25*$F$14/100/4 -> 0 | L41: =$F$25*$F$15/100/4 -> 0 | M41: =$F$25*$F$15/100/4 -> 0 | N41: =$F$25*$F$15/100/4 -> 0 | O41: =$F$25*$F$15/100/4 -> 0 | P41: =$F$25*$F$16/100/4 -> 0 | Q41: =$F$25*$F$16/100/4 -> 0 | R41: =$F$25*$F$16/100/4 -> 0 | S41: =$F$25*$F$16/100/4 -> 0 | T41: =$F$25*$F$17/100/4 -> 0 | U41: =$F$25*$F$17/100/4 -> 0 | V41: =$F$25*$F$17/100/4 -> 0 | W41: =$F$25*$F$17/100/4 -> 0 | X41: =$F$25*$F$18/100/4 -> 0 | Y41: =$F$25*$F$18/100/4 -> 0 | Z41: =$F$25*$F$18/100/4 -> 0 | AA41: =$F$25*$F$18/100/4 -> 0 | AB41: =$F$25*$F$19/100/4 -> 0 | AC41: =$F$25*$F$19/100/4 -> 0 | AD41: =$F$25*$F$19/100/4 -> 0 | AE41: =$F$25*$F$19/100/4 -> 0 | AF41: =$F$25*$F$20/100/4 -> 0 | AG41: =$F$25*$F$20/100/4 -> 0 | AH41: =$F$25*$F$20/100/4 -> 0 | AI41: =$F$25*$F$20/100/4 -> 0 | AJ41: =$F$25*$F$21/100/4 -> 0 | AK41: =$F$25*$F$21/100/4 -> 0 | AL41: =$F$25*$F$21/100/4 -> 0 | AM41: =$F$25*$F$21/100/4 -> 0
A42: MONTH -3 (COMMERCIAL) | D42: =SUM(E42:AZ42) -> 0 | I42: =$G$24*$G$14/100/4 -> 0 | J42: =$G$24*$G$14/100/4 -> 0 | K42: =$G$24*$G$14/100/4 -> 0 | L42: =$G$24*$G$14/100/4 -> 0 | M42: =$G$24*$G$15/100/4 -> 0 | N42: =$G$24*$G$15/100/4 -> 0 | O42: =$G$24*$G$15/100/4 -> 0 | P42: =$G$24*$G$15/100/4 -> 0 | Q42: =$G$24*$G$16/100/4 -> 0 | R42: =$G$24*$G$16/100/4 -> 0 | S42: =$G$24*$G$16/100/4 -> 0 | T42: =$G$24*$G$16/100/4 -> 0 | U42: =$G$24*$G$17/100/4 -> 0 | V42: =$G$24*$G$17/100/4 -> 0 | W42: =$G$24*$G$17/100/4 -> 0 | X42: =$G$24*$G$17/100/4 -> 0 | Y42: =$G$24*$G$18/100/4 -> 0 | Z42: =$G$24*$G$18/100/4 -> 0 | AA42: =$G$24*$G$18/100/4 -> 0 | AB42: =$G$24*$G$18/100/4 -> 0 | AC42: =$G$24*$G$19/100/4 -> 0 | AD42: =$G$24*$G$19/100/4 -> 0 | AE42: =$G$24*$G$19/100/4 -> 0 | AF42: =$G$24*$G$19/100/4 -> 0 | AG42: =$G$24*$G$20/100/4 -> 0 | AH42: =$G$24*$G$20/100/4 -> 0 | AI42: =$G$24*$G$20/100/4 -> 0 | AJ42: =$G$24*$G$20/100/4 -> 0 | AK42: =$G$24*$G$21/100/4 -> 0 | AL42: =$G$24*$G$21/100/4 -> 0 | AM42: =$G$24*$G$21/100/4 -> 0 | AN42: =$G$24*$G$21/100/4 -> 0
A43: MONTH -3 (ADMIN) | D43: =SUM(E43:AZ43) -> 0 | I43: =$G$25*$G$14/100/4 -> 0 | J43: =$G$25*$G$14/100/4 -> 0 | K43: =$G$25*$G$14/100/4 -> 0 | L43: =$G$25*$G$14/100/4 -> 0 | M43: =$G$25*$G$15/100/4 -> 0 | N43: =$G$25*$G$15/100/4 -> 0 | O43: =$G$25*$G$15/100/4 -> 0 | P43: =$G$25*$G$15/100/4 -> 0 | Q43: =$G$25*$G$16/100/4 -> 0 | R43: =$G$25*$G$16/100/4 -> 0 | S43: =$G$25*$G$16/100/4 -> 0 | T43: =$G$25*$G$16/100/4 -> 0 | U43: =$G$25*$G$17/100/4 -> 0 | V43: =$G$25*$G$17/100/4 -> 0 | W43: =$G$25*$G$17/100/4 -> 0 | X43: =$G$25*$G$17/100/4 -> 0 | Y43: =$G$25*$G$18/100/4 -> 0 | Z43: =$G$25*$G$18/100/4 -> 0 | AA43: =$G$25*$G$18/100/4 -> 0 | AB43: =$G$25*$G$18/100/4 -> 0 | AC43: =$G$25*$G$19/100/4 -> 0 | AD43: =$G$25*$G$19/100/4 -> 0 | AE43: =$G$25*$G$19/100/4 -> 0 | AF43: =$G$25*$G$19/100/4 -> 0 | AG43: =$G$25*$G$20/100/4 -> 0 | AH43: =$G$25*$G$20/100/4 -> 0 | AI43: =$G$25*$G$20/100/4 -> 0 | AJ43: =$G$25*$G$20/100/4 -> 0 | AK43: =$G$25*$G$21/100/4 -> 0 | AL43: =$G$25*$G$21/100/4 -> 0 | AM43: =$G$25*$G$21/100/4 -> 0 | AN43: =$G$25*$G$21/100/4 -> 0
A44: MONTH 0 (COMMERCIAL) | D44: =SUM(E44:AZ44) -> 0 | J44: =$H$24*$H$14/100/4 -> 0 | K44: =$H$24*$H$14/100/4 -> 0 | L44: =$H$24*$H$14/100/4 -> 0 | M44: =$H$24*$H$14/100/4 -> 0 | N44: =$H$24*$H$15/100/4 -> 0 | O44: =$H$24*$H$15/100/4 -> 0 | P44: =$H$24*$H$15/100/4 -> 0 | Q44: =$H$24*$H$15/100/4 -> 0 | R44: =$H$24*$H$16/100/4 -> 0 | S44: =$H$24*$H$16/100/4 -> 0 | T44: =$H$24*$H$16/100/4 -> 0 | U44: =$H$24*$H$16/100/4 -> 0 | V44: =$H$24*$H$17/100/4 -> 0 | W44: =$H$24*$H$17/100/4 -> 0 | X44: =$H$24*$H$17/100/4 -> 0 | Y44: =$H$24*$H$17/100/4 -> 0 | Z44: =$H$24*$H$18/100/4 -> 0 | AA44: =$H$24*$H$18/100/4 -> 0 | AB44: =$H$24*$H$18/100/4 -> 0 | AC44: =$H$24*$H$18/100/4 -> 0 | AD44: =$H$24*$H$19/100/4 -> 0 | AE44: =$H$24*$H$19/100/4 -> 0 | AF44: =$H$24*$H$19/100/4 -> 0 | AG44: =$H$24*$H$19/100/4 -> 0 | AH44: =$H$24*$H$20/100/4 -> 0 | AI44: =$H$24*$H$20/100/4 -> 0 | AJ44: =$H$24*$H$20/100/4 -> 0 | AK44: =$H$24*$H$20/100/4 -> 0 | AL44: =$H$24*$H$21/100/4 -> 0 | AM44: =$H$24*$H$21/100/4 -> 0 | AN44: =$H$24*$H$21/100/4 -> 0 | AO44: =$H$24*$H$21/100/4 -> 0
A45: MONTH 0 (ADMIN) | D45: =SUM(E45:AZ45) -> 0 | J45: =$H$25*$H$14/100/4 -> 0 | K45: =$H$25*$H$14/100/4 -> 0 | L45: =$H$25*$H$14/100/4 -> 0 | M45: =$H$25*$H$14/100/4 -> 0 | N45: =$H$25*$H$15/100/4 -> 0 | O45: =$H$25*$H$15/100/4 -> 0 | P45: =$H$25*$H$15/100/4 -> 0 | Q45: =$H$25*$H$15/100/4 -> 0 | R45: =$H$25*$H$16/100/4 -> 0 | S45: =$H$25*$H$16/100/4 -> 0 | T45: =$H$25*$H$16/100/4 -> 0 | U45: =$H$25*$H$16/100/4 -> 0 | V45: =$H$25*$H$17/100/4 -> 0 | W45: =$H$25*$H$17/100/4 -> 0 | X45: =$H$25*$H$17/100/4 -> 0 | Y45: =$H$25*$H$17/100/4 -> 0 | Z45: =$H$25*$H$18/100/4 -> 0 | AA45: =$H$25*$H$18/100/4 -> 0 | AB45: =$H$25*$H$18/100/4 -> 0 | AC45: =$H$25*$H$18/100/4 -> 0 | AD45: =$H$25*$H$19/100/4 -> 0 | AE45: =$H$25*$H$19/100/4 -> 0 | AF45: =$H$25*$H$19/100/4 -> 0 | AG45: =$H$25*$H$19/100/4 -> 0 | AH45: =$H$25*$H$20/100/4 -> 0 | AI45: =$H$25*$H$20/100/4 -> 0 | AJ45: =$H$25*$H$20/100/4 -> 0 | AK45: =$H$25*$H$20/100/4 -> 0 | AL45: =$H$25*$H$21/100/4 -> 0 | AM45: =$H$25*$H$21/100/4 -> 0 | AN45: =$H$25*$H$21/100/4 -> 0 | AO45: =$H$25*$H$21/100/4 -> 0
A46: MONTH 3 (COMMERCIAL) | D46: =SUM(E46:AZ46) -> 78277.5 | K46: =$I$24*$I$14/100/4 -> 2795.625 | L46: =$I$24*$I$14/100/4 -> 2795.625 | M46: =$I$24*$I$14/100/4 -> 2795.625 | N46: =$I$24*$I$14/100/4 -> 2795.625 | O46: =$I$24*$I$15/100/4 -> 2795.625 | P46: =$I$24*$I$15/100/4 -> 2795.625 | Q46: =$I$24*$I$15/100/4 -> 2795.625 | R46: =$I$24*$I$15/100/4 -> 2795.625 | S46: =$I$24*$I$16/100/4 -> 2795.625 | T46: =$I$24*$I$16/100/4 -> 2795.625 | U46: =$I$24*$I$16/100/4 -> 2795.625 | V46: =$I$24*$I$16/100/4 -> 2795.625 | W46: =$I$24*$I$17/100/4 -> 2236.5 | X46: =$I$24*$I$17/100/4 -> 2236.5 | Y46: =$I$24*$I$17/100/4 -> 2236.5 | Z46: =$I$24*$I$17/100/4 -> 2236.5 | AA46: =$I$24*$I$18/100/4 -> 2236.5 | AB46: =$I$24*$I$18/100/4 -> 2236.5 | AC46: =$I$24*$I$18/100/4 -> 2236.5 | AD46: =$I$24*$I$18/100/4 -> 2236.5 | AE46: =$I$24*$I$19/100/4 -> 2236.5 | AF46: =$I$24*$I$19/100/4 -> 2236.5 | AG46: =$I$24*$I$19/100/4 -> 2236.5 | AH46: =$I$24*$I$19/100/4 -> 2236.5 | AI46: =$I$24*$I$20/100/4 -> 2236.5 | AJ46: =$I$24*$I$20/100/4 -> 2236.5 | AK46: =$I$24*$I$20/100/4 -> 2236.5 | AL46: =$I$24*$I$20/100/4 -> 2236.5 | AM46: =$I$24*$I$21/100/4 -> 2236.5 | AN46: =$I$24*$I$21/100/4 -> 2236.5 | AO46: =$I$24*$I$21/100/4 -> 2236.5 | AP46: =$I$24*$I$21/100/4 -> 2236.5
A47: MONTH 3 (ADMIN) | D47: =SUM(E47:AZ47) -> 175341.6 | K47: =$I$25*$I$14/100/4 -> 6262.2 | L47: =$I$25*$I$14/100/4 -> 6262.2 | M47: =$I$25*$I$14/100/4 -> 6262.2 | N47: =$I$25*$I$14/100/4 -> 6262.2 | O47: =$I$25*$I$15/100/4 -> 6262.2 | P47: =$I$25*$I$15/100/4 -> 6262.2 | Q47: =$I$25*$I$15/100/4 -> 6262.2 | R47: =$I$25*$I$15/100/4 -> 6262.2 | S47: =$I$25*$I$16/100/4 -> 6262.2 | T47: =$I$25*$I$16/100/4 -> 6262.2 | U47: =$I$25*$I$16/100/4 -> 6262.2 | V47: =$I$25*$I$16/100/4 -> 6262.2 | W47: =$I$25*$I$17/100/4 -> 5009.76 | X47: =$I$25*$I$17/100/4 -> 5009.76 | Y47: =$I$25*$I$17/100/4 -> 5009.76 | Z47: =$I$25*$I$17/100/4 -> 5009.76 | AA47: =$I$25*$I$18/100/4 -> 5009.76 | AB47: =$I$25*$I$18/100/4 -> 5009.76 | AC47: =$I$25*$I$18/100/4 -> 5009.76 | AD47: =$I$25*$I$18/100/4 -> 5009.76 | AE47: =$I$25*$I$19/100/4 -> 5009.76 | AF47: =$I$25*$I$19/100/4 -> 5009.76 | AG47: =$I$25*$I$19/100/4 -> 5009.76 | AH47: =$I$25*$I$19/100/4 -> 5009.76 | AI47: =$I$25*$I$20/100/4 -> 5009.76 | AJ47: =$I$25*$I$20/100/4 -> 5009.76 | AK47: =$I$25*$I$20/100/4 -> 5009.76 | AL47: =$I$25*$I$20/100/4 -> 5009.76 | AM47: =$I$25*$I$21/100/4 -> 5009.76 | AN47: =$I$25*$I$21/100/4 -> 5009.76 | AO47: =$I$25*$I$21/100/4 -> 5009.76 | AP47: =$I$25*$I$21/100/4 -> 5009.76
A48: MONTH 6 (COMMERCIAL) | D48: =SUM(E48:AZ48) -> 78277.5 | L48: =$J$24*$J$14/100/4 -> 3354.75 | M48: =$J$24*$J$14/100/4 -> 3354.75 | N48: =$J$24*$J$14/100/4 -> 3354.75 | O48: =$J$24*$J$14/100/4 -> 3354.75 | P48: =$J$24*$J$15/100/4 -> 3354.75 | Q48: =$J$24*$J$15/100/4 -> 3354.75 | R48: =$J$24*$J$15/100/4 -> 3354.75 | S48: =$J$24*$J$15/100/4 -> 3354.75 | T48: =$J$24*$J$16/100/4 -> 3354.75 | U48: =$J$24*$J$16/100/4 -> 3354.75 | V48: =$J$24*$J$16/100/4 -> 3354.75 | W48: =$J$24*$J$16/100/4 -> 3354.75 | X48: =$J$24*$J$17/100/4 -> 2795.625 | Y48: =$J$24*$J$17/100/4 -> 2795.625 | Z48: =$J$24*$J$17/100/4 -> 2795.625 | AA48: =$J$24*$J$17/100/4 -> 2795.625 | AB48: =$J$24*$J$18/100/4 -> 2236.5 | AC48: =$J$24*$J$18/100/4 -> 2236.5 | AD48: =$J$24*$J$18/100/4 -> 2236.5 | AE48: =$J$24*$J$18/100/4 -> 2236.5 | AF48: =$J$24*$J$19/100/4 -> 2236.5 | AG48: =$J$24*$J$19/100/4 -> 2236.5 | AH48: =$J$24*$J$19/100/4 -> 2236.5 | AI48: =$J$24*$J$19/100/4 -> 2236.5 | AJ48: =$J$24*$J$20/100/4 -> 2236.5 | AK48: =$J$24*$J$20/100/4 -> 2236.5 | AL48: =$J$24*$J$20/100/4 -> 2236.5 | AM48: =$J$24*$J$20/100/4 -> 2236.5 | AN48: =$J$24*$J$21/100/4 -> 0 | AO48: =$J$24*$J$21/100/4 -> 0 | AP48: =$J$24*$J$21/100/4 -> 0 | AQ48: =$J$24*$J$21/100/4 -> 0
A49: MONTH 6 (ADMIN) | D49: =SUM(E49:AZ49) -> 175341.6 | L49: =$J$25*$J$14/100/4 -> 7514.64 | M49: =$J$25*$J$14/100/4 -> 7514.64 | N49: =$J$25*$J$14/100/4 -> 7514.64 | O49: =$J$25*$J$14/100/4 -> 7514.64 | P49: =$J$25*$J$15/100/4 -> 7514.64 | Q49: =$J$25*$J$15/100/4 -> 7514.64 | R49: =$J$25*$J$15/100/4 -> 7514.64 | S49: =$J$25*$J$15/100/4 -> 7514.64 | T49: =$J$25*$J$16/100/4 -> 7514.64 | U49: =$J$25*$J$16/100/4 -> 7514.64 | V49: =$J$25*$J$16/100/4 -> 7514.64 | W49: =$J$25*$J$16/100/4 -> 7514.64 | X49: =$J$25*$J$17/100/4 -> 6262.2 | Y49: =$J$25*$J$17/100/4 -> 6262.2 | Z49: =$J$25*$J$17/100/4 -> 6262.2 | AA49: =$J$25*$J$17/100/4 -> 6262.2 | AB49: =$J$25*$J$18/100/4 -> 5009.76 | AC49: =$J$25*$J$18/100/4 -> 5009.76 | AD49: =$J$25*$J$18/100/4 -> 5009.76 | AE49: =$J$25*$J$18/100/4 -> 5009.76 | AF49: =$J$25*$J$19/100/4 -> 5009.76 | AG49: =$J$25*$J$19/100/4 -> 5009.76 | AH49: =$J$25*$J$19/100/4 -> 5009.76 | AI49: =$J$25*$J$19/100/4 -> 5009.76 | AJ49: =$J$25*$J$20/100/4 -> 5009.76 | AK49: =$J$25*$J$20/100/4 -> 5009.76 | AL49: =$J$25*$J$20/100/4 -> 5009.76 | AM49: =$J$25*$J$20/100/4 -> 5009.76 | AN49: =$J$25*$J$21/100/4 -> 0 | AO49: =$J$25*$J$21/100/4 -> 0 | AP49: =$J$25*$J$21/100/4 -> 0 | AQ49: =$J$25*$J$21/100/4 -> 0 | AU49: =AS49 -> 0 | AV49: =AU49 -> 0
A50: MONTH 9 (COMMERCIAL) | D50: =SUM(E50:AZ50) -> 73804.5 | M50: =$K$24*$K$14/100/4 -> 3690.225 | N50: =$K$24*$K$14/100/4 -> 3690.225 | O50: =$K$24*$K$14/100/4 -> 3690.225 | P50: =$K$24*$K$14/100/4 -> 3690.225 | Q50: =$K$24*$K$15/100/4 -> 3690.225 | R50: =$K$24*$K$15/100/4 -> 3690.225 | S50: =$K$24*$K$15/100/4 -> 3690.225 | T50: =$K$24*$K$15/100/4 -> 3690.225 | U50: =$K$24*$K$16/100/4 -> 3690.225 | V50: =$K$24*$K$16/100/4 -> 3690.225 | W50: =$K$24*$K$16/100/4 -> 3690.225 | X50: =$K$24*$K$16/100/4 -> 3690.225 | Y50: =$K$24*$K$17/100/4 -> 2460.15 | Z50: =$K$24*$K$17/100/4 -> 2460.15 | AA50: =$K$24*$K$17/100/4 -> 2460.15 | AB50: =$K$24*$K$17/100/4 -> 2460.15 | AC50: =$K$24*$K$18/100/4 -> 2460.15 | AD50: =$K$24*$K$18/100/4 -> 2460.15 | AE50: =$K$24*$K$18/100/4 -> 2460.15 | AF50: =$K$24*$K$18/100/4 -> 2460.15 | AG50: =$K$24*$K$19/100/4 -> 2460.15 | AH50: =$K$24*$K$19/100/4 -> 2460.15 | AI50: =$K$24*$K$19/100/4 -> 2460.15 | AJ50: =$K$24*$K$19/100/4 -> 2460.15 | AK50: =$K$24*$K$20/100/4 -> 0 | AL50: =$K$24*$K$20/100/4 -> 0 | AM50: =$K$24*$K$20/100/4 -> 0 | AN50: =$K$24*$K$20/100/4 -> 0 | AO50: =$K$24*$K$21/100/4 -> 0 | AP50: =$K$24*$K$21/100/4 -> 0 | AQ50: =$K$24*$K$21/100/4 -> 0 | AR50: =$K$24*$K$21/100/4 -> 0
A51: MONTH 9 (ADMIN) | D51: =SUM(E51:AZ51) -> 112719.6 | M51: =$K$25*$K$14/100/4 -> 5635.98 | N51: =$K$25*$K$14/100/4 -> 5635.98 | O51: =$K$25*$K$14/100/4 -> 5635.98 | P51: =$K$25*$K$14/100/4 -> 5635.98 | Q51: =$K$25*$K$15/100/4 -> 5635.98 | R51: =$K$25*$K$15/100/4 -> 5635.98 | S51: =$K$25*$K$15/100/4 -> 5635.98 | T51: =$K$25*$K$15/100/4 -> 5635.98 | U51: =$K$25*$K$16/100/4 -> 5635.98 | V51: =$K$25*$K$16/100/4 -> 5635.98 | W51: =$K$25*$K$16/100/4 -> 5635.98 | X51: =$K$25*$K$16/100/4 -> 5635.98 | Y51: =$K$25*$K$17/100/4 -> 3757.32 | Z51: =$K$25*$K$17/100/4 -> 3757.32 | AA51: =$K$25*$K$17/100/4 -> 3757.32 | AB51: =$K$25*$K$17/100/4 -> 3757.32 | AC51: =$K$25*$K$18/100/4 -> 3757.32 | AD51: =$K$25*$K$18/100/4 -> 3757.32 | AE51: =$K$25*$K$18/100/4 -> 3757.32 | AF51: =$K$25*$K$18/100/4 -> 3757.32 | AG51: =$K$25*$K$19/100/4 -> 3757.32 | AH51: =$K$25*$K$19/100/4 -> 3757.32 | AI51: =$K$25*$K$19/100/4 -> 3757.32 | AJ51: =$K$25*$K$19/100/4 -> 3757.32 | AK51: =$K$25*$K$20/100/4 -> 0 | AL51: =$K$25*$K$20/100/4 -> 0 | AM51: =$K$25*$K$20/100/4 -> 0 | AN51: =$K$25*$K$20/100/4 -> 0 | AO51: =$K$25*$K$21/100/4 -> 0 | AP51: =$K$25*$K$21/100/4 -> 0 | AQ51: =$K$25*$K$21/100/4 -> 0 | AR51: =$K$25*$K$21/100/4 -> 0
A52: MONTH 12 (COMMERCIAL) | D52: =SUM(E52:AZ52) -> 51663.15 | N52: =$L$24*$L$14/100/4 -> 2583.1575 | O52: =$L$24*$L$14/100/4 -> 2583.1575 | P52: =$L$24*$L$14/100/4 -> 2583.1575 | Q52: =$L$24*$L$14/100/4 -> 2583.1575 | R52: =$L$24*$L$15/100/4 -> 2583.1575 | S52: =$L$24*$L$15/100/4 -> 2583.1575 | T52: =$L$24*$L$15/100/4 -> 2583.1575 | U52: =$L$24*$L$15/100/4 -> 2583.1575 | V52: =$L$24*$L$16/100/4 -> 2583.1575 | W52: =$L$24*$L$16/100/4 -> 2583.1575 | X52: =$L$24*$L$16/100/4 -> 2583.1575 | Y52: =$L$24*$L$16/100/4 -> 2583.1575 | Z52: =$L$24*$L$17/100/4 -> 1722.105 | AA52: =$L$24*$L$17/100/4 -> 1722.105 | AB52: =$L$24*$L$17/100/4 -> 1722.105 | AC52: =$L$24*$L$17/100/4 -> 1722.105 | AD52: =$L$24*$L$18/100/4 -> 1722.105 | AE52: =$L$24*$L$18/100/4 -> 1722.105 | AF52: =$L$24*$L$18/100/4 -> 1722.105 | AG52: =$L$24*$L$18/100/4 -> 1722.105 | AH52: =$L$24*$L$19/100/4 -> 1722.105 | AI52: =$L$24*$L$19/100/4 -> 1722.105 | AJ52: =$L$24*$L$19/100/4 -> 1722.105 | AK52: =$L$24*$L$19/100/4 -> 1722.105 | AL52: =$L$24*$L$20/100/4 -> 0 | AM52: =$L$24*$L$20/100/4 -> 0 | AN52: =$L$24*$L$20/100/4 -> 0 | AO52: =$L$24*$L$20/100/4 -> 0 | AP52: =$L$24*$L$21/100/4 -> 0 | AQ52: =$L$24*$L$21/100/4 -> 0 | AR52: =$L$24*$L$21/100/4 -> 0 | AS52: =$L$24*$L$21/100/4 -> 0 | AW52: =$L$24*$L$21/100/4 -> 0 | AX52: =AW52 -> 0 | AY52: =AX52 -> 0
A53: MONTH 12 (ADMIN) | D53: =SUM(E53:AZ53) -> 56359.8 | N53: =$L$25*$L$14/100/4 -> 2817.99 | O53: =$L$25*$L$14/100/4 -> 2817.99 | P53: =$L$25*$L$14/100/4 -> 2817.99 | Q53: =$L$25*$L$14/100/4 -> 2817.99 | R53: =$L$25*$L$15/100/4 -> 2817.99 | S53: =$L$25*$L$15/100/4 -> 2817.99 | T53: =$L$25*$L$15/100/4 -> 2817.99 | U53: =$L$25*$L$15/100/4 -> 2817.99 | V53: =$L$25*$L$16/100/4 -> 2817.99 | W53: =$L$25*$L$16/100/4 -> 2817.99 | X53: =$L$25*$L$16/100/4 -> 2817.99 | Y53: =$L$25*$L$16/100/4 -> 2817.99 | Z53: =$L$25*$L$17/100/4 -> 1878.66 | AA53: =$L$25*$L$17/100/4 -> 1878.66 | AB53: =$L$25*$L$17/100/4 -> 1878.66 | AC53: =$L$25*$L$17/100/4 -> 1878.66 | AD53: =$L$25*$L$18/100/4 -> 1878.66 | AE53: =$L$25*$L$18/100/4 -> 1878.66 | AF53: =$L$25*$L$18/100/4 -> 1878.66 | AG53: =$L$25*$L$18/100/4 -> 1878.66 | AH53: =$L$25*$L$19/100/4 -> 1878.66 | AI53: =$L$25*$L$19/100/4 -> 1878.66 | AJ53: =$L$25*$L$19/100/4 -> 1878.66 | AK53: =$L$25*$L$19/100/4 -> 1878.66 | AL53: =$L$25*$L$20/100/4 -> 0 | AM53: =$L$25*$L$20/100/4 -> 0 | AN53: =$L$25*$L$20/100/4 -> 0 | AO53: =$L$25*$L$20/100/4 -> 0 | AP53: =$L$25*$L$21/100/4 -> 0 | AQ53: =$L$25*$L$21/100/4 -> 0 | AR53: =$L$25*$L$21/100/4 -> 0 | AS53: =$L$25*$L$21/100/4 -> 0 | AW53: =$L$25*$L$21/100/4 -> 0 | AX53: =AW53 -> 0 | AY53: =AX53 -> 0
A54: MONTH 15 (COMMERCIAL) | D54: =SUM(E54:AZ54) -> 56359.8 | O54: =$M$24*$M$14/100/4 -> 3522.4875 | P54: =$M$24*$M$14/100/4 -> 3522.4875 | Q54: =$M$24*$M$14/100/4 -> 3522.4875 | R54: =$M$24*$M$14/100/4 -> 3522.4875 | S54: =$M$24*$M$15/100/4 -> 3522.4875 | T54: =$M$24*$M$15/100/4 -> 3522.4875 | U54: =$M$24*$M$15/100/4 -> 3522.4875 | V54: =$M$24*$M$15/100/4 -> 3522.4875 | W54: =$M$24*$M$16/100/4 -> 3522.4875 | X54: =$M$24*$M$16/100/4 -> 3522.4875 | Y54: =$M$24*$M$16/100/4 -> 3522.4875 | Z54: =$M$24*$M$16/100/4 -> 3522.4875 | AA54: =$M$24*$M$17/100/4 -> 1174.1625 | AB54: =$M$24*$M$17/100/4 -> 1174.1625 | AC54: =$M$24*$M$17/100/4 -> 1174.1625 | AD54: =$M$24*$M$17/100/4 -> 1174.1625 | AE54: =$M$24*$M$18/100/4 -> 1174.1625 | AF54: =$M$24*$M$18/100/4 -> 1174.1625 | AG54: =$M$24*$M$18/100/4 -> 1174.1625 | AH54: =$M$24*$M$18/100/4 -> 1174.1625 | AI54: =$M$24*$M$19/100/4 -> 1174.1625 | AJ54: =$M$24*$M$19/100/4 -> 1174.1625 | AK54: =$M$24*$M$19/100/4 -> 1174.1625 | AL54: =$M$24*$M$19/100/4 -> 1174.1625 | AM54: =$M$24*$M$20/100/4 -> 0 | AN54: =$M$24*$M$20/100/4 -> 0 | AO54: =$M$24*$M$20/100/4 -> 0 | AP54: =$M$24*$M$20/100/4 -> 0 | AQ54: =$M$24*$M$21/100/4 -> 0 | AR54: =$M$24*$M$21/100/4 -> 0 | AS54: =$M$24*$M$21/100/4 -> 0 | AT54: =$M$24*$M$21/100/4 -> 0
A55: MONTH 15 (ADMIN) | D55: =SUM(E55:AZ55) -> 62622 | O55: =$M$25*$M$14/100/4 -> 3913.875 | P55: =$M$25*$M$14/100/4 -> 3913.875 | Q55: =$M$25*$M$14/100/4 -> 3913.875 | R55: =$M$25*$M$14/100/4 -> 3913.875 | S55: =$M$25*$M$15/100/4 -> 3913.875 | T55: =$M$25*$M$15/100/4 -> 3913.875 | U55: =$M$25*$M$15/100/4 -> 3913.875 | V55: =$M$25*$M$15/100/4 -> 3913.875 | W55: =$M$25*$M$16/100/4 -> 3913.875 | X55: =$M$25*$M$16/100/4 -> 3913.875 | Y55: =$M$25*$M$16/100/4 -> 3913.875 | Z55: =$M$25*$M$16/100/4 -> 3913.875 | AA55: =$M$25*$M$17/100/4 -> 1304.625 | AB55: =$M$25*$M$17/100/4 -> 1304.625 | AC55: =$M$25*$M$17/100/4 -> 1304.625 | AD55: =$M$25*$M$17/100/4 -> 1304.625 | AE55: =$M$25*$M$18/100/4 -> 1304.625 | AF55: =$M$25*$M$18/100/4 -> 1304.625 | AG55: =$M$25*$M$18/100/4 -> 1304.625 | AH55: =$M$25*$M$18/100/4 -> 1304.625 | AI55: =$M$25*$M$19/100/4 -> 1304.625 | AJ55: =$M$25*$M$19/100/4 -> 1304.625 | AK55: =$M$25*$M$19/100/4 -> 1304.625 | AL55: =$M$25*$M$19/100/4 -> 1304.625 | AM55: =$M$25*$M$20/100/4 -> 0 | AN55: =$M$25*$M$20/100/4 -> 0 | AO55: =$M$25*$M$20/100/4 -> 0 | AP55: =$M$25*$M$20/100/4 -> 0 | AQ55: =$M$25*$M$21/100/4 -> 0 | AR55: =$M$25*$M$21/100/4 -> 0 | AS55: =$M$25*$M$21/100/4 -> 0 | AT55: =$M$25*$M$21/100/4 -> 0
A56: MONTH 18 (COMMERCIAL) | D56: =SUM(E56:AZ56) -> 48308.4 | P56: =$N$24*$N$14/100/4 -> 3019.275 | Q56: =$N$24*$N$14/100/4 -> 3019.275 | R56: =$N$24*$N$14/100/4 -> 3019.275 | S56: =$N$24*$N$14/100/4 -> 3019.275 | T56: =$N$24*$N$15/100/4 -> 3019.275 | U56: =$N$24*$N$15/100/4 -> 3019.275 | V56: =$N$24*$N$15/100/4 -> 3019.275 | W56: =$N$24*$N$15/100/4 -> 3019.275 | X56: =$N$24*$N$16/100/4 -> 3019.275 | Y56: =$N$24*$N$16/100/4 -> 3019.275 | Z56: =$N$24*$N$16/100/4 -> 3019.275 | AA56: =$N$24*$N$16/100/4 -> 3019.275 | AB56: =$N$24*$N$17/100/4 -> 1006.425 | AC56: =$N$24*$N$17/100/4 -> 1006.425 | AD56: =$N$24*$N$17/100/4 -> 1006.425 | AE56: =$N$24*$N$17/100/4 -> 1006.425 | AF56: =$N$24*$N$18/100/4 -> 1006.425 | AG56: =$N$24*$N$18/100/4 -> 1006.425 | AH56: =$N$24*$N$18/100/4 -> 1006.425 | AI56: =$N$24*$N$18/100/4 -> 1006.425 | AJ56: =$N$24*$N$19/100/4 -> 1006.425 | AK56: =$N$24*$N$19/100/4 -> 1006.425 | AL56: =$N$24*$N$19/100/4 -> 1006.425 | AM56: =$N$24*$N$19/100/4 -> 1006.425 | AN56: =$N$24*$N$20/100/4 -> 0 | AO56: =$N$24*$N$20/100/4 -> 0 | AP56: =$N$24*$N$20/100/4 -> 0 | AQ56: =$N$24*$N$20/100/4 -> 0 | AR56: =$N$24*$N$21/100/4 -> 0 | AS56: =$N$24*$N$21/100/4 -> 0 | AT56: =$N$24*$N$21/100/4 -> 0 | AU56: =$N$24*$N$21/100/4 -> 0 | AY56: =AW56 -> 0 | AZ56: =$N$24*$N$21/100/4 -> 0 | BA56: =AZ56 -> 0 | BB56: =BA56 -> 0
A57: MONTH 18 (ADMIN) | D57: =SUM(E57:AZ57) -> 62622 | P57: =$N$25*$N$14/100/4 -> 3913.875 | Q57: =$N$25*$N$14/100/4 -> 3913.875 | R57: =$N$25*$N$14/100/4 -> 3913.875 | S57: =$N$25*$N$14/100/4 -> 3913.875 | T57: =$N$25*$N$15/100/4 -> 3913.875 | U57: =$N$25*$N$15/100/4 -> 3913.875 | V57: =$N$25*$N$15/100/4 -> 3913.875 | W57: =$N$25*$N$15/100/4 -> 3913.875 | X57: =$N$25*$N$16/100/4 -> 3913.875 | Y57: =$N$25*$N$16/100/4 -> 3913.875 | Z57: =$N$25*$N$16/100/4 -> 3913.875 | AA57: =$N$25*$N$16/100/4 -> 3913.875 | AB57: =$N$25*$N$17/100/4 -> 1304.625 | AC57: =$N$25*$N$17/100/4 -> 1304.625 | AD57: =$N$25*$N$17/100/4 -> 1304.625 | AE57: =$N$25*$N$17/100/4 -> 1304.625 | AF57: =$N$25*$N$18/100/4 -> 1304.625 | AG57: =$N$25*$N$18/100/4 -> 1304.625 | AH57: =$N$25*$N$18/100/4 -> 1304.625 | AI57: =$N$25*$N$18/100/4 -> 1304.625 | AJ57: =$N$25*$N$19/100/4 -> 1304.625 | AK57: =$N$25*$N$19/100/4 -> 1304.625 | AL57: =$N$25*$N$19/100/4 -> 1304.625 | AM57: =$N$25*$N$19/100/4 -> 1304.625 | AN57: =$N$25*$N$20/100/4 -> 0 | AO57: =$N$25*$N$20/100/4 -> 0 | AP57: =$N$25*$N$20/100/4 -> 0 | AQ57: =$N$25*$N$20/100/4 -> 0 | AR57: =$N$25*$N$21/100/4 -> 0 | AS57: =$N$25*$N$21/100/4 -> 0 | AT57: =$N$25*$N$21/100/4 -> 0 | AU57: =$N$25*$N$21/100/4 -> 0 | AY57: =AW57 -> 0 | AZ57: =$N$25*$N$21/100/4 -> 0 | BA57: =AZ57 -> 0 | BB57: =BA57 -> 0
A58: MONTH 21 (COMMERCIAL) | D58: =SUM(E58:AZ58) -> 33212.025 | Q58: =$O$24*$O$14/100/4 -> 2767.6687 | R58: =$O$24*$O$14/100/4 -> 2767.6687 | S58: =$O$24*$O$14/100/4 -> 2767.6687 | T58: =$O$24*$O$14/100/4 -> 2767.6687 | U58: =$O$24*$O$15/100/4 -> 2767.6687 | V58: =$O$24*$O$15/100/4 -> 2767.6687 | W58: =$O$24*$O$15/100/4 -> 2767.6687 | X58: =$O$24*$O$15/100/4 -> 2767.6687 | Y58: =$O$24*$O$16/100/4 -> 1383.8344 | Z58: =$O$24*$O$16/100/4 -> 1383.8344 | AA58: =$O$24*$O$16/100/4 -> 1383.8344 | AB58: =$O$24*$O$16/100/4 -> 1383.8344 | AC58: =$O$24*$O$17/100/4 -> 1383.8344 | AD58: =$O$24*$O$17/100/4 -> 1383.8344 | AE58: =$O$24*$O$17/100/4 -> 1383.8344 | AF58: =$O$24*$O$17/100/4 -> 1383.8344 | AG58: =$O$24*$O$18/100/4 -> 0 | AH58: =$O$24*$O$18/100/4 -> 0 | AI58: =$O$24*$O$18/100/4 -> 0 | AJ58: =$O$24*$O$18/100/4 -> 0 | AK58: =$O$24*$O$19/100/4 -> 0 | AL58: =$O$24*$O$19/100/4 -> 0 | AM58: =$O$24*$O$19/100/4 -> 0 | AN58: =$O$24*$O$19/100/4 -> 0 | AO58: =$O$24*$O$20/100/4 -> 0 | AP58: =$O$24*$O$20/100/4 -> 0 | AQ58: =$O$24*$O$20/100/4 -> 0 | AR58: =$O$24*$O$20/100/4 -> 0 | AS58: =$O$24*$O$21/100/4 -> 0 | AT58: =$O$24*$O$21/100/4 -> 0 | AU58: =$O$24*$O$21/100/4 -> 0 | AV58: =$O$24*$O$21/100/4 -> 0
A59: MONTH 21 (ADMIN) | D59: =SUM(E59:AZ59) -> 51663.15 | Q59: =$O$25*$O$14/100/4 -> 4305.2625 | R59: =$O$25*$O$14/100/4 -> 4305.2625 | S59: =$O$25*$O$14/100/4 -> 4305.2625 | T59: =$O$25*$O$14/100/4 -> 4305.2625 | U59: =$O$25*$O$15/100/4 -> 4305.2625 | V59: =$O$25*$O$15/100/4 -> 4305.2625 | W59: =$O$25*$O$15/100/4 -> 4305.2625 | X59: =$O$25*$O$15/100/4 -> 4305.2625 | Y59: =$O$25*$O$16/100/4 -> 2152.6312 | Z59: =$O$25*$O$16/100/4 -> 2152.6312 | AA59: =$O$25*$O$16/100/4 -> 2152.6312 | AB59: =$O$25*$O$16/100/4 -> 2152.6312 | AC59: =$O$25*$O$17/100/4 -> 2152.6312 | AD59: =$O$25*$O$17/100/4 -> 2152.6312 | AE59: =$O$25*$O$17/100/4 -> 2152.6312 | AF59: =$O$25*$O$17/100/4 -> 2152.6312 | AG59: =$O$25*$O$18/100/4 -> 0 | AH59: =$O$25*$O$18/100/4 -> 0 | AI59: =$O$25*$O$18/100/4 -> 0 | AJ59: =$O$25*$O$18/100/4 -> 0 | AK59: =$O$25*$O$19/100/4 -> 0 | AL59: =$O$25*$O$19/100/4 -> 0 | AM59: =$O$25*$O$19/100/4 -> 0 | AN59: =$O$25*$O$19/100/4 -> 0 | AO59: =$O$25*$O$20/100/4 -> 0 | AP59: =$O$25*$O$20/100/4 -> 0 | AQ59: =$O$25*$O$20/100/4 -> 0 | AR59: =$O$25*$O$20/100/4 -> 0 | AS59: =$O$25*$O$21/100/4 -> 0 | AT59: =$O$25*$O$21/100/4 -> 0 | AU59: =$O$25*$O$21/100/4 -> 0 | AV59: =$O$25*$O$21/100/4 -> 0
A60: MONTH 24 (COMMERCIAL) | D60: =SUM(E60:AZ60) -> 33212.025 | R60: =$P$24*$P$14/100/4 -> 2767.6687 | S60: =$P$24*$P$14/100/4 -> 2767.6687 | T60: =$P$24*$P$14/100/4 -> 2767.6687 | U60: =$P$24*$P$14/100/4 -> 2767.6687 | V60: =$P$24*$P$15/100/4 -> 2767.6687 | W60: =$P$24*$P$15/100/4 -> 2767.6687 | X60: =$P$24*$P$15/100/4 -> 2767.6687 | Y60: =$P$24*$P$15/100/4 -> 2767.6687 | Z60: =$P$24*$P$16/100/4 -> 1383.8344 | AA60: =$P$24*$P$16/100/4 -> 1383.8344 | AB60: =$P$24*$P$16/100/4 -> 1383.8344 | AC60: =$P$24*$P$16/100/4 -> 1383.8344 | AD60: =$P$24*$P$17/100/4 -> 1383.8344 | AE60: =$P$24*$P$17/100/4 -> 1383.8344 | AF60: =$P$24*$P$17/100/4 -> 1383.8344 | AG60: =$P$24*$P$17/100/4 -> 1383.8344 | AH60: =$P$24*$P$18/100/4 -> 0 | AI60: =$P$24*$P$18/100/4 -> 0 | AJ60: =$P$24*$P$18/100/4 -> 0 | AK60: =$P$24*$P$18/100/4 -> 0 | AL60: =$P$24*$P$19/100/4 -> 0 | AM60: =$P$24*$P$19/100/4 -> 0 | AN60: =$P$24*$P$19/100/4 -> 0 | AO60: =$P$24*$P$19/100/4 -> 0 | AP60: =$P$24*$P$20/100/4 -> 0 | AQ60: =$P$24*$P$20/100/4 -> 0 | AR60: =$P$24*$P$20/100/4 -> 0 | AS60: =$P$24*$P$20/100/4 -> 0 | AT60: =$P$24*$P$21/100/4 -> 0 | AU60: =$P$24*$P$21/100/4 -> 0 | AV60: =$P$24*$P$21/100/4 -> 0 | AW60: =$P$24*$P$21/100/4 -> 0 | BA60: =$P$24*$P$20/100/4 -> 0 | BB60: =BA60 -> 0 | BC60: =$P$24*$P$21/100/4 -> 0 | BD60: =BC60 -> 0 | BE60: =BD60 -> 0
A61: MONTH 24 (ADMIN) | D61: =SUM(E61:AZ61) -> 51663.15 | R61: =$P$25*$P$14/100/4 -> 4305.2625 | S61: =$P$25*$P$14/100/4 -> 4305.2625 | T61: =$P$25*$P$14/100/4 -> 4305.2625 | U61: =$P$25*$P$14/100/4 -> 4305.2625 | V61: =$P$25*$P$15/100/4 -> 4305.2625 | W61: =$P$25*$P$15/100/4 -> 4305.2625 | X61: =$P$25*$P$15/100/4 -> 4305.2625 | Y61: =$P$25*$P$15/100/4 -> 4305.2625 | Z61: =$P$25*$P$16/100/4 -> 2152.6312 | AA61: =$P$25*$P$16/100/4 -> 2152.6312 | AB61: =$P$25*$P$16/100/4 -> 2152.6312 | AC61: =$P$25*$P$16/100/4 -> 2152.6312 | AD61: =$P$25*$P$17/100/4 -> 2152.6312 | AE61: =$P$25*$P$17/100/4 -> 2152.6312 | AF61: =$P$25*$P$17/100/4 -> 2152.6312 | AG61: =$P$25*$P$17/100/4 -> 2152.6312 | AH61: =$P$25*$P$18/100/4 -> 0 | AI61: =$P$25*$P$18/100/4 -> 0 | AJ61: =$P$25*$P$18/100/4 -> 0 | AK61: =$P$25*$P$18/100/4 -> 0 | AL61: =$P$25*$P$19/100/4 -> 0 | AM61: =$P$25*$P$19/100/4 -> 0 | AN61: =$P$25*$P$19/100/4 -> 0 | AO61: =$P$25*$P$19/100/4 -> 0 | AP61: =$P$25*$P$20/100/4 -> 0 | AQ61: =$P$25*$P$20/100/4 -> 0 | AR61: =$P$25*$P$20/100/4 -> 0 | AS61: =$P$25*$P$20/100/4 -> 0 | AT61: =$P$25*$P$21/100/4 -> 0 | AU61: =$P$25*$P$21/100/4 -> 0 | AV61: =$P$25*$P$21/100/4 -> 0 | AW61: =$P$25*$P$21/100/4 -> 0 | BA61: =$P$25*$P$20/100/4 -> 0 | BB61: =BA61 -> 0 | BC61: =$P$25*$P$21/100/4 -> 0 | BD61: =BC61 -> 0 | BE61: =BD61 -> 0
A62: MONTH 27 (COMMERCIAL) | D62: =SUM(E62:AZ62) -> 36231.3 | S62: =$Q$24*$Q$14/100/4 -> 3019.275 | T62: =$Q$24*$Q$14/100/4 -> 3019.275 | U62: =$Q$24*$Q$14/100/4 -> 3019.275 | V62: =$Q$24*$Q$14/100/4 -> 3019.275 | W62: =$Q$24*$Q$15/100/4 -> 3019.275 | X62: =$Q$24*$Q$15/100/4 -> 3019.275 | Y62: =$Q$24*$Q$15/100/4 -> 3019.275 | Z62: =$Q$24*$Q$15/100/4 -> 3019.275 | AA62: =$Q$24*$Q$16/100/4 -> 1509.6375 | AB62: =$Q$24*$Q$16/100/4 -> 1509.6375 | AC62: =$Q$24*$Q$16/100/4 -> 1509.6375 | AD62: =$Q$24*$Q$16/100/4 -> 1509.6375 | AE62: =$Q$24*$Q$17/100/4 -> 1509.6375 | AF62: =$Q$24*$Q$17/100/4 -> 1509.6375 | AG62: =$Q$24*$Q$17/100/4 -> 1509.6375 | AH62: =$Q$24*$Q$17/100/4 -> 1509.6375 | AI62: =$Q$24*$Q$18/100/4 -> 0 | AJ62: =$Q$24*$Q$18/100/4 -> 0 | AK62: =$Q$24*$Q$18/100/4 -> 0 | AL62: =$Q$24*$Q$18/100/4 -> 0 | AM62: =$Q$24*$Q$19/100/4 -> 0 | AN62: =$Q$24*$Q$19/100/4 -> 0 | AO62: =$Q$24*$Q$19/100/4 -> 0 | AP62: =$Q$24*$Q$19/100/4 -> 0 | AQ62: =$Q$24*$Q$20/100/4 -> 0 | AR62: =$Q$24*$Q$20/100/4 -> 0 | AS62: =$Q$24*$Q$20/100/4 -> 0 | AT62: =$Q$24*$Q$20/100/4 -> 0 | AU62: =$Q$24*$Q$21/100/4 -> 0 | AV62: =$Q$24*$Q$21/100/4 -> 0 | AW62: =$Q$24*$Q$21/100/4 -> 0 | AX62: =$Q$24*$Q$21/100/4 -> 0
A63: MONTH 27 (ADMIN) | D63: =SUM(E63:AZ63) -> 56359.8 | S63: =$Q$25*$Q$14/100/4 -> 4696.65 | T63: =$Q$25*$Q$14/100/4 -> 4696.65 | U63: =$Q$25*$Q$14/100/4 -> 4696.65 | V63: =$Q$25*$Q$14/100/4 -> 4696.65 | W63: =$Q$25*$Q$15/100/4 -> 4696.65 | X63: =$Q$25*$Q$15/100/4 -> 4696.65 | Y63: =$Q$25*$Q$15/100/4 -> 4696.65 | Z63: =$Q$25*$Q$15/100/4 -> 4696.65 | AA63: =$Q$25*$Q$16/100/4 -> 2348.325 | AB63: =$Q$25*$Q$16/100/4 -> 2348.325 | AC63: =$Q$25*$Q$16/100/4 -> 2348.325 | AD63: =$Q$25*$Q$16/100/4 -> 2348.325 | AE63: =$Q$25*$Q$17/100/4 -> 2348.325 | AF63: =$Q$25*$Q$17/100/4 -> 2348.325 | AG63: =$Q$25*$Q$17/100/4 -> 2348.325 | AH63: =$Q$25*$Q$17/100/4 -> 2348.325 | AI63: =$Q$25*$Q$18/100/4 -> 0 | AJ63: =$Q$25*$Q$18/100/4 -> 0 | AK63: =$Q$25*$Q$18/100/4 -> 0 | AL63: =$Q$25*$Q$18/100/4 -> 0 | AM63: =$Q$25*$Q$19/100/4 -> 0 | AN63: =$Q$25*$Q$19/100/4 -> 0 | AO63: =$Q$25*$Q$19/100/4 -> 0 | AP63: =$Q$25*$Q$19/100/4 -> 0 | AQ63: =$Q$25*$Q$20/100/4 -> 0 | AR63: =$Q$25*$Q$20/100/4 -> 0 | AS63: =$Q$25*$Q$20/100/4 -> 0 | AT63: =$Q$25*$Q$20/100/4 -> 0 | AU63: =$Q$25*$Q$21/100/4 -> 0 | AV63: =$Q$25*$Q$21/100/4 -> 0 | AW63: =$Q$25*$Q$21/100/4 -> 0 | AX63: =$Q$25*$Q$21/100/4 -> 0
A64: MONTH 30 (COMMERCIAL) | D64: =SUM(E64:AZ64) -> 36231.3 | T64: =$R$24*$R$14/100/4 -> 3019.275 | U64: =$R$24*$R$14/100/4 -> 3019.275 | V64: =$R$24*$R$14/100/4 -> 3019.275 | W64: =$R$24*$R$14/100/4 -> 3019.275 | X64: =$R$24*$R$15/100/4 -> 3019.275 | Y64: =$R$24*$R$15/100/4 -> 3019.275 | Z64: =$R$24*$R$15/100/4 -> 3019.275 | AA64: =$R$24*$R$15/100/4 -> 3019.275 | AB64: =$R$24*$R$16/100/4 -> 1509.6375 | AC64: =$R$24*$R$16/100/4 -> 1509.6375 | AD64: =$R$24*$R$16/100/4 -> 1509.6375 | AE64: =$R$24*$R$16/100/4 -> 1509.6375 | AF64: =$R$24*$R$17/100/4 -> 1509.6375 | AG64: =$R$24*$R$17/100/4 -> 1509.6375 | AH64: =$R$24*$R$17/100/4 -> 1509.6375 | AI64: =$R$24*$R$17/100/4 -> 1509.6375 | AJ64: =$R$24*$R$18/100/4 -> 0 | AK64: =$R$24*$R$18/100/4 -> 0 | AL64: =$R$24*$R$18/100/4 -> 0 | AM64: =$R$24*$R$18/100/4 -> 0 | AN64: =$R$24*$R$19/100/4 -> 0 | AO64: =$R$24*$R$19/100/4 -> 0 | AP64: =$R$24*$R$19/100/4 -> 0 | AQ64: =$R$24*$R$19/100/4 -> 0 | AR64: =$R$24*$R$20/100/4 -> 0 | AS64: =$R$24*$R$20/100/4 -> 0 | AT64: =$R$24*$R$20/100/4 -> 0 | AU64: =$R$24*$R$20/100/4 -> 0 | AV64: =$R$24*$R$21/100/4 -> 0 | AW64: =$R$24*$R$21/100/4 -> 0 | AX64: =$R$24*$R$21/100/4 -> 0 | AY64: =$R$24*$R$21/100/4 -> 0 | BC64: =BA64 -> 0 | BD64: =$R$24*$R$20/100/4 -> 0 | BE64: =BD64 -> 0 | BF64: =$R$24*$R$21/100/4 -> 0 | BG64: =BF64 -> 0 | BH64: =BG64 -> 0
A65: MONTH 30 (ADMIN) | D65: =SUM(E65:AZ65) -> 56359.8 | T65: =$R$25*$R$14/100/4 -> 4696.65 | U65: =$R$25*$R$14/100/4 -> 4696.65 | V65: =$R$25*$R$14/100/4 -> 4696.65 | W65: =$R$25*$R$14/100/4 -> 4696.65 | X65: =$R$25*$R$15/100/4 -> 4696.65 | Y65: =$R$25*$R$15/100/4 -> 4696.65 | Z65: =$R$25*$R$15/100/4 -> 4696.65 | AA65: =$R$25*$R$15/100/4 -> 4696.65 | AB65: =$R$25*$R$16/100/4 -> 2348.325 | AC65: =$R$25*$R$16/100/4 -> 2348.325 | AD65: =$R$25*$R$16/100/4 -> 2348.325 | AE65: =$R$25*$R$16/100/4 -> 2348.325 | AF65: =$R$25*$R$17/100/4 -> 2348.325 | AG65: =$R$25*$R$17/100/4 -> 2348.325 | AH65: =$R$25*$R$17/100/4 -> 2348.325 | AI65: =$R$25*$R$17/100/4 -> 2348.325 | AJ65: =$R$25*$R$18/100/4 -> 0 | AK65: =$R$25*$R$18/100/4 -> 0 | AL65: =$R$25*$R$18/100/4 -> 0 | AM65: =$R$25*$R$18/100/4 -> 0 | AN65: =$R$25*$R$19/100/4 -> 0 | AO65: =$R$25*$R$19/100/4 -> 0 | AP65: =$R$25*$R$19/100/4 -> 0 | AQ65: =$R$25*$R$19/100/4 -> 0 | AR65: =$R$25*$R$20/100/4 -> 0 | AS65: =$R$25*$R$20/100/4 -> 0 | AT65: =$R$25*$R$20/100/4 -> 0 | AU65: =$R$25*$R$20/100/4 -> 0 | AV65: =$R$25*$R$21/100/4 -> 0 | AW65: =$R$25*$R$21/100/4 -> 0 | AX65: =$R$25*$R$21/100/4 -> 0 | AY65: =$R$25*$R$21/100/4 -> 0 | BC65: =BA65 -> 0 | BD65: =$R$25*$R$20/100/4 -> 0 | BE65: =BD65 -> 0 | BF65: =$R$25*$R$21/100/4 -> 0 | BG65: =BF65 -> 0 | BH65: =BG65 -> 0
A66: MONTH 33 (COMMERCIAL) | D66: =SUM(E66:AZ66) -> 28179.9 | U66: =$S$24*$S$14/100/4 -> 3019.275 | V66: =$S$24*$S$14/100/4 -> 3019.275 | W66: =$S$24*$S$14/100/4 -> 3019.275 | X66: =$S$24*$S$14/100/4 -> 3019.275 | Y66: =$S$24*$S$15/100/4 -> 2012.85 | Z66: =$S$24*$S$15/100/4 -> 2012.85 | AA66: =$S$24*$S$15/100/4 -> 2012.85 | AB66: =$S$24*$S$15/100/4 -> 2012.85 | AC66: =$S$24*$S$16/100/4 -> 2012.85 | AD66: =$S$24*$S$16/100/4 -> 2012.85 | AE66: =$S$24*$S$16/100/4 -> 2012.85 | AF66: =$S$24*$S$16/100/4 -> 2012.85 | AG66: =$S$24*$S$17/100/4 -> 0 | AH66: =$S$24*$S$17/100/4 -> 0 | AI66: =$S$24*$S$17/100/4 -> 0 | AJ66: =$S$24*$S$17/100/4 -> 0 | AK66: =$S$24*$S$18/100/4 -> 0 | AL66: =$S$24*$S$18/100/4 -> 0 | AM66: =$S$24*$S$18/100/4 -> 0 | AN66: =$S$24*$S$18/100/4 -> 0 | AO66: =$S$24*$S$19/100/4 -> 0 | AP66: =$S$24*$S$19/100/4 -> 0 | AQ66: =$S$24*$S$19/100/4 -> 0 | AR66: =$S$24*$S$19/100/4 -> 0 | AS66: =$S$24*$S$20/100/4 -> 0 | AT66: =$S$24*$S$20/100/4 -> 0 | AU66: =$S$24*$S$20/100/4 -> 0 | AV66: =$S$24*$S$20/100/4 -> 0 | AW66: =$S$24*$S$21/100/4 -> 0 | AX66: =$S$24*$S$21/100/4 -> 0 | AY66: =$S$24*$S$21/100/4 -> 0 | AZ66: =$S$24*$S$21/100/4 -> 0
A67: MONTH 33 (ADMIN) | D67: =SUM(E67:AZ67) -> 21917.7 | U67: =$S$25*$S$14/100/4 -> 2348.325 | V67: =$S$25*$S$14/100/4 -> 2348.325 | W67: =$S$25*$S$14/100/4 -> 2348.325 | X67: =$S$25*$S$14/100/4 -> 2348.325 | Y67: =$S$25*$S$15/100/4 -> 1565.55 | Z67: =$S$25*$S$15/100/4 -> 1565.55 | AA67: =$S$25*$S$15/100/4 -> 1565.55 | AB67: =$S$25*$S$15/100/4 -> 1565.55 | AC67: =$S$25*$S$16/100/4 -> 1565.55 | AD67: =$S$25*$S$16/100/4 -> 1565.55 | AE67: =$S$25*$S$16/100/4 -> 1565.55 | AF67: =$S$25*$S$16/100/4 -> 1565.55 | AG67: =$S$25*$S$17/100/4 -> 0 | AH67: =$S$25*$S$17/100/4 -> 0 | AI67: =$S$25*$S$17/100/4 -> 0 | AJ67: =$S$25*$S$17/100/4 -> 0 | AK67: =$S$25*$S$18/100/4 -> 0 | AL67: =$S$25*$S$18/100/4 -> 0 | AM67: =$S$25*$S$18/100/4 -> 0 | AN67: =$S$25*$S$18/100/4 -> 0 | AO67: =$S$25*$S$19/100/4 -> 0 | AP67: =$S$25*$S$19/100/4 -> 0 | AQ67: =$S$25*$S$19/100/4 -> 0 | AR67: =$S$25*$S$19/100/4 -> 0 | AS67: =$S$25*$S$20/100/4 -> 0 | AT67: =$S$25*$S$20/100/4 -> 0 | AU67: =$S$25*$S$20/100/4 -> 0 | AV67: =$S$25*$S$20/100/4 -> 0 | AW67: =$S$25*$S$21/100/4 -> 0 | AX67: =$S$25*$S$21/100/4 -> 0 | AY67: =$S$25*$S$21/100/4 -> 0 | AZ67: =$S$25*$S$21/100/4 -> 0
A68: MONTH 36 (COMMERCIAL) | D68: =SUM(E68:AZ68) -> 28179.9 | V68: =$T$24*$T$14/100/4 -> 3019.275 | W68: =$T$24*$T$14/100/4 -> 3019.275 | X68: =$T$24*$T$14/100/4 -> 3019.275 | Y68: =$T$24*$T$14/100/4 -> 3019.275 | Z68: =$T$24*$T$15/100/4 -> 2012.85 | AA68: =$T$24*$T$15/100/4 -> 2012.85 | AB68: =$T$24*$T$15/100/4 -> 2012.85 | AC68: =$T$24*$T$15/100/4 -> 2012.85 | AD68: =$T$24*$T$16/100/4 -> 2012.85 | AE68: =$T$24*$T$16/100/4 -> 2012.85 | AF68: =$T$24*$T$16/100/4 -> 2012.85 | AG68: =$T$24*$T$16/100/4 -> 2012.85 | AH68: =$T$24*$T$17/100/4 -> 0 | AI68: =$T$24*$T$17/100/4 -> 0 | AJ68: =$T$24*$T$17/100/4 -> 0 | AK68: =$T$24*$T$17/100/4 -> 0 | AL68: =$T$24*$T$18/100/4 -> 0 | AM68: =$T$24*$T$18/100/4 -> 0 | AN68: =$T$24*$T$18/100/4 -> 0 | AO68: =$T$24*$T$18/100/4 -> 0 | AP68: =$T$24*$T$19/100/4 -> 0 | AQ68: =$T$24*$T$19/100/4 -> 0 | AR68: =$T$24*$T$19/100/4 -> 0 | AS68: =$T$24*$T$19/100/4 -> 0 | AT68: =$T$24*$T$20/100/4 -> 0 | AU68: =$T$24*$T$20/100/4 -> 0 | AV68: =$T$24*$T$20/100/4 -> 0 | AW68: =$T$24*$T$20/100/4 -> 0 | AX68: =$T$24*$T$21/100/4 -> 0 | AY68: =$T$24*$T$21/100/4 -> 0 | AZ68: =$T$24*$T$21/100/4 -> 0 | BA68: =$T$24*$T$21/100/4 -> 0 | BE68: =$T$24*$T$19/100/4 -> 0 | BF68: =BE68 -> 0 | BG68: =$T$24*$T$20/100/4 -> 0 | BH68: =BG68 -> 0 | BI68: =$T$24*$T$21/100/4 -> 0 | BJ68: =BI68 -> 0 | BK68: =BJ68 -> 0
A69: MONTH 36 (ADMIN) | D69: =SUM(E69:AZ69) -> 21917.7 | V69: =$T$25*$T$14/100/4 -> 2348.325 | W69: =$T$25*$T$14/100/4 -> 2348.325 | X69: =$T$25*$T$14/100/4 -> 2348.325 | Y69: =$T$25*$T$14/100/4 -> 2348.325 | Z69: =$T$25*$T$15/100/4 -> 1565.55 | AA69: =$T$25*$T$15/100/4 -> 1565.55 | AB69: =$T$25*$T$15/100/4 -> 1565.55 | AC69: =$T$25*$T$15/100/4 -> 1565.55 | AD69: =$T$25*$T$16/100/4 -> 1565.55 | AE69: =$T$25*$T$16/100/4 -> 1565.55 | AF69: =$T$25*$T$16/100/4 -> 1565.55 | AG69: =$T$25*$T$16/100/4 -> 1565.55 | AH69: =$T$25*$T$17/100/4 -> 0 | AI69: =$T$25*$T$17/100/4 -> 0 | AJ69: =$T$25*$T$17/100/4 -> 0 | AK69: =$T$25*$T$17/100/4 -> 0 | AL69: =$T$25*$T$18/100/4 -> 0 | AM69: =$T$25*$T$18/100/4 -> 0 | AN69: =$T$25*$T$18/100/4 -> 0 | AO69: =$T$25*$T$18/100/4 -> 0 | AP69: =$T$25*$T$19/100/4 -> 0 | AQ69: =$T$25*$T$19/100/4 -> 0 | AR69: =$T$25*$T$19/100/4 -> 0 | AS69: =$T$25*$T$19/100/4 -> 0 | AT69: =$T$25*$T$20/100/4 -> 0 | AU69: =$T$25*$T$20/100/4 -> 0 | AV69: =$T$25*$T$20/100/4 -> 0 | AW69: =$T$25*$T$20/100/4 -> 0 | AX69: =$T$25*$T$21/100/4 -> 0 | AY69: =$T$25*$T$21/100/4 -> 0 | AZ69: =$T$25*$T$21/100/4 -> 0 | BA69: =$T$25*$T$21/100/4 -> 0 | BE69: =$T$25*$T$19/100/4 -> 0 | BF69: =BE69 -> 0 | BG69: =$T$25*$T$20/100/4 -> 0 | BH69: =BG69 -> 0 | BI69: =$T$25*$T$21/100/4 -> 0 | BJ69: =BI69 -> 0 | BK69: =BJ69 -> 0
A70: Total Collections | D70: =SUM(E70:AZ70) -> 2673735.8 | E70: =SUM(E31:E69) -> 0 | F70: =SUM(F31:F69) -> 0 | G70: =SUM(G31:G69) -> 0 | H70: =SUM(H31:H69) -> 0 | I70: =SUM(I31:I69) -> 18115.65 | J70: =SUM(J31:J69) -> 36231.3 | K70: =SUM(K31:K69) -> 58260.825 | L70: =SUM(L31:L69) -> 69018.39 | ... AQ70: =SUM(AQ31:AQ69) -> 0
A71: Total Sales NPV | D71: =SUM(E71:AS71) -> 1766311.8 | E71: =+E70/((1+$C$72)^E$73) -> 0 | F71: =+F70/((1+$C$72)^F$73) -> 0 | G71: =+G70/((1+$C$72)^G$73) -> 0 | H71: =+H70/((1+$C$72)^H$73) -> 0 | I71: =+I70/((1+$C$72)^I$73) -> 17531.848 | J71: =+J70/((1+$C$72)^J$73) -> 33933.722 | K71: =+K70/((1+$C$72)^K$73) -> 52807.79 | L71: =+L70/((1+$C$72)^L$73) -> 60542.447 | ... AS71: =+AS70/((1+$C$72)^AS$73) -> 0
A72: Cost Of Capital | B72: % | C72: =Assumptions!$C$5 -> 0.14
E73: =Assumptions!E$7 -> -0.75 | F73: =Assumptions!F$7 -> -0.5 | G73: =Assumptions!G$7 -> -0.25 | H73: =Assumptions!H$7 -> 0 | I73: =Assumptions!I$7 -> 0.25 | J73: =Assumptions!J$7 -> 0.5 | K73: =Assumptions!K$7 -> 0.75 | L73: =Assumptions!L$7 -> 1 | ... AS73: =Assumptions!AS$7 -> 9.25
A75: Total Sales Accumulated NPV | E75: =E71 -> 0 | F75: =E75+F71 -> 0 | G75: =F75+G71 -> 0 | H75: =G75+H71 -> 0 | I75: =H75+I71 -> 17531.848 | J75: =I75+J71 -> 51465.57 | K75: =J75+K71 -> 104273.36 | L75: =K75+L71 -> 164815.81 | M75: =L75+M71 -> 221768.05 | ... AQ75: =AP75+AQ71 -> 1766311.8
A76: Total Sales Accumulated | E76: =SUM(E77:E78) -> 0 | F76: =SUM(F77:F78) -> 0 | G76: =SUM(G77:G78) -> 0 | H76: =SUM(H77:H78) -> 0 | I76: =SUM(I77:I78) -> 18115.65 | J76: =SUM(J77:J78) -> 54346.95 | K76: =SUM(K77:K78) -> 112607.77 | L76: =SUM(L77:L78) -> 181626.17 | ... AS76: =SUM(AS77:AS78) -> 2673735.8
A77: Bulk Payments Accumulated | E77: =SUM(E31:E36) -> 0 | F77: =E77+SUM(F31:F36) -> 0 | G77: =F77+SUM(G31:G36) -> 0 | H77: =G77+SUM(H31:H36) -> 0 | I77: =H77+SUM(I31:I36) -> 18115.65 | J77: =I77+SUM(J31:J36) -> 54346.95 | K77: =J77+SUM(K31:K36) -> 103549.95 | L77: =K77+SUM(L31:L36) -> 152641.12 | M77: =L77+SUM(M31:M36) -> 190475.25 | ... AS77: =AR77+SUM(AS31:AS36) -> 1186910.6
A78: Instalments Accumulated | E78: =SUM(E38:E69) -> 0 | F78: =E78+SUM(F38:F69) -> 0 | G78: =F78+SUM(G38:G69) -> 0 | H78: =G78+SUM(H38:H69) -> 0 | I78: =H78+SUM(I38:I69) -> 0 | J78: =I78+SUM(J38:J69) -> 0 | K78: =J78+SUM(K38:K69) -> 9057.825 | L78: =K78+SUM(L38:L69) -> 28985.04 | M78: =L78+SUM(M38:M69) -> 58238.46 | ... AS78: =AR78+SUM(AS38:AS69) -> 1486825.2
A81: NOTES:
A82: ="1- LAUNCH : MONTH "&Assumptions!$C$10 -> 1- LAUNCH : MONTH 1
A83: ="2- START OF CONSTRUCTION : MONTH "&Assumptions!$C$12 -> 2- START OF CONSTRUCTION : MONTH 7
A85: DELIVERY PAYMENT (COMMERCIAL) | D85: =D70-D24-D25 -> 0 | E85: =E24*E12/100 -> 0 | F85: =F24*F12/100 -> 0 | G85: =G24*G12/100 -> 0 | H85: =H24*H12/100 -> 0 | I85: =I24*I12/100 -> 22365 | J85: =J24*J12/100 -> 22365 | K85: =K24*K12/100 -> 24601.5 | L85: =L24*L12/100 -> 17221.05 | ... Y85: =Y24*Y12/100 -> 0
A86: DELIVERY PAYMENT (ADMIN) | E86: =E25*E12/100 -> 0 | F86: =F25*F12/100 -> 0 | G86: =G25*G12/100 -> 0 | H86: =H25*H12/100 -> 0 | I86: =I25*I12/100 -> 50097.6 | J86: =J25*J12/100 -> 50097.6 | K86: =K25*K12/100 -> 37573.2 | L86: =L25*L12/100 -> 18786.6 | ... Y86: =Y25*Y12/100 -> 0

Sheet Stage Schedule & Costs (2)
A1: Construction Schedule & Cost Plan
A2: Enter Duration (months) and Stage Cost (EGP) in the grey cells. All other fields calculate automatically.
A4: No. | B4: Category | C4: Stage | D4: Duration (Months) | E4: Start Month | F4: End Month | G4: Stage Cost (EGP) | H4: Cost / Month (EGP)
A5: 1 | B5: Excavation | C5: Excavation | D5: 3 | E5: 0 | F5: =E5+D5 -> 3 | G5: 2500000 | H5: =IF(D5=0,0,G5/D5) -> 833333.33
A6: 2 | B6: Replacement | C6: Replacement (Backfill) | D6: 3 | E6: =F5 -> 3 | F6: =E6+D6 -> 6 | G6: 3300000 | H6: =IF(D6=0,0,G6/D6) -> 1100000
A7: 3 | B7: Concrete Structure | C7: Basement Floor | D7: 3 | E7: =F6 -> 6 | F7: =E7+D7 -> 9 | G7: 5000000 | H7: =IF(D7=0,0,G7/D7) -> 1666666.7
A8: 4 | C8: Ground Floor | D8: 3 | E8: =F7 -> 9 | F8: =E8+D8 -> 12 | G8: 3300000 | H8: =IF(D8=0,0,G8/D8) -> 1100000
A9: 5 | C9: 1st Floor | D9: 3 | E9: =F8 -> 12 | F9: =E9+D9 -> 15 | G9: 3300000 | H9: =IF(D9=0,0,G9/D9) -> 1100000
A10: 6 | C10: 2nd Floor | D10: 3 | E10: =F9 -> 15 | F10: =E10+D10 -> 18 | G10: 3300000 | H10: =IF(D10=0,0,G10/D10) -> 1100000
A11: 7 | C11: 3rd Floor | E11: =F10 -> 18 | F11: =E11+D11 -> 18 | H11: =IF(D11=0,0,G11/D11) -> 0
A12: 8 | B12: Building Works | C12: Basement Floor | D12: 1.5 | E12: =F11 -> 18 | F12: =E12+D12 -> 19.5 | G12: 330000 | H12: =IF(D12=0,0,G12/D12) -> 220000
A13: 9 | C13: Ground Floor | D13: 1.5 | E13: =F12 -> 19.5 | F13: =E13+D13 -> 21 | G13: 330000 | H13: =IF(D13=0,0,G13/D13) -> 220000
A14: 10 | C14: 1st Floor | D14: 1.5 | E14: =F13 -> 21 | F14: =E14+D14 -> 22.5 | G14: 330000 | H14: =IF(D14=0,0,G14/D14) -> 220000
A15: 11 | C15: 2nd Floor | D15: 1.5 | E15: =F14 -> 22.5 | F15: =E15+D15 -> 24 | G15: 330000 | H15: =IF(D15=0,0,G15/D15) -> 220000
A16: 12 | C16: 3rd Floor | D16: 0 | E16: =F15 -> 24 | F16: =E16+D16 -> 24 | G16: 0 | H16: =IF(D16=0,0,G16/D16) -> 0
A17: 13 | B17: MEP & Plumbing | C17: Basement Floor | D17: 2 | E17: =F16 -> 24 | F17: =E17+D17 -> 26 | G17: 10000000 | H17: =IF(D17=0,0,G17/D17) -> 5000000
A18: 14 | C18: Ground Floor | D18: 2 | E18: =F17 -> 26 | F18: =E18+D18 -> 28 | G18: 10000000 | H18: =IF(D18=0,0,G18/D18) -> 5000000
A19: 15 | C19: 1st Floor | D19: 2 | E19: =F18 -> 28 | F19: =E19+D19 -> 30 | G19: 10000000 | H19: =IF(D19=0,0,G19/D19) -> 5000000
A20: 16 | C20: 2nd Floor | D20: 2 | E20: =F19 -> 30 | F20: =E20+D20 -> 32 | G20: 10000000 | H20: =IF(D20=0,0,G20/D20) -> 5000000
A21: 17 | C21: 3rd Floor | D21: 0 | E21: =F20 -> 32 | F21: =E21+D21 -> 32 | H21: =IF(D21=0,0,G21/D21) -> 0
A22: 18 | B22: Curtain Walls | C22: Curtain Walls | D22: 2 | E22: =F21 -> 32 | F22: =E22+D22 -> 34 | G22: 21000000 | H22: =IF(D22=0,0,G22/D22) -> 10500000
A23: 19 | B23: Landscape | C23: Landscape | D23: 2 | E23: =F22 -> 34 | F23: =E23+D23 -> 36 | G23: 4125000 | H23: =IF(D23=0,0,G23/D23) -> 2062500
B25: TOTAL | C25: Project Duration & Cost | F25: =F23 -> 36 | G25: =SUM(G5:G23) -> 87145000
A27: Notes: Stages run sequentially (Start Month of each stage = End Month of the previous stage). MEP & Plumbing duration is split evenly across the 5 floor stages. To run two stages in parallel, overwrite that stage's Start Month formula.

Sheet Cash Out Detail
A1: Cash Out — Construction Spend by Stage
A2: Stage costs are spread evenly (straight-line) across each stage's duration and pulled from the Stage Schedule & Costs sheet. Row 3 = project month (M1 = sales launch); row 4 = construction month (1 = construction start).
B3: Project month (M1 = sales launch) | D3: 1 | E3: =D3+1 -> 2 | F3: =E3+1 -> 3 | G3: =F3+1 -> 4 | H3: =G3+1 -> 5 | I3: =H3+1 -> 6 | J3: =I3+1 -> 7 | K3: =J3+1 -> 8 | L3: =K3+1 -> 9 | ... BK3: =BJ3+1 -> 60
A4: No. | B4: Stage | D4: =D3-(Assumptions!$C$12-1) -> -5 | E4: =E3-(Assumptions!$C$12-1) -> -4 | F4: =F3-(Assumptions!$C$12-1) -> -3 | G4: =G3-(Assumptions!$C$12-1) -> -2 | H4: =H3-(Assumptions!$C$12-1) -> -1 | I4: =I3-(Assumptions!$C$12-1) -> 0 | J4: =J3-(Assumptions!$C$12-1) -> 1 | K4: =K3-(Assumptions!$C$12-1) -> 2 | ... BK4: =BK3-(Assumptions!$C$12-1) -> 54
A5: ='Stage Schedule & Costs (2)'!A5 -> 1 | B5: ='Stage Schedule & Costs (2)'!B5&" - "&'Stage Schedule & Costs (2)'!C5 -> Excavation - Excavation | C5: =SUM(D5:BE5) -> 2500000 | D5: =MAX(0,MIN('Stage Schedule & Costs (2)'!$F5,D$4)-MAX('Stage Schedule & Costs (2)'!$E5,D$4-1))*'Stage Schedule & Costs (2)'!$H5 -> 0 | E5: =MAX(0,MIN('Stage Schedule & Costs (2)'!$F5,E$4)-MAX('Stage Schedule & Costs (2)'!$E5,E$4-1))*'Stage Schedule & Costs (2)'!$H5 -> 0 | F5: =MAX(0,MIN('Stage Schedule & Costs (2)'!$F5,F$4)-MAX('Stage Schedule & Costs (2)'!$E5,F$4-1))*'Stage Schedule & Costs (2)'!$H5 -> 0 | G5: =MAX(0,MIN('Stage Schedule & Costs (2)'!$F5,G$4)-MAX('Stage Schedule & Costs (2)'!$E5,G$4-1))*'Stage Schedule & Costs (2)'!$H5 -> 0 | H5: =MAX(0,MIN('Stage Schedule & Costs (2)'!$F5,H$4)-MAX('Stage Schedule & Costs (2)'!$E5,H$4-1))*'Stage Schedule & Costs (2)'!$H5 -> 0 | I5: =MAX(0,MIN('Stage Schedule & Costs (2)'!$F5,I$4)-MAX('Stage Schedule & Costs (2)'!$E5,I$4-1))*'Stage Schedule & Costs (2)'!$H5 -> 0 | J5: =MAX(0,MIN('Stage Schedule & Costs (2)'!$F5,J$4)-MAX('Stage Schedule & Costs (2)'!$E5,J$4-1))*'Stage Schedule & Costs (2)'!$H5 -> 833333.33 | K5: =MAX(0,MIN('Stage Schedule & Costs (2)'!$F5,K$4)-MAX('Stage Schedule & Costs (2)'!$E5,K$4-1))*'Stage Schedule & Costs (2)'!$H5 -> 833333.33 | ... BK5: =MAX(0,MIN('Stage Schedule & Costs (2)'!$F5,BK$4)-MAX('Stage Schedule & Costs (2)'!$E5,BK$4-1))*'Stage Schedule & Costs (2)'!$H5 -> 0
A6: ='Stage Schedule & Costs (2)'!A6 -> 2 | B6: ='Stage Schedule & Costs (2)'!B6&" - "&'Stage Schedule & Costs (2)'!C6 -> Replacement - Replacement (Backfill) | C6: =SUM(D6:BE6) -> 3300000 | D6: =MAX(0,MIN('Stage Schedule & Costs (2)'!$F6,D$4)-MAX('Stage Schedule & Costs (2)'!$E6,D$4-1))*'Stage Schedule & Costs (2)'!$H6 -> 0 | E6: =MAX(0,MIN('Stage Schedule & Costs (2)'!$F6,E$4)-MAX('Stage Schedule & Costs (2)'!$E6,E$4-1))*'Stage Schedule & Costs (2)'!$H6 -> 0 | F6: =MAX(0,MIN('Stage Schedule & Costs (2)'!$F6,F$4)-MAX('Stage Schedule & Costs (2)'!$E6,F$4-1))*'Stage Schedule & Costs (2)'!$H6 -> 0 | G6: =MAX(0,MIN('Stage Schedule & Costs (2)'!$F6,G$4)-MAX('Stage Schedule & Costs (2)'!$E6,G$4-1))*'Stage Schedule & Costs (2)'!$H6 -> 0 | H6: =MAX(0,MIN('Stage Schedule & Costs (2)'!$F6,H$4)-MAX('Stage Schedule & Costs (2)'!$E6,H$4-1))*'Stage Schedule & Costs (2)'!$H6 -> 0 | I6: =MAX(0,MIN('Stage Schedule & Costs (2)'!$F6,I$4)-MAX('Stage Schedule & Costs (2)'!$E6,I$4-1))*'Stage Schedule & Costs (2)'!$H6 -> 0 | J6: =MAX(0,MIN('Stage Schedule & Costs (2)'!$F6,J$4)-MAX('Stage Schedule & Costs (2)'!$E6,J$4-1))*'Stage Schedule & Costs (2)'!$H6 -> 0 | K6: =MAX(0,MIN('Stage Schedule & Costs (2)'!$F6,K$4)-MAX('Stage Schedule & Costs (2)'!$E6,K$4-1))*'Stage Schedule & Costs (2)'!$H6 -> 0 | ... BK6: =MAX(0,MIN('Stage Schedule & Costs (2)'!$F6,BK$4)-MAX('Stage Schedule & Costs (2)'!$E6,BK$4-1))*'Stage Schedule & Costs (2)'!$H6 -> 0
A7: ='Stage Schedule & Costs (2)'!A7 -> 3 | B7: ='Stage Schedule & Costs (2)'!B7&" - "&'Stage Schedule & Costs (2)'!C7 -> Concrete Structure - Basement Floor | C7: =SUM(D7:BE7) -> 5000000 | D7: =MAX(0,MIN('Stage Schedule & Costs (2)'!$F7,D$4)-MAX('Stage Schedule & Costs (2)'!$E7,D$4-1))*'Stage Schedule & Costs (2)'!$H7 -> 0 | E7: =MAX(0,MIN('Stage Schedule & Costs (2)'!$F7,E$4)-MAX('Stage Schedule & Costs (2)'!$E7,E$4-1))*'Stage Schedule & Costs (2)'!$H7 -> 0 | F7: =MAX(0,MIN('Stage Schedule & Costs (2)'!$F7,F$4)-MAX('Stage Schedule & Costs (2)'!$E7,F$4-1))*'Stage Schedule & Costs (2)'!$H7 -> 0 | G7: =MAX(0,MIN('Stage Schedule & Costs (2)'!$F7,G$4)-MAX('Stage Schedule & Costs (2)'!$E7,G$4-1))*'Stage Schedule & Costs (2)'!$H7 -> 0 | H7: =MAX(0,MIN('Stage Schedule & Costs (2)'!$F7,H$4)-MAX('Stage Schedule & Costs (2)'!$E7,H$4-1))*'Stage Schedule & Costs (2)'!$H7 -> 0 | I7: =MAX(0,MIN('Stage Schedule & Costs (2)'!$F7,I$4)-MAX('Stage Schedule & Costs (2)'!$E7,I$4-1))*'Stage Schedule & Costs (2)'!$H7 -> 0 | J7: =MAX(0,MIN('Stage Schedule & Costs (2)'!$F7,J$4)-MAX('Stage Schedule & Costs (2)'!$E7,J$4-1))*'Stage Schedule & Costs (2)'!$H7 -> 0 | K7: =MAX(0,MIN('Stage Schedule & Costs (2)'!$F7,K$4)-MAX('Stage Schedule & Costs (2)'!$E7,K$4-1))*'Stage Schedule & Costs (2)'!$H7 -> 0 | ... BK7: =MAX(0,MIN('Stage Schedule & Costs (2)'!$F7,BK$4)-MAX('Stage Schedule & Costs (2)'!$E7,BK$4-1))*'Stage Schedule & Costs (2)'!$H7 -> 0
A8: ='Stage Schedule & Costs (2)'!A8 -> 4 | B8: ='Stage Schedule & Costs (2)'!B8&" - "&'Stage Schedule & Costs (2)'!C8 -> - Ground Floor | C8: =SUM(D8:BE8) -> 3300000 | D8: =MAX(0,MIN('Stage Schedule & Costs (2)'!$F8,D$4)-MAX('Stage Schedule & Costs (2)'!$E8,D$4-1))*'Stage Schedule & Costs (2)'!$H8 -> 0 | E8: =MAX(0,MIN('Stage Schedule & Costs (2)'!$F8,E$4)-MAX('Stage Schedule & Costs (2)'!$E8,E$4-1))*'Stage Schedule & Costs (2)'!$H8 -> 0 | F8: =MAX(0,MIN('Stage Schedule & Costs (2)'!$F8,F$4)-MAX('Stage Schedule & Costs (2)'!$E8,F$4-1))*'Stage Schedule & Costs (2)'!$H8 -> 0 | G8: =MAX(0,MIN('Stage Schedule & Costs (2)'!$F8,G$4)-MAX('Stage Schedule & Costs (2)'!$E8,G$4-1))*'Stage Schedule & Costs (2)'!$H8 -> 0 | H8: =MAX(0,MIN('Stage Schedule & Costs (2)'!$F8,H$4)-MAX('Stage Schedule & Costs (2)'!$E8,H$4-1))*'Stage Schedule & Costs (2)'!$H8 -> 0 | I8: =MAX(0,MIN('Stage Schedule & Costs (2)'!$F8,I$4)-MAX('Stage Schedule & Costs (2)'!$E8,I$4-1))*'Stage Schedule & Costs (2)'!$H8 -> 0 | J8: =MAX(0,MIN('Stage Schedule & Costs (2)'!$F8,J$4)-MAX('Stage Schedule & Costs (2)'!$E8,J$4-1))*'Stage Schedule & Costs (2)'!$H8 -> 0 | K8: =MAX(0,MIN('Stage Schedule & Costs (2)'!$F8,K$4)-MAX('Stage Schedule & Costs (2)'!$E8,K$4-1))*'Stage Schedule & Costs (2)'!$H8 -> 0 | ... BK8: =MAX(0,MIN('Stage Schedule & Costs (2)'!$F8,BK$4)-MAX('Stage Schedule & Costs (2)'!$E8,BK$4-1))*'Stage Schedule & Costs (2)'!$H8 -> 0
A9: ='Stage Schedule & Costs (2)'!A9 -> 5 | B9: ='Stage Schedule & Costs (2)'!B9&" - "&'Stage Schedule & Costs (2)'!C9 -> - 1st Floor | C9: =SUM(D9:BE9) -> 3300000 | D9: =MAX(0,MIN('Stage Schedule & Costs (2)'!$F9,D$4)-MAX('Stage Schedule & Costs (2)'!$E9,D$4-1))*'Stage Schedule & Costs (2)'!$H9 -> 0 | E9: =MAX(0,MIN('Stage Schedule & Costs (2)'!$F9,E$4)-MAX('Stage Schedule & Costs (2)'!$E9,E$4-1))*'Stage Schedule & Costs (2)'!$H9 -> 0 | F9: =MAX(0,MIN('Stage Schedule & Costs (2)'!$F9,F$4)-MAX('Stage Schedule & Costs (2)'!$E9,F$4-1))*'Stage Schedule & Costs (2)'!$H9 -> 0 | G9: =MAX(0,MIN('Stage Schedule & Costs (2)'!$F9,G$4)-MAX('Stage Schedule & Costs (2)'!$E9,G$4-1))*'Stage Schedule & Costs (2)'!$H9 -> 0 | H9: =MAX(0,MIN('Stage Schedule & Costs (2)'!$F9,H$4)-MAX('Stage Schedule & Costs (2)'!$E9,H$4-1))*'Stage Schedule & Costs (2)'!$H9 -> 0 | I9: =MAX(0,MIN('Stage Schedule & Costs (2)'!$F9,I$4)-MAX('Stage Schedule & Costs (2)'!$E9,I$4-1))*'Stage Schedule & Costs (2)'!$H9 -> 0 | J9: =MAX(0,MIN('Stage Schedule & Costs (2)'!$F9,J$4)-MAX('Stage Schedule & Costs (2)'!$E9,J$4-1))*'Stage Schedule & Costs (2)'!$H9 -> 0 | K9: =MAX(0,MIN('Stage Schedule & Costs (2)'!$F9,K$4)-MAX('Stage Schedule & Costs (2)'!$E9,K$4-1))*'Stage Schedule & Costs (2)'!$H9 -> 0 | ... BK9: =MAX(0,MIN('Stage Schedule & Costs (2)'!$F9,BK$4)-MAX('Stage Schedule & Costs (2)'!$E9,BK$4-1))*'Stage Schedule & Costs (2)'!$H9 -> 0
A10: ='Stage Schedule & Costs (2)'!A10 -> 6 | B10: ='Stage Schedule & Costs (2)'!B10&" - "&'Stage Schedule & Costs (2)'!C10 -> - 2nd Floor | C10: =SUM(D10:BE10) -> 3300000 | D10: =MAX(0,MIN('Stage Schedule & Costs (2)'!$F10,D$4)-MAX('Stage Schedule & Costs (2)'!$E10,D$4-1))*'Stage Schedule & Costs (2)'!$H10 -> 0 | E10: =MAX(0,MIN('Stage Schedule & Costs (2)'!$F10,E$4)-MAX('Stage Schedule & Costs (2)'!$E10,E$4-1))*'Stage Schedule & Costs (2)'!$H10 -> 0 | F10: =MAX(0,MIN('Stage Schedule & Costs (2)'!$F10,F$4)-MAX('Stage Schedule & Costs (2)'!$E10,F$4-1))*'Stage Schedule & Costs (2)'!$H10 -> 0 | G10: =MAX(0,MIN('Stage Schedule & Costs (2)'!$F10,G$4)-MAX('Stage Schedule & Costs (2)'!$E10,G$4-1))*'Stage Schedule & Costs (2)'!$H10 -> 0 | H10: =MAX(0,MIN('Stage Schedule & Costs (2)'!$F10,H$4)-MAX('Stage Schedule & Costs (2)'!$E10,H$4-1))*'Stage Schedule & Costs (2)'!$H10 -> 0 | I10: =MAX(0,MIN('Stage Schedule & Costs (2)'!$F10,I$4)-MAX('Stage Schedule & Costs (2)'!$E10,I$4-1))*'Stage Schedule & Costs (2)'!$H10 -> 0 | J10: =MAX(0,MIN('Stage Schedule & Costs (2)'!$F10,J$4)-MAX('Stage Schedule & Costs (2)'!$E10,J$4-1))*'Stage Schedule & Costs (2)'!$H10 -> 0 | K10: =MAX(0,MIN('Stage Schedule & Costs (2)'!$F10,K$4)-MAX('Stage Schedule & Costs (2)'!$E10,K$4-1))*'Stage Schedule & Costs (2)'!$H10 -> 0 | ... BK10: =MAX(0,MIN('Stage Schedule & Costs (2)'!$F10,BK$4)-MAX('Stage Schedule & Costs (2)'!$E10,BK$4-1))*'Stage Schedule & Costs (2)'!$H10 -> 0
A11: ='Stage Schedule & Costs (2)'!A11 -> 7 | B11: ='Stage Schedule & Costs (2)'!B11&" - "&'Stage Schedule & Costs (2)'!C11 -> - 3rd Floor | C11: =SUM(D11:BE11) -> 0 | D11: =MAX(0,MIN('Stage Schedule & Costs (2)'!$F11,D$4)-MAX('Stage Schedule & Costs (2)'!$E11,D$4-1))*'Stage Schedule & Costs (2)'!$H11 -> 0 | E11: =MAX(0,MIN('Stage Schedule & Costs (2)'!$F11,E$4)-MAX('Stage Schedule & Costs (2)'!$E11,E$4-1))*'Stage Schedule & Costs (2)'!$H11 -> 0 | F11: =MAX(0,MIN('Stage Schedule & Costs (2)'!$F11,F$4)-MAX('Stage Schedule & Costs (2)'!$E11,F$4-1))*'Stage Schedule & Costs (2)'!$H11 -> 0 | G11: =MAX(0,MIN('Stage Schedule & Costs (2)'!$F11,G$4)-MAX('Stage Schedule & Costs (2)'!$E11,G$4-1))*'Stage Schedule & Costs (2)'!$H11 -> 0 | H11: =MAX(0,MIN('Stage Schedule & Costs (2)'!$F11,H$4)-MAX('Stage Schedule & Costs (2)'!$E11,H$4-1))*'Stage Schedule & Costs (2)'!$H11 -> 0 | I11: =MAX(0,MIN('Stage Schedule & Costs (2)'!$F11,I$4)-MAX('Stage Schedule & Costs (2)'!$E11,I$4-1))*'Stage Schedule & Costs (2)'!$H11 -> 0 | J11: =MAX(0,MIN('Stage Schedule & Costs (2)'!$F11,J$4)-MAX('Stage Schedule & Costs (2)'!$E11,J$4-1))*'Stage Schedule & Costs (2)'!$H11 -> 0 | K11: =MAX(0,MIN('Stage Schedule & Costs (2)'!$F11,K$4)-MAX('Stage Schedule & Costs (2)'!$E11,K$4-1))*'Stage Schedule & Costs (2)'!$H11 -> 0 | ... BK11: =MAX(0,MIN('Stage Schedule & Costs (2)'!$F11,BK$4)-MAX('Stage Schedule & Costs (2)'!$E11,BK$4-1))*'Stage Schedule & Costs (2)'!$H11 -> 0
A12: ='Stage Schedule & Costs (2)'!A12 -> 8 | B12: ='Stage Schedule & Costs (2)'!B12&" - "&'Stage Schedule & Costs (2)'!C12 -> Building Works - Basement Floor | C12: =SUM(D12:BE12) -> 330000 | D12: =MAX(0,MIN('Stage Schedule & Costs (2)'!$F12,D$4)-MAX('Stage Schedule & Costs (2)'!$E12,D$4-1))*'Stage Schedule & Costs (2)'!$H12 -> 0 | E12: =MAX(0,MIN('Stage Schedule & Costs (2)'!$F12,E$4)-MAX('Stage Schedule & Costs (2)'!$E12,E$4-1))*'Stage Schedule & Costs (2)'!$H12 -> 0 | F12: =MAX(0,MIN('Stage Schedule & Costs (2)'!$F12,F$4)-MAX('Stage Schedule & Costs (2)'!$E12,F$4-1))*'Stage Schedule & Costs (2)'!$H12 -> 0 | G12: =MAX(0,MIN('Stage Schedule & Costs (2)'!$F12,G$4)-MAX('Stage Schedule & Costs (2)'!$E12,G$4-1))*'Stage Schedule & Costs (2)'!$H12 -> 0 | H12: =MAX(0,MIN('Stage Schedule & Costs (2)'!$F12,H$4)-MAX('Stage Schedule & Costs (2)'!$E12,H$4-1))*'Stage Schedule & Costs (2)'!$H12 -> 0 | I12: =MAX(0,MIN('Stage Schedule & Costs (2)'!$F12,I$4)-MAX('Stage Schedule & Costs (2)'!$E12,I$4-1))*'Stage Schedule & Costs (2)'!$H12 -> 0 | J12: =MAX(0,MIN('Stage Schedule & Costs (2)'!$F12,J$4)-MAX('Stage Schedule & Costs (2)'!$E12,J$4-1))*'Stage Schedule & Costs (2)'!$H12 -> 0 | K12: =MAX(0,MIN('Stage Schedule & Costs (2)'!$F12,K$4)-MAX('Stage Schedule & Costs (2)'!$E12,K$4-1))*'Stage Schedule & Costs (2)'!$H12 -> 0 | ... BK12: =MAX(0,MIN('Stage Schedule & Costs (2)'!$F12,BK$4)-MAX('Stage Schedule & Costs (2)'!$E12,BK$4-1))*'Stage Schedule & Costs (2)'!$H12 -> 0
A13: ='Stage Schedule & Costs (2)'!A13 -> 9 | B13: ='Stage Schedule & Costs (2)'!B13&" - "&'Stage Schedule & Costs (2)'!C13 -> - Ground Floor | C13: =SUM(D13:BE13) -> 330000 | D13: =MAX(0,MIN('Stage Schedule & Costs (2)'!$F13,D$4)-MAX('Stage Schedule & Costs (2)'!$E13,D$4-1))*'Stage Schedule & Costs (2)'!$H13 -> 0 | E13: =MAX(0,MIN('Stage Schedule & Costs (2)'!$F13,E$4)-MAX('Stage Schedule & Costs (2)'!$E13,E$4-1))*'Stage Schedule & Costs (2)'!$H13 -> 0 | F13: =MAX(0,MIN('Stage Schedule & Costs (2)'!$F13,F$4)-MAX('Stage Schedule & Costs (2)'!$E13,F$4-1))*'Stage Schedule & Costs (2)'!$H13 -> 0 | G13: =MAX(0,MIN('Stage Schedule & Costs (2)'!$F13,G$4)-MAX('Stage Schedule & Costs (2)'!$E13,G$4-1))*'Stage Schedule & Costs (2)'!$H13 -> 0 | H13: =MAX(0,MIN('Stage Schedule & Costs (2)'!$F13,H$4)-MAX('Stage Schedule & Costs (2)'!$E13,H$4-1))*'Stage Schedule & Costs (2)'!$H13 -> 0 | I13: =MAX(0,MIN('Stage Schedule & Costs (2)'!$F13,I$4)-MAX('Stage Schedule & Costs (2)'!$E13,I$4-1))*'Stage Schedule & Costs (2)'!$H13 -> 0 | J13: =MAX(0,MIN('Stage Schedule & Costs (2)'!$F13,J$4)-MAX('Stage Schedule & Costs (2)'!$E13,J$4-1))*'Stage Schedule & Costs (2)'!$H13 -> 0 | K13: =MAX(0,MIN('Stage Schedule & Costs (2)'!$F13,K$4)-MAX('Stage Schedule & Costs (2)'!$E13,K$4-1))*'Stage Schedule & Costs (2)'!$H13 -> 0 | ... BK13: =MAX(0,MIN('Stage Schedule & Costs (2)'!$F13,BK$4)-MAX('Stage Schedule & Costs (2)'!$E13,BK$4-1))*'Stage Schedule & Costs (2)'!$H13 -> 0
A14: ='Stage Schedule & Costs (2)'!A14 -> 10 | B14: ='Stage Schedule & Costs (2)'!B14&" - "&'Stage Schedule & Costs (2)'!C14 -> - 1st Floor | C14: =SUM(D14:BE14) -> 330000 | D14: =MAX(0,MIN('Stage Schedule & Costs (2)'!$F14,D$4)-MAX('Stage Schedule & Costs (2)'!$E14,D$4-1))*'Stage Schedule & Costs (2)'!$H14 -> 0 | E14: =MAX(0,MIN('Stage Schedule & Costs (2)'!$F14,E$4)-MAX('Stage Schedule & Costs (2)'!$E14,E$4-1))*'Stage Schedule & Costs (2)'!$H14 -> 0 | F14: =MAX(0,MIN('Stage Schedule & Costs (2)'!$F14,F$4)-MAX('Stage Schedule & Costs (2)'!$E14,F$4-1))*'Stage Schedule & Costs (2)'!$H14 -> 0 | G14: =MAX(0,MIN('Stage Schedule & Costs (2)'!$F14,G$4)-MAX('Stage Schedule & Costs (2)'!$E14,G$4-1))*'Stage Schedule & Costs (2)'!$H14 -> 0 | H14: =MAX(0,MIN('Stage Schedule & Costs (2)'!$F14,H$4)-MAX('Stage Schedule & Costs (2)'!$E14,H$4-1))*'Stage Schedule & Costs (2)'!$H14 -> 0 | I14: =MAX(0,MIN('Stage Schedule & Costs (2)'!$F14,I$4)-MAX('Stage Schedule & Costs (2)'!$E14,I$4-1))*'Stage Schedule & Costs (2)'!$H14 -> 0 | J14: =MAX(0,MIN('Stage Schedule & Costs (2)'!$F14,J$4)-MAX('Stage Schedule & Costs (2)'!$E14,J$4-1))*'Stage Schedule & Costs (2)'!$H14 -> 0 | K14: =MAX(0,MIN('Stage Schedule & Costs (2)'!$F14,K$4)-MAX('Stage Schedule & Costs (2)'!$E14,K$4-1))*'Stage Schedule & Costs (2)'!$H14 -> 0 | ... BK14: =MAX(0,MIN('Stage Schedule & Costs (2)'!$F14,BK$4)-MAX('Stage Schedule & Costs (2)'!$E14,BK$4-1))*'Stage Schedule & Costs (2)'!$H14 -> 0
A15: ='Stage Schedule & Costs (2)'!A15 -> 11 | B15: ='Stage Schedule & Costs (2)'!B15&" - "&'Stage Schedule & Costs (2)'!C15 -> - 2nd Floor | C15: =SUM(D15:BE15) -> 330000 | D15: =MAX(0,MIN('Stage Schedule & Costs (2)'!$F15,D$4)-MAX('Stage Schedule & Costs (2)'!$E15,D$4-1))*'Stage Schedule & Costs (2)'!$H15 -> 0 | E15: =MAX(0,MIN('Stage Schedule & Costs (2)'!$F15,E$4)-MAX('Stage Schedule & Costs (2)'!$E15,E$4-1))*'Stage Schedule & Costs (2)'!$H15 -> 0 | F15: =MAX(0,MIN('Stage Schedule & Costs (2)'!$F15,F$4)-MAX('Stage Schedule & Costs (2)'!$E15,F$4-1))*'Stage Schedule & Costs (2)'!$H15 -> 0 | G15: =MAX(0,MIN('Stage Schedule & Costs (2)'!$F15,G$4)-MAX('Stage Schedule & Costs (2)'!$E15,G$4-1))*'Stage Schedule & Costs (2)'!$H15 -> 0 | H15: =MAX(0,MIN('Stage Schedule & Costs (2)'!$F15,H$4)-MAX('Stage Schedule & Costs (2)'!$E15,H$4-1))*'Stage Schedule & Costs (2)'!$H15 -> 0 | I15: =MAX(0,MIN('Stage Schedule & Costs (2)'!$F15,I$4)-MAX('Stage Schedule & Costs (2)'!$E15,I$4-1))*'Stage Schedule & Costs (2)'!$H15 -> 0 | J15: =MAX(0,MIN('Stage Schedule & Costs (2)'!$F15,J$4)-MAX('Stage Schedule & Costs (2)'!$E15,J$4-1))*'Stage Schedule & Costs (2)'!$H15 -> 0 | K15: =MAX(0,MIN('Stage Schedule & Costs (2)'!$F15,K$4)-MAX('Stage Schedule & Costs (2)'!$E15,K$4-1))*'Stage Schedule & Costs (2)'!$H15 -> 0 | ... BK15: =MAX(0,MIN('Stage Schedule & Costs (2)'!$F15,BK$4)-MAX('Stage Schedule & Costs (2)'!$E15,BK$4-1))*'Stage Schedule & Costs (2)'!$H15 -> 0
A16: ='Stage Schedule & Costs (2)'!A16 -> 12 | B16: ='Stage Schedule & Costs (2)'!B16&" - "&'Stage Schedule & Costs (2)'!C16 -> - 3rd Floor | C16: =SUM(D16:BE16) -> 0 | D16: =MAX(0,MIN('Stage Schedule & Costs (2)'!$F16,D$4)-MAX('Stage Schedule & Costs (2)'!$E16,D$4-1))*'Stage Schedule & Costs (2)'!$H16 -> 0 | E16: =MAX(0,MIN('Stage Schedule & Costs (2)'!$F16,E$4)-MAX('Stage Schedule & Costs (2)'!$E16,E$4-1))*'Stage Schedule & Costs (2)'!$H16 -> 0 | F16: =MAX(0,MIN('Stage Schedule & Costs (2)'!$F16,F$4)-MAX('Stage Schedule & Costs (2)'!$E16,F$4-1))*'Stage Schedule & Costs (2)'!$H16 -> 0 | G16: =MAX(0,MIN('Stage Schedule & Costs (2)'!$F16,G$4)-MAX('Stage Schedule & Costs (2)'!$E16,G$4-1))*'Stage Schedule & Costs (2)'!$H16 -> 0 | H16: =MAX(0,MIN('Stage Schedule & Costs (2)'!$F16,H$4)-MAX('Stage Schedule & Costs (2)'!$E16,H$4-1))*'Stage Schedule & Costs (2)'!$H16 -> 0 | I16: =MAX(0,MIN('Stage Schedule & Costs (2)'!$F16,I$4)-MAX('Stage Schedule & Costs (2)'!$E16,I$4-1))*'Stage Schedule & Costs (2)'!$H16 -> 0 | J16: =MAX(0,MIN('Stage Schedule & Costs (2)'!$F16,J$4)-MAX('Stage Schedule & Costs (2)'!$E16,J$4-1))*'Stage Schedule & Costs (2)'!$H16 -> 0 | K16: =MAX(0,MIN('Stage Schedule & Costs (2)'!$F16,K$4)-MAX('Stage Schedule & Costs (2)'!$E16,K$4-1))*'Stage Schedule & Costs (2)'!$H16 -> 0 | ... BK16: =MAX(0,MIN('Stage Schedule & Costs (2)'!$F16,BK$4)-MAX('Stage Schedule & Costs (2)'!$E16,BK$4-1))*'Stage Schedule & Costs (2)'!$H16 -> 0
... A23: ='Stage Schedule & Costs (2)'!A23 -> 19 | B23: ='Stage Schedule & Costs (2)'!B23&" - "&'Stage Schedule & Costs (2)'!C23 -> Landscape - Landscape | C23: =SUM(D23:BE23) -> 4125000 | D23: =MAX(0,MIN('Stage Schedule & Costs (2)'!$F23,D$4)-MAX('Stage Schedule & Costs (2)'!$E23,D$4-1))*'Stage Schedule & Costs (2)'!$H23 -> 0 | E23: =MAX(0,MIN('Stage Schedule & Costs (2)'!$F23,E$4)-MAX('Stage Schedule & Costs (2)'!$E23,E$4-1))*'Stage Schedule & Costs (2)'!$H23 -> 0 | F23: =MAX(0,MIN('Stage Schedule & Costs (2)'!$F23,F$4)-MAX('Stage Schedule & Costs (2)'!$E23,F$4-1))*'Stage Schedule & Costs (2)'!$H23 -> 0 | G23: =MAX(0,MIN('Stage Schedule & Costs (2)'!$F23,G$4)-MAX('Stage Schedule & Costs (2)'!$E23,G$4-1))*'Stage Schedule & Costs (2)'!$H23 -> 0 | H23: =MAX(0,MIN('Stage Schedule & Costs (2)'!$F23,H$4)-MAX('Stage Schedule & Costs (2)'!$E23,H$4-1))*'Stage Schedule & Costs (2)'!$H23 -> 0 | I23: =MAX(0,MIN('Stage Schedule & Costs (2)'!$F23,I$4)-MAX('Stage Schedule & Costs (2)'!$E23,I$4-1))*'Stage Schedule & Costs (2)'!$H23 -> 0 | J23: =MAX(0,MIN('Stage Schedule & Costs (2)'!$F23,J$4)-MAX('Stage Schedule & Costs (2)'!$E23,J$4-1))*'Stage Schedule & Costs (2)'!$H23 -> 0 | K23: =MAX(0,MIN('Stage Schedule & Costs (2)'!$F23,K$4)-MAX('Stage Schedule & Costs (2)'!$E23,K$4-1))*'Stage Schedule & Costs (2)'!$H23 -> 0 | ... BK23: =MAX(0,MIN('Stage Schedule & Costs (2)'!$F23,BK$4)-MAX('Stage Schedule & Costs (2)'!$E23,BK$4-1))*'Stage Schedule & Costs (2)'!$H23 -> 0
B24: Total Monthly Spend (EGP) | C24: =SUM(D24:BE24) -> 87145000 | D24: =SUM(D5:D23) -> 0 | E24: =SUM(E5:E23) -> 0 | F24: =SUM(F5:F23) -> 0 | G24: =SUM(G5:G23) -> 0 | H24: =SUM(H5:H23) -> 0 | I24: =SUM(I5:I23) -> 0 | J24: =SUM(J5:J23) -> 833333.33 | K24: =SUM(K5:K23) -> 833333.33 | ... BE24: =SUM(BE5:BE23) -> 0
B25: Cumulative Spend (EGP) | D25: =D24 -> 0 | E25: =D25+E24 -> 0 | F25: =E25+F24 -> 0 | G25: =F25+G24 -> 0 | H25: =G25+H24 -> 0 | I25: =H25+I24 -> 0 | J25: =I25+J24 -> 833333.33 | K25: =J25+K24 -> 1666666.7 | L25: =K25+L24 -> 2500000 | ... BE25: =BD25+BE24 -> 87145000
B27: Construction Cost
B28: L'avenir | C28: =SUM(P28:BQ28) -> 650760000 | D28: =D24*Assumptions!$C$22*Assumptions!$C$23 -> 0 | E28: =E24*Assumptions!$C$22*Assumptions!$C$23 -> 0 | F28: =F24*Assumptions!$C$22*Assumptions!$C$23 -> 0 | G28: =G24*Assumptions!$C$22*Assumptions!$C$23 -> 0 | H28: =H24*Assumptions!$C$22*Assumptions!$C$23 -> 0 | I28: =I24*Assumptions!$C$22*Assumptions!$C$23 -> 0 | J28: =J24*Assumptions!$C$22*Assumptions!$C$23 -> 6666666.7 | K28: =K24*Assumptions!$C$22*Assumptions!$C$23 -> 6666666.7 | ... BK28: =BK24*Assumptions!$C$22*Assumptions!$C$23 -> 0
B30: Sales Commission | C30: 0.04
B31: L'avenir | C31: =SUM(D31:BE31) -> 106949430 | D31: ='L''avenir'!$E$26/3*$C$30*1000 -> 0 | E31: ='L''avenir'!$E$26/3*$C$30*1000 -> 0 | F31: ='L''avenir'!$E$26/3*$C$30*1000 -> 0 | G31: ='L''avenir'!$F$26/3*$C$30*1000 -> 0 | H31: ='L''avenir'!$F$26/3*$C$30*1000 -> 0 | I31: ='L''avenir'!$F$26/3*$C$30*1000 -> 0 | J31: ='L''avenir'!$G$26/3*$C$30*1000 -> 0 | K31: ='L''avenir'!$G$26/3*$C$30*1000 -> 0 | L31: ='L''avenir'!$G$26/3*$C$30*1000 -> 0 | M31: ='L''avenir'!$H$26/3*$C$30*1000 -> 0 | N31: ='L''avenir'!$H$26/3*$C$30*1000 -> 0 | O31: ='L''avenir'!$H$26/3*$C$30*1000 -> 0 | P31: ='L''avenir'!$I$26/3*$C$30*1000 -> 4830840 | Q31: ='L''avenir'!$I$26/3*$C$30*1000 -> 4830840 | R31: ='L''avenir'!$I$26/3*$C$30*1000 -> 4830840 | S31: ='L''avenir'!$J$26/3*$C$30*1000 -> 4830840 | T31: ='L''avenir'!$J$26/3*$C$30*1000 -> 4830840 | U31: ='L''avenir'!$J$26/3*$C$30*1000 -> 4830840 | V31: ='L''avenir'!$K$26/3*$C$30*1000 -> 4144980 | W31: ='L''avenir'!$K$26/3*$C$30*1000 -> 4144980 | X31: ='L''avenir'!$K$26/3*$C$30*1000 -> 4144980 | Y31: ='L''avenir'!$L$26/3*$C$30*1000 -> 2400510 | Z31: ='L''avenir'!$L$26/3*$C$30*1000 -> 2400510 | AA31: ='L''avenir'!$L$26/3*$C$30*1000 -> 2400510 | AB31: ='L''avenir'!$M$26/3*$C$30*1000 -> 2644040 | AC31: ='L''avenir'!$M$26/3*$C$30*1000 -> 2644040 | AD31: ='L''avenir'!$M$26/3*$C$30*1000 -> 2644040 | AE31: ='L''avenir'!$N$26/3*$C$30*1000 -> 2465120 | AF31: ='L''avenir'!$N$26/3*$C$30*1000 -> 2465120 | AG31: ='L''avenir'!$N$26/3*$C$30*1000 -> 2465120 | AH31: ='L''avenir'!$O$26/3*$C$30*1000 -> 2514820 | AI31: ='L''avenir'!$O$26/3*$C$30*1000 -> 2514820 | AJ31: ='L''avenir'!$O$26/3*$C$30*1000 -> 2514820 | AK31: ='L''avenir'!$P$26/3*$C$30*1000 -> 2514820 | AL31: ='L''avenir'!$P$26/3*$C$30*1000 -> 2514820 | AM31: ='L''avenir'!$P$26/3*$C$30*1000 -> 2514820 | AN31: ='L''avenir'!$Q$26/3*$C$30*1000 -> 2743440 | AO31: ='L''avenir'!$Q$26/3*$C$30*1000 -> 2743440 | AP31: ='L''avenir'!$Q$26/3*$C$30*1000 -> 2743440 | AQ31: ='L''avenir'!$R$26/3*$C$30*1000 -> 2743440 | AR31: ='L''avenir'!$R$26/3*$C$30*1000 -> 2743440 | AS31: ='L''avenir'!$R$26/3*$C$30*1000 -> 2743440 | AT31: ='L''avenir'!$S$26/3*$C$30*1000 -> 1908480 | AU31: ='L''avenir'!$S$26/3*$C$30*1000 -> 1908480 | AV31: ='L''avenir'!$S$26/3*$C$30*1000 -> 1908480 | AW31: ='L''avenir'!$T$26/3*$C$30*1000 -> 1908480 | AX31: ='L''avenir'!$T$26/3*$C$30*1000 -> 1908480 | AY31: ='L''avenir'!$T$26/3*$C$30*1000 -> 1908480 | AZ31: ='L''avenir'!$U$26/3*$C$30*1000 -> 0 | BA31: ='L''avenir'!$U$26/3*$C$30*1000 -> 0 | BB31: ='L''avenir'!$U$26/3*$C$30*1000 -> 0 | BC31: ='L''avenir'!$V$26/3*$C$30*1000 -> 0 | BD31: ='L''avenir'!$V$26/3*$C$30*1000 -> 0 | BE31: ='L''avenir'!$V$26/3*$C$30*1000 -> 0 | BF31: ='L''avenir'!$W$26/3*$C$30*1000 -> 0 | BG31: ='L''avenir'!$W$26/3*$C$30*1000 -> 0 | BH31: ='L''avenir'!$W$26/3*$C$30*1000 -> 0 | BI31: ='L''avenir'!$X$26/3*$C$30*1000 -> 0 | BJ31: ='L''avenir'!$X$26/3*$C$30*1000 -> 0 | BK31: ='L''avenir'!$X$26/3*$C$30*1000 -> 0
B33: SGA& Others Cost | C33: =C42 -> 0.15
B34: L'avenir | C34: =SUM(D34:BE34) -> 104574000 | D34: =D28*$C$33 -> 0 | E34: =E28*$C$33 -> 0 | F34: =F28*$C$33 -> 0 | G34: =G28*$C$33 -> 0 | H34: =H28*$C$33 -> 0 | I34: =I28*$C$33 -> 0 | J34: =J28*$C$33 -> 1000000 | K34: =K28*$C$33 -> 1000000 | ... BK34: =BK28*$C$33 -> 0
B36: Total Cost
B37: L'avenir | C37: =SUM(D37:BK37) -> 908683430 | D37: =SUM(D34,D31,D28) -> 0 | E37: =SUM(E34,E31,E28) -> 0 | F37: =SUM(F34,F31,F28) -> 0 | G37: =SUM(G34,G31,G28) -> 0 | H37: =SUM(H34,H31,H28) -> 0 | I37: =SUM(I34,I31,I28) -> 0 | J37: =SUM(J34,J31,J28) -> 7666666.7 | K37: =SUM(K34,K31,K28) -> 7666666.7 | ... BK37: =SUM(BK34,BK31,BK28) -> 0
B39: Contingency (% of Construction Cost) — rate | C39: 0.05
B40: Professional Fees (% of Construction Cost) — rate | C40: 0.05
B41: G&A / Overhead (EGP, full horizon) | C41: 0.05
C42: =SUM(C39:C41) -> 0.15
D43: Cash Out Detail | E43: Net Cash Flow | F43: Diff
B44: Check: total cost (MEGP) vs capex on Net Cash Flow | D44: =C37/1000000 -> 908.68343 | E44: ='Net Cash Flow -With DP'!C20 -> 908.68343 | F44: =E44-D44 -> 0
B46: Summary basis vs full schedule (MEGP) | D46: Summary basis | E46: Full schedule | F46: Not in Summary
B47: Construction cost | D47: =C28/1000000 -> 650.76 | E47: =SUM(D28:BK28)/1000000 -> 697.16 | F47: =E47-D47 -> 46.4
B48: Sales commission | D48: =C31/1000000 -> 106.94943 | E48: =SUM(D31:BK31)/1000000 -> 106.94943 | F48: =E48-D48 -> 0
B49: SGA and others | D49: =C34/1000000 -> 104.574 | E49: =SUM(D34:BK34)/1000000 -> 104.574 | F49: =E49-D49 -> 0
B51: The Summary sheet totals each cost line over the same column ranges as the original model. Where 'Not in Summary' is non-zero, the Summary line omits part of the schedule; row 37 and the Net Cash Flow sheets always use the full schedule.

Sheet Offers
C2: L'AVENIR | D2: NOTES
B3: LANDLORD % | C3: 0.35
B4: MIN. GUARANTEED | C4: 850 M
B5: PAYMENT PERIOD | C5: 6
B6: YEAR 1 (M) | C6: 0 | D6: OR 35% OF COLLECTIONS WHICHEVER HIGHER
B7: YEAR 2 (M) | C7: 100 | D7: OR 35% OF COLLECTIONS WHICHEVER HIGHER
B8: YEAR 3 (M) | C8: 200 | D8: OR 35% OF COLLECTIONS WHICHEVER HIGHER
B9: YEAR 4 (M) | C9: 250 | D9: OR 35% OF COLLECTIONS WHICHEVER HIGHER
B10: YEAR 5 (M) | C10: 200 | D10: OR 35% OF COLLECTIONS WHICHEVER HIGHER
B11: YEAR 6 (M) | C11: 100 | D11: OR 35% OF COLLECTIONS WHICHEVER HIGHER
B12: YEAR 7 (M) | C12: 0 | D12: OR 35% OF COLLECTIONS WHICHEVER HIGHER
B13: EXCESS AMOUNT (YRS) | C13: 8
B14: PROJECT DELIVERY | C14: 54 MONTHS
B16: DEVELOPER % | C16: 0.65
B17: DESIGN | C17: ☑
B18: PERMITS | C18: ☑
B19: CONSTRUCTION | C19: ☑
B20: FINISHING | C20: CORE & SHELL
B21: MARKETING | C21: ☑
B22: SALES | C22: ☑
B23: COLLECTION | C23: ☑
B24: PROJECT NAME | C24: UNDER: JALOUR
B25: OPERATION, MANAGEMENT, MAINT. | C25: UNDER: JALOUR | D25: OR FACILITY MANAGEMENT COMPANY ASSIGNED BY JALOUR

Sheet Offers DP
B1: NPV Diff with vs without downpayments | C1: =Summary!F23 -> -23.963617
B2: NPV with DP | C2: =Summary!D23 -> 350.5869
C3: =SUM(C9:C16) -> 850 | E3: =C3-850 -> 0
B4: MEGP | C4: L'AVENIR | D4: NOTES | E4: =E3/6 -> 0
B5: Landlord Share of Collections | C5: 0.35
B6: Minimum Guaranteed Amount | C6: 850
B7: Payment Period | C7: 6
B8: Downpayment % | C8: 0.1
B9: Downpayment Amount (m) | C9: =C8*C6 -> 85
B10: Year 1 (m) | C10: 0 | D10: OR 35% OF COLLECTIONS WHICHEVER HIGHER
B11: Year 2 (m) | C11: 90 | D11: OR 35% OF COLLECTIONS WHICHEVER HIGHER
B12: Year 3 (m) | C12: 180 | D12: OR 35% OF COLLECTIONS WHICHEVER HIGHER
B13: Year 4 (m) | C13: 225 | D13: OR 35% OF COLLECTIONS WHICHEVER HIGHER
B14: Year 5 (m) | C14: 180 | D14: OR 35% OF COLLECTIONS WHICHEVER HIGHER
B15: Year 6 (m) | C15: 90 | D15: OR 35% OF COLLECTIONS WHICHEVER HIGHER
B16: Year 7 (m) | C16: 0 | D16: OR 35% OF COLLECTIONS WHICHEVER HIGHER
B17: Settlement of excess over guarantee | C17: 8
B18: PROJECT DELIVERY | C18: 54 MONTHS
C20: L'AVENIR
B21: Developer Share of Collections | C21: 0.65
B22: Design | C22: Jalour
B23: Permits & License | C23: Jalour
B24: Construction | C24: Jalour
B25: Finishing Standard | C25: CORE & SHELL
B26: Marketing, Sales and Collections | C26: Jalour
B27: Project Branding | C27: Jalour
B28: Operation, Management& Maintenance | C28: Jalour /FM co.
B29: Project Delivery | C29: 54 MONTHS | D29: OR FACILITY MANAGEMENT COMPANY ASSIGNED BY JALOUR

Sheet Cash In Flow Summary
B1: Sales - 20% RETAINED
B2: MEGP
B3: Project | C3: Total Sales | D3: M -9 | E3: M -6 | F3: M -3 | G3: M 0 | H3: M 3 | I3: M 6 | J3: M 9 | K3: M 12 | L3: M 15 | M3: M 18 | N3: M 21 | O3: M 24 | P3: M 27 | Q3: M 30 | R3: M 33 | S3: M 36 | T3: M 39 | U3: M 42 | V3: M 45 | W3: M 48 | X3: M 51 | Y3: M 54 | Z3: M 57 | AA3: M 60 | AB3: M 63 | AC3: M 66 | AD3: M 69 | AE3: M 72 | AF3: M 75 | AG3: M 78 | AH3: M 81 | AI3: M 84 | AJ3: M 87 | AK3: M 90 | AL3: M 93 | AM3: M 96 | AN3: M 99 | AO3: M 102 | AP3: M 105 | AQ3: M 108 | AR3: M 111 | AS3: M 114 | AT3: M 117
B4: L'avenir | C4: =SUM(D4:ZZ4) -> 2673.7357 | D4: ='L''avenir'!E70/1000 -> 0 | E4: ='L''avenir'!F70/1000 -> 0 | F4: ='L''avenir'!G70/1000 -> 0 | G4: ='L''avenir'!H70/1000 -> 0 | H4: ='L''avenir'!I70/1000 -> 18.11565 | I4: ='L''avenir'!J70/1000 -> 36.2313 | J4: ='L''avenir'!K70/1000 -> 58.260825 | K4: ='L''avenir'!L70/1000 -> 69.01839 | ... AT4: ='L''avenir'!AU70/1000 -> 0
B6: Project | C6: Total Sales NPV | D6: M -9 | E6: M -6 | F6: M -3 | G6: M 0 | H6: M 3 | I6: M 6 | J6: M 9 | K6: M 12 | L6: M 15 | M6: M 18 | N6: M 21 | O6: M 24 | P6: M 27 | Q6: M 30 | R6: M 33 | S6: M 36 | T6: M 39 | U6: M 42 | V6: M 45 | W6: M 48 | X6: M 51 | Y6: M 54 | Z6: M 57 | AA6: M 60 | AB6: M 63 | AC6: M 66 | AD6: M 69 | AE6: M 72 | AF6: M 75 | AG6: M 78 | AH6: M 81 | AI6: M 84 | AJ6: M 87 | AK6: M 90 | AL6: M 93 | AM6: M 96 | AN6: M 99 | AO6: M 102 | AP6: M 105 | AQ6: M 108 | AR6: M 111 | AS6: M 114 | AT6: M 117
B7: L'avenir | C7: =SUM(D7:ZZ7) -> 1766.3118 | D7: ='L''avenir'!E71/1000 -> 0 | E7: ='L''avenir'!F71/1000 -> 0 | F7: ='L''avenir'!G71/1000 -> 0 | G7: ='L''avenir'!H71/1000 -> 0 | H7: ='L''avenir'!I71/1000 -> 17.531848 | I7: ='L''avenir'!J71/1000 -> 33.933722 | J7: ='L''avenir'!K71/1000 -> 52.80779 | K7: ='L''avenir'!L71/1000 -> 60.542447 | ... AT7: ='L''avenir'!AU71/1000 -> 0
B9: Accumulated MEGP
B10: Project | C10: Total Sales | D10: M -9 | E10: M -6 | F10: M -3 | G10: M 0 | H10: M 3 | I10: M 6 | J10: M 9 | K10: M 12 | L10: M 15 | M10: M 18 | N10: M 21 | O10: M 24 | P10: M 27 | Q10: M 30 | R10: M 33 | S10: M 36 | T10: M 39 | U10: M 42 | V10: M 45 | W10: M 48 | X10: M 51 | Y10: M 54 | Z10: M 57 | AA10: M 60 | AB10: M 63 | AC10: M 66 | AD10: M 69 | AE10: M 72 | AF10: M 75 | AG10: M 78 | AH10: M 81 | AI10: M 84 | AJ10: M 87 | AK10: M 90 | AL10: M 93 | AM10: M 96 | AN10: M 99 | AO10: M 102 | AP10: M 105 | AQ10: M 108 | AR10: M 111 | AS10: M 114 | AT10: M 117
B11: L'avenir | C11: =MAX(D11:ZZ11) -> 2673.7357 | D11: =D4 -> 0 | E11: =D11+E4 -> 0 | F11: =E11+F4 -> 0 | G11: =F11+G4 -> 0 | H11: =G11+H4 -> 18.11565 | I11: =H11+I4 -> 54.34695 | J11: =I11+J4 -> 112.60778 | K11: =J11+K4 -> 181.62616 | L11: =K11+L4 -> 248.71371 | ... AT11: =AS11+AT4 -> 2673.7357
B13: Project | C13: Total Sales NPV | D13: M -9 | E13: M -6 | F13: M -3 | G13: M 0 | H13: M 3 | I13: M 6 | J13: M 9 | K13: M 12 | L13: M 15 | M13: M 18 | N13: M 21 | O13: M 24 | P13: M 27 | Q13: M 30 | R13: M 33 | S13: M 36 | T13: M 39 | U13: M 42 | V13: M 45 | W13: M 48 | X13: M 51 | Y13: M 54 | Z13: M 57 | AA13: M 60 | AB13: M 63 | AC13: M 66 | AD13: M 69 | AE13: M 72 | AF13: M 75 | AG13: M 78 | AH13: M 81 | AI13: M 84 | AJ13: M 87 | AK13: M 90 | AL13: M 93 | AM13: M 96 | AN13: M 99 | AO13: M 102 | AP13: M 105 | AQ13: M 108 | AR13: M 111 | AS13: M 114 | AT13: M 117
B14: L'avenir | C14: =MAX(D14:ZZ14) -> 1766.3118 | D14: =D7 -> 0 | E14: =D14+E7 -> 0 | F14: =E14+F7 -> 0 | G14: =F14+G7 -> 0 | H14: =G14+H7 -> 17.531848 | I14: =H14+I7 -> 51.46557 | J14: =I14+J7 -> 104.27336 | K14: =J14+K7 -> 164.81581 | L14: =K14+L7 -> 221.76805 | ... AT14: =AS14+AT7 -> 1766.3118
B16: 100% Sales
B17: Project | C17: Total Sales | D17: M -9 | E17: M -6 | F17: M -3 | G17: M 0 | H17: M 3 | I17: M 6 | J17: M 9 | K17: M 12 | L17: M 15 | M17: M 18 | N17: M 21 | O17: M 24 | P17: M 27 | Q17: M 30 | R17: M 33 | S17: M 36 | T17: M 39 | U17: M 42 | V17: M 45 | W17: M 48 | X17: M 51 | Y17: M 54 | Z17: M 57 | AA17: M 60 | AB17: M 63 | AC17: M 66 | AD17: M 69 | AE17: M 72 | AF17: M 75 | AG17: M 78 | AH17: M 81 | AI17: M 84 | AJ17: M 87 | AK17: M 90 | AL17: M 93 | AM17: M 96 | AN17: M 99 | AO17: M 102 | AP17: M 105 | AQ17: M 108 | AR17: M 111 | AS17: M 114 | AT17: M 117
B18: L'avenir | C18: =SUM(D18:ZZ18) -> 3342.1697 | D18: =D4*100/80 -> 0 | E18: =E4*100/80 -> 0 | F18: =F4*100/80 -> 0 | G18: =G4*100/80 -> 0 | H18: =H4*100/80 -> 22.644562 | I18: =I4*100/80 -> 45.289125 | J18: =J4*100/80 -> 72.826031 | K18: =K4*100/80 -> 86.272987 | ... AT18: =AT4*100/80 -> 0
B20: ALAHLY - SABBOUR % | D20: 0.35
B21: Project | C21: Total Sales | D21: M -9 | E21: M -6 | F21: M -3 | G21: M 0 | H21: M 3 | I21: M 6 | J21: M 9 | K21: M 12 | L21: M 15 | M21: M 18 | N21: M 21 | O21: M 24 | P21: M 27 | Q21: M 30 | R21: M 33 | S21: M 36 | T21: M 39 | U21: M 42 | V21: M 45 | W21: M 48 | X21: M 51 | Y21: M 54 | Z21: M 57 | AA21: M 60 | AB21: M 63 | AC21: M 66 | AD21: M 69 | AE21: M 72 | AF21: M 75 | AG21: M 78 | AH21: M 81 | AI21: M 84 | AJ21: M 87 | AK21: M 90 | AL21: M 93 | AM21: M 96 | AN21: M 99 | AO21: M 102 | AP21: M 105 | AQ21: M 108 | AR21: M 111 | AS21: M 114 | AT21: M 117
B22: L'avenir | C22: =SUM(D22:ZZ22) -> 1169.7594 | D22: =D18*$D$20 -> 0 | E22: =E18*$D$20 -> 0 | F22: =F18*$D$20 -> 0 | G22: =G18*$D$20 -> 0 | H22: =H18*$D$20 -> 7.9255969 | I22: =I18*$D$20 -> 15.851194 | J22: =J18*$D$20 -> 25.489111 | K22: =K18*$D$20 -> 30.195546 | ... AT22: =AT18*$D$20 -> 0
B24: ALAHLY - SABBOUR ACCUM
B25: Project | C25: Total Sales | D25: M -9 | E25: M -6 | F25: M -3 | G25: M 0 | H25: M 3 | I25: M 6 | J25: M 9 | K25: M 12 | L25: M 15 | M25: M 18 | N25: M 21 | O25: M 24 | P25: M 27 | Q25: M 30 | R25: M 33 | S25: M 36 | T25: M 39 | U25: M 42 | V25: M 45 | W25: M 48 | X25: M 51 | Y25: M 54 | Z25: M 57 | AA25: M 60 | AB25: M 63 | AC25: M 66 | AD25: M 69 | AE25: M 72 | AF25: M 75 | AG25: M 78 | AH25: M 81 | AI25: M 84 | AJ25: M 87 | AK25: M 90 | AL25: M 93 | AM25: M 96 | AN25: M 99 | AO25: M 102 | AP25: M 105 | AQ25: M 108 | AR25: M 111 | AS25: M 114 | AT25: M 117
B26: L'avenir | C26: =MAX(D26:ZZ26) -> 1169.7594 | D26: =D22 -> 0 | E26: =D26+E22 -> 0 | F26: =E26+F22 -> 0 | G26: =F26+G22 -> 0 | H26: =G26+H22 -> 7.9255969 | I26: =H26+I22 -> 23.776791 | J26: =I26+J22 -> 49.265902 | K26: =J26+K22 -> 79.461447 | L26: =K26+L22 -> 108.81225 | ... AT26: =AS26+AT22 -> 1169.7594

Sheet Net Cash Flow -With DP
B1: Cash Available for Operation after - 20% RETAINED UNITS
B2: Total Collections MEGP
B3: Project | C3: Total Sales | D3: M -9 | E3: M -6 | F3: M -3 | G3: M 0 | H3: M 3 | I3: M 6 | J3: M 9 | K3: M 12 | L3: M 15 | M3: M 18 | N3: M 21 | O3: M 24 | P3: M 27 | Q3: M 30 | R3: M 33 | S3: M 36 | T3: M 39 | U3: M 42 | V3: M 45 | W3: M 48 | X3: M 51 | Y3: M 54 | Z3: M 57 | AA3: M 60 | AB3: M 63 | AC3: M 66 | AD3: M 69 | AE3: M 72 | AF3: M 75 | AG3: M 78 | AH3: M 81 | AI3: M 84 | AJ3: M 87 | AK3: M 90 | AL3: M 93 | AM3: M 96 | AN3: M 99 | AO3: M 102 | AP3: M 105 | AQ3: M 108 | AR3: M 111 | AS3: M 114 | AT3: M 117
B4: L'avenir | C4: =SUM(D4:ZZ4) -> 2673.7357 | D4: ='Cash In Flow Summary'!D4 -> 0 | E4: ='Cash In Flow Summary'!E4 -> 0 | F4: ='Cash In Flow Summary'!F4 -> 0 | G4: ='Cash In Flow Summary'!G4 -> 0 | H4: ='Cash In Flow Summary'!H4 -> 18.11565 | I4: ='Cash In Flow Summary'!I4 -> 36.2313 | J4: ='Cash In Flow Summary'!J4 -> 58.260825 | K4: ='Cash In Flow Summary'!K4 -> 69.01839 | ... AT4: ='Cash In Flow Summary'!AT4 -> 0
B6: ALAHLY - SABBOUR Payments MEGP
B7: Project | C7: Total Sales | D7: M -9 | E7: M -6 | F7: M -3 | G7: M 0 | H7: M 3 | I7: M 6 | J7: M 9 | K7: M 12 | L7: M 15 | M7: M 18 | N7: M 21 | O7: M 24 | P7: M 27 | Q7: M 30 | R7: M 33 | S7: M 36 | T7: M 39 | U7: M 42 | V7: M 45 | W7: M 48 | X7: M 51 | Y7: M 54 | Z7: M 57 | AA7: M 60 | AB7: M 63 | AC7: M 66 | AD7: M 69 | AE7: M 72 | AF7: M 75 | AG7: M 78 | AH7: M 81 | AI7: M 84 | AJ7: M 87 | AK7: M 90 | AL7: M 93 | AM7: M 96 | AN7: M 99 | AO7: M 102 | AP7: M 105 | AQ7: M 108 | AR7: M 111 | AS7: M 114 | AT7: M 117
B8: L'avenir | C8: =SUM(D8:ZZ8) -> 1169.7594 | D8: ='Offers DP'!$C$10/4 -> 0 | E8: ='Offers DP'!$C$10/4 -> 0 | F8: ='Offers DP'!$C$10/4 -> 0 | G8: ='Offers DP'!$C$10/4++'Offers DP'!C9 -> 85 | H8: ='Offers DP'!$C$11/4 -> 22.5 | I8: ='Offers DP'!$C$11/4 -> 22.5 | J8: ='Offers DP'!$C$11/4 -> 22.5 | K8: ='Offers DP'!$C$11/4 -> 22.5 | L8: ='Offers DP'!$C$12/4 -> 45 | M8: ='Offers DP'!$C$12/4 -> 45 | N8: ='Offers DP'!$C$12/4 -> 45 | O8: ='Offers DP'!$C$12/4 -> 45 | P8: ='Offers DP'!$C$13/4 -> 56.25 | Q8: ='Offers DP'!$C$13/4 -> 56.25 | R8: ='Offers DP'!$C$13/4 -> 56.25 | S8: ='Offers DP'!$C$13/4 -> 56.25 | T8: ='Offers DP'!$C$14/4 -> 45 | U8: ='Offers DP'!$C$14/4 -> 45 | V8: ='Offers DP'!$C$14/4 -> 45 | W8: ='Offers DP'!$C$14/4 -> 45 | X8: ='Offers DP'!$C$15/4 -> 22.5 | Y8: ='Offers DP'!$C$15/4 -> 22.5 | Z8: ='Offers DP'!$C$15/4 -> 22.5 | AA8: ='Offers DP'!$C$15/4 -> 22.5 | AB8: ='Offers DP'!$C$16/4 -> 0 | AC8: ='Offers DP'!$C$16/4 -> 0 | AD8: ='Offers DP'!$C$16/4 -> 0 | AE8: ='Offers DP'!$C$16/4 -> 0 | AF8: =-SUM(D8:AE8)+SUM('Cash In Flow Summary'!D22:AE22)+'Cash In Flow Summary'!AF22 -> 241.19161 | AG8: ='Cash In Flow Summary'!AG22 -> 16.107226 | AH8: ='Cash In Flow Summary'!AH22 -> 14.419368 | AI8: ='Cash In Flow Summary'!AI22 -> 12.731509 | AJ8: ='Cash In Flow Summary'!AJ22 -> 10.011366 | AK8: ='Cash In Flow Summary'!AK22 -> 8.4360314 | AL8: ='Cash In Flow Summary'!AL22 -> 7.3515619 | AM8: ='Cash In Flow Summary'!AM22 -> 3.1702388 | AN8: ='Cash In Flow Summary'!AN22 -> 3.1702388 | ... AT8: ='Cash In Flow Summary'!AT22 -> 0
B10: Cash Available for Operation -MEGP
B11: Project | C11: Total Sales | D11: M -9 | E11: M -6 | F11: M -3 | G11: M 0 | H11: M 3 | I11: M 6 | J11: M 9 | K11: M 12 | L11: M 15 | M11: M 18 | N11: M 21 | O11: M 24 | P11: M 27 | Q11: M 30 | R11: M 33 | S11: M 36 | T11: M 39 | U11: M 42 | V11: M 45 | W11: M 48 | X11: M 51 | Y11: M 54 | Z11: M 57 | AA11: M 60 | AB11: M 63 | AC11: M 66 | AD11: M 69 | AE11: M 72 | AF11: M 75 | AG11: M 78 | AH11: M 81 | AI11: M 84 | AJ11: M 87 | AK11: M 90 | AL11: M 93 | AM11: M 96 | AN11: M 99 | AO11: M 102 | AP11: M 105 | AQ11: M 108 | AR11: M 111 | AS11: M 114 | AT11: M 117
B12: L'avenir | C12: =SUM(D12:ZZ12) -> 1503.9764 | D12: =D4-D8 -> 0 | E12: =E4-E8 -> 0 | F12: =F4-F8 -> 0 | G12: =G4-G8 -> -85 | H12: =H4-H8 -> -4.38435 | I12: =I4-I8 -> 13.7313 | J12: =J4-J8 -> 35.760825 | K12: =K4-K8 -> 46.51839 | ... AT12: =AT4-AT8 -> 0
B14: NPV Cash Available for Operation -MEGP
B15: Project | C15: Total Sales | D15: M -9 | E15: M -6 | F15: M -3 | G15: M 0 | H15: M 3 | I15: M 6 | J15: M 9 | K15: M 12 | L15: M 15 | M15: M 18 | N15: M 21 | O15: M 24 | P15: M 27 | Q15: M 30 | R15: M 33 | S15: M 36 | T15: M 39 | U15: M 42 | V15: M 45 | W15: M 48 | X15: M 51 | Y15: M 54 | Z15: M 57 | AA15: M 60 | AB15: M 63 | AC15: M 66 | AD15: M 69 | AE15: M 72 | AF15: M 75 | AG15: M 78 | AH15: M 81 | AI15: M 84 | AJ15: M 87 | AK15: M 90 | AL15: M 93 | AM15: M 96 | AN15: M 99 | AO15: M 102 | AP15: M 105 | AQ15: M 108 | AR15: M 111 | AS15: M 114 | AT15: M 117
B16: L'avenir | C16: =SUM(D16:AT16) -> 994.8063 | D16: =+D12/((1+Assumptions!$C$5)^Assumptions!E$7) -> 0 | E16: =+E12/((1+Assumptions!$C$5)^Assumptions!F$7) -> 0 | F16: =+F12/((1+Assumptions!$C$5)^Assumptions!G$7) -> 0 | G16: =+G12/((1+Assumptions!$C$5)^Assumptions!H$7) -> -85 | H16: =+H12/((1+Assumptions!$C$5)^Assumptions!I$7) -> -4.2430583 | I16: =+I12/((1+Assumptions!$C$5)^Assumptions!J$7) -> 12.860541 | J16: =+J12/((1+Assumptions!$C$5)^Assumptions!K$7) -> 32.413721 | K16: =+K12/((1+Assumptions!$C$5)^Assumptions!L$7) -> 40.805605 | ... AT16: =+AT12/((1+Assumptions!$C$5)^Assumptions!AU$7) -> 0
B18: CASH OUT FLOW CAPEX -MEGP
B19: Project | C19: Total Sales | D19: M -9 | E19: M -6 | F19: M -3 | G19: M 0 | H19: M 3 | I19: M 6 | J19: M 9 | K19: M 12 | L19: M 15 | M19: M 18 | N19: M 21 | O19: M 24 | P19: M 27 | Q19: M 30 | R19: M 33 | S19: M 36 | T19: M 39 | U19: M 42 | V19: M 45 | W19: M 48 | X19: M 51 | Y19: M 54 | Z19: M 57 | AA19: M 60 | AB19: M 63 | AC19: M 66 | AD19: M 69 | AE19: M 72 | AF19: M 75 | AG19: M 78 | AH19: M 81 | AI19: M 84 | AJ19: M 87 | AK19: M 90 | AL19: M 93 | AM19: M 96 | AN19: M 99 | AO19: M 102 | AP19: M 105 | AQ19: M 108 | AR19: M 111 | AS19: M 114 | AT19: M 117
B20: L'avenir | C20: =SUM(H20:AAD20) -> 908.68343 | H20: =SUM('Cash Out Detail'!D37:F37)/1000000 -> 0 | I20: =SUM('Cash Out Detail'!G37:I37)/1000000 -> 0 | J20: =SUM('Cash Out Detail'!J37:L37)/1000000 -> 23 | K20: =SUM('Cash Out Detail'!M37:O37)/1000000 -> 30.36 | L20: =SUM('Cash Out Detail'!P37:R37)/1000000 -> 60.49252 | M20: =SUM('Cash Out Detail'!S37:U37)/1000000 -> 44.85252 | N20: =SUM('Cash Out Detail'!V37:X37)/1000000 -> 42.79494 | O20: =SUM('Cash Out Detail'!Y37:AA37)/1000000 -> 37.56153 | P20: =SUM('Cash Out Detail'!AB37:AD37)/1000000 -> 14.00412 | Q20: =SUM('Cash Out Detail'!AE37:AG37)/1000000 -> 13.46736 | R20: =SUM('Cash Out Detail'!AH37:AJ37)/1000000 -> 145.54446 | S20: =SUM('Cash Out Detail'!AK37:AM37)/1000000 -> 145.54446 | T20: =SUM('Cash Out Detail'!AN37:AP37)/1000000 -> 196.83032 | U20: =SUM('Cash Out Detail'!AQ37:AS37)/1000000 -> 142.78032 | V20: =SUM('Cash Out Detail'!AT37:AV37)/1000000 -> 5.72544 | W20: =SUM('Cash Out Detail'!AW37:AY37)/1000000 -> 5.72544 | X20: =SUM('Cash Out Detail'!AZ37:BB37)/1000000 -> 0 | Y20: =SUM('Cash Out Detail'!BC37:BE37)/1000000 -> 0
B22: NPV CASH OUT FLOW CAPEX -MEGP
B23: Project | C23: Total Sales | D23: M -9 | E23: M -6 | F23: M -3 | G23: M 0 | H23: M 3 | I23: M 6 | J23: M 9 | K23: M 12 | L23: M 15 | M23: M 18 | N23: M 21 | O23: M 24 | P23: M 27 | Q23: M 30 | R23: M 33 | S23: M 36 | T23: M 39 | U23: M 42 | V23: M 45 | W23: M 48 | X23: M 51 | Y23: M 54 | Z23: M 57 | AA23: M 60 | AB23: M 63 | AC23: M 66 | AD23: M 69 | AE23: M 72 | AF23: M 75 | AG23: M 78 | AH23: M 81 | AI23: M 84 | AJ23: M 87 | AK23: M 90 | AL23: M 93 | AM23: M 96 | AN23: M 99 | AO23: M 102 | AP23: M 105 | AQ23: M 108 | AR23: M 111 | AS23: M 114 | AT23: M 117
B24: L'avenir | C24: =SUM(D24:ZZ24) -> 644.2194 | D24: =+D20/((1+Assumptions!$C$5)^Assumptions!E$7) -> 0 | E24: =+E20/((1+Assumptions!$C$5)^Assumptions!F$7) -> 0 | F24: =+F20/((1+Assumptions!$C$5)^Assumptions!G$7) -> 0 | G24: =+G20/((1+Assumptions!$C$5)^Assumptions!H$7) -> 0 | H24: =+H20/((1+Assumptions!$C$5)^Assumptions!I$7) -> 0 | I24: =+I20/((1+Assumptions!$C$5)^Assumptions!J$7) -> 0 | J24: =+J20/((1+Assumptions!$C$5)^Assumptions!K$7) -> 20.84727 | K24: =+K20/((1+Assumptions!$C$5)^Assumptions!L$7) -> 26.631579 | ... AA24: =+AA20/((1+Assumptions!$C$5)^Assumptions!AB$7) -> 0 | AB24: =+AF20/((1+Assumptions!$C$5)^Assumptions!AC$7) -> 0 | AC24: =+AG20/((1+Assumptions!$C$5)^Assumptions!AD$7) -> 0 | AD24: =+AH20/((1+Assumptions!$C$5)^Assumptions!AE$7) -> 0 | AE24: =+AI20/((1+Assumptions!$C$5)^Assumptions!AF$7) -> 0 | AF24: =+AJ20/((1+Assumptions!$C$5)^Assumptions!AG$7) -> 0 | AG24: =+AK20/((1+Assumptions!$C$5)^Assumptions!AH$7) -> 0 | AH24: =+AL20/((1+Assumptions!$C$5)^Assumptions!AI$7) -> 0 | AI24: =+AM20/((1+Assumptions!$C$5)^Assumptions!AJ$7) -> 0 | ... AT24: =+AX20/((1+Assumptions!$C$5)^Assumptions!AU$7) -> 0
B26: NET CASH FLOW -MEGP
B27: Project | C27: Total Sales | D27: M -9 | E27: M -6 | F27: M -3 | G27: M 0 | H27: M 3 | I27: M 6 | J27: M 9 | K27: M 12 | L27: M 15 | M27: M 18 | N27: M 21 | O27: M 24 | P27: M 27 | Q27: M 30 | R27: M 33 | S27: M 36 | T27: M 39 | U27: M 42 | V27: M 45 | W27: M 48 | X27: M 51 | Y27: M 54 | Z27: M 57 | AA27: M 60 | AB27: M 63 | AC27: M 66 | AD27: M 69 | AE27: M 72 | AF27: M 75 | AG27: M 78 | AH27: M 81 | AI27: M 84 | AJ27: M 87 | AK27: M 90 | AL27: M 93 | AM27: M 96 | AN27: M 99 | AO27: M 102 | AP27: M 105 | AQ27: M 108 | AR27: M 111 | AS27: M 114 | AT27: M 117
B28: L'avenir | C28: =SUM(D28:ZZ28) -> 595.29293 | D28: =D12-D20 -> 0 | E28: =E12-E20 -> 0 | F28: =F12-F20 -> 0 | G28: =G12-G20 -> -85 | H28: =H12-H20 -> -4.38435 | I28: =I12-I20 -> 13.7313 | J28: =J12-J20 -> 12.760825 | K28: =K12-K20 -> 16.15839 | ... AT28: =AT12-AT20 -> 0
B30: NPV NET CASH FLOW -MEGP
B31: Project | C31: Total Sales | D31: M -9 | E31: M -6 | F31: M -3 | G31: M 0 | H31: M 3 | I31: M 6 | J31: M 9 | K31: M 12 | L31: M 15 | M31: M 18 | N31: M 21 | O31: M 24 | P31: M 27 | Q31: M 30 | R31: M 33 | S31: M 36 | T31: M 39 | U31: M 42 | V31: M 45 | W31: M 48 | X31: M 51 | Y31: M 54 | Z31: M 57 | AA31: M 60 | AB31: M 63 | AC31: M 66 | AD31: M 69 | AE31: M 72 | AF31: M 75 | AG31: M 78 | AH31: M 81 | AI31: M 84 | AJ31: M 87 | AK31: M 90 | AL31: M 93 | AM31: M 96 | AN31: M 99 | AO31: M 102 | AP31: M 105 | AQ31: M 108 | AR31: M 111 | AS31: M 114 | AT31: M 117
B32: L'avenir | C32: =SUM(D32:ZZ32) -> 350.5869 | D32: =+D28/((1+Assumptions!$C$5)^Assumptions!E$7) -> 0 | E32: =+E28/((1+Assumptions!$C$5)^Assumptions!F$7) -> 0 | F32: =+F28/((1+Assumptions!$C$5)^Assumptions!G$7) -> 0 | G32: =+G28/((1+Assumptions!$C$5)^Assumptions!H$7) -> -85 | H32: =+H28/((1+Assumptions!$C$5)^Assumptions!I$7) -> -4.2430583 | I32: =+I28/((1+Assumptions!$C$5)^Assumptions!J$7) -> 12.860541 | J32: =+J28/((1+Assumptions!$C$5)^Assumptions!K$7) -> 11.566451 | K32: =+K28/((1+Assumptions!$C$5)^Assumptions!L$7) -> 14.174026 | ... AT32: =+AT28/((1+Assumptions!$C$5)^Assumptions!AU$7) -> 0
B34: NET CASH FLOW -MEGP-ACCUMULATED
B35: Project | C35: Total Sales | D35: M -9 | E35: M -6 | F35: M -3 | G35: M 0 | H35: M 3 | I35: M 6 | J35: M 9 | K35: M 12 | L35: M 15 | M35: M 18 | N35: M 21 | O35: M 24 | P35: M 27 | Q35: M 30 | R35: M 33 | S35: M 36 | T35: M 39 | U35: M 42 | V35: M 45 | W35: M 48 | X35: M 51 | Y35: M 54 | Z35: M 57 | AA35: M 60 | AB35: M 63 | AC35: M 66 | AD35: M 69 | AE35: M 72 | AF35: M 75 | AG35: M 78 | AH35: M 81 | AI35: M 84 | AJ35: M 87 | AK35: M 90 | AL35: M 93 | AM35: M 96 | AN35: M 99 | AO35: M 102 | AP35: M 105 | AQ35: M 108 | AR35: M 111 | AS35: M 114 | AT35: M 117
B36: L'avenir | C36: =AT36 -> 595.29293 | D36: =D28 -> 0 | E36: =D36+E28 -> 0 | F36: =E36+F28 -> 0 | G36: =F36+G28 -> -85 | H36: =G36+H28 -> -89.38435 | I36: =H36+I28 -> -75.65305 | J36: =I36+J28 -> -62.892225 | K36: =J36+K28 -> -46.733835 | L36: =K36+L28 -> -85.13881 | ... AT36: =AS36+AT28 -> 595.29293
B38: NPV NET CASH FLOW -MEGP-ACCUMULATED
B39: Project | C39: Total Sales | D39: M -9 | E39: M -6 | F39: M -3 | G39: M 0 | H39: M 3 | I39: M 6 | J39: M 9 | K39: M 12 | L39: M 15 | M39: M 18 | N39: M 21 | O39: M 24 | P39: M 27 | Q39: M 30 | R39: M 33 | S39: M 36 | T39: M 39 | U39: M 42 | V39: M 45 | W39: M 48 | X39: M 51 | Y39: M 54 | Z39: M 57 | AA39: M 60 | AB39: M 63 | AC39: M 66 | AD39: M 69 | AE39: M 72 | AF39: M 75 | AG39: M 78 | AH39: M 81 | AI39: M 84 | AJ39: M 87 | AK39: M 90 | AL39: M 93 | AM39: M 96 | AN39: M 99 | AO39: M 102 | AP39: M 105 | AQ39: M 108 | AR39: M 111 | AS39: M 114 | AT39: M 117
B40: L'avenir | C40: =AT40 -> 350.5869 | D40: =D32 -> 0 | E40: =D40+E32 -> 0 | F40: =E40+F32 -> 0 | G40: =F40+G32 -> -85 | H40: =G40+H32 -> -89.243058 | I40: =H40+I32 -> -76.382518 | J40: =I40+J32 -> -64.816067 | K40: =J40+K32 -> -50.64204 | L40: =K40+L32 -> -83.244955 | ... AT40: =AS40+AT32 -> 350.5869
B42: Accumulated Cash Available for Operation -MEGP
B43: Project | C43: Total Sales | D43: M -9 | E43: M -6 | F43: M -3 | G43: M 0 | H43: M 3 | I43: M 6 | J43: M 9 | K43: M 12 | L43: M 15 | M43: M 18 | N43: M 21 | O43: M 24 | P43: M 27 | Q43: M 30 | R43: M 33 | S43: M 36 | T43: M 39 | U43: M 42 | V43: M 45 | W43: M 48 | X43: M 51 | Y43: M 54 | Z43: M 57 | AA43: M 60 | AB43: M 63 | AC43: M 66 | AD43: M 69 | AE43: M 72 | AF43: M 75 | AG43: M 78 | AH43: M 81 | AI43: M 84 | AJ43: M 87 | AK43: M 90 | AL43: M 93 | AM43: M 96 | AN43: M 99 | AO43: M 102 | AP43: M 105 | AQ43: M 108 | AR43: M 111 | AS43: M 114 | AT43: M 117
B44: L'avenir | C44: =AT44 -> 1503.9764 | D44: =D12 -> 0 | E44: =D44+E12 -> 0 | F44: =E44+F12 -> 0 | G44: =F44+G12 -> -85 | H44: =G44+H12 -> -89.38435 | I44: =H44+I12 -> -75.65305 | J44: =I44+J12 -> -39.892225 | K44: =J44+K12 -> 6.626165 | L44: =K44+L12 -> 28.71371 | ... AT44: =AS44+AT12 -> 1503.9764

Sheet Net Cash Flow -Without DP
B1: Cash Available for Operation after - 20% RETAINED UNITS
B2: Total Collections MEGP
B3: Project | C3: Total Sales | D3: M -9 | E3: M -6 | F3: M -3 | G3: M 0 | H3: M 3 | I3: M 6 | J3: M 9 | K3: M 12 | L3: M 15 | M3: M 18 | N3: M 21 | O3: M 24 | P3: M 27 | Q3: M 30 | R3: M 33 | S3: M 36 | T3: M 39 | U3: M 42 | V3: M 45 | W3: M 48 | X3: M 51 | Y3: M 54 | Z3: M 57 | AA3: M 60 | AB3: M 63 | AC3: M 66 | AD3: M 69 | AE3: M 72 | AF3: M 75 | AG3: M 78 | AH3: M 81 | AI3: M 84 | AJ3: M 87 | AK3: M 90 | AL3: M 93 | AM3: M 96 | AN3: M 99 | AO3: M 102 | AP3: M 105 | AQ3: M 108 | AR3: M 111 | AS3: M 114 | AT3: M 117
B4: L'avenir | C4: =SUM(D4:ZZ4) -> 2673.7357 | D4: ='Cash In Flow Summary'!D4 -> 0 | E4: ='Cash In Flow Summary'!E4 -> 0 | F4: ='Cash In Flow Summary'!F4 -> 0 | G4: ='Cash In Flow Summary'!G4 -> 0 | H4: ='Cash In Flow Summary'!H4 -> 18.11565 | I4: ='Cash In Flow Summary'!I4 -> 36.2313 | J4: ='Cash In Flow Summary'!J4 -> 58.260825 | K4: ='Cash In Flow Summary'!K4 -> 69.01839 | ... AT4: ='Cash In Flow Summary'!AT4 -> 0
B6: ALAHLY - SABBOUR Payments MEGP
B7: Project | C7: Total Sales | D7: M -9 | E7: M -6 | F7: M -3 | G7: M 0 | H7: M 3 | I7: M 6 | J7: M 9 | K7: M 12 | L7: M 15 | M7: M 18 | N7: M 21 | O7: M 24 | P7: M 27 | Q7: M 30 | R7: M 33 | S7: M 36 | T7: M 39 | U7: M 42 | V7: M 45 | W7: M 48 | X7: M 51 | Y7: M 54 | Z7: M 57 | AA7: M 60 | AB7: M 63 | AC7: M 66 | AD7: M 69 | AE7: M 72 | AF7: M 75 | AG7: M 78 | AH7: M 81 | AI7: M 84 | AJ7: M 87 | AK7: M 90 | AL7: M 93 | AM7: M 96 | AN7: M 99 | AO7: M 102 | AP7: M 105 | AQ7: M 108 | AR7: M 111 | AS7: M 114 | AT7: M 117
B8: L'avenir | C8: =SUM(D8:ZZ8) -> 1169.7594 | D8: =Offers!$C$6/4 -> 0 | E8: =Offers!$C$6/4 -> 0 | F8: =Offers!$C$6/4 -> 0 | G8: =Offers!$C$6/4 -> 0 | H8: =Offers!$C$7/4 -> 25 | I8: =Offers!$C$7/4 -> 25 | J8: =Offers!$C$7/4 -> 25 | K8: =Offers!$C$7/4 -> 25 | L8: =Offers!$C$8/4 -> 50 | M8: =Offers!$C$8/4 -> 50 | N8: =Offers!$C$8/4 -> 50 | O8: =Offers!$C$8/4 -> 50 | P8: =Offers!$C$9/4 -> 62.5 | Q8: =Offers!$C$9/4 -> 62.5 | R8: =Offers!$C$9/4 -> 62.5 | S8: =Offers!$C$9/4 -> 62.5 | T8: =Offers!$C$10/4 -> 50 | U8: =Offers!$C$10/4 -> 50 | V8: =Offers!$C$10/4 -> 50 | W8: =Offers!$C$10/4 -> 50 | X8: =Offers!$C$11/4 -> 25 | Y8: =Offers!$C$11/4 -> 25 | Z8: =Offers!$C$11/4 -> 25 | AA8: =Offers!$C$11/4 -> 25 | AB8: =Offers!$C$12/4 -> 0 | AC8: =Offers!$C$12/4 -> 0 | AD8: =Offers!$C$12/4 -> 0 | AE8: =Offers!$C$12/4 -> 0 | AF8: =-SUM(D8:AE8)+SUM('Cash In Flow Summary'!D22:AE22)+'Cash In Flow Summary'!AF22 -> 241.19161 | AG8: ='Cash In Flow Summary'!AG22 -> 16.107226 | AH8: ='Cash In Flow Summary'!AH22 -> 14.419368 | AI8: ='Cash In Flow Summary'!AI22 -> 12.731509 | AJ8: ='Cash In Flow Summary'!AJ22 -> 10.011366 | AK8: ='Cash In Flow Summary'!AK22 -> 8.4360314 | AL8: ='Cash In Flow Summary'!AL22 -> 7.3515619 | AM8: ='Cash In Flow Summary'!AM22 -> 3.1702388 | AN8: ='Cash In Flow Summary'!AN22 -> 3.1702388 | ... AT8: ='Cash In Flow Summary'!AT22 -> 0
B10: Cash Available for Operation -MEGP
B11: Project | C11: Total Sales | D11: M -9 | E11: M -6 | F11: M -3 | G11: M 0 | H11: M 3 | I11: M 6 | J11: M 9 | K11: M 12 | L11: M 15 | M11: M 18 | N11: M 21 | O11: M 24 | P11: M 27 | Q11: M 30 | R11: M 33 | S11: M 36 | T11: M 39 | U11: M 42 | V11: M 45 | W11: M 48 | X11: M 51 | Y11: M 54 | Z11: M 57 | AA11: M 60 | AB11: M 63 | AC11: M 66 | AD11: M 69 | AE11: M 72 | AF11: M 75 | AG11: M 78 | AH11: M 81 | AI11: M 84 | AJ11: M 87 | AK11: M 90 | AL11: M 93 | AM11: M 96 | AN11: M 99 | AO11: M 102 | AP11: M 105 | AQ11: M 108 | AR11: M 111 | AS11: M 114 | AT11: M 117
B12: L'avenir | C12: =SUM(D12:ZZ12) -> 1503.9764 | D12: =D4-D8 -> 0 | E12: =E4-E8 -> 0 | F12: =F4-F8 -> 0 | G12: =G4-G8 -> 0 | H12: =H4-H8 -> -6.88435 | I12: =I4-I8 -> 11.2313 | J12: =J4-J8 -> 33.260825 | K12: =K4-K8 -> 44.01839 | ... AT12: =AT4-AT8 -> 0
B14: NPV Cash Available for Operation -MEGP
B15: Project | C15: Total Sales | D15: M -9 | E15: M -6 | F15: M -3 | G15: M 0 | H15: M 3 | I15: M 6 | J15: M 9 | K15: M 12 | L15: M 15 | M15: M 18 | N15: M 21 | O15: M 24 | P15: M 27 | Q15: M 30 | R15: M 33 | S15: M 36 | T15: M 39 | U15: M 42 | V15: M 45 | W15: M 48 | X15: M 51 | Y15: M 54 | Z15: M 57 | AA15: M 60 | AB15: M 63 | AC15: M 66 | AD15: M 69 | AE15: M 72 | AF15: M 75 | AG15: M 78 | AH15: M 81 | AI15: M 84 | AJ15: M 87 | AK15: M 90 | AL15: M 93 | AM15: M 96 | AN15: M 99 | AO15: M 102 | AP15: M 105 | AQ15: M 108 | AR15: M 111 | AS15: M 114 | AT15: M 117
B16: L'avenir | C16: =SUM(D16:ZZ16) -> 1018.7699 | D16: =+D12/((1+Assumptions!$C$5)^Assumptions!E$7) -> 0 | E16: =+E12/((1+Assumptions!$C$5)^Assumptions!F$7) -> 0 | F16: =+F12/((1+Assumptions!$C$5)^Assumptions!G$7) -> 0 | G16: =+G12/((1+Assumptions!$C$5)^Assumptions!H$7) -> 0 | H16: =+H12/((1+Assumptions!$C$5)^Assumptions!I$7) -> -6.6624924 | I16: =+I12/((1+Assumptions!$C$5)^Assumptions!J$7) -> 10.519076 | J16: =+J12/((1+Assumptions!$C$5)^Assumptions!K$7) -> 30.147713 | K16: =+K12/((1+Assumptions!$C$5)^Assumptions!L$7) -> 38.612623 | ... AT16: =+AT12/((1+Assumptions!$C$5)^Assumptions!AU$7) -> 0
B18: CASH OUT FLOW CAPEX -MEGP
B19: Project | C19: Total Sales | D19: M -9 | E19: M -6 | F19: M -3 | G19: M 0 | H19: M 3 | I19: M 6 | J19: M 9 | K19: M 12 | L19: M 15 | M19: M 18 | N19: M 21 | O19: M 24 | P19: M 27 | Q19: M 30 | R19: M 33 | S19: M 36 | T19: M 39 | U19: M 42 | V19: M 45 | W19: M 48 | X19: M 51 | Y19: M 54 | Z19: M 57 | AA19: M 60 | AB19: M 63 | AC19: M 66 | AD19: M 69 | AE19: M 72 | AF19: M 75 | AG19: M 78 | AH19: M 81 | AI19: M 84 | AJ19: M 87 | AK19: M 90 | AL19: M 93 | AM19: M 96 | AN19: M 99 | AO19: M 102 | AP19: M 105 | AQ19: M 108 | AR19: M 111 | AS19: M 114 | AT19: M 117
B20: L'avenir | C20: =SUM(H20:AAD20) -> 908.68343 | H20: =SUM('Cash Out Detail'!D37:F37)/1000000 -> 0 | I20: =SUM('Cash Out Detail'!G37:I37)/1000000 -> 0 | J20: =SUM('Cash Out Detail'!J37:L37)/1000000 -> 23 | K20: =SUM('Cash Out Detail'!M37:O37)/1000000 -> 30.36 | L20: =SUM('Cash Out Detail'!P37:R37)/1000000 -> 60.49252 | M20: =SUM('Cash Out Detail'!S37:U37)/1000000 -> 44.85252 | N20: =SUM('Cash Out Detail'!V37:X37)/1000000 -> 42.79494 | O20: =SUM('Cash Out Detail'!Y37:AA37)/1000000 -> 37.56153 | P20: =SUM('Cash Out Detail'!AB37:AD37)/1000000 -> 14.00412 | Q20: =SUM('Cash Out Detail'!AE37:AG37)/1000000 -> 13.46736 | R20: =SUM('Cash Out Detail'!AH37:AJ37)/1000000 -> 145.54446 | S20: =SUM('Cash Out Detail'!AK37:AM37)/1000000 -> 145.54446 | T20: =SUM('Cash Out Detail'!AN37:AP37)/1000000 -> 196.83032 | U20: =SUM('Cash Out Detail'!AQ37:AS37)/1000000 -> 142.78032 | V20: =SUM('Cash Out Detail'!AT37:AV37)/1000000 -> 5.72544 | W20: =SUM('Cash Out Detail'!AW37:AY37)/1000000 -> 5.72544 | X20: =SUM('Cash Out Detail'!AZ37:BB37)/1000000 -> 0 | Y20: =SUM('Cash Out Detail'!BC37:BE37)/1000000 -> 0
B22: NPV CASH OUT FLOW CAPEX -MEGP
B23: Project | C23: Total Sales | D23: M -9 | E23: M -6 | F23: M -3 | G23: M 0 | H23: M 3 | I23: M 6 | J23: M 9 | K23: M 12 | L23: M 15 | M23: M 18 | N23: M 21 | O23: M 24 | P23: M 27 | Q23: M 30 | R23: M 33 | S23: M 36 | T23: M 39 | U23: M 42 | V23: M 45 | W23: M 48 | X23: M 51 | Y23: M 54 | Z23: M 57 | AA23: M 60 | AB23: M 63 | AC23: M 66 | AD23: M 69 | AE23: M 72 | AF23: M 75 | AG23: M 78 | AH23: M 81 | AI23: M 84 | AJ23: M 87 | AK23: M 90 | AL23: M 93 | AM23: M 96 | AN23: M 99 | AO23: M 102 | AP23: M 105 | AQ23: M 108 | AR23: M 111 | AS23: M 114 | AT23: M 117
B24: L'avenir | C24: =SUM(D24:ZZ24) -> 644.2194 | D24: =+D20/((1+Assumptions!$C$5)^Assumptions!E$7) -> 0 | E24: =+E20/((1+Assumptions!$C$5)^Assumptions!F$7) -> 0 | F24: =+F20/((1+Assumptions!$C$5)^Assumptions!G$7) -> 0 | G24: =+G20/((1+Assumptions!$C$5)^Assumptions!H$7) -> 0 | H24: =+H20/((1+Assumptions!$C$5)^Assumptions!I$7) -> 0 | I24: =+I20/((1+Assumptions!$C$5)^Assumptions!J$7) -> 0 | J24: =+J20/((1+Assumptions!$C$5)^Assumptions!K$7) -> 20.84727 | K24: =+K20/((1+Assumptions!$C$5)^Assumptions!L$7) -> 26.631579 | ... AA24: =+AA20/((1+Assumptions!$C$5)^Assumptions!AB$7) -> 0 | AB24: =+AF20/((1+Assumptions!$C$5)^Assumptions!AC$7) -> 0 | AC24: =+AG20/((1+Assumptions!$C$5)^Assumptions!AD$7) -> 0 | AD24: =+AH20/((1+Assumptions!$C$5)^Assumptions!AE$7) -> 0 | AE24: =+AI20/((1+Assumptions!$C$5)^Assumptions!AF$7) -> 0 | AF24: =+AJ20/((1+Assumptions!$C$5)^Assumptions!AG$7) -> 0 | AG24: =+AK20/((1+Assumptions!$C$5)^Assumptions!AH$7) -> 0 | AH24: =+AL20/((1+Assumptions!$C$5)^Assumptions!AI$7) -> 0 | AI24: =+AM20/((1+Assumptions!$C$5)^Assumptions!AJ$7) -> 0 | ... AT24: =+AX20/((1+Assumptions!$C$5)^Assumptions!AU$7) -> 0
B26: NET CASH FLOW -MEGP
B27: Project | C27: Total Sales | D27: M -9 | E27: M -6 | F27: M -3 | G27: M 0 | H27: M 3 | I27: M 6 | J27: M 9 | K27: M 12 | L27: M 15 | M27: M 18 | N27: M 21 | O27: M 24 | P27: M 27 | Q27: M 30 | R27: M 33 | S27: M 36 | T27: M 39 | U27: M 42 | V27: M 45 | W27: M 48 | X27: M 51 | Y27: M 54 | Z27: M 57 | AA27: M 60 | AB27: M 63 | AC27: M 66 | AD27: M 69 | AE27: M 72 | AF27: M 75 | AG27: M 78 | AH27: M 81 | AI27: M 84 | AJ27: M 87 | AK27: M 90 | AL27: M 93 | AM27: M 96 | AN27: M 99 | AO27: M 102 | AP27: M 105 | AQ27: M 108 | AR27: M 111 | AS27: M 114 | AT27: M 117
B28: L'avenir | C28: =SUM(D28:ZZ28) -> 595.29293 | D28: =D12-D20 -> 0 | E28: =E12-E20 -> 0 | F28: =F12-F20 -> 0 | G28: =G12-G20 -> 0 | H28: =H12-H20 -> -6.88435 | I28: =I12-I20 -> 11.2313 | J28: =J12-J20 -> 10.260825 | K28: =K12-K20 -> 13.65839 | ... AT28: =AT12-AT20 -> 0
B30: NPV NET CASH FLOW -MEGP
B31: Project | C31: Total Sales | D31: M -9 | E31: M -6 | F31: M -3 | G31: M 0 | H31: M 3 | I31: M 6 | J31: M 9 | K31: M 12 | L31: M 15 | M31: M 18 | N31: M 21 | O31: M 24 | P31: M 27 | Q31: M 30 | R31: M 33 | S31: M 36 | T31: M 39 | U31: M 42 | V31: M 45 | W31: M 48 | X31: M 51 | Y31: M 54 | Z31: M 57 | AA31: M 60 | AB31: M 63 | AC31: M 66 | AD31: M 69 | AE31: M 72 | AF31: M 75 | AG31: M 78 | AH31: M 81 | AI31: M 84 | AJ31: M 87 | AK31: M 90 | AL31: M 93 | AM31: M 96 | AN31: M 99 | AO31: M 102 | AP31: M 105 | AQ31: M 108 | AR31: M 111 | AS31: M 114 | AT31: M 117
B32: L'avenir | C32: =SUM(D32:ZZ32) -> 374.55052 | D32: =+D28/((1+Assumptions!$C$5)^Assumptions!E$7) -> 0 | E32: =+E28/((1+Assumptions!$C$5)^Assumptions!F$7) -> 0 | F32: =+F28/((1+Assumptions!$C$5)^Assumptions!G$7) -> 0 | G32: =+G28/((1+Assumptions!$C$5)^Assumptions!H$7) -> 0 | H32: =+H28/((1+Assumptions!$C$5)^Assumptions!I$7) -> -6.6624924 | I32: =+I28/((1+Assumptions!$C$5)^Assumptions!J$7) -> 10.519076 | J32: =+J28/((1+Assumptions!$C$5)^Assumptions!K$7) -> 9.3004431 | K32: =+K28/((1+Assumptions!$C$5)^Assumptions!L$7) -> 11.981044 | ... AT32: =+AT28/((1+Assumptions!$C$5)^Assumptions!AU$7) -> 0
B34: NET CASH FLOW -MEGP-ACCUMULATED
B35: Project | C35: Total Sales | D35: M -9 | E35: M -6 | F35: M -3 | G35: M 0 | H35: M 3 | I35: M 6 | J35: M 9 | K35: M 12 | L35: M 15 | M35: M 18 | N35: M 21 | O35: M 24 | P35: M 27 | Q35: M 30 | R35: M 33 | S35: M 36 | T35: M 39 | U35: M 42 | V35: M 45 | W35: M 48 | X35: M 51 | Y35: M 54 | Z35: M 57 | AA35: M 60 | AB35: M 63 | AC35: M 66 | AD35: M 69 | AE35: M 72 | AF35: M 75 | AG35: M 78 | AH35: M 81 | AI35: M 84 | AJ35: M 87 | AK35: M 90 | AL35: M 93 | AM35: M 96 | AN35: M 99 | AO35: M 102 | AP35: M 105 | AQ35: M 108 | AR35: M 111 | AS35: M 114 | AT35: M 117
B36: L'avenir | C36: =AT36 -> 595.29293 | D36: =D28 -> 0 | E36: =D36+E28 -> 0 | F36: =E36+F28 -> 0 | G36: =F36+G28 -> 0 | H36: =G36+H28 -> -6.88435 | I36: =H36+I28 -> 4.34695 | J36: =I36+J28 -> 14.607775 | K36: =J36+K28 -> 28.266165 | L36: =K36+L28 -> -15.13881 | ... AT36: =AS36+AT28 -> 595.29293
B38: NPV NET CASH FLOW -MEGP-ACCUMULATED
B39: Project | C39: Total Sales | D39: M -9 | E39: M -6 | F39: M -3 | G39: M 0 | H39: M 3 | I39: M 6 | J39: M 9 | K39: M 12 | L39: M 15 | M39: M 18 | N39: M 21 | O39: M 24 | P39: M 27 | Q39: M 30 | R39: M 33 | S39: M 36 | T39: M 39 | U39: M 42 | V39: M 45 | W39: M 48 | X39: M 51 | Y39: M 54 | Z39: M 57 | AA39: M 60 | AB39: M 63 | AC39: M 66 | AD39: M 69 | AE39: M 72 | AF39: M 75 | AG39: M 78 | AH39: M 81 | AI39: M 84 | AJ39: M 87 | AK39: M 90 | AL39: M 93 | AM39: M 96 | AN39: M 99 | AO39: M 102 | AP39: M 105 | AQ39: M 108 | AR39: M 111 | AS39: M 114 | AT39: M 117
B40: L'avenir | C40: =AT40 -> 374.55052 | D40: =D32 -> 0 | E40: =D40+E32 -> 0 | F40: =E40+F32 -> 0 | G40: =F40+G32 -> 0 | H40: =G40+H32 -> -6.6624924 | I40: =H40+I32 -> 3.8565838 | J40: =I40+J32 -> 13.157027 | K40: =J40+K32 -> 25.138071 | L40: =K40+L32 -> -11.709465 | ... AT40: =AS40+AT32 -> 374.55052
B42: Accumulated Cash Available for Operation -MEGP
B43: Project | C43: Total Sales | D43: M -9 | E43: M -6 | F43: M -3 | G43: M 0 | H43: M 3 | I43: M 6 | J43: M 9 | K43: M 12 | L43: M 15 | M43: M 18 | N43: M 21 | O43: M 24 | P43: M 27 | Q43: M 30 | R43: M 33 | S43: M 36 | T43: M 39 | U43: M 42 | V43: M 45 | W43: M 48 | X43: M 51 | Y43: M 54 | Z43: M 57 | AA43: M 60 | AB43: M 63 | AC43: M 66 | AD43: M 69 | AE43: M 72 | AF43: M 75 | AG43: M 78 | AH43: M 81 | AI43: M 84 | AJ43: M 87 | AK43: M 90 | AL43: M 93 | AM43: M 96 | AN43: M 99 | AO43: M 102 | AP43: M 105 | AQ43: M 108 | AR43: M 111 | AS43: M 114 | AT43: M 117
B44: L'avenir | C44: =AT44 -> 1503.9764 | D44: =D12 -> 0 | E44: =D44+E12 -> 0 | F44: =E44+F12 -> 0 | G44: =F44+G12 -> 0 | H44: =G44+H12 -> -6.88435 | I44: =H44+I12 -> 4.34695 | J44: =I44+J12 -> 37.607775 | K44: =J44+K12 -> 81.626165 | L44: =K44+L12 -> 98.71371 | ... AT44: =AS44+AT12 -> 1503.9764
