Workbook

Sheet Cover
A1: Green Square - Financial Annex
A2: Investor ticket EGP 100 million | Strictly private and confidential | Projections only, not guarantees
A4: ALL INFORMATION IN THIS WORKBOOK IS CONFIDENTIAL AND SUBJECT TO THE NON-DISCLOSURE AGREEMENT. Do not copy, forward or disclose it.
A5: Purpose: supports the Investment Memorandum, Pitch Deck and Due Diligence Memorandum. Every figure in those documents traces to the Summary sheet.
A6: Colour code: blue = input or value transcribed from the source model; black = formula; green = link to another sheet.
A7: Units: EGP million unless stated. Quarter-end months. NPV at 14% p.a. (end-of-quarter discounting). IRRs are annualised from quarterly flows.
A8: Sheets: Inputs, Source_Data, Project_CF, Sources_Uses, Option_A, Option_B, Scenarios, Sensitivity, Summary, Reconciliation.
A9: The balance of project funding is provided by Jalour sponsor equity, project collections and other capital sources.
A10: Jalour may raise further capital at project or holding level, subject to the investor's stated rights.
A11: Reconciliation status: | B11: =Reconciliation!D25 -> ALL CHECKS ZERO

Sheet Summary
A1: Green Square: key outputs, ticket EGP 100m (all cells are live links)
A2: USD equivalents at 48 EGP per USD.
A4: Metric | B4: Value | C4: USD m | D4: Source sheet
A5: Project (base case)
A6: Jalour net cash flow, nominal (EGP m) | B6: =Project_CF!$B$18 -> 375.44753 | C6: =B6/Inputs!$B$52 -> 7.8218235 | D6: Project_CF
A7: NPV of net cash flow @ 14% (EGP m) | B7: =Project_CF!$B$19 -> 215.31139 | C7: =B7/Inputs!$B$52 -> 4.485654 | D7: Project_CF
A8: Peak cumulative cash shortage (EGP m) | B8: =-Project_CF!$B$20 -> 102.5 | C8: =B8/Inputs!$B$52 -> 2.1354167 | D8: Project_CF
A9: Month of peak shortage | B9: =Project_CF!$B$21 -> 6 | D9: Project_CF
A10: Total collections, 80% of units sold (EGP m) | B10: =Project_CF!$C$8 -> 2252.979 | C10: =B10/Inputs!$B$52 -> 46.937063 | D10: Project_CF
A11: Landlord payments (EGP m) | B11: =Project_CF!$C$9 -> 985.67831 | D11: Project_CF
A12: Construction, commission and SG&A (EGP m) | B12: =Project_CF!$C$10+Project_CF!$C$11+Project_CF!$C$12 -> 891.85316 | D12: Project_CF
A13: Funding plan
A14: Total uses at peak (EGP m) | B14: =Sources_Uses!B8 -> 112.9574 | C14: =B14/Inputs!$B$52 -> 2.3532792 | D14: Sources_Uses
A15: Balance of project funding (EGP m) | B15: =Sources_Uses!B13 -> 12.9574 | D15: Sources_Uses
A16: Ticket in excess of modelled uses (EGP m) | B16: =Sources_Uses!B15 -> 0 | D16: Sources_Uses
A17: Ticket as % of modelled peak | B17: =Sources_Uses!B16 -> 0.97560976 | D17: Sources_Uses
A18: Ticket above modelled peak (EGP m) | B18: =Sources_Uses!B18 -> 0 | D18: Sources_Uses
A19: Option A (units)
A20: Units face value at launch list (EGP m) | B20: =Option_A!B5 -> 200 | C20: =B20/Inputs!$B$52 -> 4.1666667 | D20: Option_A
A21: Share of launch-tranche inventory | B21: =Option_A!B6 -> 0.33026762 | D21: Option_A
A22: Units value at final list price (EGP m) | B22: =Option_A!B11 -> 286.73835 | D22: Option_A
A23: Investor IRR, base | B23: =Option_A!B26 -> 0.26402991 | D23: Option_A
A24: Investor MOIC, base | B24: =Option_A!B27 -> 2.781362 | D24: Option_A
A25: Investor payback month | B25: =Option_A!B28 -> 54 | D25: Option_A
A26: Investor IRR, downside | B26: =Scenarios!$B$66 -> 0.18640161 | D26: Scenarios
A27: Investor MOIC, downside | B27: =Scenarios!$B$67 -> 2.5032258 | D27: Scenarios
A28: Investor IRR, upside | B28: =Scenarios!$B$102 -> 0.29199284 | D28: Scenarios
A29: Investor MOIC, upside | B29: =Scenarios!$B$103 -> 3.0594982 | D29: Scenarios
A30: Jalour cost of capital | B30: =Option_A!B29 -> 0.20741957 | D30: Option_A
A31: NPV cost to Jalour @ 14% (EGP m) | B31: =Option_A!B30 -> -19.093021 | D31: Option_A
A32: Nominal net cost to Jalour (EGP m) | B32: =Option_A!B31 -> -92 | D32: Option_A
A33: Option B (cash), recommended structure S1
A34: Investor IRR, base | B34: =Option_B!B34 -> 0.26546399 | D34: Option_B
A35: Investor MOIC | B35: =Option_B!B33 -> 2.3 | D35: Option_B
A36: Investor payback month | B36: =Option_B!B46 -> 45 | D36: Option_B
A37: Jalour cost of capital | B37: =Option_B!B35 -> 0.26546399 | D37: Option_B
A38: NPV cost to Jalour @ 14% (EGP m) | B38: =Option_B!B36 -> -42.536579 | D38: Option_B
A39: Lowest quarterly coverage (net cash flow / payout) | B39: =Option_B!B37 -> -8.9504782 | D39: Option_B
A40: Quarters below 1.5x (net cash flow basis) | B40: =Option_B!B38 -> 9 | D40: Option_B
A41: Payout quarters | B41: =Option_B!B39 -> 12 | D41: Option_B
A42: Lowest coverage (cash available / payout) | B42: =Option_B!B40 -> 2.9584222 | D42: Option_B
A43: Quarters below 1.5x (cash available basis) | B43: =Option_B!B41 -> 0 | D43: Option_B
A44: Lowest pooled cash after ticket and payouts (EGP m) | B44: =Option_B!B42 -> -2.5 | D44: Option_B
A45: Investor IRR if S2 (alternative) | B45: =Option_B!C34 -> 0.29027663 | D45: Option_B
A46: Investor IRR if S3 (alternative) | B46: =Option_B!D34 -> 0.27835276 | D46: Option_B
A47: Scenario results: peak cumulative shortage / NPV / Option B lowest pooled cash (EGP m)
A48: Base case | B48: =-Scenarios!$B$28 -> 102.5 | C48: =Scenarios!$B$27 -> 215.31139 | D48: =Scenarios!$B$33 -> -2.5
A49: Downside: sales +12 months, prices -10% | B49: =-Scenarios!$B$64 -> 441.19461 | C49: =Scenarios!$B$63 -> -33.594685 | D49: =Scenarios!$B$69 -> -417.86128
A50: Upside: prices +10% | B50: =-Scenarios!$B$100 -> 102.5 | C50: =Scenarios!$B$99 -> 314.58159 | D50: =Scenarios!$B$105 -> -2.5
A51: Construction cost +10% | B51: =-Scenarios!$B$136 -> 102.5 | C51: =Scenarios!$B$135 -> 162.34568 | D51: =Scenarios!$B$141 -> -42.636974
A52: Collections slip 2 quarters | B52: =-Scenarios!$B$172 -> 235.69078 | C52: =Scenarios!$B$171 -> 125.46422 | D52: =Scenarios!$B$177 -> -154.85745
A53: Delivery payments at handover | B53: =-Scenarios!$B$208 -> 269.19792 | C53: =Scenarios!$B$207 -> 155.32932 | D53: =Scenarios!$B$213 -> -284.19792
A54: Handover payments and downside combined | B54: =-Scenarios!$B$244 -> 729.38647 | C54: =Scenarios!$B$243 -> -80.948949 | D54: =Scenarios!$B$249 -> -763.7132
A55: (columns: peak shortage | NPV | Option B lowest pooled cash)
A56: Sensitivities: NPV (EGP m) and peak shortage (EGP m)
A57: price 0.8 | B57: =-Sensitivity!$B$28 -> 183.65099 | C57: =Sensitivity!$B$27 -> 12.57309 | D57: =Sensitivity!$B$30 -> 0.20094658
A58: price 0.9 | B58: =-Sensitivity!$B$64 -> 114.44061 | C58: =Sensitivity!$B$63 -> 116.04119 | D58: =Sensitivity!$B$66 -> 0.23383437
A59: price 1.1 | B59: =-Sensitivity!$B$100 -> 102.5 | C59: =Sensitivity!$B$99 -> 314.58159 | D59: =Sensitivity!$B$102 -> 0.29199284
A60: price 1.2 | B60: =-Sensitivity!$B$136 -> 102.5 | C60: =Sensitivity!$B$135 -> 413.85179 | D60: =Sensitivity!$B$138 -> 0.31807065
A61: delay 2 | B61: =-Sensitivity!$B$172 -> 216.64826 | C61: =Sensitivity!$B$171 -> 129.45819 | D61: =Sensitivity!$B$174 -> 0.23390984
A62: delay 4 | B62: =-Sensitivity!$B$208 -> 408.48468 | C62: =Sensitivity!$B$207 -> 49.049307 | D62: =Sensitivity!$B$210 -> 0.20994926
A63: delay 6 | B63: =-Sensitivity!$B$244 -> 825.08468 | C63: =Sensitivity!$B$243 -> -26.260516 | D63: =Sensitivity!$B$246 -> 0.19043592
A64: delay 8 | B64: =-Sensitivity!$B$280 -> 1075.4423 | C64: =Sensitivity!$B$279 -> -96.794627 | D64: =Sensitivity!$B$282 -> 0.17423789
A65: cost 1.1 | B65: =-Sensitivity!$B$316 -> 102.5 | C65: =Sensitivity!$B$315 -> 162.34568 | D65: =Sensitivity!$B$318 -> 0.26402991
A66: cost 1.2 | B66: =-Sensitivity!$B$352 -> 114.37226 | C66: =Sensitivity!$B$351 -> 109.37997 | D66: =Sensitivity!$B$354 -> 0.26402991
A67: slip 1 | B67: =-Sensitivity!$B$388 -> 162.05952 | C67: =Sensitivity!$B$387 -> 169.65209 | D67: =Sensitivity!$B$390 -> 0.26402991
A68: slip 2 | B68: =-Sensitivity!$B$424 -> 235.69078 | C68: =Sensitivity!$B$423 -> 125.46422 | D68: =Sensitivity!$B$426 -> 0.26402991
A69: slip 4 | B69: =-Sensitivity!$B$460 -> 439.682 | C69: =Sensitivity!$B$459 -> 41.314632 | D69: =Sensitivity!$B$462 -> 0.26402991

Sheet Inputs
A1: Inputs - Green Square, ticket EGP 100m (EGP million unless stated)
A2: Blue = input. Series from the source model are on Source_Data. Every figure traces to a source cell or is labelled ASSUMPTION.
A4: Parameter | B4: Value | C4: Unit | D4: Source / basis
A6: Transaction
A7: Investor ticket | B7: 100 | C7: EGP m | D7: Offer term
A8: Option A: face value multiple of ticket (units at launch list price) | B8: 2 | C8: x | D8: Offer term (Option A)
A9: Option B: total cash return multiple | B9: 2.3 | C9: x | D9: Offer term (Option B)
A10: Option B: grace period | B10: 24 | C10: months | D10: Offer term
A11: Option B: number of quarterly payouts | B11: 12 | C11: quarters | D11: Offer term (3 years)
A12: Investor funding month (t0) | B12: 3 | C12: month | D12: ASSUMPTION: month the down payment falls due in the model ('Net Cash Flow -With DP' row 10)
A13: Project handover month | B13: 48 | C13: month | D13: Source model, Green Square Summary!E4
A14: Discount rate | B14: 0.14 | C14: % p.a. | D14: Source model, sales sheet cell C72 (labelled Cost Of Capital); kept at 14% by Jalour
A15: Option A: investor resale friction | B15: 0.03 | C15: % | D15: ASSUMPTION: broker plus developer transfer fee
A16: Option A: resale spread (quarters from handover + 3 months) | B16: 4 | C16: quarters | D16: ASSUMPTION
A18: Project and landlord terms (source model)
A19: Landlord share of collections | B19: 0.35 | C19: % | D19: Offers DP!C5
A20: Landlord minimum guarantee | B20: 800 | C20: EGP m | D20: Offers DP!C3
A21: Down payment to landlord (10% of guarantee) | B21: 80 | C21: EGP m | D21: Offers DP!C9
A22: Total sales value at 100% of units | B22: 2816.2238 | C22: EGP m | D22: Summary C27 (sold 80% plus retained 20% at modelled prices)
A23: Sales commission rate | B23: 0.04 | C23: % | D23: Summary B19
A24: Professional fees (% of construction cost) | B24: 0.05 | C24: % | D24: Cash Out Detail!C49
A25: Share of professional fees incurred before construction start | B25: 0.3 | C25: % | D25: ASSUMPTION: the model has no pre-construction cost; to be confirmed
A27: Launch price list and tranche values (source model sales sheet)
A28: Launch list price, retail | B28: 225 | C28: EGP k / m2 | D28: First sales column, row 3
A29: Launch list price, offices | B29: 135 | C29: EGP k / m2 | D29: First sales column, row 4
A30: Delivery list price, retail (last list price in the plan) | B30: 300 | C30: EGP k / m2 | D30: Last sales column, row 3
A31: Delivery list price, offices (last list price in the plan) | B31: 200 | C31: EGP k / m2 | D31: Last sales column, row 4
A32: Launch tranches: retail sales value at list | B32: 195.345 | C32: EGP m | D32: First two sales tranches (months 9 and 12), row 24
A33: Launch tranches: office sales value at list | B33: 410.2245 | C33: EGP m | D33: Same tranches, row 25
A34: Price appreciation launch to delivery list (value-weighted) | B34: =($B$32/($B$32+$B$33))*($B$30/$B$28)+($B$33/($B$32+$B$33))*($B$31/$B$29) -> 1.4336918 | C34: x | D34: Calculated. Investor resale value = face x this factor (base)
A36: Option B alternatives (considered, not recommended)
A37: S2: share of collections | B37: 0.24724933 | C37: % | D37: Calibrated (Python) so the base case reaches the target multiple by the end of the payout window
A38: S2: floor per quarter as multiple of equal instalment | B38: 0.4 | C38: x | D38: Design
A39: S2: cap per quarter as multiple of equal instalment | B39: 1.5 | C39: x | D39: Design
A40: S3: fixed minimum multiple | B40: 1.8 | C40: x | D40: Design
A41: S3: total cap multiple | B41: 2.8 | C41: x | D41: Design
A42: S3: share of collections | B42: 0.034752087 | C42: % | D42: Calibrated (Python)
A43: Coverage test threshold | B43: 1.5 | C43: x | D43: Brief
A45: Reference values from the source model (for reconciliation only)
A46: Jalour net cash flow, nominal | B46: 375.44753 | C46: EGP m | D46: 'Net Cash Flow -With DP'!C40
A47: NPV of net cash flow with down payment | B47: 215.31139 | C47: EGP m | D47: Summary!D9
A48: Peak cumulative cash shortage | B48: -102.5 | C48: EGP m | D48: Green Square Summary!E7
A49: Total collections (80% of units sold) | B49: 2252.979 | C49: EGP m | D49: 'Net Cash Flow -With DP'!C4
A50: Total landlord payments | B50: 985.67831 | C50: EGP m | D50: 'Net Cash Flow -With DP'!C10
A51: Total construction, commission and SG&A | B51: 891.85316 | C51: EGP m | D51: 'Net Cash Flow -With DP'!C28
A52: USD exchange rate (executive summary only) | B52: 48 | C52: EGP per USD | D52: Brief / model
A54: First payout month | B54: =Inputs!$B$12+Inputs!$B$10+3 -> 30 | C54: month | D54: Calculated: funding month + grace + 3
A55: Launch tranche face capacity (value at launch list) | B55: =Inputs!$B$32+Inputs!$B$33 -> 605.5695 | C55: EGP m | D55: Calculated: retail plus office value of the launch tranches

Sheet Source_Data
A1: Source model series - Green Square (EGP million, quarter-end months)
A2: Blue = values transcribed from the source model cells named in column B. Columns D onward = quarters 1..60 (month = 3 x quarter).
A4: Series | B4: Source cell / basis | C4: Total
A5: Quarter index | B5: structural | D5: 1 | E5: 2 | F5: 3 | G5: 4 | H5: 5 | I5: 6 | J5: 7 | K5: 8 | L5: 9 | M5: 10 | N5: 11 | O5: 12 | P5: 13 | Q5: 14 | R5: 15 | S5: 16 | T5: 17 | U5: 18 | V5: 19 | W5: 20 | X5: 21 | Y5: 22 | Z5: 23 | AA5: 24 | AB5: 25 | AC5: 26 | AD5: 27 | AE5: 28 | AF5: 29 | AG5: 30 | AH5: 31 | AI5: 32 | AJ5: 33 | AK5: 34 | AL5: 35 | AM5: 36 | AN5: 37 | AO5: 38 | AP5: 39 | AQ5: 40 | AR5: 41 | AS5: 42 | AT5: 43 | AU5: 44 | AV5: 45 | AW5: 46 | AX5: 47 | AY5: 48 | AZ5: 49 | BA5: 50 | BB5: 51 | BC5: 52 | BD5: 53 | BE5: 54 | BF5: 55 | BG5: 56 | BH5: 57 | BI5: 58 | BJ5: 59 | BK5: 60
A6: Month | B6: 3 x index | D6: =D5*3 -> 3 | E6: =E5*3 -> 6 | F6: =F5*3 -> 9 | G6: =G5*3 -> 12 | H6: =H5*3 -> 15 | I6: =I5*3 -> 18 | J6: =J5*3 -> 21 | K6: =K5*3 -> 24 | ... BK6: =BK5*3 -> 180
A7: Collections excluding delivery payments | B7: Net Cash Flow -With DP row 4 less delivery component | C7: =SUM(D7:BK7) -> 1761.2884 | D7: 0 | E7: 0 | F7: 15.139238 | G7: 30.278475 | H7: 46.512006 | I7: 62.745537 | J7: 62.3657 | K7: 63.473559 | L7: 80.328848 | M7: 103.04449 | N7: 127.69775 | O7: 134.93275 | P7: 97.31075 | Q7: 71.309969 | R7: 71.309969 | S7: 68.037036 | T7: 61.22664 | U7: 59.712716 | V7: 53.723945 | W7: 49.382945 | X7: 49.382945 | Y7: 42.102726 | Z7: 42.102726 | AA7: 42.102726 | AB7: 36.314726 | AC7: 33.038627 | AD7: 29.430171 | AE7: 25.089171 | AF7: 25.089171 | AG7: 25.089171 | AH7: 25.089171 | AI7: 25.089171 | AJ7: 25.089171 | AK7: 22.905106 | AL7: 22.905106 | AM7: 18.739554 | AN7: 9.6261675 | AO7: 3.5704725 | AP7: 0 | AQ7: 0 | AR7: 0 | AS7: 0 | AT7: 0 | AU7: 0 | AV7: 0 | AW7: 0 | AX7: 0 | AY7: 0 | AZ7: 0 | BA7: 0 | BB7: 0 | BC7: 0 | BD7: 0 | BE7: 0 | BF7: 0 | BG7: 0 | BH7: 0 | BI7: 0 | BJ7: 0 | BK7: 0
A8: Delivery payments (within collections) | B8: Green Square sheet rows 35-36 | C8: =SUM(D8:BK8) -> 491.6906 | D8: 0 | E8: 0 | F8: 0 | G8: 0 | H8: 0 | I8: 0 | J8: 0 | K8: 0 | L8: 0 | M8: 392.20935 | N8: 57.88 | O8: 41.60125 | P8: 0 | Q8: 0 | R8: 0 | S8: 0 | T8: 0 | U8: 0 | V8: 0 | W8: 0 | X8: 0 | Y8: 0 | Z8: 0 | AA8: 0 | AB8: 0 | AC8: 0 | AD8: 0 | AE8: 0 | AF8: 0 | AG8: 0 | AH8: 0 | AI8: 0 | AJ8: 0 | AK8: 0 | AL8: 0 | AM8: 0 | AN8: 0 | AO8: 0 | AP8: 0 | AQ8: 0 | AR8: 0 | AS8: 0 | AT8: 0 | AU8: 0 | AV8: 0 | AW8: 0 | AX8: 0 | AY8: 0 | AZ8: 0 | BA8: 0 | BB8: 0 | BC8: 0 | BD8: 0 | BE8: 0 | BF8: 0 | BG8: 0 | BH8: 0 | BI8: 0 | BJ8: 0 | BK8: 0
A9: Landlord payments: down payment and guarantee schedule | B9: Net Cash Flow -With DP row 10, schedule part | C9: =SUM(D9:BK9) -> 800 | D9: 91.25 | E9: 11.25 | F9: 11.25 | G9: 11.25 | H9: 22.5 | I9: 22.5 | J9: 22.5 | K9: 22.5 | L9: 33.75 | M9: 33.75 | N9: 33.75 | O9: 33.75 | P9: 45 | Q9: 45 | R9: 45 | S9: 45 | T9: 45 | U9: 45 | V9: 45 | W9: 45 | X9: 22.5 | Y9: 22.5 | Z9: 22.5 | AA9: 22.5 | AB9: 0 | AC9: 0 | AD9: 0 | AE9: 0 | AF9: 0 | AG9: 0 | AH9: 0 | AI9: 0 | AJ9: 0 | AK9: 0 | AL9: 0 | AM9: 0 | AN9: 0 | AO9: 0 | AP9: 0 | AQ9: 0 | AR9: 0 | AS9: 0 | AT9: 0 | AU9: 0 | AV9: 0 | AW9: 0 | AX9: 0 | AY9: 0 | AZ9: 0 | BA9: 0 | BB9: 0 | BC9: 0 | BD9: 0 | BE9: 0 | BF9: 0 | BG9: 0 | BH9: 0 | BI9: 0 | BJ9: 0 | BK9: 0
A10: Landlord payments: excess over guarantee (years 8+) | B10: Same row, excess settlement | C10: =SUM(D10:BK10) -> 185.67831 | D10: 0 | E10: 0 | F10: 0 | G10: 0 | H10: 0 | I10: 0 | J10: 0 | K10: 0 | L10: 0 | M10: 0 | N10: 0 | O10: 0 | P10: 0 | Q10: 0 | R10: 0 | S10: 0 | T10: 0 | U10: 0 | V10: 0 | W10: 0 | X10: 0 | Y10: 0 | Z10: 0 | AA10: 0 | AB10: 0 | AC10: 0 | AD10: 0 | AE10: 0 | AF10: 107.75821 | AG10: 10.976512 | AH10: 10.976512 | AI10: 10.976512 | AJ10: 10.976512 | AK10: 10.020984 | AL10: 10.020984 | AM10: 8.198555 | AN10: 4.2114483 | AO10: 1.5620817 | AP10: 0 | AQ10: 0 | AR10: 0 | AS10: 0 | AT10: 0 | AU10: 0 | AV10: 0 | AW10: 0 | AX10: 0 | AY10: 0 | AZ10: 0 | BA10: 0 | BB10: 0 | BC10: 0 | BD10: 0 | BE10: 0 | BF10: 0 | BG10: 0 | BH10: 0 | BI10: 0 | BJ10: 0 | BK10: 0
A11: Construction cost | B11: Cash Out Detail row 28 | C11: =SUM(D11:BK11) -> 697.16 | D11: 0 | E11: 0 | F11: 0 | G11: 0 | H11: 20 | I11: 26.4 | J11: 40 | K11: 26.4 | L11: 26.4 | M11: 26.4 | N11: 5.28 | O11: 5.28 | P11: 120 | Q11: 120 | R11: 164 | S11: 117 | T11: 0 | U11: 0 | V11: 0 | W11: 0 | X11: 0 | Y11: 0 | Z11: 0 | AA11: 0 | AB11: 0 | AC11: 0 | AD11: 0 | AE11: 0 | AF11: 0 | AG11: 0 | AH11: 0 | AI11: 0 | AJ11: 0 | AK11: 0 | AL11: 0 | AM11: 0 | AN11: 0 | AO11: 0 | AP11: 0 | AQ11: 0 | AR11: 0 | AS11: 0 | AT11: 0 | AU11: 0 | AV11: 0 | AW11: 0 | AX11: 0 | AY11: 0 | AZ11: 0 | BA11: 0 | BB11: 0 | BC11: 0 | BD11: 0 | BE11: 0 | BF11: 0 | BG11: 0 | BH11: 0 | BI11: 0 | BJ11: 0 | BK11: 0
A12: Sales commission | B12: Cash Out Detail row 33 | C12: =SUM(D12:BK12) -> 90.11916 | D12: 0 | E12: 0 | F12: 0 | G12: 0 | H12: 0 | I12: 0 | J12: 12.11139 | K12: 12.11139 | L12: 9.52126 | M12: 9.52126 | N12: 6.98901 | O12: 6.98901 | P12: 7.69804 | Q12: 9.2608 | R12: 9.2608 | S12: 6.6562 | T12: 0 | U12: 0 | V12: 0 | W12: 0 | X12: 0 | Y12: 0 | Z12: 0 | AA12: 0 | AB12: 0 | AC12: 0 | AD12: 0 | AE12: 0 | AF12: 0 | AG12: 0 | AH12: 0 | AI12: 0 | AJ12: 0 | AK12: 0 | AL12: 0 | AM12: 0 | AN12: 0 | AO12: 0 | AP12: 0 | AQ12: 0 | AR12: 0 | AS12: 0 | AT12: 0 | AU12: 0 | AV12: 0 | AW12: 0 | AX12: 0 | AY12: 0 | AZ12: 0 | BA12: 0 | BB12: 0 | BC12: 0 | BD12: 0 | BE12: 0 | BF12: 0 | BG12: 0 | BH12: 0 | BI12: 0 | BJ12: 0 | BK12: 0
A13: SG&A and others (15% of construction) | B13: Cash Out Detail row 38 | C13: =SUM(D13:BK13) -> 104.574 | D13: 0 | E13: 0 | F13: 0 | G13: 0 | H13: 3 | I13: 3.96 | J13: 6 | K13: 3.96 | L13: 3.96 | M13: 3.96 | N13: 0.792 | O13: 0.792 | P13: 18 | Q13: 18 | R13: 24.6 | S13: 17.55 | T13: 0 | U13: 0 | V13: 0 | W13: 0 | X13: 0 | Y13: 0 | Z13: 0 | AA13: 0 | AB13: 0 | AC13: 0 | AD13: 0 | AE13: 0 | AF13: 0 | AG13: 0 | AH13: 0 | AI13: 0 | AJ13: 0 | AK13: 0 | AL13: 0 | AM13: 0 | AN13: 0 | AO13: 0 | AP13: 0 | AQ13: 0 | AR13: 0 | AS13: 0 | AT13: 0 | AU13: 0 | AV13: 0 | AW13: 0 | AX13: 0 | AY13: 0 | AZ13: 0 | BA13: 0 | BB13: 0 | BC13: 0 | BD13: 0 | BE13: 0 | BF13: 0 | BG13: 0 | BH13: 0 | BI13: 0 | BJ13: 0 | BK13: 0
A14: Launch tranches: collections, retail and offices | B14: Green Square sheet rows 31-36, 38-69 for the first two sales tranches | C14: =SUM(D14:BK14) -> 605.5695 | D14: 0 | E14: 0 | F14: 15.139238 | G14: 30.278475 | H14: 22.708856 | I14: 15.139238 | J14: 15.139238 | K14: 15.139238 | L14: 15.139238 | M14: 136.25314 | N14: 15.139238 | O14: 15.139238 | P14: 15.139238 | Q14: 15.139238 | R14: 15.139238 | S14: 15.139238 | T14: 13.625314 | U14: 12.11139 | V14: 12.11139 | W14: 12.11139 | X14: 12.11139 | Y14: 12.11139 | Z14: 12.11139 | AA14: 12.11139 | AB14: 12.11139 | AC14: 12.11139 | AD14: 12.11139 | AE14: 12.11139 | AF14: 12.11139 | AG14: 12.11139 | AH14: 12.11139 | AI14: 12.11139 | AJ14: 12.11139 | AK14: 12.11139 | AL14: 12.11139 | AM14: 12.11139 | AN14: 6.055695 | AO14: 0 | AP14: 0 | AQ14: 0 | AR14: 0 | AS14: 0 | AT14: 0 | AU14: 0 | AV14: 0 | AW14: 0 | AX14: 0 | AY14: 0 | AZ14: 0 | BA14: 0 | BB14: 0 | BC14: 0 | BD14: 0 | BE14: 0 | BF14: 0 | BG14: 0 | BH14: 0 | BI14: 0 | BJ14: 0 | BK14: 0
A15: Launch tranches: collections, retail | B15: same, commercial rows | C15: =SUM(D15:BK15) -> 195.345 | D15: 0 | E15: 0 | F15: 4.883625 | G15: 9.76725 | H15: 7.3254375 | I15: 4.883625 | J15: 4.883625 | K15: 4.883625 | L15: 4.883625 | M15: 43.952625 | N15: 4.883625 | O15: 4.883625 | P15: 4.883625 | Q15: 4.883625 | R15: 4.883625 | S15: 4.883625 | T15: 4.3952625 | U15: 3.9069 | V15: 3.9069 | W15: 3.9069 | X15: 3.9069 | Y15: 3.9069 | Z15: 3.9069 | AA15: 3.9069 | AB15: 3.9069 | AC15: 3.9069 | AD15: 3.9069 | AE15: 3.9069 | AF15: 3.9069 | AG15: 3.9069 | AH15: 3.9069 | AI15: 3.9069 | AJ15: 3.9069 | AK15: 3.9069 | AL15: 3.9069 | AM15: 3.9069 | AN15: 1.95345 | AO15: 0 | AP15: 0 | AQ15: 0 | AR15: 0 | AS15: 0 | AT15: 0 | AU15: 0 | AV15: 0 | AW15: 0 | AX15: 0 | AY15: 0 | AZ15: 0 | BA15: 0 | BB15: 0 | BC15: 0 | BD15: 0 | BE15: 0 | BF15: 0 | BG15: 0 | BH15: 0 | BI15: 0 | BJ15: 0 | BK15: 0
A16: Launch tranches: collections, offices | B16: same, admin rows | C16: =SUM(D16:BK16) -> 410.2245 | D16: 0 | E16: 0 | F16: 10.255612 | G16: 20.511225 | H16: 15.383419 | I16: 10.255612 | J16: 10.255612 | K16: 10.255612 | L16: 10.255612 | M16: 92.300512 | N16: 10.255612 | O16: 10.255612 | P16: 10.255612 | Q16: 10.255612 | R16: 10.255612 | S16: 10.255612 | T16: 9.2300513 | U16: 8.20449 | V16: 8.20449 | W16: 8.20449 | X16: 8.20449 | Y16: 8.20449 | Z16: 8.20449 | AA16: 8.20449 | AB16: 8.20449 | AC16: 8.20449 | AD16: 8.20449 | AE16: 8.20449 | AF16: 8.20449 | AG16: 8.20449 | AH16: 8.20449 | AI16: 8.20449 | AJ16: 8.20449 | AK16: 8.20449 | AL16: 8.20449 | AM16: 8.20449 | AN16: 4.102245 | AO16: 0 | AP16: 0 | AQ16: 0 | AR16: 0 | AS16: 0 | AT16: 0 | AU16: 0 | AV16: 0 | AW16: 0 | AX16: 0 | AY16: 0 | AZ16: 0 | BA16: 0 | BB16: 0 | BC16: 0 | BD16: 0 | BE16: 0 | BF16: 0 | BG16: 0 | BH16: 0 | BI16: 0 | BJ16: 0 | BK16: 0
A17: Launch tranches: sales value at the quarter commission is paid (12 months after sale) | B17: Cash Out Detail row 33 timing | C17: =SUM(D17:BK17) -> 605.5695 | D17: 0 | E17: 0 | F17: 0 | G17: 0 | H17: 0 | I17: 0 | J17: 302.78475 | K17: 302.78475 | L17: 0 | M17: 0 | N17: 0 | O17: 0 | P17: 0 | Q17: 0 | R17: 0 | S17: 0 | T17: 0 | U17: 0 | V17: 0 | W17: 0 | X17: 0 | Y17: 0 | Z17: 0 | AA17: 0 | AB17: 0 | AC17: 0 | AD17: 0 | AE17: 0 | AF17: 0 | AG17: 0 | AH17: 0 | AI17: 0 | AJ17: 0 | AK17: 0 | AL17: 0 | AM17: 0 | AN17: 0 | AO17: 0 | AP17: 0 | AQ17: 0 | AR17: 0 | AS17: 0 | AT17: 0 | AU17: 0 | AV17: 0 | AW17: 0 | AX17: 0 | AY17: 0 | AZ17: 0 | BA17: 0 | BB17: 0 | BC17: 0 | BD17: 0 | BE17: 0 | BF17: 0 | BG17: 0 | BH17: 0 | BI17: 0 | BJ17: 0 | BK17: 0

Sheet Project_CF
A1: Green Square: project cash flow to Jalour, base case (quarterly, as per the source model)
A2: Net cash flow = collections less landlord payments, construction, commission and SG&A. Positive = cash in.
A4: Line (EGP m) | B4: Unit | C4: Total
A5: Quarter | D5: =Source_Data!D$5 -> 1 | E5: =Source_Data!E$5 -> 2 | F5: =Source_Data!F$5 -> 3 | G5: =Source_Data!G$5 -> 4 | H5: =Source_Data!H$5 -> 5 | I5: =Source_Data!I$5 -> 6 | J5: =Source_Data!J$5 -> 7 | K5: =Source_Data!K$5 -> 8 | ... BK5: =Source_Data!BK$5 -> 60
A6: Month | D6: =Source_Data!D$6 -> 3 | E6: =Source_Data!E$6 -> 6 | F6: =Source_Data!F$6 -> 9 | G6: =Source_Data!G$6 -> 12 | H6: =Source_Data!H$6 -> 15 | I6: =Source_Data!I$6 -> 18 | J6: =Source_Data!J$6 -> 21 | K6: =Source_Data!K$6 -> 24 | ... BK6: =Source_Data!BK$6 -> 180
A7: Years from month 0 | D7: =D6/12 -> 0.25 | E7: =E6/12 -> 0.5 | F7: =F6/12 -> 0.75 | G7: =G6/12 -> 1 | H7: =H6/12 -> 1.25 | I7: =I6/12 -> 1.5 | J7: =J6/12 -> 1.75 | K7: =K6/12 -> 2 | ... BK7: =BK6/12 -> 15
A8: Collections (80% of units sold) | C8: =SUM(D8:BK8) -> 2252.979 | D8: =Source_Data!D$7+Source_Data!D$8 -> 0 | E8: =Source_Data!E$7+Source_Data!E$8 -> 0 | F8: =Source_Data!F$7+Source_Data!F$8 -> 15.139238 | G8: =Source_Data!G$7+Source_Data!G$8 -> 30.278475 | H8: =Source_Data!H$7+Source_Data!H$8 -> 46.512006 | I8: =Source_Data!I$7+Source_Data!I$8 -> 62.745537 | J8: =Source_Data!J$7+Source_Data!J$8 -> 62.3657 | K8: =Source_Data!K$7+Source_Data!K$8 -> 63.473559 | ... BK8: =Source_Data!BK$7+Source_Data!BK$8 -> 0
A9: Landlord payments (35% share, guarantee, down payment) | C9: =SUM(D9:BK9) -> 985.67831 | D9: =Source_Data!D$9+Source_Data!D$10 -> 91.25 | E9: =Source_Data!E$9+Source_Data!E$10 -> 11.25 | F9: =Source_Data!F$9+Source_Data!F$10 -> 11.25 | G9: =Source_Data!G$9+Source_Data!G$10 -> 11.25 | H9: =Source_Data!H$9+Source_Data!H$10 -> 22.5 | I9: =Source_Data!I$9+Source_Data!I$10 -> 22.5 | J9: =Source_Data!J$9+Source_Data!J$10 -> 22.5 | K9: =Source_Data!K$9+Source_Data!K$10 -> 22.5 | ... BK9: =Source_Data!BK$9+Source_Data!BK$10 -> 0
A10: Construction cost | C10: =SUM(D10:BK10) -> 697.16 | D10: =Source_Data!D$11 -> 0 | E10: =Source_Data!E$11 -> 0 | F10: =Source_Data!F$11 -> 0 | G10: =Source_Data!G$11 -> 0 | H10: =Source_Data!H$11 -> 20 | I10: =Source_Data!I$11 -> 26.4 | J10: =Source_Data!J$11 -> 40 | K10: =Source_Data!K$11 -> 26.4 | ... BK10: =Source_Data!BK$11 -> 0
A11: Sales commission | C11: =SUM(D11:BK11) -> 90.11916 | D11: =Source_Data!D$12 -> 0 | E11: =Source_Data!E$12 -> 0 | F11: =Source_Data!F$12 -> 0 | G11: =Source_Data!G$12 -> 0 | H11: =Source_Data!H$12 -> 0 | I11: =Source_Data!I$12 -> 0 | J11: =Source_Data!J$12 -> 12.11139 | K11: =Source_Data!K$12 -> 12.11139 | ... BK11: =Source_Data!BK$12 -> 0
A12: SG&A and others | C12: =SUM(D12:BK12) -> 104.574 | D12: =Source_Data!D$13 -> 0 | E12: =Source_Data!E$13 -> 0 | F12: =Source_Data!F$13 -> 0 | G12: =Source_Data!G$13 -> 0 | H12: =Source_Data!H$13 -> 3 | I12: =Source_Data!I$13 -> 3.96 | J12: =Source_Data!J$13 -> 6 | K12: =Source_Data!K$13 -> 3.96 | ... BK12: =Source_Data!BK$13 -> 0
A13: Net cash flow | C13: =SUM(D13:BK13) -> 375.44753 | D13: =D8-D9-D10-D11-D12 -> -91.25 | E13: =E8-E9-E10-E11-E12 -> -11.25 | F13: =F8-F9-F10-F11-F12 -> 3.8892375 | G13: =G8-G9-G10-G11-G12 -> 19.028475 | H13: =H8-H9-H10-H11-H12 -> 1.0120062 | I13: =I8-I9-I10-I11-I12 -> 9.8855375 | J13: =J8-J9-J10-J11-J12 -> -18.24569 | K13: =K8-K9-K10-K11-K12 -> -1.4978306 | ... BK13: =BK8-BK9-BK10-BK11-BK12 -> 0
A14: Cumulative net cash flow | D14: =D13 -> -91.25 | E14: =D14+E13 -> -102.5 | F14: =E14+F13 -> -98.610763 | G14: =F14+G13 -> -79.582288 | H14: =G14+H13 -> -78.570281 | I14: =H14+I13 -> -68.684744 | J14: =I14+J13 -> -86.930434 | K14: =J14+K13 -> -88.428264 | L14: =K14+L13 -> -81.730676 | ... BK14: =BJ14+BK13 -> 375.44753
A15: Discount factor | D15: =1/(1+Inputs!$B$14)^D7 -> 0.96777364 | E15: =1/(1+Inputs!$B$14)^E7 -> 0.93658581 | F15: =1/(1+Inputs!$B$14)^F7 -> 0.90640306 | G15: =1/(1+Inputs!$B$14)^G7 -> 0.87719298 | H15: =1/(1+Inputs!$B$14)^H7 -> 0.84892424 | I15: =1/(1+Inputs!$B$14)^I7 -> 0.8215665 | J15: =1/(1+Inputs!$B$14)^J7 -> 0.7950904 | K15: =1/(1+Inputs!$B$14)^K7 -> 0.76946753 | ... BK15: =1/(1+Inputs!$B$14)^BK7 -> 0.14009648
A16: Present value of net cash flow | C16: =SUM(D16:BK16) -> 215.31139 | D16: =D13*D15 -> -88.309344 | E16: =E13*E15 -> -10.53659 | F16: =F13*F15 -> 3.5252168 | G16: =G13*G15 -> 16.691645 | H16: =H13*H15 -> 0.85911664 | I16: =I13*I15 -> 8.1216265 | J16: =J13*J15 -> -14.506973 | K16: =K13*K15 -> -1.152532 | ... BK16: =BK13*BK15 -> 0
A18: Net cash flow, nominal | B18: =C13 -> 375.44753
A19: NPV of net cash flow @ discount rate | B19: =C16 -> 215.31139
A20: Peak cumulative cash shortage | B20: =MIN(D14:BK14) -> -102.5
A21: Month of peak shortage | B21: =INDEX(D6:BK6,MATCH(B20,D14:BK14,0)) -> 6

Sheet Sources_Uses
A1: Green Square: sources and uses of funds at the modelled peak, ticket EGP 100m
A2: Nothing is ring-fenced: the ticket is project funding, not a restricted account.
A4: Uses (EGP m) | B4: Amount | C4: Basis
A5: Down payment to landlord | B5: =Inputs!$B$21 -> 80 | C5: Source model
A6: Landlord guarantee instalments and working capital to modelled peak, net of collections | B6: =-Project_CF!$B$20-Inputs!$B$21 -> 22.5 | C6: Peak shortage less down payment
A7: Design, permits and pre-construction (ASSUMPTION) | B7: =Inputs!$B$24*Project_CF!$C$10*Inputs!$B$25 -> 10.4574 | C7: 30% of the 5% professional-fee line, incurred ahead of construction start
A8: Total uses at peak | B8: =SUM(B5:B7) -> 112.9574
A11: Sources (EGP m) | B11: Amount | C11: Basis
A12: Investor ticket | B12: =Inputs!$B$7 -> 100 | C12: This offer
A13: Balance of project funding | B13: =MAX(0,B8-B12) -> 12.9574 | C13: The balance of project funding is provided by Jalour sponsor equity, project collections and other capital sources.
A14: Total sources | B14: =B12+B13 -> 112.9574
A15: Ticket in excess of modelled uses (general project liquidity, not ring-fenced) | B15: =MAX(0,B12-B8) -> 0 | C15: Flag if above zero
A16: Ticket as % of modelled peak shortage | B16: =B12/-Project_CF!$B$20 -> 0.97560976
A17: Ticket applied to uses as % of total uses | B17: =MIN(B12,B8)/B8 -> 0.8852895
A18: Ticket above modelled peak shortage | B18: =MAX(0,B12+Project_CF!$B$20) -> 0 | C18: Flag if above zero
A20: Funding-gap exposure (sponsor covers gaps in excess of project cash)

Sheet Option_A
A1: Green Square: Option A (units), ticket EGP 100m
A2: Units priced at launch list; allocated from the first two sales tranches; Jalour bears the landlord 35% on those units (landlord payments unchanged).
A4: Allocation | B4: Value | C4: Unit
A5: Face value of units at launch list | B5: =Inputs!$B$8*Inputs!$B$7 -> 200 | C5: EGP m
A6: Share of launch-tranche inventory allocated | B6: =B5/Inputs!$B$55 -> 0.33026762
A7: of which retail | B7: =B5*Inputs!$B$32/Inputs!$B$55 -> 64.516129 | C7: EGP m
A8: of which offices | B8: =B5*Inputs!$B$33/Inputs!$B$55 -> 135.48387 | C8: EGP m
A9: Retail area allocated | B9: =B7*1000/Inputs!$B$28 -> 286.73835 | C9: m2
A10: Office area allocated | B10: =B8*1000/Inputs!$B$29 -> 1003.5842 | C10: m2
A11: Value at delivery list price (before resale friction) | B11: =B5*Inputs!$B$34 -> 286.73835 | C11: EGP m
A12: Landlord 35% on the allocated units, borne by Jalour | B12: =Inputs!$B$19*B5 -> 70 | C12: EGP m
A15: Quarterly flows (EGP m) | B15: Total
A16: Month | D16: =Source_Data!D$6 -> 3 | E16: =Source_Data!E$6 -> 6 | F16: =Source_Data!F$6 -> 9 | G16: =Source_Data!G$6 -> 12 | H16: =Source_Data!H$6 -> 15 | I16: =Source_Data!I$6 -> 18 | J16: =Source_Data!J$6 -> 21 | K16: =Source_Data!K$6 -> 24 | ... BK16: =Source_Data!BK$6 -> 180
A17: Investor cash flow (base) | B17: =SUM(D17:BK17) -> 178.1362 | D17: =IF(Source_Data!D$6=Inputs!$B$12,-Inputs!$B$7,0)+IF(AND(Source_Data!D$6>=Inputs!$B$13+3,Source_Data!D$6<Inputs!$B$13+3+3*Inputs!$B$16,MOD(Source_Data!D$6-(Inputs!$B$13+3),3)=0),$B$5*Inputs!$B$34*(1-Inputs!$B$15)/Inputs!$B$16,0) -> -100 | E17: =IF(Source_Data!E$6=Inputs!$B$12,-Inputs!$B$7,0)+IF(AND(Source_Data!E$6>=Inputs!$B$13+3,Source_Data!E$6<Inputs!$B$13+3+3*Inputs!$B$16,MOD(Source_Data!E$6-(Inputs!$B$13+3),3)=0),$B$5*Inputs!$B$34*(1-Inputs!$B$15)/Inputs!$B$16,0) -> 0 | F17: =IF(Source_Data!F$6=Inputs!$B$12,-Inputs!$B$7,0)+IF(AND(Source_Data!F$6>=Inputs!$B$13+3,Source_Data!F$6<Inputs!$B$13+3+3*Inputs!$B$16,MOD(Source_Data!F$6-(Inputs!$B$13+3),3)=0),$B$5*Inputs!$B$34*(1-Inputs!$B$15)/Inputs!$B$16,0) -> 0 | G17: =IF(Source_Data!G$6=Inputs!$B$12,-Inputs!$B$7,0)+IF(AND(Source_Data!G$6>=Inputs!$B$13+3,Source_Data!G$6<Inputs!$B$13+3+3*Inputs!$B$16,MOD(Source_Data!G$6-(Inputs!$B$13+3),3)=0),$B$5*Inputs!$B$34*(1-Inputs!$B$15)/Inputs!$B$16,0) -> 0 | H17: =IF(Source_Data!H$6=Inputs!$B$12,-Inputs!$B$7,0)+IF(AND(Source_Data!H$6>=Inputs!$B$13+3,Source_Data!H$6<Inputs!$B$13+3+3*Inputs!$B$16,MOD(Source_Data!H$6-(Inputs!$B$13+3),3)=0),$B$5*Inputs!$B$34*(1-Inputs!$B$15)/Inputs!$B$16,0) -> 0 | I17: =IF(Source_Data!I$6=Inputs!$B$12,-Inputs!$B$7,0)+IF(AND(Source_Data!I$6>=Inputs!$B$13+3,Source_Data!I$6<Inputs!$B$13+3+3*Inputs!$B$16,MOD(Source_Data!I$6-(Inputs!$B$13+3),3)=0),$B$5*Inputs!$B$34*(1-Inputs!$B$15)/Inputs!$B$16,0) -> 0 | J17: =IF(Source_Data!J$6=Inputs!$B$12,-Inputs!$B$7,0)+IF(AND(Source_Data!J$6>=Inputs!$B$13+3,Source_Data!J$6<Inputs!$B$13+3+3*Inputs!$B$16,MOD(Source_Data!J$6-(Inputs!$B$13+3),3)=0),$B$5*Inputs!$B$34*(1-Inputs!$B$15)/Inputs!$B$16,0) -> 0 | K17: =IF(Source_Data!K$6=Inputs!$B$12,-Inputs!$B$7,0)+IF(AND(Source_Data!K$6>=Inputs!$B$13+3,Source_Data!K$6<Inputs!$B$13+3+3*Inputs!$B$16,MOD(Source_Data!K$6-(Inputs!$B$13+3),3)=0),$B$5*Inputs!$B$34*(1-Inputs!$B$15)/Inputs!$B$16,0) -> 0 | ... BK17: =IF(Source_Data!BK$6=Inputs!$B$12,-Inputs!$B$7,0)+IF(AND(Source_Data!BK$6>=Inputs!$B$13+3,Source_Data!BK$6<Inputs!$B$13+3+3*Inputs!$B$16,MOD(Source_Data!BK$6-(Inputs!$B$13+3),3)=0),$B$5*Inputs!$B$34*(1-Inputs!$B$15)/Inputs!$B$16,0) -> 0
A18: Jalour: ticket received | B18: =SUM(D18:BK18) -> 100 | D18: =IF(Source_Data!D$6=Inputs!$B$12,Inputs!$B$7,0) -> 100 | E18: =IF(Source_Data!E$6=Inputs!$B$12,Inputs!$B$7,0) -> 0 | F18: =IF(Source_Data!F$6=Inputs!$B$12,Inputs!$B$7,0) -> 0 | G18: =IF(Source_Data!G$6=Inputs!$B$12,Inputs!$B$7,0) -> 0 | H18: =IF(Source_Data!H$6=Inputs!$B$12,Inputs!$B$7,0) -> 0 | I18: =IF(Source_Data!I$6=Inputs!$B$12,Inputs!$B$7,0) -> 0 | J18: =IF(Source_Data!J$6=Inputs!$B$12,Inputs!$B$7,0) -> 0 | K18: =IF(Source_Data!K$6=Inputs!$B$12,Inputs!$B$7,0) -> 0 | ... BK18: =IF(Source_Data!BK$6=Inputs!$B$12,Inputs!$B$7,0) -> 0
A19: Jalour: collections forgone on allocated units | B19: =SUM(D19:BK19) -> -200 | D19: =-$B$6*Source_Data!D$14 -> 0 | E19: =-$B$6*Source_Data!E$14 -> 0 | F19: =-$B$6*Source_Data!F$14 -> -5 | G19: =-$B$6*Source_Data!G$14 -> -10 | H19: =-$B$6*Source_Data!H$14 -> -7.5 | I19: =-$B$6*Source_Data!I$14 -> -5 | J19: =-$B$6*Source_Data!J$14 -> -5 | K19: =-$B$6*Source_Data!K$14 -> -5 | ... BK19: =-$B$6*Source_Data!BK$14 -> 0
A20: Jalour: commission saved | B20: =SUM(D20:BK20) -> 8 | D20: =$B$6*Source_Data!D$17*Inputs!$B$23 -> 0 | E20: =$B$6*Source_Data!E$17*Inputs!$B$23 -> 0 | F20: =$B$6*Source_Data!F$17*Inputs!$B$23 -> 0 | G20: =$B$6*Source_Data!G$17*Inputs!$B$23 -> 0 | H20: =$B$6*Source_Data!H$17*Inputs!$B$23 -> 0 | I20: =$B$6*Source_Data!I$17*Inputs!$B$23 -> 0 | J20: =$B$6*Source_Data!J$17*Inputs!$B$23 -> 4 | K20: =$B$6*Source_Data!K$17*Inputs!$B$23 -> 4 | ... BK20: =$B$6*Source_Data!BK$17*Inputs!$B$23 -> 0
A21: Jalour: net incremental cash flow | B21: =SUM(D21:BK21) -> -92 | D21: =D18+D19+D20 -> 100 | E21: =E18+E19+E20 -> 0 | F21: =F18+F19+F20 -> -5 | G21: =G18+G19+G20 -> -10 | H21: =H18+H19+H20 -> -7.5 | I21: =I18+I19+I20 -> -5 | J21: =J18+J19+J20 -> -1 | K21: =K18+K19+K20 -> -1 | ... BK21: =BK18+BK19+BK20 -> 0
A22: Jalour: pooled position effect (cumulative) | D22: =D21 -> 100 | E22: =D22+E21 -> 100 | F22: =E22+F21 -> 95 | G22: =F22+G21 -> 85 | H22: =G22+H21 -> 77.5 | I22: =H22+I21 -> 72.5 | J22: =I22+J21 -> 71.5 | K22: =J22+K21 -> 70.5 | L22: =K22+L21 -> 65.5 | ... BK22: =BJ22+BK21 -> -92
A25: Returns | B25: Value | C25: Note
A26: Investor IRR, base | B26: =(1+IRR(D17:BK17,0.05))^4-1 -> 0.26402991 | C26: Appreciation to delivery list price in the model
A27: Investor MOIC, base | B27: =SUMIF(D17:BK17,">0")/-SUMIF(D17:BK17,"<0") -> 2.781362
A28: Investor payback month | B28: =INDEX(D16:BK16,MATCH(1,D36:BK36,0)) -> 54 | C28: First quarter cumulative cash is not negative
A29: Jalour cost of capital (IRR of ticket vs forgone collections) | B29: =(1+IRR(D21:BK21,0.05))^4-1 -> 0.20741957 | C29: Jalour bears landlord share
A30: NPV to Jalour @ discount rate | B30: =SUMPRODUCT(D21:BK21,Project_CF!$D$15:$BK$15) -> -19.093021
A31: Nominal net cost to Jalour | B31: =B21 -> -92
A32: Project NPV after the deal | B32: =Project_CF!$B$19+B30 -> 196.21837 | C32: Project NPV before the deal plus deal NPV
A33: Peak cumulative shortage excluding ticket cash (after forgone collections) | B33: =MIN(D38:BK38) -> -117.92826 | C33: Project cumulative plus deal effect, ticket cash excluded
A35: Investor cumulative cash flow | D35: =D17 -> -100 | E35: =D35+E17 -> -100 | F35: =E35+F17 -> -100 | G35: =F35+G17 -> -100 | H35: =G35+H17 -> -100 | I35: =H35+I17 -> -100 | J35: =I35+J17 -> -100 | K35: =J35+K17 -> -100 | L35: =K35+L17 -> -100 | ... BK35: =BJ35+BK17 -> 178.1362
A36: Cumulative not negative (1/0) | D36: =IF(AND(D35>=0,D16>Inputs!$B$12),1,0) -> 0 | E36: =IF(AND(E35>=0,E16>Inputs!$B$12),1,0) -> 0 | F36: =IF(AND(F35>=0,F16>Inputs!$B$12),1,0) -> 0 | G36: =IF(AND(G35>=0,G16>Inputs!$B$12),1,0) -> 0 | H36: =IF(AND(H35>=0,H16>Inputs!$B$12),1,0) -> 0 | I36: =IF(AND(I35>=0,I16>Inputs!$B$12),1,0) -> 0 | J36: =IF(AND(J35>=0,J16>Inputs!$B$12),1,0) -> 0 | K36: =IF(AND(K35>=0,K16>Inputs!$B$12),1,0) -> 0 | ... BK36: =IF(AND(BK35>=0,BK16>Inputs!$B$12),1,0) -> 1
A37: Ticket cash received (cumulative) | D37: =IF(D16>=Inputs!$B$12,Inputs!$B$7,0) -> 100 | E37: =IF(E16>=Inputs!$B$12,Inputs!$B$7,0) -> 100 | F37: =IF(F16>=Inputs!$B$12,Inputs!$B$7,0) -> 100 | G37: =IF(G16>=Inputs!$B$12,Inputs!$B$7,0) -> 100 | H37: =IF(H16>=Inputs!$B$12,Inputs!$B$7,0) -> 100 | I37: =IF(I16>=Inputs!$B$12,Inputs!$B$7,0) -> 100 | J37: =IF(J16>=Inputs!$B$12,Inputs!$B$7,0) -> 100 | K37: =IF(K16>=Inputs!$B$12,Inputs!$B$7,0) -> 100 | ... BK37: =IF(BK16>=Inputs!$B$12,Inputs!$B$7,0) -> 100
A38: Project cumulative cash plus deal effect, ticket cash excluded | D38: =Project_CF!D14+D22-D37 -> -91.25 | E38: =Project_CF!E14+E22-E37 -> -102.5 | F38: =Project_CF!F14+F22-F37 -> -103.61076 | G38: =Project_CF!G14+G22-G37 -> -94.582288 | H38: =Project_CF!H14+H22-H37 -> -101.07028 | I38: =Project_CF!I14+I22-I37 -> -96.184744 | J38: =Project_CF!J14+J22-J37 -> -115.43043 | K38: =Project_CF!K14+K22-K37 -> -117.92826 | ... BK38: =Project_CF!BK14+BK22-BK37 -> 183.44753
A40: Face multiple sensitivity | B40: Investor IRR | C40: Investor MOIC
A41: 1.5 | B41: =(1+IRR(D50:BK50,0.05))^4-1 -> 0.18330574 | C41: =SUMIF(D50:BK50,">0")/-SUMIF(D50:BK50,"<0") -> 2.0860215
A42: 1.75 | B42: =(1+IRR(D51:BK51,0.05))^4-1 -> 0.22588591 | C42: =SUMIF(D51:BK51,">0")/-SUMIF(D51:BK51,"<0") -> 2.4336918
A43: 2 | B43: =(1+IRR(D52:BK52,0.05))^4-1 -> 0.26402991 | C43: =SUMIF(D52:BK52,">0")/-SUMIF(D52:BK52,"<0") -> 2.781362
A44: 2.25 | B44: =(1+IRR(D53:BK53,0.05))^4-1 -> 0.29867736 | C44: =SUMIF(D53:BK53,">0")/-SUMIF(D53:BK53,"<0") -> 3.1290323
A45: 2.5 | B45: =(1+IRR(D54:BK54,0.05))^4-1 -> 0.33048927 | C45: =SUMIF(D54:BK54,">0")/-SUMIF(D54:BK54,"<0") -> 3.4767025
A47: Early assignment 24 months after funding (units at face, no appreciation) | B47: Investor IRR | C47: Investor MOIC
A48: 0 | B48: =(1+IRR(D56:BK56,0.05))^4-1 -> 0.39283883 | C48: =SUMIF(D56:BK56,">0")/-SUMIF(D56:BK56,"<0") -> 1.94
A49: 0.1 | B49: =(1+IRR(D57:BK57,0.05))^4-1 -> 0.32136293 | C49: =SUMIF(D57:BK57,">0")/-SUMIF(D57:BK57,"<0") -> 1.746
A50: 0.2 | B50: =(1+IRR(D58:BK58,0.05))^4-1 -> 0.24579292 | C50: =SUMIF(D58:BK58,">0")/-SUMIF(D58:BK58,"<0") -> 1.552 | D50: =IF(Source_Data!D$6=Inputs!$B$12,-Inputs!$B$7,0)+IF(AND(Source_Data!D$6>=Inputs!$B$13+3,Source_Data!D$6<Inputs!$B$13+3+3*Inputs!$B$16,MOD(Source_Data!D$6-(Inputs!$B$13+3),3)=0),$A$41*Inputs!$B$7*Inputs!$B$34*(1-Inputs!$B$15)/Inputs!$B$16,0) -> -100 | E50: =IF(Source_Data!E$6=Inputs!$B$12,-Inputs!$B$7,0)+IF(AND(Source_Data!E$6>=Inputs!$B$13+3,Source_Data!E$6<Inputs!$B$13+3+3*Inputs!$B$16,MOD(Source_Data!E$6-(Inputs!$B$13+3),3)=0),$A$41*Inputs!$B$7*Inputs!$B$34*(1-Inputs!$B$15)/Inputs!$B$16,0) -> 0 | F50: =IF(Source_Data!F$6=Inputs!$B$12,-Inputs!$B$7,0)+IF(AND(Source_Data!F$6>=Inputs!$B$13+3,Source_Data!F$6<Inputs!$B$13+3+3*Inputs!$B$16,MOD(Source_Data!F$6-(Inputs!$B$13+3),3)=0),$A$41*Inputs!$B$7*Inputs!$B$34*(1-Inputs!$B$15)/Inputs!$B$16,0) -> 0 | G50: =IF(Source_Data!G$6=Inputs!$B$12,-Inputs!$B$7,0)+IF(AND(Source_Data!G$6>=Inputs!$B$13+3,Source_Data!G$6<Inputs!$B$13+3+3*Inputs!$B$16,MOD(Source_Data!G$6-(Inputs!$B$13+3),3)=0),$A$41*Inputs!$B$7*Inputs!$B$34*(1-Inputs!$B$15)/Inputs!$B$16,0) -> 0 | H50: =IF(Source_Data!H$6=Inputs!$B$12,-Inputs!$B$7,0)+IF(AND(Source_Data!H$6>=Inputs!$B$13+3,Source_Data!H$6<Inputs!$B$13+3+3*Inputs!$B$16,MOD(Source_Data!H$6-(Inputs!$B$13+3),3)=0),$A$41*Inputs!$B$7*Inputs!$B$34*(1-Inputs!$B$15)/Inputs!$B$16,0) -> 0 | I50: =IF(Source_Data!I$6=Inputs!$B$12,-Inputs!$B$7,0)+IF(AND(Source_Data!I$6>=Inputs!$B$13+3,Source_Data!I$6<Inputs!$B$13+3+3*Inputs!$B$16,MOD(Source_Data!I$6-(Inputs!$B$13+3),3)=0),$A$41*Inputs!$B$7*Inputs!$B$34*(1-Inputs!$B$15)/Inputs!$B$16,0) -> 0 | J50: =IF(Source_Data!J$6=Inputs!$B$12,-Inputs!$B$7,0)+IF(AND(Source_Data!J$6>=Inputs!$B$13+3,Source_Data!J$6<Inputs!$B$13+3+3*Inputs!$B$16,MOD(Source_Data!J$6-(Inputs!$B$13+3),3)=0),$A$41*Inputs!$B$7*Inputs!$B$34*(1-Inputs!$B$15)/Inputs!$B$16,0) -> 0 | K50: =IF(Source_Data!K$6=Inputs!$B$12,-Inputs!$B$7,0)+IF(AND(Source_Data!K$6>=Inputs!$B$13+3,Source_Data!K$6<Inputs!$B$13+3+3*Inputs!$B$16,MOD(Source_Data!K$6-(Inputs!$B$13+3),3)=0),$A$41*Inputs!$B$7*Inputs!$B$34*(1-Inputs!$B$15)/Inputs!$B$16,0) -> 0 | ... BK50: =IF(Source_Data!BK$6=Inputs!$B$12,-Inputs!$B$7,0)+IF(AND(Source_Data!BK$6>=Inputs!$B$13+3,Source_Data!BK$6<Inputs!$B$13+3+3*Inputs!$B$16,MOD(Source_Data!BK$6-(Inputs!$B$13+3),3)=0),$A$41*Inputs!$B$7*Inputs!$B$34*(1-Inputs!$B$15)/Inputs!$B$16,0) -> 0
A51: 0.3 | B51: =(1+IRR(D59:BK59,0.05))^4-1 -> 0.16533257 | C51: =SUMIF(D59:BK59,">0")/-SUMIF(D59:BK59,"<0") -> 1.358 | D51: =IF(Source_Data!D$6=Inputs!$B$12,-Inputs!$B$7,0)+IF(AND(Source_Data!D$6>=Inputs!$B$13+3,Source_Data!D$6<Inputs!$B$13+3+3*Inputs!$B$16,MOD(Source_Data!D$6-(Inputs!$B$13+3),3)=0),$A$42*Inputs!$B$7*Inputs!$B$34*(1-Inputs!$B$15)/Inputs!$B$16,0) -> -100 | E51: =IF(Source_Data!E$6=Inputs!$B$12,-Inputs!$B$7,0)+IF(AND(Source_Data!E$6>=Inputs!$B$13+3,Source_Data!E$6<Inputs!$B$13+3+3*Inputs!$B$16,MOD(Source_Data!E$6-(Inputs!$B$13+3),3)=0),$A$42*Inputs!$B$7*Inputs!$B$34*(1-Inputs!$B$15)/Inputs!$B$16,0) -> 0 | F51: =IF(Source_Data!F$6=Inputs!$B$12,-Inputs!$B$7,0)+IF(AND(Source_Data!F$6>=Inputs!$B$13+3,Source_Data!F$6<Inputs!$B$13+3+3*Inputs!$B$16,MOD(Source_Data!F$6-(Inputs!$B$13+3),3)=0),$A$42*Inputs!$B$7*Inputs!$B$34*(1-Inputs!$B$15)/Inputs!$B$16,0) -> 0 | G51: =IF(Source_Data!G$6=Inputs!$B$12,-Inputs!$B$7,0)+IF(AND(Source_Data!G$6>=Inputs!$B$13+3,Source_Data!G$6<Inputs!$B$13+3+3*Inputs!$B$16,MOD(Source_Data!G$6-(Inputs!$B$13+3),3)=0),$A$42*Inputs!$B$7*Inputs!$B$34*(1-Inputs!$B$15)/Inputs!$B$16,0) -> 0 | H51: =IF(Source_Data!H$6=Inputs!$B$12,-Inputs!$B$7,0)+IF(AND(Source_Data!H$6>=Inputs!$B$13+3,Source_Data!H$6<Inputs!$B$13+3+3*Inputs!$B$16,MOD(Source_Data!H$6-(Inputs!$B$13+3),3)=0),$A$42*Inputs!$B$7*Inputs!$B$34*(1-Inputs!$B$15)/Inputs!$B$16,0) -> 0 | I51: =IF(Source_Data!I$6=Inputs!$B$12,-Inputs!$B$7,0)+IF(AND(Source_Data!I$6>=Inputs!$B$13+3,Source_Data!I$6<Inputs!$B$13+3+3*Inputs!$B$16,MOD(Source_Data!I$6-(Inputs!$B$13+3),3)=0),$A$42*Inputs!$B$7*Inputs!$B$34*(1-Inputs!$B$15)/Inputs!$B$16,0) -> 0 | J51: =IF(Source_Data!J$6=Inputs!$B$12,-Inputs!$B$7,0)+IF(AND(Source_Data!J$6>=Inputs!$B$13+3,Source_Data!J$6<Inputs!$B$13+3+3*Inputs!$B$16,MOD(Source_Data!J$6-(Inputs!$B$13+3),3)=0),$A$42*Inputs!$B$7*Inputs!$B$34*(1-Inputs!$B$15)/Inputs!$B$16,0) -> 0 | K51: =IF(Source_Data!K$6=Inputs!$B$12,-Inputs!$B$7,0)+IF(AND(Source_Data!K$6>=Inputs!$B$13+3,Source_Data!K$6<Inputs!$B$13+3+3*Inputs!$B$16,MOD(Source_Data!K$6-(Inputs!$B$13+3),3)=0),$A$42*Inputs!$B$7*Inputs!$B$34*(1-Inputs!$B$15)/Inputs!$B$16,0) -> 0 | ... BK51: =IF(Source_Data!BK$6=Inputs!$B$12,-Inputs!$B$7,0)+IF(AND(Source_Data!BK$6>=Inputs!$B$13+3,Source_Data!BK$6<Inputs!$B$13+3+3*Inputs!$B$16,MOD(Source_Data!BK$6-(Inputs!$B$13+3),3)=0),$A$42*Inputs!$B$7*Inputs!$B$34*(1-Inputs!$B$15)/Inputs!$B$16,0) -> 0
A52: Investor flow at face multiple row 43 | D52: =IF(Source_Data!D$6=Inputs!$B$12,-Inputs!$B$7,0)+IF(AND(Source_Data!D$6>=Inputs!$B$13+3,Source_Data!D$6<Inputs!$B$13+3+3*Inputs!$B$16,MOD(Source_Data!D$6-(Inputs!$B$13+3),3)=0),$A$43*Inputs!$B$7*Inputs!$B$34*(1-Inputs!$B$15)/Inputs!$B$16,0) -> -100 | E52: =IF(Source_Data!E$6=Inputs!$B$12,-Inputs!$B$7,0)+IF(AND(Source_Data!E$6>=Inputs!$B$13+3,Source_Data!E$6<Inputs!$B$13+3+3*Inputs!$B$16,MOD(Source_Data!E$6-(Inputs!$B$13+3),3)=0),$A$43*Inputs!$B$7*Inputs!$B$34*(1-Inputs!$B$15)/Inputs!$B$16,0) -> 0 | F52: =IF(Source_Data!F$6=Inputs!$B$12,-Inputs!$B$7,0)+IF(AND(Source_Data!F$6>=Inputs!$B$13+3,Source_Data!F$6<Inputs!$B$13+3+3*Inputs!$B$16,MOD(Source_Data!F$6-(Inputs!$B$13+3),3)=0),$A$43*Inputs!$B$7*Inputs!$B$34*(1-Inputs!$B$15)/Inputs!$B$16,0) -> 0 | G52: =IF(Source_Data!G$6=Inputs!$B$12,-Inputs!$B$7,0)+IF(AND(Source_Data!G$6>=Inputs!$B$13+3,Source_Data!G$6<Inputs!$B$13+3+3*Inputs!$B$16,MOD(Source_Data!G$6-(Inputs!$B$13+3),3)=0),$A$43*Inputs!$B$7*Inputs!$B$34*(1-Inputs!$B$15)/Inputs!$B$16,0) -> 0 | H52: =IF(Source_Data!H$6=Inputs!$B$12,-Inputs!$B$7,0)+IF(AND(Source_Data!H$6>=Inputs!$B$13+3,Source_Data!H$6<Inputs!$B$13+3+3*Inputs!$B$16,MOD(Source_Data!H$6-(Inputs!$B$13+3),3)=0),$A$43*Inputs!$B$7*Inputs!$B$34*(1-Inputs!$B$15)/Inputs!$B$16,0) -> 0 | I52: =IF(Source_Data!I$6=Inputs!$B$12,-Inputs!$B$7,0)+IF(AND(Source_Data!I$6>=Inputs!$B$13+3,Source_Data!I$6<Inputs!$B$13+3+3*Inputs!$B$16,MOD(Source_Data!I$6-(Inputs!$B$13+3),3)=0),$A$43*Inputs!$B$7*Inputs!$B$34*(1-Inputs!$B$15)/Inputs!$B$16,0) -> 0 | J52: =IF(Source_Data!J$6=Inputs!$B$12,-Inputs!$B$7,0)+IF(AND(Source_Data!J$6>=Inputs!$B$13+3,Source_Data!J$6<Inputs!$B$13+3+3*Inputs!$B$16,MOD(Source_Data!J$6-(Inputs!$B$13+3),3)=0),$A$43*Inputs!$B$7*Inputs!$B$34*(1-Inputs!$B$15)/Inputs!$B$16,0) -> 0 | K52: =IF(Source_Data!K$6=Inputs!$B$12,-Inputs!$B$7,0)+IF(AND(Source_Data!K$6>=Inputs!$B$13+3,Source_Data!K$6<Inputs!$B$13+3+3*Inputs!$B$16,MOD(Source_Data!K$6-(Inputs!$B$13+3),3)=0),$A$43*Inputs!$B$7*Inputs!$B$34*(1-Inputs!$B$15)/Inputs!$B$16,0) -> 0 | ... BK52: =IF(Source_Data!BK$6=Inputs!$B$12,-Inputs!$B$7,0)+IF(AND(Source_Data!BK$6>=Inputs!$B$13+3,Source_Data!BK$6<Inputs!$B$13+3+3*Inputs!$B$16,MOD(Source_Data!BK$6-(Inputs!$B$13+3),3)=0),$A$43*Inputs!$B$7*Inputs!$B$34*(1-Inputs!$B$15)/Inputs!$B$16,0) -> 0
A53: Investor flow at face multiple row 44 | D53: =IF(Source_Data!D$6=Inputs!$B$12,-Inputs!$B$7,0)+IF(AND(Source_Data!D$6>=Inputs!$B$13+3,Source_Data!D$6<Inputs!$B$13+3+3*Inputs!$B$16,MOD(Source_Data!D$6-(Inputs!$B$13+3),3)=0),$A$44*Inputs!$B$7*Inputs!$B$34*(1-Inputs!$B$15)/Inputs!$B$16,0) -> -100 | E53: =IF(Source_Data!E$6=Inputs!$B$12,-Inputs!$B$7,0)+IF(AND(Source_Data!E$6>=Inputs!$B$13+3,Source_Data!E$6<Inputs!$B$13+3+3*Inputs!$B$16,MOD(Source_Data!E$6-(Inputs!$B$13+3),3)=0),$A$44*Inputs!$B$7*Inputs!$B$34*(1-Inputs!$B$15)/Inputs!$B$16,0) -> 0 | F53: =IF(Source_Data!F$6=Inputs!$B$12,-Inputs!$B$7,0)+IF(AND(Source_Data!F$6>=Inputs!$B$13+3,Source_Data!F$6<Inputs!$B$13+3+3*Inputs!$B$16,MOD(Source_Data!F$6-(Inputs!$B$13+3),3)=0),$A$44*Inputs!$B$7*Inputs!$B$34*(1-Inputs!$B$15)/Inputs!$B$16,0) -> 0 | G53: =IF(Source_Data!G$6=Inputs!$B$12,-Inputs!$B$7,0)+IF(AND(Source_Data!G$6>=Inputs!$B$13+3,Source_Data!G$6<Inputs!$B$13+3+3*Inputs!$B$16,MOD(Source_Data!G$6-(Inputs!$B$13+3),3)=0),$A$44*Inputs!$B$7*Inputs!$B$34*(1-Inputs!$B$15)/Inputs!$B$16,0) -> 0 | H53: =IF(Source_Data!H$6=Inputs!$B$12,-Inputs!$B$7,0)+IF(AND(Source_Data!H$6>=Inputs!$B$13+3,Source_Data!H$6<Inputs!$B$13+3+3*Inputs!$B$16,MOD(Source_Data!H$6-(Inputs!$B$13+3),3)=0),$A$44*Inputs!$B$7*Inputs!$B$34*(1-Inputs!$B$15)/Inputs!$B$16,0) -> 0 | I53: =IF(Source_Data!I$6=Inputs!$B$12,-Inputs!$B$7,0)+IF(AND(Source_Data!I$6>=Inputs!$B$13+3,Source_Data!I$6<Inputs!$B$13+3+3*Inputs!$B$16,MOD(Source_Data!I$6-(Inputs!$B$13+3),3)=0),$A$44*Inputs!$B$7*Inputs!$B$34*(1-Inputs!$B$15)/Inputs!$B$16,0) -> 0 | J53: =IF(Source_Data!J$6=Inputs!$B$12,-Inputs!$B$7,0)+IF(AND(Source_Data!J$6>=Inputs!$B$13+3,Source_Data!J$6<Inputs!$B$13+3+3*Inputs!$B$16,MOD(Source_Data!J$6-(Inputs!$B$13+3),3)=0),$A$44*Inputs!$B$7*Inputs!$B$34*(1-Inputs!$B$15)/Inputs!$B$16,0) -> 0 | K53: =IF(Source_Data!K$6=Inputs!$B$12,-Inputs!$B$7,0)+IF(AND(Source_Data!K$6>=Inputs!$B$13+3,Source_Data!K$6<Inputs!$B$13+3+3*Inputs!$B$16,MOD(Source_Data!K$6-(Inputs!$B$13+3),3)=0),$A$44*Inputs!$B$7*Inputs!$B$34*(1-Inputs!$B$15)/Inputs!$B$16,0) -> 0 | ... BK53: =IF(Source_Data!BK$6=Inputs!$B$12,-Inputs!$B$7,0)+IF(AND(Source_Data!BK$6>=Inputs!$B$13+3,Source_Data!BK$6<Inputs!$B$13+3+3*Inputs!$B$16,MOD(Source_Data!BK$6-(Inputs!$B$13+3),3)=0),$A$44*Inputs!$B$7*Inputs!$B$34*(1-Inputs!$B$15)/Inputs!$B$16,0) -> 0
A54: Investor flow at face multiple row 45 | D54: =IF(Source_Data!D$6=Inputs!$B$12,-Inputs!$B$7,0)+IF(AND(Source_Data!D$6>=Inputs!$B$13+3,Source_Data!D$6<Inputs!$B$13+3+3*Inputs!$B$16,MOD(Source_Data!D$6-(Inputs!$B$13+3),3)=0),$A$45*Inputs!$B$7*Inputs!$B$34*(1-Inputs!$B$15)/Inputs!$B$16,0) -> -100 | E54: =IF(Source_Data!E$6=Inputs!$B$12,-Inputs!$B$7,0)+IF(AND(Source_Data!E$6>=Inputs!$B$13+3,Source_Data!E$6<Inputs!$B$13+3+3*Inputs!$B$16,MOD(Source_Data!E$6-(Inputs!$B$13+3),3)=0),$A$45*Inputs!$B$7*Inputs!$B$34*(1-Inputs!$B$15)/Inputs!$B$16,0) -> 0 | F54: =IF(Source_Data!F$6=Inputs!$B$12,-Inputs!$B$7,0)+IF(AND(Source_Data!F$6>=Inputs!$B$13+3,Source_Data!F$6<Inputs!$B$13+3+3*Inputs!$B$16,MOD(Source_Data!F$6-(Inputs!$B$13+3),3)=0),$A$45*Inputs!$B$7*Inputs!$B$34*(1-Inputs!$B$15)/Inputs!$B$16,0) -> 0 | G54: =IF(Source_Data!G$6=Inputs!$B$12,-Inputs!$B$7,0)+IF(AND(Source_Data!G$6>=Inputs!$B$13+3,Source_Data!G$6<Inputs!$B$13+3+3*Inputs!$B$16,MOD(Source_Data!G$6-(Inputs!$B$13+3),3)=0),$A$45*Inputs!$B$7*Inputs!$B$34*(1-Inputs!$B$15)/Inputs!$B$16,0) -> 0 | H54: =IF(Source_Data!H$6=Inputs!$B$12,-Inputs!$B$7,0)+IF(AND(Source_Data!H$6>=Inputs!$B$13+3,Source_Data!H$6<Inputs!$B$13+3+3*Inputs!$B$16,MOD(Source_Data!H$6-(Inputs!$B$13+3),3)=0),$A$45*Inputs!$B$7*Inputs!$B$34*(1-Inputs!$B$15)/Inputs!$B$16,0) -> 0 | I54: =IF(Source_Data!I$6=Inputs!$B$12,-Inputs!$B$7,0)+IF(AND(Source_Data!I$6>=Inputs!$B$13+3,Source_Data!I$6<Inputs!$B$13+3+3*Inputs!$B$16,MOD(Source_Data!I$6-(Inputs!$B$13+3),3)=0),$A$45*Inputs!$B$7*Inputs!$B$34*(1-Inputs!$B$15)/Inputs!$B$16,0) -> 0 | J54: =IF(Source_Data!J$6=Inputs!$B$12,-Inputs!$B$7,0)+IF(AND(Source_Data!J$6>=Inputs!$B$13+3,Source_Data!J$6<Inputs!$B$13+3+3*Inputs!$B$16,MOD(Source_Data!J$6-(Inputs!$B$13+3),3)=0),$A$45*Inputs!$B$7*Inputs!$B$34*(1-Inputs!$B$15)/Inputs!$B$16,0) -> 0 | K54: =IF(Source_Data!K$6=Inputs!$B$12,-Inputs!$B$7,0)+IF(AND(Source_Data!K$6>=Inputs!$B$13+3,Source_Data!K$6<Inputs!$B$13+3+3*Inputs!$B$16,MOD(Source_Data!K$6-(Inputs!$B$13+3),3)=0),$A$45*Inputs!$B$7*Inputs!$B$34*(1-Inputs!$B$15)/Inputs!$B$16,0) -> 0 | ... BK54: =IF(Source_Data!BK$6=Inputs!$B$12,-Inputs!$B$7,0)+IF(AND(Source_Data!BK$6>=Inputs!$B$13+3,Source_Data!BK$6<Inputs!$B$13+3+3*Inputs!$B$16,MOD(Source_Data!BK$6-(Inputs!$B$13+3),3)=0),$A$45*Inputs!$B$7*Inputs!$B$34*(1-Inputs!$B$15)/Inputs!$B$16,0) -> 0
A56: Early assignment flow row 48 | D56: =IF(Source_Data!D$6=Inputs!$B$12,-Inputs!$B$7,0)+IF(Source_Data!D$6=Inputs!$B$12+24,Inputs!$B$8*Inputs!$B$7*(1-$A$48)*(1-Inputs!$B$15),0) -> -100 | E56: =IF(Source_Data!E$6=Inputs!$B$12,-Inputs!$B$7,0)+IF(Source_Data!E$6=Inputs!$B$12+24,Inputs!$B$8*Inputs!$B$7*(1-$A$48)*(1-Inputs!$B$15),0) -> 0 | F56: =IF(Source_Data!F$6=Inputs!$B$12,-Inputs!$B$7,0)+IF(Source_Data!F$6=Inputs!$B$12+24,Inputs!$B$8*Inputs!$B$7*(1-$A$48)*(1-Inputs!$B$15),0) -> 0 | G56: =IF(Source_Data!G$6=Inputs!$B$12,-Inputs!$B$7,0)+IF(Source_Data!G$6=Inputs!$B$12+24,Inputs!$B$8*Inputs!$B$7*(1-$A$48)*(1-Inputs!$B$15),0) -> 0 | H56: =IF(Source_Data!H$6=Inputs!$B$12,-Inputs!$B$7,0)+IF(Source_Data!H$6=Inputs!$B$12+24,Inputs!$B$8*Inputs!$B$7*(1-$A$48)*(1-Inputs!$B$15),0) -> 0 | I56: =IF(Source_Data!I$6=Inputs!$B$12,-Inputs!$B$7,0)+IF(Source_Data!I$6=Inputs!$B$12+24,Inputs!$B$8*Inputs!$B$7*(1-$A$48)*(1-Inputs!$B$15),0) -> 0 | J56: =IF(Source_Data!J$6=Inputs!$B$12,-Inputs!$B$7,0)+IF(Source_Data!J$6=Inputs!$B$12+24,Inputs!$B$8*Inputs!$B$7*(1-$A$48)*(1-Inputs!$B$15),0) -> 0 | K56: =IF(Source_Data!K$6=Inputs!$B$12,-Inputs!$B$7,0)+IF(Source_Data!K$6=Inputs!$B$12+24,Inputs!$B$8*Inputs!$B$7*(1-$A$48)*(1-Inputs!$B$15),0) -> 0 | ... BK56: =IF(Source_Data!BK$6=Inputs!$B$12,-Inputs!$B$7,0)+IF(Source_Data!BK$6=Inputs!$B$12+24,Inputs!$B$8*Inputs!$B$7*(1-$A$48)*(1-Inputs!$B$15),0) -> 0
A57: Early assignment flow row 49 | D57: =IF(Source_Data!D$6=Inputs!$B$12,-Inputs!$B$7,0)+IF(Source_Data!D$6=Inputs!$B$12+24,Inputs!$B$8*Inputs!$B$7*(1-$A$49)*(1-Inputs!$B$15),0) -> -100 | E57: =IF(Source_Data!E$6=Inputs!$B$12,-Inputs!$B$7,0)+IF(Source_Data!E$6=Inputs!$B$12+24,Inputs!$B$8*Inputs!$B$7*(1-$A$49)*(1-Inputs!$B$15),0) -> 0 | F57: =IF(Source_Data!F$6=Inputs!$B$12,-Inputs!$B$7,0)+IF(Source_Data!F$6=Inputs!$B$12+24,Inputs!$B$8*Inputs!$B$7*(1-$A$49)*(1-Inputs!$B$15),0) -> 0 | G57: =IF(Source_Data!G$6=Inputs!$B$12,-Inputs!$B$7,0)+IF(Source_Data!G$6=Inputs!$B$12+24,Inputs!$B$8*Inputs!$B$7*(1-$A$49)*(1-Inputs!$B$15),0) -> 0 | H57: =IF(Source_Data!H$6=Inputs!$B$12,-Inputs!$B$7,0)+IF(Source_Data!H$6=Inputs!$B$12+24,Inputs!$B$8*Inputs!$B$7*(1-$A$49)*(1-Inputs!$B$15),0) -> 0 | I57: =IF(Source_Data!I$6=Inputs!$B$12,-Inputs!$B$7,0)+IF(Source_Data!I$6=Inputs!$B$12+24,Inputs!$B$8*Inputs!$B$7*(1-$A$49)*(1-Inputs!$B$15),0) -> 0 | J57: =IF(Source_Data!J$6=Inputs!$B$12,-Inputs!$B$7,0)+IF(Source_Data!J$6=Inputs!$B$12+24,Inputs!$B$8*Inputs!$B$7*(1-$A$49)*(1-Inputs!$B$15),0) -> 0 | K57: =IF(Source_Data!K$6=Inputs!$B$12,-Inputs!$B$7,0)+IF(Source_Data!K$6=Inputs!$B$12+24,Inputs!$B$8*Inputs!$B$7*(1-$A$49)*(1-Inputs!$B$15),0) -> 0 | ... BK57: =IF(Source_Data!BK$6=Inputs!$B$12,-Inputs!$B$7,0)+IF(Source_Data!BK$6=Inputs!$B$12+24,Inputs!$B$8*Inputs!$B$7*(1-$A$49)*(1-Inputs!$B$15),0) -> 0
A58: Early assignment flow row 50 | D58: =IF(Source_Data!D$6=Inputs!$B$12,-Inputs!$B$7,0)+IF(Source_Data!D$6=Inputs!$B$12+24,Inputs!$B$8*Inputs!$B$7*(1-$A$50)*(1-Inputs!$B$15),0) -> -100 | E58: =IF(Source_Data!E$6=Inputs!$B$12,-Inputs!$B$7,0)+IF(Source_Data!E$6=Inputs!$B$12+24,Inputs!$B$8*Inputs!$B$7*(1-$A$50)*(1-Inputs!$B$15),0) -> 0 | F58: =IF(Source_Data!F$6=Inputs!$B$12,-Inputs!$B$7,0)+IF(Source_Data!F$6=Inputs!$B$12+24,Inputs!$B$8*Inputs!$B$7*(1-$A$50)*(1-Inputs!$B$15),0) -> 0 | G58: =IF(Source_Data!G$6=Inputs!$B$12,-Inputs!$B$7,0)+IF(Source_Data!G$6=Inputs!$B$12+24,Inputs!$B$8*Inputs!$B$7*(1-$A$50)*(1-Inputs!$B$15),0) -> 0 | H58: =IF(Source_Data!H$6=Inputs!$B$12,-Inputs!$B$7,0)+IF(Source_Data!H$6=Inputs!$B$12+24,Inputs!$B$8*Inputs!$B$7*(1-$A$50)*(1-Inputs!$B$15),0) -> 0 | I58: =IF(Source_Data!I$6=Inputs!$B$12,-Inputs!$B$7,0)+IF(Source_Data!I$6=Inputs!$B$12+24,Inputs!$B$8*Inputs!$B$7*(1-$A$50)*(1-Inputs!$B$15),0) -> 0 | J58: =IF(Source_Data!J$6=Inputs!$B$12,-Inputs!$B$7,0)+IF(Source_Data!J$6=Inputs!$B$12+24,Inputs!$B$8*Inputs!$B$7*(1-$A$50)*(1-Inputs!$B$15),0) -> 0 | K58: =IF(Source_Data!K$6=Inputs!$B$12,-Inputs!$B$7,0)+IF(Source_Data!K$6=Inputs!$B$12+24,Inputs!$B$8*Inputs!$B$7*(1-$A$50)*(1-Inputs!$B$15),0) -> 0 | ... BK58: =IF(Source_Data!BK$6=Inputs!$B$12,-Inputs!$B$7,0)+IF(Source_Data!BK$6=Inputs!$B$12+24,Inputs!$B$8*Inputs!$B$7*(1-$A$50)*(1-Inputs!$B$15),0) -> 0
A59: Early assignment flow row 51 | D59: =IF(Source_Data!D$6=Inputs!$B$12,-Inputs!$B$7,0)+IF(Source_Data!D$6=Inputs!$B$12+24,Inputs!$B$8*Inputs!$B$7*(1-$A$51)*(1-Inputs!$B$15),0) -> -100 | E59: =IF(Source_Data!E$6=Inputs!$B$12,-Inputs!$B$7,0)+IF(Source_Data!E$6=Inputs!$B$12+24,Inputs!$B$8*Inputs!$B$7*(1-$A$51)*(1-Inputs!$B$15),0) -> 0 | F59: =IF(Source_Data!F$6=Inputs!$B$12,-Inputs!$B$7,0)+IF(Source_Data!F$6=Inputs!$B$12+24,Inputs!$B$8*Inputs!$B$7*(1-$A$51)*(1-Inputs!$B$15),0) -> 0 | G59: =IF(Source_Data!G$6=Inputs!$B$12,-Inputs!$B$7,0)+IF(Source_Data!G$6=Inputs!$B$12+24,Inputs!$B$8*Inputs!$B$7*(1-$A$51)*(1-Inputs!$B$15),0) -> 0 | H59: =IF(Source_Data!H$6=Inputs!$B$12,-Inputs!$B$7,0)+IF(Source_Data!H$6=Inputs!$B$12+24,Inputs!$B$8*Inputs!$B$7*(1-$A$51)*(1-Inputs!$B$15),0) -> 0 | I59: =IF(Source_Data!I$6=Inputs!$B$12,-Inputs!$B$7,0)+IF(Source_Data!I$6=Inputs!$B$12+24,Inputs!$B$8*Inputs!$B$7*(1-$A$51)*(1-Inputs!$B$15),0) -> 0 | J59: =IF(Source_Data!J$6=Inputs!$B$12,-Inputs!$B$7,0)+IF(Source_Data!J$6=Inputs!$B$12+24,Inputs!$B$8*Inputs!$B$7*(1-$A$51)*(1-Inputs!$B$15),0) -> 0 | K59: =IF(Source_Data!K$6=Inputs!$B$12,-Inputs!$B$7,0)+IF(Source_Data!K$6=Inputs!$B$12+24,Inputs!$B$8*Inputs!$B$7*(1-$A$51)*(1-Inputs!$B$15),0) -> 0 | ... BK59: =IF(Source_Data!BK$6=Inputs!$B$12,-Inputs!$B$7,0)+IF(Source_Data!BK$6=Inputs!$B$12+24,Inputs!$B$8*Inputs!$B$7*(1-$A$51)*(1-Inputs!$B$15),0) -> 0

Sheet Option_B
A1: Green Square: Option B (cash), ticket EGP 100m
A2: S1 is the recommended structure. S2 and S3 are alternatives considered. Payouts after a grace period; nothing is held in a restricted account.
A4: Quarterly flows (EGP m) | B4: Total
A5: Month | D5: =Source_Data!D$6 -> 3 | E5: =Source_Data!E$6 -> 6 | F5: =Source_Data!F$6 -> 9 | G5: =Source_Data!G$6 -> 12 | H5: =Source_Data!H$6 -> 15 | I5: =Source_Data!I$6 -> 18 | J5: =Source_Data!J$6 -> 21 | K5: =Source_Data!K$6 -> 24 | ... BK5: =Source_Data!BK$6 -> 180
A6: Payout window flag | D6: =IF(AND(Source_Data!D$6>=Inputs!$B$54,Source_Data!D$6<Inputs!$B$54+3*Inputs!$B$11),1,0) -> 0 | E6: =IF(AND(Source_Data!E$6>=Inputs!$B$54,Source_Data!E$6<Inputs!$B$54+3*Inputs!$B$11),1,0) -> 0 | F6: =IF(AND(Source_Data!F$6>=Inputs!$B$54,Source_Data!F$6<Inputs!$B$54+3*Inputs!$B$11),1,0) -> 0 | G6: =IF(AND(Source_Data!G$6>=Inputs!$B$54,Source_Data!G$6<Inputs!$B$54+3*Inputs!$B$11),1,0) -> 0 | H6: =IF(AND(Source_Data!H$6>=Inputs!$B$54,Source_Data!H$6<Inputs!$B$54+3*Inputs!$B$11),1,0) -> 0 | I6: =IF(AND(Source_Data!I$6>=Inputs!$B$54,Source_Data!I$6<Inputs!$B$54+3*Inputs!$B$11),1,0) -> 0 | J6: =IF(AND(Source_Data!J$6>=Inputs!$B$54,Source_Data!J$6<Inputs!$B$54+3*Inputs!$B$11),1,0) -> 0 | K6: =IF(AND(Source_Data!K$6>=Inputs!$B$54,Source_Data!K$6<Inputs!$B$54+3*Inputs!$B$11),1,0) -> 0 | ... BK6: =IF(AND(Source_Data!BK$6>=Inputs!$B$54,Source_Data!BK$6<Inputs!$B$54+3*Inputs!$B$11),1,0) -> 0
A7: Net cash flow before payouts (Project_CF) | B7: =SUM(D7:BK7) -> 375.44753 | D7: =Project_CF!D13 -> -91.25 | E7: =Project_CF!E13 -> -11.25 | F7: =Project_CF!F13 -> 3.8892375 | G7: =Project_CF!G13 -> 19.028475 | H7: =Project_CF!H13 -> 1.0120062 | I7: =Project_CF!I13 -> 9.8855375 | J7: =Project_CF!J13 -> -18.24569 | K7: =Project_CF!K13 -> -1.4978306 | ... BK7: =Project_CF!BK13 -> 0
A8: Collections (Project_CF) | B8: =SUM(D8:BK8) -> 2252.979 | D8: =Project_CF!D8 -> 0 | E8: =Project_CF!E8 -> 0 | F8: =Project_CF!F8 -> 15.139238 | G8: =Project_CF!G8 -> 30.278475 | H8: =Project_CF!H8 -> 46.512006 | I8: =Project_CF!I8 -> 62.745537 | J8: =Project_CF!J8 -> 62.3657 | K8: =Project_CF!K8 -> 63.473559 | ... BK8: =Project_CF!BK8 -> 0
A9: S1 payouts: fixed multiple, equal instalments | B9: =SUM(D9:BK9) -> 230 | D9: =D6*(Inputs!$B$9*Inputs!$B$7/Inputs!$B$11) -> 0 | E9: =E6*(Inputs!$B$9*Inputs!$B$7/Inputs!$B$11) -> 0 | F9: =F6*(Inputs!$B$9*Inputs!$B$7/Inputs!$B$11) -> 0 | G9: =G6*(Inputs!$B$9*Inputs!$B$7/Inputs!$B$11) -> 0 | H9: =H6*(Inputs!$B$9*Inputs!$B$7/Inputs!$B$11) -> 0 | I9: =I6*(Inputs!$B$9*Inputs!$B$7/Inputs!$B$11) -> 0 | J9: =J6*(Inputs!$B$9*Inputs!$B$7/Inputs!$B$11) -> 0 | K9: =K6*(Inputs!$B$9*Inputs!$B$7/Inputs!$B$11) -> 0 | ... BK9: =BK6*(Inputs!$B$9*Inputs!$B$7/Inputs!$B$11) -> 0
A10: S2 payouts: share of collections with floor and cap | B10: =SUM(D10:BK10) -> 230 | D10: =IF(Source_Data!D$6>=Inputs!$B$54,MAX(0,MIN(MAX(MIN(Inputs!$B$37*D8,Inputs!$B$39*(Inputs!$B$9*Inputs!$B$7/Inputs!$B$11)),Inputs!$B$38*(Inputs!$B$9*Inputs!$B$7/Inputs!$B$11)),Inputs!$B$9*Inputs!$B$7-0)),0) -> 0 | E10: =IF(Source_Data!E$6>=Inputs!$B$54,MAX(0,MIN(MAX(MIN(Inputs!$B$37*E8,Inputs!$B$39*(Inputs!$B$9*Inputs!$B$7/Inputs!$B$11)),Inputs!$B$38*(Inputs!$B$9*Inputs!$B$7/Inputs!$B$11)),Inputs!$B$9*Inputs!$B$7-SUM($D$10:D10))),0) -> 0 | F10: =IF(Source_Data!F$6>=Inputs!$B$54,MAX(0,MIN(MAX(MIN(Inputs!$B$37*F8,Inputs!$B$39*(Inputs!$B$9*Inputs!$B$7/Inputs!$B$11)),Inputs!$B$38*(Inputs!$B$9*Inputs!$B$7/Inputs!$B$11)),Inputs!$B$9*Inputs!$B$7-SUM($D$10:E10))),0) -> 0 | G10: =IF(Source_Data!G$6>=Inputs!$B$54,MAX(0,MIN(MAX(MIN(Inputs!$B$37*G8,Inputs!$B$39*(Inputs!$B$9*Inputs!$B$7/Inputs!$B$11)),Inputs!$B$38*(Inputs!$B$9*Inputs!$B$7/Inputs!$B$11)),Inputs!$B$9*Inputs!$B$7-SUM($D$10:F10))),0) -> 0 | H10: =IF(Source_Data!H$6>=Inputs!$B$54,MAX(0,MIN(MAX(MIN(Inputs!$B$37*H8,Inputs!$B$39*(Inputs!$B$9*Inputs!$B$7/Inputs!$B$11)),Inputs!$B$38*(Inputs!$B$9*Inputs!$B$7/Inputs!$B$11)),Inputs!$B$9*Inputs!$B$7-SUM($D$10:G10))),0) -> 0 | I10: =IF(Source_Data!I$6>=Inputs!$B$54,MAX(0,MIN(MAX(MIN(Inputs!$B$37*I8,Inputs!$B$39*(Inputs!$B$9*Inputs!$B$7/Inputs!$B$11)),Inputs!$B$38*(Inputs!$B$9*Inputs!$B$7/Inputs!$B$11)),Inputs!$B$9*Inputs!$B$7-SUM($D$10:H10))),0) -> 0 | J10: =IF(Source_Data!J$6>=Inputs!$B$54,MAX(0,MIN(MAX(MIN(Inputs!$B$37*J8,Inputs!$B$39*(Inputs!$B$9*Inputs!$B$7/Inputs!$B$11)),Inputs!$B$38*(Inputs!$B$9*Inputs!$B$7/Inputs!$B$11)),Inputs!$B$9*Inputs!$B$7-SUM($D$10:I10))),0) -> 0 | K10: =IF(Source_Data!K$6>=Inputs!$B$54,MAX(0,MIN(MAX(MIN(Inputs!$B$37*K8,Inputs!$B$39*(Inputs!$B$9*Inputs!$B$7/Inputs!$B$11)),Inputs!$B$38*(Inputs!$B$9*Inputs!$B$7/Inputs!$B$11)),Inputs!$B$9*Inputs!$B$7-SUM($D$10:J10))),0) -> 0 | L10: =IF(Source_Data!L$6>=Inputs!$B$54,MAX(0,MIN(MAX(MIN(Inputs!$B$37*L8,Inputs!$B$39*(Inputs!$B$9*Inputs!$B$7/Inputs!$B$11)),Inputs!$B$38*(Inputs!$B$9*Inputs!$B$7/Inputs!$B$11)),Inputs!$B$9*Inputs!$B$7-SUM($D$10:K10))),0) -> 0 | ... BK10: =IF(Source_Data!BK$6>=Inputs!$B$54,MAX(0,MIN(MAX(MIN(Inputs!$B$37*BK8,Inputs!$B$39*(Inputs!$B$9*Inputs!$B$7/Inputs!$B$11)),Inputs!$B$38*(Inputs!$B$9*Inputs!$B$7/Inputs!$B$11)),Inputs!$B$9*Inputs!$B$7-SUM($D$10:BJ10))),0) -> 0
A11: S3 fixed part | B11: =SUM(D11:BK11) -> 180 | D11: =D6*Inputs!$B$40*Inputs!$B$7/Inputs!$B$11 -> 0 | E11: =E6*Inputs!$B$40*Inputs!$B$7/Inputs!$B$11 -> 0 | F11: =F6*Inputs!$B$40*Inputs!$B$7/Inputs!$B$11 -> 0 | G11: =G6*Inputs!$B$40*Inputs!$B$7/Inputs!$B$11 -> 0 | H11: =H6*Inputs!$B$40*Inputs!$B$7/Inputs!$B$11 -> 0 | I11: =I6*Inputs!$B$40*Inputs!$B$7/Inputs!$B$11 -> 0 | J11: =J6*Inputs!$B$40*Inputs!$B$7/Inputs!$B$11 -> 0 | K11: =K6*Inputs!$B$40*Inputs!$B$7/Inputs!$B$11 -> 0 | ... BK11: =BK6*Inputs!$B$40*Inputs!$B$7/Inputs!$B$11 -> 0
A12: S3 collections share | B12: =SUM(D12:BK12) -> 50 | D12: =IF(D6=1,MAX(0,MIN(Inputs!$B$42*D8,Inputs!$B$41*Inputs!$B$7-Inputs!$B$40*Inputs!$B$7-0)),0) -> 0 | E12: =IF(E6=1,MAX(0,MIN(Inputs!$B$42*E8,Inputs!$B$41*Inputs!$B$7-Inputs!$B$40*Inputs!$B$7-SUM($D$12:D12))),0) -> 0 | F12: =IF(F6=1,MAX(0,MIN(Inputs!$B$42*F8,Inputs!$B$41*Inputs!$B$7-Inputs!$B$40*Inputs!$B$7-SUM($D$12:E12))),0) -> 0 | G12: =IF(G6=1,MAX(0,MIN(Inputs!$B$42*G8,Inputs!$B$41*Inputs!$B$7-Inputs!$B$40*Inputs!$B$7-SUM($D$12:F12))),0) -> 0 | H12: =IF(H6=1,MAX(0,MIN(Inputs!$B$42*H8,Inputs!$B$41*Inputs!$B$7-Inputs!$B$40*Inputs!$B$7-SUM($D$12:G12))),0) -> 0 | I12: =IF(I6=1,MAX(0,MIN(Inputs!$B$42*I8,Inputs!$B$41*Inputs!$B$7-Inputs!$B$40*Inputs!$B$7-SUM($D$12:H12))),0) -> 0 | J12: =IF(J6=1,MAX(0,MIN(Inputs!$B$42*J8,Inputs!$B$41*Inputs!$B$7-Inputs!$B$40*Inputs!$B$7-SUM($D$12:I12))),0) -> 0 | K12: =IF(K6=1,MAX(0,MIN(Inputs!$B$42*K8,Inputs!$B$41*Inputs!$B$7-Inputs!$B$40*Inputs!$B$7-SUM($D$12:J12))),0) -> 0 | L12: =IF(L6=1,MAX(0,MIN(Inputs!$B$42*L8,Inputs!$B$41*Inputs!$B$7-Inputs!$B$40*Inputs!$B$7-SUM($D$12:K12))),0) -> 0 | ... BK12: =IF(BK6=1,MAX(0,MIN(Inputs!$B$42*BK8,Inputs!$B$41*Inputs!$B$7-Inputs!$B$40*Inputs!$B$7-SUM($D$12:BJ12))),0) -> 0
A13: S3 payouts: hybrid | B13: =SUM(D13:BK13) -> 230 | D13: =D11+D12 -> 0 | E13: =E11+E12 -> 0 | F13: =F11+F12 -> 0 | G13: =G11+G12 -> 0 | H13: =H11+H12 -> 0 | I13: =I11+I12 -> 0 | J13: =J11+J12 -> 0 | K13: =K11+K12 -> 0 | ... BK13: =BK11+BK12 -> 0
A14: S1 investor cash flow | D14: =-IF(Source_Data!D$6=Inputs!$B$12,Inputs!$B$7,0)+D9 -> -100 | E14: =-IF(Source_Data!E$6=Inputs!$B$12,Inputs!$B$7,0)+E9 -> 0 | F14: =-IF(Source_Data!F$6=Inputs!$B$12,Inputs!$B$7,0)+F9 -> 0 | G14: =-IF(Source_Data!G$6=Inputs!$B$12,Inputs!$B$7,0)+G9 -> 0 | H14: =-IF(Source_Data!H$6=Inputs!$B$12,Inputs!$B$7,0)+H9 -> 0 | I14: =-IF(Source_Data!I$6=Inputs!$B$12,Inputs!$B$7,0)+I9 -> 0 | J14: =-IF(Source_Data!J$6=Inputs!$B$12,Inputs!$B$7,0)+J9 -> 0 | K14: =-IF(Source_Data!K$6=Inputs!$B$12,Inputs!$B$7,0)+K9 -> 0 | ... BK14: =-IF(Source_Data!BK$6=Inputs!$B$12,Inputs!$B$7,0)+BK9 -> 0
A15: S2 investor cash flow | D15: =-IF(Source_Data!D$6=Inputs!$B$12,Inputs!$B$7,0)+D10 -> -100 | E15: =-IF(Source_Data!E$6=Inputs!$B$12,Inputs!$B$7,0)+E10 -> 0 | F15: =-IF(Source_Data!F$6=Inputs!$B$12,Inputs!$B$7,0)+F10 -> 0 | G15: =-IF(Source_Data!G$6=Inputs!$B$12,Inputs!$B$7,0)+G10 -> 0 | H15: =-IF(Source_Data!H$6=Inputs!$B$12,Inputs!$B$7,0)+H10 -> 0 | I15: =-IF(Source_Data!I$6=Inputs!$B$12,Inputs!$B$7,0)+I10 -> 0 | J15: =-IF(Source_Data!J$6=Inputs!$B$12,Inputs!$B$7,0)+J10 -> 0 | K15: =-IF(Source_Data!K$6=Inputs!$B$12,Inputs!$B$7,0)+K10 -> 0 | ... BK15: =-IF(Source_Data!BK$6=Inputs!$B$12,Inputs!$B$7,0)+BK10 -> 0
A16: S3 investor cash flow | D16: =-IF(Source_Data!D$6=Inputs!$B$12,Inputs!$B$7,0)+D13 -> -100 | E16: =-IF(Source_Data!E$6=Inputs!$B$12,Inputs!$B$7,0)+E13 -> 0 | F16: =-IF(Source_Data!F$6=Inputs!$B$12,Inputs!$B$7,0)+F13 -> 0 | G16: =-IF(Source_Data!G$6=Inputs!$B$12,Inputs!$B$7,0)+G13 -> 0 | H16: =-IF(Source_Data!H$6=Inputs!$B$12,Inputs!$B$7,0)+H13 -> 0 | I16: =-IF(Source_Data!I$6=Inputs!$B$12,Inputs!$B$7,0)+I13 -> 0 | J16: =-IF(Source_Data!J$6=Inputs!$B$12,Inputs!$B$7,0)+J13 -> 0 | K16: =-IF(Source_Data!K$6=Inputs!$B$12,Inputs!$B$7,0)+K13 -> 0 | ... BK16: =-IF(Source_Data!BK$6=Inputs!$B$12,Inputs!$B$7,0)+BK13 -> 0
A17: S1 Jalour cash flow (ticket less payouts) | D17: =IF(Source_Data!D$6=Inputs!$B$12,Inputs!$B$7,0)-D9 -> 100 | E17: =IF(Source_Data!E$6=Inputs!$B$12,Inputs!$B$7,0)-E9 -> 0 | F17: =IF(Source_Data!F$6=Inputs!$B$12,Inputs!$B$7,0)-F9 -> 0 | G17: =IF(Source_Data!G$6=Inputs!$B$12,Inputs!$B$7,0)-G9 -> 0 | H17: =IF(Source_Data!H$6=Inputs!$B$12,Inputs!$B$7,0)-H9 -> 0 | I17: =IF(Source_Data!I$6=Inputs!$B$12,Inputs!$B$7,0)-I9 -> 0 | J17: =IF(Source_Data!J$6=Inputs!$B$12,Inputs!$B$7,0)-J9 -> 0 | K17: =IF(Source_Data!K$6=Inputs!$B$12,Inputs!$B$7,0)-K9 -> 0 | ... BK17: =IF(Source_Data!BK$6=Inputs!$B$12,Inputs!$B$7,0)-BK9 -> 0
A18: S2 Jalour cash flow | D18: =IF(Source_Data!D$6=Inputs!$B$12,Inputs!$B$7,0)-D10 -> 100 | E18: =IF(Source_Data!E$6=Inputs!$B$12,Inputs!$B$7,0)-E10 -> 0 | F18: =IF(Source_Data!F$6=Inputs!$B$12,Inputs!$B$7,0)-F10 -> 0 | G18: =IF(Source_Data!G$6=Inputs!$B$12,Inputs!$B$7,0)-G10 -> 0 | H18: =IF(Source_Data!H$6=Inputs!$B$12,Inputs!$B$7,0)-H10 -> 0 | I18: =IF(Source_Data!I$6=Inputs!$B$12,Inputs!$B$7,0)-I10 -> 0 | J18: =IF(Source_Data!J$6=Inputs!$B$12,Inputs!$B$7,0)-J10 -> 0 | K18: =IF(Source_Data!K$6=Inputs!$B$12,Inputs!$B$7,0)-K10 -> 0 | ... BK18: =IF(Source_Data!BK$6=Inputs!$B$12,Inputs!$B$7,0)-BK10 -> 0
A19: S3 Jalour cash flow | D19: =IF(Source_Data!D$6=Inputs!$B$12,Inputs!$B$7,0)-D13 -> 100 | E19: =IF(Source_Data!E$6=Inputs!$B$12,Inputs!$B$7,0)-E13 -> 0 | F19: =IF(Source_Data!F$6=Inputs!$B$12,Inputs!$B$7,0)-F13 -> 0 | G19: =IF(Source_Data!G$6=Inputs!$B$12,Inputs!$B$7,0)-G13 -> 0 | H19: =IF(Source_Data!H$6=Inputs!$B$12,Inputs!$B$7,0)-H13 -> 0 | I19: =IF(Source_Data!I$6=Inputs!$B$12,Inputs!$B$7,0)-I13 -> 0 | J19: =IF(Source_Data!J$6=Inputs!$B$12,Inputs!$B$7,0)-J13 -> 0 | K19: =IF(Source_Data!K$6=Inputs!$B$12,Inputs!$B$7,0)-K13 -> 0 | ... BK19: =IF(Source_Data!BK$6=Inputs!$B$12,Inputs!$B$7,0)-BK13 -> 0
A20: S1 pooled cash after ticket and payouts | D20: =0+IF(Source_Data!D$6=Inputs!$B$12,Inputs!$B$7,0)+D7-D9 -> 8.75 | E20: =D20+IF(Source_Data!E$6=Inputs!$B$12,Inputs!$B$7,0)+E7-E9 -> -2.5 | F20: =E20+IF(Source_Data!F$6=Inputs!$B$12,Inputs!$B$7,0)+F7-F9 -> 1.3892375 | G20: =F20+IF(Source_Data!G$6=Inputs!$B$12,Inputs!$B$7,0)+G7-G9 -> 20.417713 | H20: =G20+IF(Source_Data!H$6=Inputs!$B$12,Inputs!$B$7,0)+H7-H9 -> 21.429719 | I20: =H20+IF(Source_Data!I$6=Inputs!$B$12,Inputs!$B$7,0)+I7-I9 -> 31.315256 | J20: =I20+IF(Source_Data!J$6=Inputs!$B$12,Inputs!$B$7,0)+J7-J9 -> 13.069566 | K20: =J20+IF(Source_Data!K$6=Inputs!$B$12,Inputs!$B$7,0)+K7-K9 -> 11.571736 | L20: =K20+IF(Source_Data!L$6=Inputs!$B$12,Inputs!$B$7,0)+L7-L9 -> 18.269324 | ... BK20: =BJ20+IF(Source_Data!BK$6=Inputs!$B$12,Inputs!$B$7,0)+BK7-BK9 -> 245.44753
A21: S2 pooled cash | D21: =0+IF(Source_Data!D$6=Inputs!$B$12,Inputs!$B$7,0)+D7-D10 -> 8.75 | E21: =D21+IF(Source_Data!E$6=Inputs!$B$12,Inputs!$B$7,0)+E7-E10 -> -2.5 | F21: =E21+IF(Source_Data!F$6=Inputs!$B$12,Inputs!$B$7,0)+F7-F10 -> 1.3892375 | G21: =F21+IF(Source_Data!G$6=Inputs!$B$12,Inputs!$B$7,0)+G7-G10 -> 20.417713 | H21: =G21+IF(Source_Data!H$6=Inputs!$B$12,Inputs!$B$7,0)+H7-H10 -> 21.429719 | I21: =H21+IF(Source_Data!I$6=Inputs!$B$12,Inputs!$B$7,0)+I7-I10 -> 31.315256 | J21: =I21+IF(Source_Data!J$6=Inputs!$B$12,Inputs!$B$7,0)+J7-J10 -> 13.069566 | K21: =J21+IF(Source_Data!K$6=Inputs!$B$12,Inputs!$B$7,0)+K7-K10 -> 11.571736 | L21: =K21+IF(Source_Data!L$6=Inputs!$B$12,Inputs!$B$7,0)+L7-L10 -> 18.269324 | ... BK21: =BJ21+IF(Source_Data!BK$6=Inputs!$B$12,Inputs!$B$7,0)+BK7-BK10 -> 245.44753
A22: S3 pooled cash | D22: =0+IF(Source_Data!D$6=Inputs!$B$12,Inputs!$B$7,0)+D7-D13 -> 8.75 | E22: =D22+IF(Source_Data!E$6=Inputs!$B$12,Inputs!$B$7,0)+E7-E13 -> -2.5 | F22: =E22+IF(Source_Data!F$6=Inputs!$B$12,Inputs!$B$7,0)+F7-F13 -> 1.3892375 | G22: =F22+IF(Source_Data!G$6=Inputs!$B$12,Inputs!$B$7,0)+G7-G13 -> 20.417713 | H22: =G22+IF(Source_Data!H$6=Inputs!$B$12,Inputs!$B$7,0)+H7-H13 -> 21.429719 | I22: =H22+IF(Source_Data!I$6=Inputs!$B$12,Inputs!$B$7,0)+I7-I13 -> 31.315256 | J22: =I22+IF(Source_Data!J$6=Inputs!$B$12,Inputs!$B$7,0)+J7-J13 -> 13.069566 | K22: =J22+IF(Source_Data!K$6=Inputs!$B$12,Inputs!$B$7,0)+K7-K13 -> 11.571736 | L22: =K22+IF(Source_Data!L$6=Inputs!$B$12,Inputs!$B$7,0)+L7-L13 -> 18.269324 | ... BK22: =BJ22+IF(Source_Data!BK$6=Inputs!$B$12,Inputs!$B$7,0)+BK7-BK13 -> 245.44753
A23: S1 coverage: net cash flow / payout | D23: =IF(D9>0,D7/D9,"") | E23: =IF(E9>0,E7/E9,"") | F23: =IF(F9>0,F7/F9,"") | G23: =IF(G9>0,G7/G9,"") | H23: =IF(H9>0,H7/H9,"") | I23: =IF(I9>0,I7/I9,"") | J23: =IF(J9>0,J7/J9,"") | K23: =IF(K9>0,K7/K9,"") | ... BK23: =IF(BK9>0,BK7/BK9,"")
A24: S1 coverage: cash available / payout | D24: =IF(D9>0,(0+IF(Source_Data!D$6=Inputs!$B$12,Inputs!$B$7,0)+D7)/D9,"") | E24: =IF(E9>0,(D20+IF(Source_Data!E$6=Inputs!$B$12,Inputs!$B$7,0)+E7)/E9,"") | F24: =IF(F9>0,(E20+IF(Source_Data!F$6=Inputs!$B$12,Inputs!$B$7,0)+F7)/F9,"") | G24: =IF(G9>0,(F20+IF(Source_Data!G$6=Inputs!$B$12,Inputs!$B$7,0)+G7)/G9,"") | H24: =IF(H9>0,(G20+IF(Source_Data!H$6=Inputs!$B$12,Inputs!$B$7,0)+H7)/H9,"") | I24: =IF(I9>0,(H20+IF(Source_Data!I$6=Inputs!$B$12,Inputs!$B$7,0)+I7)/I9,"") | J24: =IF(J9>0,(I20+IF(Source_Data!J$6=Inputs!$B$12,Inputs!$B$7,0)+J7)/J9,"") | K24: =IF(K9>0,(J20+IF(Source_Data!K$6=Inputs!$B$12,Inputs!$B$7,0)+K7)/K9,"") | L24: =IF(L9>0,(K20+IF(Source_Data!L$6=Inputs!$B$12,Inputs!$B$7,0)+L7)/L9,"") | ... BK24: =IF(BK9>0,(BJ20+IF(Source_Data!BK$6=Inputs!$B$12,Inputs!$B$7,0)+BK7)/BK9,"")
A25: S2 coverage: net cash flow / payout | D25: =IF(D10>0,D7/D10,"") | E25: =IF(E10>0,E7/E10,"") | F25: =IF(F10>0,F7/F10,"") | G25: =IF(G10>0,G7/G10,"") | H25: =IF(H10>0,H7/H10,"") | I25: =IF(I10>0,I7/I10,"") | J25: =IF(J10>0,J7/J10,"") | K25: =IF(K10>0,K7/K10,"") | ... BK25: =IF(BK10>0,BK7/BK10,"")
A26: S2 coverage: cash available / payout | D26: =IF(D10>0,(0+IF(Source_Data!D$6=Inputs!$B$12,Inputs!$B$7,0)+D7)/D10,"") | E26: =IF(E10>0,(D21+IF(Source_Data!E$6=Inputs!$B$12,Inputs!$B$7,0)+E7)/E10,"") | F26: =IF(F10>0,(E21+IF(Source_Data!F$6=Inputs!$B$12,Inputs!$B$7,0)+F7)/F10,"") | G26: =IF(G10>0,(F21+IF(Source_Data!G$6=Inputs!$B$12,Inputs!$B$7,0)+G7)/G10,"") | H26: =IF(H10>0,(G21+IF(Source_Data!H$6=Inputs!$B$12,Inputs!$B$7,0)+H7)/H10,"") | I26: =IF(I10>0,(H21+IF(Source_Data!I$6=Inputs!$B$12,Inputs!$B$7,0)+I7)/I10,"") | J26: =IF(J10>0,(I21+IF(Source_Data!J$6=Inputs!$B$12,Inputs!$B$7,0)+J7)/J10,"") | K26: =IF(K10>0,(J21+IF(Source_Data!K$6=Inputs!$B$12,Inputs!$B$7,0)+K7)/K10,"") | L26: =IF(L10>0,(K21+IF(Source_Data!L$6=Inputs!$B$12,Inputs!$B$7,0)+L7)/L10,"") | ... BK26: =IF(BK10>0,(BJ21+IF(Source_Data!BK$6=Inputs!$B$12,Inputs!$B$7,0)+BK7)/BK10,"")
A27: S3 coverage: net cash flow / payout | D27: =IF(D13>0,D7/D13,"") | E27: =IF(E13>0,E7/E13,"") | F27: =IF(F13>0,F7/F13,"") | G27: =IF(G13>0,G7/G13,"") | H27: =IF(H13>0,H7/H13,"") | I27: =IF(I13>0,I7/I13,"") | J27: =IF(J13>0,J7/J13,"") | K27: =IF(K13>0,K7/K13,"") | ... BK27: =IF(BK13>0,BK7/BK13,"")
A28: S3 coverage: cash available / payout | D28: =IF(D13>0,(0+IF(Source_Data!D$6=Inputs!$B$12,Inputs!$B$7,0)+D7)/D13,"") | E28: =IF(E13>0,(D22+IF(Source_Data!E$6=Inputs!$B$12,Inputs!$B$7,0)+E7)/E13,"") | F28: =IF(F13>0,(E22+IF(Source_Data!F$6=Inputs!$B$12,Inputs!$B$7,0)+F7)/F13,"") | G28: =IF(G13>0,(F22+IF(Source_Data!G$6=Inputs!$B$12,Inputs!$B$7,0)+G7)/G13,"") | H28: =IF(H13>0,(G22+IF(Source_Data!H$6=Inputs!$B$12,Inputs!$B$7,0)+H7)/H13,"") | I28: =IF(I13>0,(H22+IF(Source_Data!I$6=Inputs!$B$12,Inputs!$B$7,0)+I7)/I13,"") | J28: =IF(J13>0,(I22+IF(Source_Data!J$6=Inputs!$B$12,Inputs!$B$7,0)+J7)/J13,"") | K28: =IF(K13>0,(J22+IF(Source_Data!K$6=Inputs!$B$12,Inputs!$B$7,0)+K7)/K13,"") | L28: =IF(L13>0,(K22+IF(Source_Data!L$6=Inputs!$B$12,Inputs!$B$7,0)+L7)/L13,"") | ... BK28: =IF(BK13>0,(BJ22+IF(Source_Data!BK$6=Inputs!$B$12,Inputs!$B$7,0)+BK7)/BK13,"")
A31: Structure comparison (base case) | B31: S1 Fixed multiple | C31: S2 % of collections | D31: S3 Hybrid
A32: Total paid (EGP m) | B32: =SUM(D9:BK9) -> 230 | C32: =SUM(D10:BK10) -> 230 | D32: =SUM(D13:BK13) -> 230
A33: Total multiple | B33: =B32/Inputs!$B$7 -> 2.3 | C33: =C32/Inputs!$B$7 -> 2.3 | D33: =D32/Inputs!$B$7 -> 2.3
A34: Investor IRR | B34: =(1+IRR(D14:BK14,0.05))^4-1 -> 0.26546399 | C34: =(1+IRR(D15:BK15,0.05))^4-1 -> 0.29027663 | D34: =(1+IRR(D16:BK16,0.05))^4-1 -> 0.27835276
A35: Jalour cost of capital | B35: =(1+IRR(D17:BK17,0.05))^4-1 -> 0.26546399 | C35: =(1+IRR(D18:BK18,0.05))^4-1 -> 0.29027663 | D35: =(1+IRR(D19:BK19,0.05))^4-1 -> 0.27835276
A36: NPV to Jalour @ discount rate | B36: =SUMPRODUCT(D17:BK17,Project_CF!$D$15:$BK$15) -> -42.536579 | C36: =SUMPRODUCT(D18:BK18,Project_CF!$D$15:$BK$15) -> -47.47675 | D36: =SUMPRODUCT(D19:BK19,Project_CF!$D$15:$BK$15) -> -45.110927
A37: Lowest quarterly coverage: net cash flow / payout | B37: =MIN(D23:BK23) -> -8.9504782 | C37: =MIN(D25:BK25) -> -9.7298793 | D37: =MIN(D27:BK27) -> -9.8151482
A38: Quarters below threshold (net cash flow basis) | B38: =COUNTIF(D23:BK23,"<"&Inputs!$B$43) -> 9 | C38: =COUNTIF(D25:BK25,"<"&Inputs!$B$43) -> 8 | D38: =COUNTIF(D27:BK27,"<"&Inputs!$B$43) -> 8
A39: Payout quarters | B39: =COUNTIF(D9:BK9,">0") -> 12 | C39: =COUNTIF(D10:BK10,">0") -> 13 | D39: =COUNTIF(D13:BK13,">0") -> 12
A40: Lowest coverage: cash available / payout | B40: =MIN(D24:BK24) -> 2.9584222 | C40: =MIN(D26:BK26) -> 3.4924755 | D40: =MIN(D28:BK28) -> 3.0989222
A41: Quarters below threshold (cash available basis) | B41: =COUNTIF(D24:BK24,"<"&Inputs!$B$43) -> 0 | C41: =COUNTIF(D26:BK26,"<"&Inputs!$B$43) -> 0 | D41: =COUNTIF(D28:BK28,"<"&Inputs!$B$43) -> 0
A42: Lowest pooled cash after ticket and payouts | B42: =MIN(D20:BK20) -> -2.5 | C42: =MIN(D21:BK21) -> -2.5 | D42: =MIN(D22:BK22) -> -2.5
A43: Last payout month | B43: =SUMPRODUCT(MAX((D9:BK9>0)*D5:BK5)) -> 63 | C43: =SUMPRODUCT(MAX((D10:BK10>0)*D5:BK5)) -> 66 | D43: =SUMPRODUCT(MAX((D13:BK13>0)*D5:BK5)) -> 63
A46: Payback month (S1): first quarter cumulative investor cash flow is not negative | B46: =INDEX(D5:BK5,MATCH(1,D48:BK48,0)) -> 45
A47: S1 investor cumulative cash flow | D47: =D14 -> -100 | E47: =D47+E14 -> -100 | F47: =E47+F14 -> -100 | G47: =F47+G14 -> -100 | H47: =G47+H14 -> -100 | I47: =H47+I14 -> -100 | J47: =I47+J14 -> -100 | K47: =J47+K14 -> -100 | L47: =K47+L14 -> -100 | ... BK47: =BJ47+BK14 -> 130
A48: Not negative (1/0) | D48: =IF(AND(D47>=0,D5>Inputs!$B$12),1,0) -> 0 | E48: =IF(AND(E47>=0,E5>Inputs!$B$12),1,0) -> 0 | F48: =IF(AND(F47>=0,F5>Inputs!$B$12),1,0) -> 0 | G48: =IF(AND(G47>=0,G5>Inputs!$B$12),1,0) -> 0 | H48: =IF(AND(H47>=0,H5>Inputs!$B$12),1,0) -> 0 | I48: =IF(AND(I47>=0,I5>Inputs!$B$12),1,0) -> 0 | J48: =IF(AND(J47>=0,J5>Inputs!$B$12),1,0) -> 0 | K48: =IF(AND(K47>=0,K5>Inputs!$B$12),1,0) -> 0 | ... BK48: =IF(AND(BK47>=0,BK5>Inputs!$B$12),1,0) -> 1

Sheet Scenarios
A1: Green Square: scenario analysis (live blocks; edit the blue parameters)
A2: Each block recalculates the project, Option A (investor resale at the scenario price and delay) and Option B (fixed payouts) from Source_Data.
A4: Base case
A5: Price factor | B5: 1
A6: Sales delay (quarters) | B6: 0
A7: Cost factor | B7: 1
A8: Collections slip (quarters) | B8: 0
A9: Delivery payments at handover (1 = yes) | B9: 0
A10: Resale start month (Option A) | B10: =Inputs!$B$13+3+3*$B$6 -> 51
A11: Collections before delay and price | D11: =Source_Data!D$7+IF($B$9=1,IF(Source_Data!D$6=Inputs!$B$13,Source_Data!$C$8,0),Source_Data!D$8) -> 0 | E11: =Source_Data!E$7+IF($B$9=1,IF(Source_Data!E$6=Inputs!$B$13,Source_Data!$C$8,0),Source_Data!E$8) -> 0 | F11: =Source_Data!F$7+IF($B$9=1,IF(Source_Data!F$6=Inputs!$B$13,Source_Data!$C$8,0),Source_Data!F$8) -> 15.139238 | G11: =Source_Data!G$7+IF($B$9=1,IF(Source_Data!G$6=Inputs!$B$13,Source_Data!$C$8,0),Source_Data!G$8) -> 30.278475 | H11: =Source_Data!H$7+IF($B$9=1,IF(Source_Data!H$6=Inputs!$B$13,Source_Data!$C$8,0),Source_Data!H$8) -> 46.512006 | I11: =Source_Data!I$7+IF($B$9=1,IF(Source_Data!I$6=Inputs!$B$13,Source_Data!$C$8,0),Source_Data!I$8) -> 62.745537 | J11: =Source_Data!J$7+IF($B$9=1,IF(Source_Data!J$6=Inputs!$B$13,Source_Data!$C$8,0),Source_Data!J$8) -> 62.3657 | K11: =Source_Data!K$7+IF($B$9=1,IF(Source_Data!K$6=Inputs!$B$13,Source_Data!$C$8,0),Source_Data!K$8) -> 63.473559 | ... BK11: =Source_Data!BK$7+IF($B$9=1,IF(Source_Data!BK$6=Inputs!$B$13,Source_Data!$C$8,0),Source_Data!BK$8) -> 0
A12: Collections | D12: =$B$5*IF(Source_Data!D$5-($B$6+$B$8)>=1,INDEX($D$11:$BK$11,1,Source_Data!D$5-($B$6+$B$8)),0) -> 0 | E12: =$B$5*IF(Source_Data!E$5-($B$6+$B$8)>=1,INDEX($D$11:$BK$11,1,Source_Data!E$5-($B$6+$B$8)),0) -> 0 | F12: =$B$5*IF(Source_Data!F$5-($B$6+$B$8)>=1,INDEX($D$11:$BK$11,1,Source_Data!F$5-($B$6+$B$8)),0) -> 15.139238 | G12: =$B$5*IF(Source_Data!G$5-($B$6+$B$8)>=1,INDEX($D$11:$BK$11,1,Source_Data!G$5-($B$6+$B$8)),0) -> 30.278475 | H12: =$B$5*IF(Source_Data!H$5-($B$6+$B$8)>=1,INDEX($D$11:$BK$11,1,Source_Data!H$5-($B$6+$B$8)),0) -> 46.512006 | I12: =$B$5*IF(Source_Data!I$5-($B$6+$B$8)>=1,INDEX($D$11:$BK$11,1,Source_Data!I$5-($B$6+$B$8)),0) -> 62.745537 | J12: =$B$5*IF(Source_Data!J$5-($B$6+$B$8)>=1,INDEX($D$11:$BK$11,1,Source_Data!J$5-($B$6+$B$8)),0) -> 62.3657 | K12: =$B$5*IF(Source_Data!K$5-($B$6+$B$8)>=1,INDEX($D$11:$BK$11,1,Source_Data!K$5-($B$6+$B$8)),0) -> 63.473559 | ... BK12: =$B$5*IF(Source_Data!BK$5-($B$6+$B$8)>=1,INDEX($D$11:$BK$11,1,Source_Data!BK$5-($B$6+$B$8)),0) -> 0
A13: Landlord payments | D13: =Source_Data!D$9+Source_Data!D$10*IF(Source_Data!$C$10=0,0,MAX(0,Inputs!$B$19*Inputs!$B$22*$B$5-Inputs!$B$20)/Source_Data!$C$10) -> 91.25 | E13: =Source_Data!E$9+Source_Data!E$10*IF(Source_Data!$C$10=0,0,MAX(0,Inputs!$B$19*Inputs!$B$22*$B$5-Inputs!$B$20)/Source_Data!$C$10) -> 11.25 | F13: =Source_Data!F$9+Source_Data!F$10*IF(Source_Data!$C$10=0,0,MAX(0,Inputs!$B$19*Inputs!$B$22*$B$5-Inputs!$B$20)/Source_Data!$C$10) -> 11.25 | G13: =Source_Data!G$9+Source_Data!G$10*IF(Source_Data!$C$10=0,0,MAX(0,Inputs!$B$19*Inputs!$B$22*$B$5-Inputs!$B$20)/Source_Data!$C$10) -> 11.25 | H13: =Source_Data!H$9+Source_Data!H$10*IF(Source_Data!$C$10=0,0,MAX(0,Inputs!$B$19*Inputs!$B$22*$B$5-Inputs!$B$20)/Source_Data!$C$10) -> 22.5 | I13: =Source_Data!I$9+Source_Data!I$10*IF(Source_Data!$C$10=0,0,MAX(0,Inputs!$B$19*Inputs!$B$22*$B$5-Inputs!$B$20)/Source_Data!$C$10) -> 22.5 | J13: =Source_Data!J$9+Source_Data!J$10*IF(Source_Data!$C$10=0,0,MAX(0,Inputs!$B$19*Inputs!$B$22*$B$5-Inputs!$B$20)/Source_Data!$C$10) -> 22.5 | K13: =Source_Data!K$9+Source_Data!K$10*IF(Source_Data!$C$10=0,0,MAX(0,Inputs!$B$19*Inputs!$B$22*$B$5-Inputs!$B$20)/Source_Data!$C$10) -> 22.5 | ... BK13: =Source_Data!BK$9+Source_Data!BK$10*IF(Source_Data!$C$10=0,0,MAX(0,Inputs!$B$19*Inputs!$B$22*$B$5-Inputs!$B$20)/Source_Data!$C$10) -> 0
A14: Construction cost | D14: =Source_Data!D$11*$B$7 -> 0 | E14: =Source_Data!E$11*$B$7 -> 0 | F14: =Source_Data!F$11*$B$7 -> 0 | G14: =Source_Data!G$11*$B$7 -> 0 | H14: =Source_Data!H$11*$B$7 -> 20 | I14: =Source_Data!I$11*$B$7 -> 26.4 | J14: =Source_Data!J$11*$B$7 -> 40 | K14: =Source_Data!K$11*$B$7 -> 26.4 | ... BK14: =Source_Data!BK$11*$B$7 -> 0
A15: Sales commission | D15: =$B$5*IF(Source_Data!D$5-$B$6>=1,INDEX(Source_Data!$D$12:$BK$12,1,Source_Data!D$5-$B$6),0) -> 0 | E15: =$B$5*IF(Source_Data!E$5-$B$6>=1,INDEX(Source_Data!$D$12:$BK$12,1,Source_Data!E$5-$B$6),0) -> 0 | F15: =$B$5*IF(Source_Data!F$5-$B$6>=1,INDEX(Source_Data!$D$12:$BK$12,1,Source_Data!F$5-$B$6),0) -> 0 | G15: =$B$5*IF(Source_Data!G$5-$B$6>=1,INDEX(Source_Data!$D$12:$BK$12,1,Source_Data!G$5-$B$6),0) -> 0 | H15: =$B$5*IF(Source_Data!H$5-$B$6>=1,INDEX(Source_Data!$D$12:$BK$12,1,Source_Data!H$5-$B$6),0) -> 0 | I15: =$B$5*IF(Source_Data!I$5-$B$6>=1,INDEX(Source_Data!$D$12:$BK$12,1,Source_Data!I$5-$B$6),0) -> 0 | J15: =$B$5*IF(Source_Data!J$5-$B$6>=1,INDEX(Source_Data!$D$12:$BK$12,1,Source_Data!J$5-$B$6),0) -> 12.11139 | K15: =$B$5*IF(Source_Data!K$5-$B$6>=1,INDEX(Source_Data!$D$12:$BK$12,1,Source_Data!K$5-$B$6),0) -> 12.11139 | ... BK15: =$B$5*IF(Source_Data!BK$5-$B$6>=1,INDEX(Source_Data!$D$12:$BK$12,1,Source_Data!BK$5-$B$6),0) -> 0
A16: SG&A and others | D16: =Source_Data!D$13*$B$7 -> 0 | E16: =Source_Data!E$13*$B$7 -> 0 | F16: =Source_Data!F$13*$B$7 -> 0 | G16: =Source_Data!G$13*$B$7 -> 0 | H16: =Source_Data!H$13*$B$7 -> 3 | I16: =Source_Data!I$13*$B$7 -> 3.96 | J16: =Source_Data!J$13*$B$7 -> 6 | K16: =Source_Data!K$13*$B$7 -> 3.96 | ... BK16: =Source_Data!BK$13*$B$7 -> 0
A17: Net cash flow | D17: =D12-D13-D14-D15-D16 -> -91.25 | E17: =E12-E13-E14-E15-E16 -> -11.25 | F17: =F12-F13-F14-F15-F16 -> 3.8892375 | G17: =G12-G13-G14-G15-G16 -> 19.028475 | H17: =H12-H13-H14-H15-H16 -> 1.0120062 | I17: =I12-I13-I14-I15-I16 -> 9.8855375 | J17: =J12-J13-J14-J15-J16 -> -18.24569 | K17: =K12-K13-K14-K15-K16 -> -1.4978306 | ... BK17: =BK12-BK13-BK14-BK15-BK16 -> 0
A18: Cumulative net cash flow | D18: =D17 -> -91.25 | E18: =D18+E17 -> -102.5 | F18: =E18+F17 -> -98.610763 | G18: =F18+G17 -> -79.582288 | H18: =G18+H17 -> -78.570281 | I18: =H18+I17 -> -68.684744 | J18: =I18+J17 -> -86.930434 | K18: =J18+K17 -> -88.428264 | L18: =K18+L17 -> -81.730676 | ... BK18: =BJ18+BK17 -> 375.44753
A19: Option A investor cash flow | D19: =IF(Source_Data!D$6=Inputs!$B$12,-Inputs!$B$7,0)+IF(AND(Source_Data!D$6>=$B$10,Source_Data!D$6<$B$10+3*Inputs!$B$16,MOD(Source_Data!D$6-$B$10,3)=0),Inputs!$B$8*Inputs!$B$7*Inputs!$B$34*$B$5*(1-Inputs!$B$15)/Inputs!$B$16,0) -> -100 | E19: =IF(Source_Data!E$6=Inputs!$B$12,-Inputs!$B$7,0)+IF(AND(Source_Data!E$6>=$B$10,Source_Data!E$6<$B$10+3*Inputs!$B$16,MOD(Source_Data!E$6-$B$10,3)=0),Inputs!$B$8*Inputs!$B$7*Inputs!$B$34*$B$5*(1-Inputs!$B$15)/Inputs!$B$16,0) -> 0 | F19: =IF(Source_Data!F$6=Inputs!$B$12,-Inputs!$B$7,0)+IF(AND(Source_Data!F$6>=$B$10,Source_Data!F$6<$B$10+3*Inputs!$B$16,MOD(Source_Data!F$6-$B$10,3)=0),Inputs!$B$8*Inputs!$B$7*Inputs!$B$34*$B$5*(1-Inputs!$B$15)/Inputs!$B$16,0) -> 0 | G19: =IF(Source_Data!G$6=Inputs!$B$12,-Inputs!$B$7,0)+IF(AND(Source_Data!G$6>=$B$10,Source_Data!G$6<$B$10+3*Inputs!$B$16,MOD(Source_Data!G$6-$B$10,3)=0),Inputs!$B$8*Inputs!$B$7*Inputs!$B$34*$B$5*(1-Inputs!$B$15)/Inputs!$B$16,0) -> 0 | H19: =IF(Source_Data!H$6=Inputs!$B$12,-Inputs!$B$7,0)+IF(AND(Source_Data!H$6>=$B$10,Source_Data!H$6<$B$10+3*Inputs!$B$16,MOD(Source_Data!H$6-$B$10,3)=0),Inputs!$B$8*Inputs!$B$7*Inputs!$B$34*$B$5*(1-Inputs!$B$15)/Inputs!$B$16,0) -> 0 | I19: =IF(Source_Data!I$6=Inputs!$B$12,-Inputs!$B$7,0)+IF(AND(Source_Data!I$6>=$B$10,Source_Data!I$6<$B$10+3*Inputs!$B$16,MOD(Source_Data!I$6-$B$10,3)=0),Inputs!$B$8*Inputs!$B$7*Inputs!$B$34*$B$5*(1-Inputs!$B$15)/Inputs!$B$16,0) -> 0 | J19: =IF(Source_Data!J$6=Inputs!$B$12,-Inputs!$B$7,0)+IF(AND(Source_Data!J$6>=$B$10,Source_Data!J$6<$B$10+3*Inputs!$B$16,MOD(Source_Data!J$6-$B$10,3)=0),Inputs!$B$8*Inputs!$B$7*Inputs!$B$34*$B$5*(1-Inputs!$B$15)/Inputs!$B$16,0) -> 0 | K19: =IF(Source_Data!K$6=Inputs!$B$12,-Inputs!$B$7,0)+IF(AND(Source_Data!K$6>=$B$10,Source_Data!K$6<$B$10+3*Inputs!$B$16,MOD(Source_Data!K$6-$B$10,3)=0),Inputs!$B$8*Inputs!$B$7*Inputs!$B$34*$B$5*(1-Inputs!$B$15)/Inputs!$B$16,0) -> 0 | ... BK19: =IF(Source_Data!BK$6=Inputs!$B$12,-Inputs!$B$7,0)+IF(AND(Source_Data!BK$6>=$B$10,Source_Data!BK$6<$B$10+3*Inputs!$B$16,MOD(Source_Data!BK$6-$B$10,3)=0),Inputs!$B$8*Inputs!$B$7*Inputs!$B$34*$B$5*(1-Inputs!$B$15)/Inputs!$B$16,0) -> 0
A20: Option B payouts (fixed schedule) | D20: =IF(AND(Source_Data!D$6>=Inputs!$B$54,Source_Data!D$6<Inputs!$B$54+3*Inputs!$B$11),Inputs!$B$9*Inputs!$B$7/Inputs!$B$11,0) -> 0 | E20: =IF(AND(Source_Data!E$6>=Inputs!$B$54,Source_Data!E$6<Inputs!$B$54+3*Inputs!$B$11),Inputs!$B$9*Inputs!$B$7/Inputs!$B$11,0) -> 0 | F20: =IF(AND(Source_Data!F$6>=Inputs!$B$54,Source_Data!F$6<Inputs!$B$54+3*Inputs!$B$11),Inputs!$B$9*Inputs!$B$7/Inputs!$B$11,0) -> 0 | G20: =IF(AND(Source_Data!G$6>=Inputs!$B$54,Source_Data!G$6<Inputs!$B$54+3*Inputs!$B$11),Inputs!$B$9*Inputs!$B$7/Inputs!$B$11,0) -> 0 | H20: =IF(AND(Source_Data!H$6>=Inputs!$B$54,Source_Data!H$6<Inputs!$B$54+3*Inputs!$B$11),Inputs!$B$9*Inputs!$B$7/Inputs!$B$11,0) -> 0 | I20: =IF(AND(Source_Data!I$6>=Inputs!$B$54,Source_Data!I$6<Inputs!$B$54+3*Inputs!$B$11),Inputs!$B$9*Inputs!$B$7/Inputs!$B$11,0) -> 0 | J20: =IF(AND(Source_Data!J$6>=Inputs!$B$54,Source_Data!J$6<Inputs!$B$54+3*Inputs!$B$11),Inputs!$B$9*Inputs!$B$7/Inputs!$B$11,0) -> 0 | K20: =IF(AND(Source_Data!K$6>=Inputs!$B$54,Source_Data!K$6<Inputs!$B$54+3*Inputs!$B$11),Inputs!$B$9*Inputs!$B$7/Inputs!$B$11,0) -> 0 | ... BK20: =IF(AND(Source_Data!BK$6>=Inputs!$B$54,Source_Data!BK$6<Inputs!$B$54+3*Inputs!$B$11),Inputs!$B$9*Inputs!$B$7/Inputs!$B$11,0) -> 0
A21: Option B investor cash flow | D21: =IF(Source_Data!D$6=Inputs!$B$12,-Inputs!$B$7,0)+D20 -> -100 | E21: =IF(Source_Data!E$6=Inputs!$B$12,-Inputs!$B$7,0)+E20 -> 0 | F21: =IF(Source_Data!F$6=Inputs!$B$12,-Inputs!$B$7,0)+F20 -> 0 | G21: =IF(Source_Data!G$6=Inputs!$B$12,-Inputs!$B$7,0)+G20 -> 0 | H21: =IF(Source_Data!H$6=Inputs!$B$12,-Inputs!$B$7,0)+H20 -> 0 | I21: =IF(Source_Data!I$6=Inputs!$B$12,-Inputs!$B$7,0)+I20 -> 0 | J21: =IF(Source_Data!J$6=Inputs!$B$12,-Inputs!$B$7,0)+J20 -> 0 | K21: =IF(Source_Data!K$6=Inputs!$B$12,-Inputs!$B$7,0)+K20 -> 0 | ... BK21: =IF(Source_Data!BK$6=Inputs!$B$12,-Inputs!$B$7,0)+BK20 -> 0
A22: Pooled project cash after ticket and payouts | D22: =IF(Source_Data!D$6=Inputs!$B$12,Inputs!$B$7,0)+D17-D20 -> 8.75 | E22: =D22+IF(Source_Data!E$6=Inputs!$B$12,Inputs!$B$7,0)+E17-E20 -> -2.5 | F22: =E22+IF(Source_Data!F$6=Inputs!$B$12,Inputs!$B$7,0)+F17-F20 -> 1.3892375 | G22: =F22+IF(Source_Data!G$6=Inputs!$B$12,Inputs!$B$7,0)+G17-G20 -> 20.417713 | H22: =G22+IF(Source_Data!H$6=Inputs!$B$12,Inputs!$B$7,0)+H17-H20 -> 21.429719 | I22: =H22+IF(Source_Data!I$6=Inputs!$B$12,Inputs!$B$7,0)+I17-I20 -> 31.315256 | J22: =I22+IF(Source_Data!J$6=Inputs!$B$12,Inputs!$B$7,0)+J17-J20 -> 13.069566 | K22: =J22+IF(Source_Data!K$6=Inputs!$B$12,Inputs!$B$7,0)+K17-K20 -> 11.571736 | L22: =K22+IF(Source_Data!L$6=Inputs!$B$12,Inputs!$B$7,0)+L17-L20 -> 18.269324 | ... BK22: =BJ22+IF(Source_Data!BK$6=Inputs!$B$12,Inputs!$B$7,0)+BK17-BK20 -> 245.44753
A23: Coverage: net cash flow / payout | D23: =IF(D20>0,D17/D20,"") | E23: =IF(E20>0,E17/E20,"") | F23: =IF(F20>0,F17/F20,"") | G23: =IF(G20>0,G17/G20,"") | H23: =IF(H20>0,H17/H20,"") | I23: =IF(I20>0,I17/I20,"") | J23: =IF(J20>0,J17/J20,"") | K23: =IF(K20>0,K17/K20,"") | ... BK23: =IF(BK20>0,BK17/BK20,"")
A24: Coverage: cash available / payout | D24: =IF(D20>0,(0+D17+IF(Source_Data!D$6=Inputs!$B$12,Inputs!$B$7,0))/D20,"") | E24: =IF(E20>0,(D22+E17+IF(Source_Data!E$6=Inputs!$B$12,Inputs!$B$7,0))/E20,"") | F24: =IF(F20>0,(E22+F17+IF(Source_Data!F$6=Inputs!$B$12,Inputs!$B$7,0))/F20,"") | G24: =IF(G20>0,(F22+G17+IF(Source_Data!G$6=Inputs!$B$12,Inputs!$B$7,0))/G20,"") | H24: =IF(H20>0,(G22+H17+IF(Source_Data!H$6=Inputs!$B$12,Inputs!$B$7,0))/H20,"") | I24: =IF(I20>0,(H22+I17+IF(Source_Data!I$6=Inputs!$B$12,Inputs!$B$7,0))/I20,"") | J24: =IF(J20>0,(I22+J17+IF(Source_Data!J$6=Inputs!$B$12,Inputs!$B$7,0))/J20,"") | K24: =IF(K20>0,(J22+K17+IF(Source_Data!K$6=Inputs!$B$12,Inputs!$B$7,0))/K20,"") | L24: =IF(L20>0,(K22+L17+IF(Source_Data!L$6=Inputs!$B$12,Inputs!$B$7,0))/L20,"") | ... BK24: =IF(BK20>0,(BJ22+BK17+IF(Source_Data!BK$6=Inputs!$B$12,Inputs!$B$7,0))/BK20,"")
A26: Net cash flow, nominal | B26: =SUM(D17:BK17) -> 375.44753
A27: NPV @ discount rate | B27: =SUMPRODUCT(D17:BK17,Project_CF!$D$15:$BK$15) -> 215.31139
A28: Peak cumulative cash shortage | B28: =MIN(D18:BK18) -> -102.5
A29: Month of peak | B29: =INDEX(Project_CF!$D$6:$BK$6,MATCH(MIN(D18:BK18),D18:BK18,0)) -> 6
A30: Option A investor IRR | B30: =(1+IRR(D19:BK19,0.05))^4-1 -> 0.26402991
A31: Option A investor MOIC | B31: =SUMIF(D19:BK19,">0")/-SUMIF(D19:BK19,"<0") -> 2.781362
A32: Option B investor IRR | B32: =(1+IRR(D21:BK21,0.05))^4-1 -> 0.26546399
A33: Option B lowest pooled cash (negative = sponsor support needed) | B33: =MIN(D22:BK22) -> -2.5
A34: Option B lowest quarterly coverage (net cash flow / payout) | B34: =MIN(D23:BK23) -> -8.9504782
A35: Quarters below threshold (strict) | B35: =COUNTIF(D23:BK23,"<"&Inputs!$B$43) -> 9
A36: Option B lowest cash-available coverage | B36: =MIN(D24:BK24) -> 2.9584222
A37: Quarters below threshold (cash available) | B37: =COUNTIF(D24:BK24,"<"&Inputs!$B$43) -> 0
A40: Downside: sales +12 months, prices -10%
A41: Price factor | B41: 0.9
A42: Sales delay (quarters) | B42: 4
A43: Cost factor | B43: 1
A44: Collections slip (quarters) | B44: 0
A45: Delivery payments at handover (1 = yes) | B45: 0
A46: Resale start month (Option A) | B46: =Inputs!$B$13+3+3*$B$42 -> 63
A47: Collections before delay and price | D47: =Source_Data!D$7+IF($B$45=1,IF(Source_Data!D$6=Inputs!$B$13,Source_Data!$C$8,0),Source_Data!D$8) -> 0 | E47: =Source_Data!E$7+IF($B$45=1,IF(Source_Data!E$6=Inputs!$B$13,Source_Data!$C$8,0),Source_Data!E$8) -> 0 | F47: =Source_Data!F$7+IF($B$45=1,IF(Source_Data!F$6=Inputs!$B$13,Source_Data!$C$8,0),Source_Data!F$8) -> 15.139238 | G47: =Source_Data!G$7+IF($B$45=1,IF(Source_Data!G$6=Inputs!$B$13,Source_Data!$C$8,0),Source_Data!G$8) -> 30.278475 | H47: =Source_Data!H$7+IF($B$45=1,IF(Source_Data!H$6=Inputs!$B$13,Source_Data!$C$8,0),Source_Data!H$8) -> 46.512006 | I47: =Source_Data!I$7+IF($B$45=1,IF(Source_Data!I$6=Inputs!$B$13,Source_Data!$C$8,0),Source_Data!I$8) -> 62.745537 | J47: =Source_Data!J$7+IF($B$45=1,IF(Source_Data!J$6=Inputs!$B$13,Source_Data!$C$8,0),Source_Data!J$8) -> 62.3657 | K47: =Source_Data!K$7+IF($B$45=1,IF(Source_Data!K$6=Inputs!$B$13,Source_Data!$C$8,0),Source_Data!K$8) -> 63.473559 | ... BK47: =Source_Data!BK$7+IF($B$45=1,IF(Source_Data!BK$6=Inputs!$B$13,Source_Data!$C$8,0),Source_Data!BK$8) -> 0
A48: Collections | D48: =$B$41*IF(Source_Data!D$5-($B$42+$B$44)>=1,INDEX($D$47:$BK$47,1,Source_Data!D$5-($B$42+$B$44)),0) -> 0 | E48: =$B$41*IF(Source_Data!E$5-($B$42+$B$44)>=1,INDEX($D$47:$BK$47,1,Source_Data!E$5-($B$42+$B$44)),0) -> 0 | F48: =$B$41*IF(Source_Data!F$5-($B$42+$B$44)>=1,INDEX($D$47:$BK$47,1,Source_Data!F$5-($B$42+$B$44)),0) -> 0 | G48: =$B$41*IF(Source_Data!G$5-($B$42+$B$44)>=1,INDEX($D$47:$BK$47,1,Source_Data!G$5-($B$42+$B$44)),0) -> 0 | H48: =$B$41*IF(Source_Data!H$5-($B$42+$B$44)>=1,INDEX($D$47:$BK$47,1,Source_Data!H$5-($B$42+$B$44)),0) -> 0 | I48: =$B$41*IF(Source_Data!I$5-($B$42+$B$44)>=1,INDEX($D$47:$BK$47,1,Source_Data!I$5-($B$42+$B$44)),0) -> 0 | J48: =$B$41*IF(Source_Data!J$5-($B$42+$B$44)>=1,INDEX($D$47:$BK$47,1,Source_Data!J$5-($B$42+$B$44)),0) -> 13.625314 | K48: =$B$41*IF(Source_Data!K$5-($B$42+$B$44)>=1,INDEX($D$47:$BK$47,1,Source_Data!K$5-($B$42+$B$44)),0) -> 27.250628 | ... BK48: =$B$41*IF(Source_Data!BK$5-($B$42+$B$44)>=1,INDEX($D$47:$BK$47,1,Source_Data!BK$5-($B$42+$B$44)),0) -> 0
A49: Landlord payments | D49: =Source_Data!D$9+Source_Data!D$10*IF(Source_Data!$C$10=0,0,MAX(0,Inputs!$B$19*Inputs!$B$22*$B$41-Inputs!$B$20)/Source_Data!$C$10) -> 91.25 | E49: =Source_Data!E$9+Source_Data!E$10*IF(Source_Data!$C$10=0,0,MAX(0,Inputs!$B$19*Inputs!$B$22*$B$41-Inputs!$B$20)/Source_Data!$C$10) -> 11.25 | F49: =Source_Data!F$9+Source_Data!F$10*IF(Source_Data!$C$10=0,0,MAX(0,Inputs!$B$19*Inputs!$B$22*$B$41-Inputs!$B$20)/Source_Data!$C$10) -> 11.25 | G49: =Source_Data!G$9+Source_Data!G$10*IF(Source_Data!$C$10=0,0,MAX(0,Inputs!$B$19*Inputs!$B$22*$B$41-Inputs!$B$20)/Source_Data!$C$10) -> 11.25 | H49: =Source_Data!H$9+Source_Data!H$10*IF(Source_Data!$C$10=0,0,MAX(0,Inputs!$B$19*Inputs!$B$22*$B$41-Inputs!$B$20)/Source_Data!$C$10) -> 22.5 | I49: =Source_Data!I$9+Source_Data!I$10*IF(Source_Data!$C$10=0,0,MAX(0,Inputs!$B$19*Inputs!$B$22*$B$41-Inputs!$B$20)/Source_Data!$C$10) -> 22.5 | J49: =Source_Data!J$9+Source_Data!J$10*IF(Source_Data!$C$10=0,0,MAX(0,Inputs!$B$19*Inputs!$B$22*$B$41-Inputs!$B$20)/Source_Data!$C$10) -> 22.5 | K49: =Source_Data!K$9+Source_Data!K$10*IF(Source_Data!$C$10=0,0,MAX(0,Inputs!$B$19*Inputs!$B$22*$B$41-Inputs!$B$20)/Source_Data!$C$10) -> 22.5 | ... BK49: =Source_Data!BK$9+Source_Data!BK$10*IF(Source_Data!$C$10=0,0,MAX(0,Inputs!$B$19*Inputs!$B$22*$B$41-Inputs!$B$20)/Source_Data!$C$10) -> 0
A50: Construction cost | D50: =Source_Data!D$11*$B$43 -> 0 | E50: =Source_Data!E$11*$B$43 -> 0 | F50: =Source_Data!F$11*$B$43 -> 0 | G50: =Source_Data!G$11*$B$43 -> 0 | H50: =Source_Data!H$11*$B$43 -> 20 | I50: =Source_Data!I$11*$B$43 -> 26.4 | J50: =Source_Data!J$11*$B$43 -> 40 | K50: =Source_Data!K$11*$B$43 -> 26.4 | ... BK50: =Source_Data!BK$11*$B$43 -> 0
A51: Sales commission | D51: =$B$41*IF(Source_Data!D$5-$B$42>=1,INDEX(Source_Data!$D$12:$BK$12,1,Source_Data!D$5-$B$42),0) -> 0 | E51: =$B$41*IF(Source_Data!E$5-$B$42>=1,INDEX(Source_Data!$D$12:$BK$12,1,Source_Data!E$5-$B$42),0) -> 0 | F51: =$B$41*IF(Source_Data!F$5-$B$42>=1,INDEX(Source_Data!$D$12:$BK$12,1,Source_Data!F$5-$B$42),0) -> 0 | G51: =$B$41*IF(Source_Data!G$5-$B$42>=1,INDEX(Source_Data!$D$12:$BK$12,1,Source_Data!G$5-$B$42),0) -> 0 | H51: =$B$41*IF(Source_Data!H$5-$B$42>=1,INDEX(Source_Data!$D$12:$BK$12,1,Source_Data!H$5-$B$42),0) -> 0 | I51: =$B$41*IF(Source_Data!I$5-$B$42>=1,INDEX(Source_Data!$D$12:$BK$12,1,Source_Data!I$5-$B$42),0) -> 0 | J51: =$B$41*IF(Source_Data!J$5-$B$42>=1,INDEX(Source_Data!$D$12:$BK$12,1,Source_Data!J$5-$B$42),0) -> 0 | K51: =$B$41*IF(Source_Data!K$5-$B$42>=1,INDEX(Source_Data!$D$12:$BK$12,1,Source_Data!K$5-$B$42),0) -> 0 | ... BK51: =$B$41*IF(Source_Data!BK$5-$B$42>=1,INDEX(Source_Data!$D$12:$BK$12,1,Source_Data!BK$5-$B$42),0) -> 0
A52: SG&A and others | D52: =Source_Data!D$13*$B$43 -> 0 | E52: =Source_Data!E$13*$B$43 -> 0 | F52: =Source_Data!F$13*$B$43 -> 0 | G52: =Source_Data!G$13*$B$43 -> 0 | H52: =Source_Data!H$13*$B$43 -> 3 | I52: =Source_Data!I$13*$B$43 -> 3.96 | J52: =Source_Data!J$13*$B$43 -> 6 | K52: =Source_Data!K$13*$B$43 -> 3.96 | ... BK52: =Source_Data!BK$13*$B$43 -> 0
A53: Net cash flow | D53: =D48-D49-D50-D51-D52 -> -91.25 | E53: =E48-E49-E50-E51-E52 -> -11.25 | F53: =F48-F49-F50-F51-F52 -> -11.25 | G53: =G48-G49-G50-G51-G52 -> -11.25 | H53: =H48-H49-H50-H51-H52 -> -45.5 | I53: =I48-I49-I50-I51-I52 -> -52.86 | J53: =J48-J49-J50-J51-J52 -> -54.874686 | K53: =K48-K49-K50-K51-K52 -> -25.609372 | ... BK53: =BK48-BK49-BK50-BK51-BK52 -> 0
A54: Cumulative net cash flow | D54: =D53 -> -91.25 | E54: =D54+E53 -> -102.5 | F54: =E54+F53 -> -113.75 | G54: =F54+G53 -> -125 | H54: =G54+H53 -> -170.5 | I54: =H54+I53 -> -223.36 | J54: =I54+J53 -> -278.23469 | K54: =J54+K53 -> -303.84406 | L54: =K54+L53 -> -326.09325 | ... BK54: =BJ54+BK53 -> 257.72937
A55: Option A investor cash flow | D55: =IF(Source_Data!D$6=Inputs!$B$12,-Inputs!$B$7,0)+IF(AND(Source_Data!D$6>=$B$46,Source_Data!D$6<$B$46+3*Inputs!$B$16,MOD(Source_Data!D$6-$B$46,3)=0),Inputs!$B$8*Inputs!$B$7*Inputs!$B$34*$B$41*(1-Inputs!$B$15)/Inputs!$B$16,0) -> -100 | E55: =IF(Source_Data!E$6=Inputs!$B$12,-Inputs!$B$7,0)+IF(AND(Source_Data!E$6>=$B$46,Source_Data!E$6<$B$46+3*Inputs!$B$16,MOD(Source_Data!E$6-$B$46,3)=0),Inputs!$B$8*Inputs!$B$7*Inputs!$B$34*$B$41*(1-Inputs!$B$15)/Inputs!$B$16,0) -> 0 | F55: =IF(Source_Data!F$6=Inputs!$B$12,-Inputs!$B$7,0)+IF(AND(Source_Data!F$6>=$B$46,Source_Data!F$6<$B$46+3*Inputs!$B$16,MOD(Source_Data!F$6-$B$46,3)=0),Inputs!$B$8*Inputs!$B$7*Inputs!$B$34*$B$41*(1-Inputs!$B$15)/Inputs!$B$16,0) -> 0 | G55: =IF(Source_Data!G$6=Inputs!$B$12,-Inputs!$B$7,0)+IF(AND(Source_Data!G$6>=$B$46,Source_Data!G$6<$B$46+3*Inputs!$B$16,MOD(Source_Data!G$6-$B$46,3)=0),Inputs!$B$8*Inputs!$B$7*Inputs!$B$34*$B$41*(1-Inputs!$B$15)/Inputs!$B$16,0) -> 0 | H55: =IF(Source_Data!H$6=Inputs!$B$12,-Inputs!$B$7,0)+IF(AND(Source_Data!H$6>=$B$46,Source_Data!H$6<$B$46+3*Inputs!$B$16,MOD(Source_Data!H$6-$B$46,3)=0),Inputs!$B$8*Inputs!$B$7*Inputs!$B$34*$B$41*(1-Inputs!$B$15)/Inputs!$B$16,0) -> 0 | I55: =IF(Source_Data!I$6=Inputs!$B$12,-Inputs!$B$7,0)+IF(AND(Source_Data!I$6>=$B$46,Source_Data!I$6<$B$46+3*Inputs!$B$16,MOD(Source_Data!I$6-$B$46,3)=0),Inputs!$B$8*Inputs!$B$7*Inputs!$B$34*$B$41*(1-Inputs!$B$15)/Inputs!$B$16,0) -> 0 | J55: =IF(Source_Data!J$6=Inputs!$B$12,-Inputs!$B$7,0)+IF(AND(Source_Data!J$6>=$B$46,Source_Data!J$6<$B$46+3*Inputs!$B$16,MOD(Source_Data!J$6-$B$46,3)=0),Inputs!$B$8*Inputs!$B$7*Inputs!$B$34*$B$41*(1-Inputs!$B$15)/Inputs!$B$16,0) -> 0 | K55: =IF(Source_Data!K$6=Inputs!$B$12,-Inputs!$B$7,0)+IF(AND(Source_Data!K$6>=$B$46,Source_Data!K$6<$B$46+3*Inputs!$B$16,MOD(Source_Data!K$6-$B$46,3)=0),Inputs!$B$8*Inputs!$B$7*Inputs!$B$34*$B$41*(1-Inputs!$B$15)/Inputs!$B$16,0) -> 0 | ... BK55: =IF(Source_Data!BK$6=Inputs!$B$12,-Inputs!$B$7,0)+IF(AND(Source_Data!BK$6>=$B$46,Source_Data!BK$6<$B$46+3*Inputs!$B$16,MOD(Source_Data!BK$6-$B$46,3)=0),Inputs!$B$8*Inputs!$B$7*Inputs!$B$34*$B$41*(1-Inputs!$B$15)/Inputs!$B$16,0) -> 0
A56: Option B payouts (fixed schedule) | D56: =IF(AND(Source_Data!D$6>=Inputs!$B$54,Source_Data!D$6<Inputs!$B$54+3*Inputs!$B$11),Inputs!$B$9*Inputs!$B$7/Inputs!$B$11,0) -> 0 | E56: =IF(AND(Source_Data!E$6>=Inputs!$B$54,Source_Data!E$6<Inputs!$B$54+3*Inputs!$B$11),Inputs!$B$9*Inputs!$B$7/Inputs!$B$11,0) -> 0 | F56: =IF(AND(Source_Data!F$6>=Inputs!$B$54,Source_Data!F$6<Inputs!$B$54+3*Inputs!$B$11),Inputs!$B$9*Inputs!$B$7/Inputs!$B$11,0) -> 0 | G56: =IF(AND(Source_Data!G$6>=Inputs!$B$54,Source_Data!G$6<Inputs!$B$54+3*Inputs!$B$11),Inputs!$B$9*Inputs!$B$7/Inputs!$B$11,0) -> 0 | H56: =IF(AND(Source_Data!H$6>=Inputs!$B$54,Source_Data!H$6<Inputs!$B$54+3*Inputs!$B$11),Inputs!$B$9*Inputs!$B$7/Inputs!$B$11,0) -> 0 | I56: =IF(AND(Source_Data!I$6>=Inputs!$B$54,Source_Data!I$6<Inputs!$B$54+3*Inputs!$B$11),Inputs!$B$9*Inputs!$B$7/Inputs!$B$11,0) -> 0 | J56: =IF(AND(Source_Data!J$6>=Inputs!$B$54,Source_Data!J$6<Inputs!$B$54+3*Inputs!$B$11),Inputs!$B$9*Inputs!$B$7/Inputs!$B$11,0) -> 0 | K56: =IF(AND(Source_Data!K$6>=Inputs!$B$54,Source_Data!K$6<Inputs!$B$54+3*Inputs!$B$11),Inputs!$B$9*Inputs!$B$7/Inputs!$B$11,0) -> 0 | ... BK56: =IF(AND(Source_Data!BK$6>=Inputs!$B$54,Source_Data!BK$6<Inputs!$B$54+3*Inputs!$B$11),Inputs!$B$9*Inputs!$B$7/Inputs!$B$11,0) -> 0
A57: Option B investor cash flow | D57: =IF(Source_Data!D$6=Inputs!$B$12,-Inputs!$B$7,0)+D56 -> -100 | E57: =IF(Source_Data!E$6=Inputs!$B$12,-Inputs!$B$7,0)+E56 -> 0 | F57: =IF(Source_Data!F$6=Inputs!$B$12,-Inputs!$B$7,0)+F56 -> 0 | G57: =IF(Source_Data!G$6=Inputs!$B$12,-Inputs!$B$7,0)+G56 -> 0 | H57: =IF(Source_Data!H$6=Inputs!$B$12,-Inputs!$B$7,0)+H56 -> 0 | I57: =IF(Source_Data!I$6=Inputs!$B$12,-Inputs!$B$7,0)+I56 -> 0 | J57: =IF(Source_Data!J$6=Inputs!$B$12,-Inputs!$B$7,0)+J56 -> 0 | K57: =IF(Source_Data!K$6=Inputs!$B$12,-Inputs!$B$7,0)+K56 -> 0 | ... BK57: =IF(Source_Data!BK$6=Inputs!$B$12,-Inputs!$B$7,0)+BK56 -> 0
A58: Pooled project cash after ticket and payouts | D58: =IF(Source_Data!D$6=Inputs!$B$12,Inputs!$B$7,0)+D53-D56 -> 8.75 | E58: =D58+IF(Source_Data!E$6=Inputs!$B$12,Inputs!$B$7,0)+E53-E56 -> -2.5 | F58: =E58+IF(Source_Data!F$6=Inputs!$B$12,Inputs!$B$7,0)+F53-F56 -> -13.75 | G58: =F58+IF(Source_Data!G$6=Inputs!$B$12,Inputs!$B$7,0)+G53-G56 -> -25 | H58: =G58+IF(Source_Data!H$6=Inputs!$B$12,Inputs!$B$7,0)+H53-H56 -> -70.5 | I58: =H58+IF(Source_Data!I$6=Inputs!$B$12,Inputs!$B$7,0)+I53-I56 -> -123.36 | J58: =I58+IF(Source_Data!J$6=Inputs!$B$12,Inputs!$B$7,0)+J53-J56 -> -178.23469 | K58: =J58+IF(Source_Data!K$6=Inputs!$B$12,Inputs!$B$7,0)+K53-K56 -> -203.84406 | L58: =K58+IF(Source_Data!L$6=Inputs!$B$12,Inputs!$B$7,0)+L53-L56 -> -226.09325 | ... BK58: =BJ58+IF(Source_Data!BK$6=Inputs!$B$12,Inputs!$B$7,0)+BK53-BK56 -> 127.72937
A59: Coverage: net cash flow / payout | D59: =IF(D56>0,D53/D56,"") | E59: =IF(E56>0,E53/E56,"") | F59: =IF(F56>0,F53/F56,"") | G59: =IF(G56>0,G53/G56,"") | H59: =IF(H56>0,H53/H56,"") | I59: =IF(I56>0,I53/I56,"") | J59: =IF(J56>0,J53/J56,"") | K59: =IF(K56>0,K53/K56,"") | ... BK59: =IF(BK56>0,BK53/BK56,"")
A60: Coverage: cash available / payout | D60: =IF(D56>0,(0+D53+IF(Source_Data!D$6=Inputs!$B$12,Inputs!$B$7,0))/D56,"") | E60: =IF(E56>0,(D58+E53+IF(Source_Data!E$6=Inputs!$B$12,Inputs!$B$7,0))/E56,"") | F60: =IF(F56>0,(E58+F53+IF(Source_Data!F$6=Inputs!$B$12,Inputs!$B$7,0))/F56,"") | G60: =IF(G56>0,(F58+G53+IF(Source_Data!G$6=Inputs!$B$12,Inputs!$B$7,0))/G56,"") | H60: =IF(H56>0,(G58+H53+IF(Source_Data!H$6=Inputs!$B$12,Inputs!$B$7,0))/H56,"") | I60: =IF(I56>0,(H58+I53+IF(Source_Data!I$6=Inputs!$B$12,Inputs!$B$7,0))/I56,"") | J60: =IF(J56>0,(I58+J53+IF(Source_Data!J$6=Inputs!$B$12,Inputs!$B$7,0))/J56,"") | K60: =IF(K56>0,(J58+K53+IF(Source_Data!K$6=Inputs!$B$12,Inputs!$B$7,0))/K56,"") | L60: =IF(L56>0,(K58+L53+IF(Source_Data!L$6=Inputs!$B$12,Inputs!$B$7,0))/L56,"") | ... BK60: =IF(BK56>0,(BJ58+BK53+IF(Source_Data!BK$6=Inputs!$B$12,Inputs!$B$7,0))/BK56,"")
A62: Net cash flow, nominal | B62: =SUM(D53:BK53) -> 257.72937
A63: NPV @ discount rate | B63: =SUMPRODUCT(D53:BK53,Project_CF!$D$15:$BK$15) -> -33.594685
A64: Peak cumulative cash shortage | B64: =MIN(D54:BK54) -> -441.19461
A65: Month of peak | B65: =INDEX(Project_CF!$D$6:$BK$6,MATCH(MIN(D54:BK54),D54:BK54,0)) -> 39
A66: Option A investor IRR | B66: =(1+IRR(D55:BK55,0.05))^4-1 -> 0.18640161
A67: Option A investor MOIC | B67: =SUMIF(D55:BK55,">0")/-SUMIF(D55:BK55,"<0") -> 2.5032258
A68: Option B investor IRR | B68: =(1+IRR(D57:BK57,0.05))^4-1 -> 0.26546399
A69: Option B lowest pooled cash (negative = sponsor support needed) | B69: =MIN(D58:BK58) -> -417.86128
A70: Option B lowest quarterly coverage (net cash flow / payout) | B70: =MIN(D59:BK59) -> -6.222948
A71: Quarters below threshold (strict) | B71: =COUNTIF(D59:BK59,"<"&Inputs!$B$43) -> 9
A72: Option B lowest cash-available coverage | B72: =MIN(D60:BK60) -> -20.801458
A73: Quarters below threshold (cash available) | B73: =COUNTIF(D60:BK60,"<"&Inputs!$B$43) -> 12
A76: Upside: prices +10%
A77: Price factor | B77: 1.1
A78: Sales delay (quarters) | B78: 0
A79: Cost factor | B79: 1
A80: Collections slip (quarters) | B80: 0
A81: Delivery payments at handover (1 = yes) | B81: 0
A82: Resale start month (Option A) | B82: =Inputs!$B$13+3+3*$B$78 -> 51
A83: Collections before delay and price | D83: =Source_Data!D$7+IF($B$81=1,IF(Source_Data!D$6=Inputs!$B$13,Source_Data!$C$8,0),Source_Data!D$8) -> 0 | E83: =Source_Data!E$7+IF($B$81=1,IF(Source_Data!E$6=Inputs!$B$13,Source_Data!$C$8,0),Source_Data!E$8) -> 0 | F83: =Source_Data!F$7+IF($B$81=1,IF(Source_Data!F$6=Inputs!$B$13,Source_Data!$C$8,0),Source_Data!F$8) -> 15.139238 | G83: =Source_Data!G$7+IF($B$81=1,IF(Source_Data!G$6=Inputs!$B$13,Source_Data!$C$8,0),Source_Data!G$8) -> 30.278475 | H83: =Source_Data!H$7+IF($B$81=1,IF(Source_Data!H$6=Inputs!$B$13,Source_Data!$C$8,0),Source_Data!H$8) -> 46.512006 | I83: =Source_Data!I$7+IF($B$81=1,IF(Source_Data!I$6=Inputs!$B$13,Source_Data!$C$8,0),Source_Data!I$8) -> 62.745537 | J83: =Source_Data!J$7+IF($B$81=1,IF(Source_Data!J$6=Inputs!$B$13,Source_Data!$C$8,0),Source_Data!J$8) -> 62.3657 | K83: =Source_Data!K$7+IF($B$81=1,IF(Source_Data!K$6=Inputs!$B$13,Source_Data!$C$8,0),Source_Data!K$8) -> 63.473559 | ... BK83: =Source_Data!BK$7+IF($B$81=1,IF(Source_Data!BK$6=Inputs!$B$13,Source_Data!$C$8,0),Source_Data!BK$8) -> 0
A84: Collections | D84: =$B$77*IF(Source_Data!D$5-($B$78+$B$80)>=1,INDEX($D$83:$BK$83,1,Source_Data!D$5-($B$78+$B$80)),0) -> 0 | E84: =$B$77*IF(Source_Data!E$5-($B$78+$B$80)>=1,INDEX($D$83:$BK$83,1,Source_Data!E$5-($B$78+$B$80)),0) -> 0 | F84: =$B$77*IF(Source_Data!F$5-($B$78+$B$80)>=1,INDEX($D$83:$BK$83,1,Source_Data!F$5-($B$78+$B$80)),0) -> 16.653161 | G84: =$B$77*IF(Source_Data!G$5-($B$78+$B$80)>=1,INDEX($D$83:$BK$83,1,Source_Data!G$5-($B$78+$B$80)),0) -> 33.306323 | H84: =$B$77*IF(Source_Data!H$5-($B$78+$B$80)>=1,INDEX($D$83:$BK$83,1,Source_Data!H$5-($B$78+$B$80)),0) -> 51.163207 | I84: =$B$77*IF(Source_Data!I$5-($B$78+$B$80)>=1,INDEX($D$83:$BK$83,1,Source_Data!I$5-($B$78+$B$80)),0) -> 69.020091 | J84: =$B$77*IF(Source_Data!J$5-($B$78+$B$80)>=1,INDEX($D$83:$BK$83,1,Source_Data!J$5-($B$78+$B$80)),0) -> 68.60227 | K84: =$B$77*IF(Source_Data!K$5-($B$78+$B$80)>=1,INDEX($D$83:$BK$83,1,Source_Data!K$5-($B$78+$B$80)),0) -> 69.820915 | ... BK84: =$B$77*IF(Source_Data!BK$5-($B$78+$B$80)>=1,INDEX($D$83:$BK$83,1,Source_Data!BK$5-($B$78+$B$80)),0) -> 0
A85: Landlord payments | D85: =Source_Data!D$9+Source_Data!D$10*IF(Source_Data!$C$10=0,0,MAX(0,Inputs!$B$19*Inputs!$B$22*$B$77-Inputs!$B$20)/Source_Data!$C$10) -> 91.25 | E85: =Source_Data!E$9+Source_Data!E$10*IF(Source_Data!$C$10=0,0,MAX(0,Inputs!$B$19*Inputs!$B$22*$B$77-Inputs!$B$20)/Source_Data!$C$10) -> 11.25 | F85: =Source_Data!F$9+Source_Data!F$10*IF(Source_Data!$C$10=0,0,MAX(0,Inputs!$B$19*Inputs!$B$22*$B$77-Inputs!$B$20)/Source_Data!$C$10) -> 11.25 | G85: =Source_Data!G$9+Source_Data!G$10*IF(Source_Data!$C$10=0,0,MAX(0,Inputs!$B$19*Inputs!$B$22*$B$77-Inputs!$B$20)/Source_Data!$C$10) -> 11.25 | H85: =Source_Data!H$9+Source_Data!H$10*IF(Source_Data!$C$10=0,0,MAX(0,Inputs!$B$19*Inputs!$B$22*$B$77-Inputs!$B$20)/Source_Data!$C$10) -> 22.5 | I85: =Source_Data!I$9+Source_Data!I$10*IF(Source_Data!$C$10=0,0,MAX(0,Inputs!$B$19*Inputs!$B$22*$B$77-Inputs!$B$20)/Source_Data!$C$10) -> 22.5 | J85: =Source_Data!J$9+Source_Data!J$10*IF(Source_Data!$C$10=0,0,MAX(0,Inputs!$B$19*Inputs!$B$22*$B$77-Inputs!$B$20)/Source_Data!$C$10) -> 22.5 | K85: =Source_Data!K$9+Source_Data!K$10*IF(Source_Data!$C$10=0,0,MAX(0,Inputs!$B$19*Inputs!$B$22*$B$77-Inputs!$B$20)/Source_Data!$C$10) -> 22.5 | ... BK85: =Source_Data!BK$9+Source_Data!BK$10*IF(Source_Data!$C$10=0,0,MAX(0,Inputs!$B$19*Inputs!$B$22*$B$77-Inputs!$B$20)/Source_Data!$C$10) -> 0
A86: Construction cost | D86: =Source_Data!D$11*$B$79 -> 0 | E86: =Source_Data!E$11*$B$79 -> 0 | F86: =Source_Data!F$11*$B$79 -> 0 | G86: =Source_Data!G$11*$B$79 -> 0 | H86: =Source_Data!H$11*$B$79 -> 20 | I86: =Source_Data!I$11*$B$79 -> 26.4 | J86: =Source_Data!J$11*$B$79 -> 40 | K86: =Source_Data!K$11*$B$79 -> 26.4 | ... BK86: =Source_Data!BK$11*$B$79 -> 0
A87: Sales commission | D87: =$B$77*IF(Source_Data!D$5-$B$78>=1,INDEX(Source_Data!$D$12:$BK$12,1,Source_Data!D$5-$B$78),0) -> 0 | E87: =$B$77*IF(Source_Data!E$5-$B$78>=1,INDEX(Source_Data!$D$12:$BK$12,1,Source_Data!E$5-$B$78),0) -> 0 | F87: =$B$77*IF(Source_Data!F$5-$B$78>=1,INDEX(Source_Data!$D$12:$BK$12,1,Source_Data!F$5-$B$78),0) -> 0 | G87: =$B$77*IF(Source_Data!G$5-$B$78>=1,INDEX(Source_Data!$D$12:$BK$12,1,Source_Data!G$5-$B$78),0) -> 0 | H87: =$B$77*IF(Source_Data!H$5-$B$78>=1,INDEX(Source_Data!$D$12:$BK$12,1,Source_Data!H$5-$B$78),0) -> 0 | I87: =$B$77*IF(Source_Data!I$5-$B$78>=1,INDEX(Source_Data!$D$12:$BK$12,1,Source_Data!I$5-$B$78),0) -> 0 | J87: =$B$77*IF(Source_Data!J$5-$B$78>=1,INDEX(Source_Data!$D$12:$BK$12,1,Source_Data!J$5-$B$78),0) -> 13.322529 | K87: =$B$77*IF(Source_Data!K$5-$B$78>=1,INDEX(Source_Data!$D$12:$BK$12,1,Source_Data!K$5-$B$78),0) -> 13.322529 | ... BK87: =$B$77*IF(Source_Data!BK$5-$B$78>=1,INDEX(Source_Data!$D$12:$BK$12,1,Source_Data!BK$5-$B$78),0) -> 0
A88: SG&A and others | D88: =Source_Data!D$13*$B$79 -> 0 | E88: =Source_Data!E$13*$B$79 -> 0 | F88: =Source_Data!F$13*$B$79 -> 0 | G88: =Source_Data!G$13*$B$79 -> 0 | H88: =Source_Data!H$13*$B$79 -> 3 | I88: =Source_Data!I$13*$B$79 -> 3.96 | J88: =Source_Data!J$13*$B$79 -> 6 | K88: =Source_Data!K$13*$B$79 -> 3.96 | ... BK88: =Source_Data!BK$13*$B$79 -> 0
A89: Net cash flow | D89: =D84-D85-D86-D87-D88 -> -91.25 | E89: =E84-E85-E86-E87-E88 -> -11.25 | F89: =F84-F85-F86-F87-F88 -> 5.4031613 | G89: =G84-G85-G86-G87-G88 -> 22.056323 | H89: =H84-H85-H86-H87-H88 -> 5.6632069 | I89: =I84-I85-I86-I87-I88 -> 16.160091 | J89: =J84-J85-J86-J87-J88 -> -13.220259 | K89: =K84-K85-K86-K87-K88 -> 3.6383863 | ... BK89: =BK84-BK85-BK86-BK87-BK88 -> 0
A90: Cumulative net cash flow | D90: =D89 -> -91.25 | E90: =D90+E89 -> -102.5 | F90: =E90+F89 -> -97.096839 | G90: =F90+G89 -> -75.040516 | H90: =G90+H89 -> -69.377309 | I90: =H90+I89 -> -53.217218 | J90: =I90+J89 -> -66.437477 | K90: =J90+K89 -> -62.799091 | L90: =K90+L89 -> -49.020744 | ... BK90: =BJ90+BK89 -> 493.16568
A91: Option A investor cash flow | D91: =IF(Source_Data!D$6=Inputs!$B$12,-Inputs!$B$7,0)+IF(AND(Source_Data!D$6>=$B$82,Source_Data!D$6<$B$82+3*Inputs!$B$16,MOD(Source_Data!D$6-$B$82,3)=0),Inputs!$B$8*Inputs!$B$7*Inputs!$B$34*$B$77*(1-Inputs!$B$15)/Inputs!$B$16,0) -> -100 | E91: =IF(Source_Data!E$6=Inputs!$B$12,-Inputs!$B$7,0)+IF(AND(Source_Data!E$6>=$B$82,Source_Data!E$6<$B$82+3*Inputs!$B$16,MOD(Source_Data!E$6-$B$82,3)=0),Inputs!$B$8*Inputs!$B$7*Inputs!$B$34*$B$77*(1-Inputs!$B$15)/Inputs!$B$16,0) -> 0 | F91: =IF(Source_Data!F$6=Inputs!$B$12,-Inputs!$B$7,0)+IF(AND(Source_Data!F$6>=$B$82,Source_Data!F$6<$B$82+3*Inputs!$B$16,MOD(Source_Data!F$6-$B$82,3)=0),Inputs!$B$8*Inputs!$B$7*Inputs!$B$34*$B$77*(1-Inputs!$B$15)/Inputs!$B$16,0) -> 0 | G91: =IF(Source_Data!G$6=Inputs!$B$12,-Inputs!$B$7,0)+IF(AND(Source_Data!G$6>=$B$82,Source_Data!G$6<$B$82+3*Inputs!$B$16,MOD(Source_Data!G$6-$B$82,3)=0),Inputs!$B$8*Inputs!$B$7*Inputs!$B$34*$B$77*(1-Inputs!$B$15)/Inputs!$B$16,0) -> 0 | H91: =IF(Source_Data!H$6=Inputs!$B$12,-Inputs!$B$7,0)+IF(AND(Source_Data!H$6>=$B$82,Source_Data!H$6<$B$82+3*Inputs!$B$16,MOD(Source_Data!H$6-$B$82,3)=0),Inputs!$B$8*Inputs!$B$7*Inputs!$B$34*$B$77*(1-Inputs!$B$15)/Inputs!$B$16,0) -> 0 | I91: =IF(Source_Data!I$6=Inputs!$B$12,-Inputs!$B$7,0)+IF(AND(Source_Data!I$6>=$B$82,Source_Data!I$6<$B$82+3*Inputs!$B$16,MOD(Source_Data!I$6-$B$82,3)=0),Inputs!$B$8*Inputs!$B$7*Inputs!$B$34*$B$77*(1-Inputs!$B$15)/Inputs!$B$16,0) -> 0 | J91: =IF(Source_Data!J$6=Inputs!$B$12,-Inputs!$B$7,0)+IF(AND(Source_Data!J$6>=$B$82,Source_Data!J$6<$B$82+3*Inputs!$B$16,MOD(Source_Data!J$6-$B$82,3)=0),Inputs!$B$8*Inputs!$B$7*Inputs!$B$34*$B$77*(1-Inputs!$B$15)/Inputs!$B$16,0) -> 0 | K91: =IF(Source_Data!K$6=Inputs!$B$12,-Inputs!$B$7,0)+IF(AND(Source_Data!K$6>=$B$82,Source_Data!K$6<$B$82+3*Inputs!$B$16,MOD(Source_Data!K$6-$B$82,3)=0),Inputs!$B$8*Inputs!$B$7*Inputs!$B$34*$B$77*(1-Inputs!$B$15)/Inputs!$B$16,0) -> 0 | ... BK91: =IF(Source_Data!BK$6=Inputs!$B$12,-Inputs!$B$7,0)+IF(AND(Source_Data!BK$6>=$B$82,Source_Data!BK$6<$B$82+3*Inputs!$B$16,MOD(Source_Data!BK$6-$B$82,3)=0),Inputs!$B$8*Inputs!$B$7*Inputs!$B$34*$B$77*(1-Inputs!$B$15)/Inputs!$B$16,0) -> 0
A92: Option B payouts (fixed schedule) | D92: =IF(AND(Source_Data!D$6>=Inputs!$B$54,Source_Data!D$6<Inputs!$B$54+3*Inputs!$B$11),Inputs!$B$9*Inputs!$B$7/Inputs!$B$11,0) -> 0 | E92: =IF(AND(Source_Data!E$6>=Inputs!$B$54,Source_Data!E$6<Inputs!$B$54+3*Inputs!$B$11),Inputs!$B$9*Inputs!$B$7/Inputs!$B$11,0) -> 0 | F92: =IF(AND(Source_Data!F$6>=Inputs!$B$54,Source_Data!F$6<Inputs!$B$54+3*Inputs!$B$11),Inputs!$B$9*Inputs!$B$7/Inputs!$B$11,0) -> 0 | G92: =IF(AND(Source_Data!G$6>=Inputs!$B$54,Source_Data!G$6<Inputs!$B$54+3*Inputs!$B$11),Inputs!$B$9*Inputs!$B$7/Inputs!$B$11,0) -> 0 | H92: =IF(AND(Source_Data!H$6>=Inputs!$B$54,Source_Data!H$6<Inputs!$B$54+3*Inputs!$B$11),Inputs!$B$9*Inputs!$B$7/Inputs!$B$11,0) -> 0 | I92: =IF(AND(Source_Data!I$6>=Inputs!$B$54,Source_Data!I$6<Inputs!$B$54+3*Inputs!$B$11),Inputs!$B$9*Inputs!$B$7/Inputs!$B$11,0) -> 0 | J92: =IF(AND(Source_Data!J$6>=Inputs!$B$54,Source_Data!J$6<Inputs!$B$54+3*Inputs!$B$11),Inputs!$B$9*Inputs!$B$7/Inputs!$B$11,0) -> 0 | K92: =IF(AND(Source_Data!K$6>=Inputs!$B$54,Source_Data!K$6<Inputs!$B$54+3*Inputs!$B$11),Inputs!$B$9*Inputs!$B$7/Inputs!$B$11,0) -> 0 | ... BK92: =IF(AND(Source_Data!BK$6>=Inputs!$B$54,Source_Data!BK$6<Inputs!$B$54+3*Inputs!$B$11),Inputs!$B$9*Inputs!$B$7/Inputs!$B$11,0) -> 0
A93: Option B investor cash flow | D93: =IF(Source_Data!D$6=Inputs!$B$12,-Inputs!$B$7,0)+D92 -> -100 | E93: =IF(Source_Data!E$6=Inputs!$B$12,-Inputs!$B$7,0)+E92 -> 0 | F93: =IF(Source_Data!F$6=Inputs!$B$12,-Inputs!$B$7,0)+F92 -> 0 | G93: =IF(Source_Data!G$6=Inputs!$B$12,-Inputs!$B$7,0)+G92 -> 0 | H93: =IF(Source_Data!H$6=Inputs!$B$12,-Inputs!$B$7,0)+H92 -> 0 | I93: =IF(Source_Data!I$6=Inputs!$B$12,-Inputs!$B$7,0)+I92 -> 0 | J93: =IF(Source_Data!J$6=Inputs!$B$12,-Inputs!$B$7,0)+J92 -> 0 | K93: =IF(Source_Data!K$6=Inputs!$B$12,-Inputs!$B$7,0)+K92 -> 0 | ... BK93: =IF(Source_Data!BK$6=Inputs!$B$12,-Inputs!$B$7,0)+BK92 -> 0
A94: Pooled project cash after ticket and payouts | D94: =IF(Source_Data!D$6=Inputs!$B$12,Inputs!$B$7,0)+D89-D92 -> 8.75 | E94: =D94+IF(Source_Data!E$6=Inputs!$B$12,Inputs!$B$7,0)+E89-E92 -> -2.5 | F94: =E94+IF(Source_Data!F$6=Inputs!$B$12,Inputs!$B$7,0)+F89-F92 -> 2.9031613 | G94: =F94+IF(Source_Data!G$6=Inputs!$B$12,Inputs!$B$7,0)+G89-G92 -> 24.959484 | H94: =G94+IF(Source_Data!H$6=Inputs!$B$12,Inputs!$B$7,0)+H89-H92 -> 30.622691 | I94: =H94+IF(Source_Data!I$6=Inputs!$B$12,Inputs!$B$7,0)+I89-I92 -> 46.782782 | J94: =I94+IF(Source_Data!J$6=Inputs!$B$12,Inputs!$B$7,0)+J89-J92 -> 33.562523 | K94: =J94+IF(Source_Data!K$6=Inputs!$B$12,Inputs!$B$7,0)+K89-K92 -> 37.200909 | L94: =K94+IF(Source_Data!L$6=Inputs!$B$12,Inputs!$B$7,0)+L89-L92 -> 50.979256 | ... BK94: =BJ94+IF(Source_Data!BK$6=Inputs!$B$12,Inputs!$B$7,0)+BK89-BK92 -> 363.16568
A95: Coverage: net cash flow / payout | D95: =IF(D92>0,D89/D92,"") | E95: =IF(E92>0,E89/E92,"") | F95: =IF(F92>0,F89/F92,"") | G95: =IF(G92>0,G89/G92,"") | H95: =IF(H92>0,H89/H92,"") | I95: =IF(I92>0,I89/I92,"") | J95: =IF(J92>0,J89/J92,"") | K95: =IF(K92>0,K89/K92,"") | ... BK95: =IF(BK92>0,BK89/BK92,"")
A96: Coverage: cash available / payout | D96: =IF(D92>0,(0+D89+IF(Source_Data!D$6=Inputs!$B$12,Inputs!$B$7,0))/D92,"") | E96: =IF(E92>0,(D94+E89+IF(Source_Data!E$6=Inputs!$B$12,Inputs!$B$7,0))/E92,"") | F96: =IF(F92>0,(E94+F89+IF(Source_Data!F$6=Inputs!$B$12,Inputs!$B$7,0))/F92,"") | G96: =IF(G92>0,(F94+G89+IF(Source_Data!G$6=Inputs!$B$12,Inputs!$B$7,0))/G92,"") | H96: =IF(H92>0,(G94+H89+IF(Source_Data!H$6=Inputs!$B$12,Inputs!$B$7,0))/H92,"") | I96: =IF(I92>0,(H94+I89+IF(Source_Data!I$6=Inputs!$B$12,Inputs!$B$7,0))/I92,"") | J96: =IF(J92>0,(I94+J89+IF(Source_Data!J$6=Inputs!$B$12,Inputs!$B$7,0))/J92,"") | K96: =IF(K92>0,(J94+K89+IF(Source_Data!K$6=Inputs!$B$12,Inputs!$B$7,0))/K92,"") | L96: =IF(L92>0,(K94+L89+IF(Source_Data!L$6=Inputs!$B$12,Inputs!$B$7,0))/L92,"") | ... BK96: =IF(BK92>0,(BJ94+BK89+IF(Source_Data!BK$6=Inputs!$B$12,Inputs!$B$7,0))/BK92,"")
A98: Net cash flow, nominal | B98: =SUM(D89:BK89) -> 493.16568
A99: NPV @ discount rate | B99: =SUMPRODUCT(D89:BK89,Project_CF!$D$15:$BK$15) -> 314.58159
A100: Peak cumulative cash shortage | B100: =MIN(D90:BK90) -> -102.5
A101: Month of peak | B101: =INDEX(Project_CF!$D$6:$BK$6,MATCH(MIN(D90:BK90),D90:BK90,0)) -> 6
A102: Option A investor IRR | B102: =(1+IRR(D91:BK91,0.05))^4-1 -> 0.29199284
A103: Option A investor MOIC | B103: =SUMIF(D91:BK91,">0")/-SUMIF(D91:BK91,"<0") -> 3.0594982
A104: Option B investor IRR | B104: =(1+IRR(D93:BK93,0.05))^4-1 -> 0.26546399
A105: Option B lowest pooled cash (negative = sponsor support needed) | B105: =MIN(D94:BK94) -> -2.5
A106: Option B lowest quarterly coverage (net cash flow / payout) | B106: =MIN(D95:BK95) -> -8.6267434
A107: Quarters below threshold (strict) | B107: =COUNTIF(D95:BK95,"<"&Inputs!$B$43) -> 8
A108: Option B lowest cash-available coverage | B108: =MIN(D96:BK96) -> 11.619833
...

Sheet Sensitivity
A1: Green Square: one-factor sensitivities (live blocks)
A2: Sales delay, price change, cost overrun and collections slippage.
A4: price: 0.8
A5: Price factor | B5: 0.8
A6: Sales delay (quarters) | B6: 0
A7: Cost factor | B7: 1
A8: Collections slip (quarters) | B8: 0
A9: Delivery payments at handover (1 = yes) | B9: 0
A10: Resale start month (Option A) | B10: =Inputs!$B$13+3+3*$B$6 -> 51
A11: Collections before delay and price | D11: =Source_Data!D$7+IF($B$9=1,IF(Source_Data!D$6=Inputs!$B$13,Source_Data!$C$8,0),Source_Data!D$8) -> 0 | E11: =Source_Data!E$7+IF($B$9=1,IF(Source_Data!E$6=Inputs!$B$13,Source_Data!$C$8,0),Source_Data!E$8) -> 0 | F11: =Source_Data!F$7+IF($B$9=1,IF(Source_Data!F$6=Inputs!$B$13,Source_Data!$C$8,0),Source_Data!F$8) -> 15.139238 | G11: =Source_Data!G$7+IF($B$9=1,IF(Source_Data!G$6=Inputs!$B$13,Source_Data!$C$8,0),Source_Data!G$8) -> 30.278475 | H11: =Source_Data!H$7+IF($B$9=1,IF(Source_Data!H$6=Inputs!$B$13,Source_Data!$C$8,0),Source_Data!H$8) -> 46.512006 | I11: =Source_Data!I$7+IF($B$9=1,IF(Source_Data!I$6=Inputs!$B$13,Source_Data!$C$8,0),Source_Data!I$8) -> 62.745537 | J11: =Source_Data!J$7+IF($B$9=1,IF(Source_Data!J$6=Inputs!$B$13,Source_Data!$C$8,0),Source_Data!J$8) -> 62.3657 | K11: =Source_Data!K$7+IF($B$9=1,IF(Source_Data!K$6=Inputs!$B$13,Source_Data!$C$8,0),Source_Data!K$8) -> 63.473559 | ... BK11: =Source_Data!BK$7+IF($B$9=1,IF(Source_Data!BK$6=Inputs!$B$13,Source_Data!$C$8,0),Source_Data!BK$8) -> 0
A12: Collections | D12: =$B$5*IF(Source_Data!D$5-($B$6+$B$8)>=1,INDEX($D$11:$BK$11,1,Source_Data!D$5-($B$6+$B$8)),0) -> 0 | E12: =$B$5*IF(Source_Data!E$5-($B$6+$B$8)>=1,INDEX($D$11:$BK$11,1,Source_Data!E$5-($B$6+$B$8)),0) -> 0 | F12: =$B$5*IF(Source_Data!F$5-($B$6+$B$8)>=1,INDEX($D$11:$BK$11,1,Source_Data!F$5-($B$6+$B$8)),0) -> 12.11139 | G12: =$B$5*IF(Source_Data!G$5-($B$6+$B$8)>=1,INDEX($D$11:$BK$11,1,Source_Data!G$5-($B$6+$B$8)),0) -> 24.22278 | H12: =$B$5*IF(Source_Data!H$5-($B$6+$B$8)>=1,INDEX($D$11:$BK$11,1,Source_Data!H$5-($B$6+$B$8)),0) -> 37.209605 | I12: =$B$5*IF(Source_Data!I$5-($B$6+$B$8)>=1,INDEX($D$11:$BK$11,1,Source_Data!I$5-($B$6+$B$8)),0) -> 50.19643 | J12: =$B$5*IF(Source_Data!J$5-($B$6+$B$8)>=1,INDEX($D$11:$BK$11,1,Source_Data!J$5-($B$6+$B$8)),0) -> 49.89256 | K12: =$B$5*IF(Source_Data!K$5-($B$6+$B$8)>=1,INDEX($D$11:$BK$11,1,Source_Data!K$5-($B$6+$B$8)),0) -> 50.778847 | ... BK12: =$B$5*IF(Source_Data!BK$5-($B$6+$B$8)>=1,INDEX($D$11:$BK$11,1,Source_Data!BK$5-($B$6+$B$8)),0) -> 0
A13: Landlord payments | D13: =Source_Data!D$9+Source_Data!D$10*IF(Source_Data!$C$10=0,0,MAX(0,Inputs!$B$19*Inputs!$B$22*$B$5-Inputs!$B$20)/Source_Data!$C$10) -> 91.25 | E13: =Source_Data!E$9+Source_Data!E$10*IF(Source_Data!$C$10=0,0,MAX(0,Inputs!$B$19*Inputs!$B$22*$B$5-Inputs!$B$20)/Source_Data!$C$10) -> 11.25 | F13: =Source_Data!F$9+Source_Data!F$10*IF(Source_Data!$C$10=0,0,MAX(0,Inputs!$B$19*Inputs!$B$22*$B$5-Inputs!$B$20)/Source_Data!$C$10) -> 11.25 | G13: =Source_Data!G$9+Source_Data!G$10*IF(Source_Data!$C$10=0,0,MAX(0,Inputs!$B$19*Inputs!$B$22*$B$5-Inputs!$B$20)/Source_Data!$C$10) -> 11.25 | H13: =Source_Data!H$9+Source_Data!H$10*IF(Source_Data!$C$10=0,0,MAX(0,Inputs!$B$19*Inputs!$B$22*$B$5-Inputs!$B$20)/Source_Data!$C$10) -> 22.5 | I13: =Source_Data!I$9+Source_Data!I$10*IF(Source_Data!$C$10=0,0,MAX(0,Inputs!$B$19*Inputs!$B$22*$B$5-Inputs!$B$20)/Source_Data!$C$10) -> 22.5 | J13: =Source_Data!J$9+Source_Data!J$10*IF(Source_Data!$C$10=0,0,MAX(0,Inputs!$B$19*Inputs!$B$22*$B$5-Inputs!$B$20)/Source_Data!$C$10) -> 22.5 | K13: =Source_Data!K$9+Source_Data!K$10*IF(Source_Data!$C$10=0,0,MAX(0,Inputs!$B$19*Inputs!$B$22*$B$5-Inputs!$B$20)/Source_Data!$C$10) -> 22.5 | ... BK13: =Source_Data!BK$9+Source_Data!BK$10*IF(Source_Data!$C$10=0,0,MAX(0,Inputs!$B$19*Inputs!$B$22*$B$5-Inputs!$B$20)/Source_Data!$C$10) -> 0
A14: Construction cost | D14: =Source_Data!D$11*$B$7 -> 0 | E14: =Source_Data!E$11*$B$7 -> 0 | F14: =Source_Data!F$11*$B$7 -> 0 | G14: =Source_Data!G$11*$B$7 -> 0 | H14: =Source_Data!H$11*$B$7 -> 20 | I14: =Source_Data!I$11*$B$7 -> 26.4 | J14: =Source_Data!J$11*$B$7 -> 40 | K14: =Source_Data!K$11*$B$7 -> 26.4 | ... BK14: =Source_Data!BK$11*$B$7 -> 0
A15: Sales commission | D15: =$B$5*IF(Source_Data!D$5-$B$6>=1,INDEX(Source_Data!$D$12:$BK$12,1,Source_Data!D$5-$B$6),0) -> 0 | E15: =$B$5*IF(Source_Data!E$5-$B$6>=1,INDEX(Source_Data!$D$12:$BK$12,1,Source_Data!E$5-$B$6),0) -> 0 | F15: =$B$5*IF(Source_Data!F$5-$B$6>=1,INDEX(Source_Data!$D$12:$BK$12,1,Source_Data!F$5-$B$6),0) -> 0 | G15: =$B$5*IF(Source_Data!G$5-$B$6>=1,INDEX(Source_Data!$D$12:$BK$12,1,Source_Data!G$5-$B$6),0) -> 0 | H15: =$B$5*IF(Source_Data!H$5-$B$6>=1,INDEX(Source_Data!$D$12:$BK$12,1,Source_Data!H$5-$B$6),0) -> 0 | I15: =$B$5*IF(Source_Data!I$5-$B$6>=1,INDEX(Source_Data!$D$12:$BK$12,1,Source_Data!I$5-$B$6),0) -> 0 | J15: =$B$5*IF(Source_Data!J$5-$B$6>=1,INDEX(Source_Data!$D$12:$BK$12,1,Source_Data!J$5-$B$6),0) -> 9.689112 | K15: =$B$5*IF(Source_Data!K$5-$B$6>=1,INDEX(Source_Data!$D$12:$BK$12,1,Source_Data!K$5-$B$6),0) -> 9.689112 | ... BK15: =$B$5*IF(Source_Data!BK$5-$B$6>=1,INDEX(Source_Data!$D$12:$BK$12,1,Source_Data!BK$5-$B$6),0) -> 0
A16: SG&A and others | D16: =Source_Data!D$13*$B$7 -> 0 | E16: =Source_Data!E$13*$B$7 -> 0 | F16: =Source_Data!F$13*$B$7 -> 0 | G16: =Source_Data!G$13*$B$7 -> 0 | H16: =Source_Data!H$13*$B$7 -> 3 | I16: =Source_Data!I$13*$B$7 -> 3.96 | J16: =Source_Data!J$13*$B$7 -> 6 | K16: =Source_Data!K$13*$B$7 -> 3.96 | ... BK16: =Source_Data!BK$13*$B$7 -> 0
A17: Net cash flow | D17: =D12-D13-D14-D15-D16 -> -91.25 | E17: =E12-E13-E14-E15-E16 -> -11.25 | F17: =F12-F13-F14-F15-F16 -> 0.86139 | G17: =G12-G13-G14-G15-G16 -> 12.97278 | H17: =H12-H13-H14-H15-H16 -> -8.290395 | I17: =I12-I13-I14-I15-I16 -> -2.66357 | J17: =J12-J13-J14-J15-J16 -> -28.296552 | K17: =K12-K13-K14-K15-K16 -> -11.770264 | ... BK17: =BK12-BK13-BK14-BK15-BK16 -> 0
A18: Cumulative net cash flow | D18: =D17 -> -91.25 | E18: =D18+E17 -> -102.5 | F18: =E18+F17 -> -101.63861 | G18: =F18+G17 -> -88.66583 | H18: =G18+H17 -> -96.956225 | I18: =H18+I17 -> -99.619795 | J18: =I18+J17 -> -127.91635 | K18: =J18+K17 -> -139.68661 | L18: =K18+L17 -> -147.15054 | ... BK18: =BJ18+BK17 -> 128.55387
A19: Option A investor cash flow | D19: =IF(Source_Data!D$6=Inputs!$B$12,-Inputs!$B$7,0)+IF(AND(Source_Data!D$6>=$B$10,Source_Data!D$6<$B$10+3*Inputs!$B$16,MOD(Source_Data!D$6-$B$10,3)=0),Inputs!$B$8*Inputs!$B$7*Inputs!$B$34*$B$5*(1-Inputs!$B$15)/Inputs!$B$16,0) -> -100 | E19: =IF(Source_Data!E$6=Inputs!$B$12,-Inputs!$B$7,0)+IF(AND(Source_Data!E$6>=$B$10,Source_Data!E$6<$B$10+3*Inputs!$B$16,MOD(Source_Data!E$6-$B$10,3)=0),Inputs!$B$8*Inputs!$B$7*Inputs!$B$34*$B$5*(1-Inputs!$B$15)/Inputs!$B$16,0) -> 0 | F19: =IF(Source_Data!F$6=Inputs!$B$12,-Inputs!$B$7,0)+IF(AND(Source_Data!F$6>=$B$10,Source_Data!F$6<$B$10+3*Inputs!$B$16,MOD(Source_Data!F$6-$B$10,3)=0),Inputs!$B$8*Inputs!$B$7*Inputs!$B$34*$B$5*(1-Inputs!$B$15)/Inputs!$B$16,0) -> 0 | G19: =IF(Source_Data!G$6=Inputs!$B$12,-Inputs!$B$7,0)+IF(AND(Source_Data!G$6>=$B$10,Source_Data!G$6<$B$10+3*Inputs!$B$16,MOD(Source_Data!G$6-$B$10,3)=0),Inputs!$B$8*Inputs!$B$7*Inputs!$B$34*$B$5*(1-Inputs!$B$15)/Inputs!$B$16,0) -> 0 | H19: =IF(Source_Data!H$6=Inputs!$B$12,-Inputs!$B$7,0)+IF(AND(Source_Data!H$6>=$B$10,Source_Data!H$6<$B$10+3*Inputs!$B$16,MOD(Source_Data!H$6-$B$10,3)=0),Inputs!$B$8*Inputs!$B$7*Inputs!$B$34*$B$5*(1-Inputs!$B$15)/Inputs!$B$16,0) -> 0 | I19: =IF(Source_Data!I$6=Inputs!$B$12,-Inputs!$B$7,0)+IF(AND(Source_Data!I$6>=$B$10,Source_Data!I$6<$B$10+3*Inputs!$B$16,MOD(Source_Data!I$6-$B$10,3)=0),Inputs!$B$8*Inputs!$B$7*Inputs!$B$34*$B$5*(1-Inputs!$B$15)/Inputs!$B$16,0) -> 0 | J19: =IF(Source_Data!J$6=Inputs!$B$12,-Inputs!$B$7,0)+IF(AND(Source_Data!J$6>=$B$10,Source_Data!J$6<$B$10+3*Inputs!$B$16,MOD(Source_Data!J$6-$B$10,3)=0),Inputs!$B$8*Inputs!$B$7*Inputs!$B$34*$B$5*(1-Inputs!$B$15)/Inputs!$B$16,0) -> 0 | K19: =IF(Source_Data!K$6=Inputs!$B$12,-Inputs!$B$7,0)+IF(AND(Source_Data!K$6>=$B$10,Source_Data!K$6<$B$10+3*Inputs!$B$16,MOD(Source_Data!K$6-$B$10,3)=0),Inputs!$B$8*Inputs!$B$7*Inputs!$B$34*$B$5*(1-Inputs!$B$15)/Inputs!$B$16,0) -> 0 | ... BK19: =IF(Source_Data!BK$6=Inputs!$B$12,-Inputs!$B$7,0)+IF(AND(Source_Data!BK$6>=$B$10,Source_Data!BK$6<$B$10+3*Inputs!$B$16,MOD(Source_Data!BK$6-$B$10,3)=0),Inputs!$B$8*Inputs!$B$7*Inputs!$B$34*$B$5*(1-Inputs!$B$15)/Inputs!$B$16,0) -> 0
A20: Option B payouts (fixed schedule) | D20: =IF(AND(Source_Data!D$6>=Inputs!$B$54,Source_Data!D$6<Inputs!$B$54+3*Inputs!$B$11),Inputs!$B$9*Inputs!$B$7/Inputs!$B$11,0) -> 0 | E20: =IF(AND(Source_Data!E$6>=Inputs!$B$54,Source_Data!E$6<Inputs!$B$54+3*Inputs!$B$11),Inputs!$B$9*Inputs!$B$7/Inputs!$B$11,0) -> 0 | F20: =IF(AND(Source_Data!F$6>=Inputs!$B$54,Source_Data!F$6<Inputs!$B$54+3*Inputs!$B$11),Inputs!$B$9*Inputs!$B$7/Inputs!$B$11,0) -> 0 | G20: =IF(AND(Source_Data!G$6>=Inputs!$B$54,Source_Data!G$6<Inputs!$B$54+3*Inputs!$B$11),Inputs!$B$9*Inputs!$B$7/Inputs!$B$11,0) -> 0 | H20: =IF(AND(Source_Data!H$6>=Inputs!$B$54,Source_Data!H$6<Inputs!$B$54+3*Inputs!$B$11),Inputs!$B$9*Inputs!$B$7/Inputs!$B$11,0) -> 0 | I20: =IF(AND(Source_Data!I$6>=Inputs!$B$54,Source_Data!I$6<Inputs!$B$54+3*Inputs!$B$11),Inputs!$B$9*Inputs!$B$7/Inputs!$B$11,0) -> 0 | J20: =IF(AND(Source_Data!J$6>=Inputs!$B$54,Source_Data!J$6<Inputs!$B$54+3*Inputs!$B$11),Inputs!$B$9*Inputs!$B$7/Inputs!$B$11,0) -> 0 | K20: =IF(AND(Source_Data!K$6>=Inputs!$B$54,Source_Data!K$6<Inputs!$B$54+3*Inputs!$B$11),Inputs!$B$9*Inputs!$B$7/Inputs!$B$11,0) -> 0 | ... BK20: =IF(AND(Source_Data!BK$6>=Inputs!$B$54,Source_Data!BK$6<Inputs!$B$54+3*Inputs!$B$11),Inputs!$B$9*Inputs!$B$7/Inputs!$B$11,0) -> 0
A21: Option B investor cash flow | D21: =IF(Source_Data!D$6=Inputs!$B$12,-Inputs!$B$7,0)+D20 -> -100 | E21: =IF(Source_Data!E$6=Inputs!$B$12,-Inputs!$B$7,0)+E20 -> 0 | F21: =IF(Source_Data!F$6=Inputs!$B$12,-Inputs!$B$7,0)+F20 -> 0 | G21: =IF(Source_Data!G$6=Inputs!$B$12,-Inputs!$B$7,0)+G20 -> 0 | H21: =IF(Source_Data!H$6=Inputs!$B$12,-Inputs!$B$7,0)+H20 -> 0 | I21: =IF(Source_Data!I$6=Inputs!$B$12,-Inputs!$B$7,0)+I20 -> 0 | J21: =IF(Source_Data!J$6=Inputs!$B$12,-Inputs!$B$7,0)+J20 -> 0 | K21: =IF(Source_Data!K$6=Inputs!$B$12,-Inputs!$B$7,0)+K20 -> 0 | ... BK21: =IF(Source_Data!BK$6=Inputs!$B$12,-Inputs!$B$7,0)+BK20 -> 0
A22: Pooled project cash after ticket and payouts | D22: =IF(Source_Data!D$6=Inputs!$B$12,Inputs!$B$7,0)+D17-D20 -> 8.75 | E22: =D22+IF(Source_Data!E$6=Inputs!$B$12,Inputs!$B$7,0)+E17-E20 -> -2.5 | F22: =E22+IF(Source_Data!F$6=Inputs!$B$12,Inputs!$B$7,0)+F17-F20 -> -1.63861 | G22: =F22+IF(Source_Data!G$6=Inputs!$B$12,Inputs!$B$7,0)+G17-G20 -> 11.33417 | H22: =G22+IF(Source_Data!H$6=Inputs!$B$12,Inputs!$B$7,0)+H17-H20 -> 3.043775 | I22: =H22+IF(Source_Data!I$6=Inputs!$B$12,Inputs!$B$7,0)+I17-I20 -> 0.380205 | J22: =I22+IF(Source_Data!J$6=Inputs!$B$12,Inputs!$B$7,0)+J17-J20 -> -27.916347 | K22: =J22+IF(Source_Data!K$6=Inputs!$B$12,Inputs!$B$7,0)+K17-K20 -> -39.686611 | L22: =K22+IF(Source_Data!L$6=Inputs!$B$12,Inputs!$B$7,0)+L17-L20 -> -47.150541 | ... BK22: =BJ22+IF(Source_Data!BK$6=Inputs!$B$12,Inputs!$B$7,0)+BK17-BK20 -> -1.446128
A23: Coverage: net cash flow / payout | D23: =IF(D20>0,D17/D20,"") | E23: =IF(E20>0,E17/E20,"") | F23: =IF(F20>0,F17/F20,"") | G23: =IF(G20>0,G17/G20,"") | H23: =IF(H20>0,H17/H20,"") | I23: =IF(I20>0,I17/I20,"") | J23: =IF(J20>0,J17/J20,"") | K23: =IF(K20>0,K17/K20,"") | ... BK23: =IF(BK20>0,BK17/BK20,"")
A24: Coverage: cash available / payout | D24: =IF(D20>0,(0+D17+IF(Source_Data!D$6=Inputs!$B$12,Inputs!$B$7,0))/D20,"") | E24: =IF(E20>0,(D22+E17+IF(Source_Data!E$6=Inputs!$B$12,Inputs!$B$7,0))/E20,"") | F24: =IF(F20>0,(E22+F17+IF(Source_Data!F$6=Inputs!$B$12,Inputs!$B$7,0))/F20,"") | G24: =IF(G20>0,(F22+G17+IF(Source_Data!G$6=Inputs!$B$12,Inputs!$B$7,0))/G20,"") | H24: =IF(H20>0,(G22+H17+IF(Source_Data!H$6=Inputs!$B$12,Inputs!$B$7,0))/H20,"") | I24: =IF(I20>0,(H22+I17+IF(Source_Data!I$6=Inputs!$B$12,Inputs!$B$7,0))/I20,"") | J24: =IF(J20>0,(I22+J17+IF(Source_Data!J$6=Inputs!$B$12,Inputs!$B$7,0))/J20,"") | K24: =IF(K20>0,(J22+K17+IF(Source_Data!K$6=Inputs!$B$12,Inputs!$B$7,0))/K20,"") | L24: =IF(L20>0,(K22+L17+IF(Source_Data!L$6=Inputs!$B$12,Inputs!$B$7,0))/L20,"") | ... BK24: =IF(BK20>0,(BJ22+BK17+IF(Source_Data!BK$6=Inputs!$B$12,Inputs!$B$7,0))/BK20,"")
A26: Net cash flow, nominal | B26: =SUM(D17:BK17) -> 128.55387
A27: NPV @ discount rate | B27: =SUMPRODUCT(D17:BK17,Project_CF!$D$15:$BK$15) -> 12.57309
A28: Peak cumulative cash shortage | B28: =MIN(D18:BK18) -> -183.65099
A29: Month of peak | B29: =INDEX(Project_CF!$D$6:$BK$6,MATCH(MIN(D18:BK18),D18:BK18,0)) -> 60
A30: Option A investor IRR | B30: =(1+IRR(D19:BK19,0.05))^4-1 -> 0.20094658
A31: Option A investor MOIC | B31: =SUMIF(D19:BK19,">0")/-SUMIF(D19:BK19,"<0") -> 2.2250896
A32: Option B investor IRR | B32: =(1+IRR(D21:BK21,0.05))^4-1 -> 0.26546399
A33: Option B lowest pooled cash (negative = sponsor support needed) | B33: =MIN(D22:BK22) -> -296.64464
A34: Option B lowest quarterly coverage (net cash flow / payout) | B34: =MIN(D23:BK23) -> -9.5979477
A35: Quarters below threshold (strict) | B35: =COUNTIF(D23:BK23,"<"&Inputs!$B$43) -> 9
A36: Option B lowest cash-available coverage | B36: =MIN(D24:BK24) -> -14.477111
A37: Quarters below threshold (cash available) | B37: =COUNTIF(D24:BK24,"<"&Inputs!$B$43) -> 7
A40: price: 0.9
A41: Price factor | B41: 0.9
A42: Sales delay (quarters) | B42: 0
A43: Cost factor | B43: 1
A44: Collections slip (quarters) | B44: 0
A45: Delivery payments at handover (1 = yes) | B45: 0
A46: Resale start month (Option A) | B46: =Inputs!$B$13+3+3*$B$42 -> 51
A47: Collections before delay and price | D47: =Source_Data!D$7+IF($B$45=1,IF(Source_Data!D$6=Inputs!$B$13,Source_Data!$C$8,0),Source_Data!D$8) -> 0 | E47: =Source_Data!E$7+IF($B$45=1,IF(Source_Data!E$6=Inputs!$B$13,Source_Data!$C$8,0),Source_Data!E$8) -> 0 | F47: =Source_Data!F$7+IF($B$45=1,IF(Source_Data!F$6=Inputs!$B$13,Source_Data!$C$8,0),Source_Data!F$8) -> 15.139238 | G47: =Source_Data!G$7+IF($B$45=1,IF(Source_Data!G$6=Inputs!$B$13,Source_Data!$C$8,0),Source_Data!G$8) -> 30.278475 | H47: =Source_Data!H$7+IF($B$45=1,IF(Source_Data!H$6=Inputs!$B$13,Source_Data!$C$8,0),Source_Data!H$8) -> 46.512006 | I47: =Source_Data!I$7+IF($B$45=1,IF(Source_Data!I$6=Inputs!$B$13,Source_Data!$C$8,0),Source_Data!I$8) -> 62.745537 | J47: =Source_Data!J$7+IF($B$45=1,IF(Source_Data!J$6=Inputs!$B$13,Source_Data!$C$8,0),Source_Data!J$8) -> 62.3657 | K47: =Source_Data!K$7+IF($B$45=1,IF(Source_Data!K$6=Inputs!$B$13,Source_Data!$C$8,0),Source_Data!K$8) -> 63.473559 | ... BK47: =Source_Data!BK$7+IF($B$45=1,IF(Source_Data!BK$6=Inputs!$B$13,Source_Data!$C$8,0),Source_Data!BK$8) -> 0
A48: Collections | D48: =$B$41*IF(Source_Data!D$5-($B$42+$B$44)>=1,INDEX($D$47:$BK$47,1,Source_Data!D$5-($B$42+$B$44)),0) -> 0 | E48: =$B$41*IF(Source_Data!E$5-($B$42+$B$44)>=1,INDEX($D$47:$BK$47,1,Source_Data!E$5-($B$42+$B$44)),0) -> 0 | F48: =$B$41*IF(Source_Data!F$5-($B$42+$B$44)>=1,INDEX($D$47:$BK$47,1,Source_Data!F$5-($B$42+$B$44)),0) -> 13.625314 | G48: =$B$41*IF(Source_Data!G$5-($B$42+$B$44)>=1,INDEX($D$47:$BK$47,1,Source_Data!G$5-($B$42+$B$44)),0) -> 27.250628 | H48: =$B$41*IF(Source_Data!H$5-($B$42+$B$44)>=1,INDEX($D$47:$BK$47,1,Source_Data!H$5-($B$42+$B$44)),0) -> 41.860806 | I48: =$B$41*IF(Source_Data!I$5-($B$42+$B$44)>=1,INDEX($D$47:$BK$47,1,Source_Data!I$5-($B$42+$B$44)),0) -> 56.470984 | J48: =$B$41*IF(Source_Data!J$5-($B$42+$B$44)>=1,INDEX($D$47:$BK$47,1,Source_Data!J$5-($B$42+$B$44)),0) -> 56.12913 | K48: =$B$41*IF(Source_Data!K$5-($B$42+$B$44)>=1,INDEX($D$47:$BK$47,1,Source_Data!K$5-($B$42+$B$44)),0) -> 57.126203 | ... BK48: =$B$41*IF(Source_Data!BK$5-($B$42+$B$44)>=1,INDEX($D$47:$BK$47,1,Source_Data!BK$5-($B$42+$B$44)),0) -> 0
A49: Landlord payments | D49: =Source_Data!D$9+Source_Data!D$10*IF(Source_Data!$C$10=0,0,MAX(0,Inputs!$B$19*Inputs!$B$22*$B$41-Inputs!$B$20)/Source_Data!$C$10) -> 91.25 | E49: =Source_Data!E$9+Source_Data!E$10*IF(Source_Data!$C$10=0,0,MAX(0,Inputs!$B$19*Inputs!$B$22*$B$41-Inputs!$B$20)/Source_Data!$C$10) -> 11.25 | F49: =Source_Data!F$9+Source_Data!F$10*IF(Source_Data!$C$10=0,0,MAX(0,Inputs!$B$19*Inputs!$B$22*$B$41-Inputs!$B$20)/Source_Data!$C$10) -> 11.25 | G49: =Source_Data!G$9+Source_Data!G$10*IF(Source_Data!$C$10=0,0,MAX(0,Inputs!$B$19*Inputs!$B$22*$B$41-Inputs!$B$20)/Source_Data!$C$10) -> 11.25 | H49: =Source_Data!H$9+Source_Data!H$10*IF(Source_Data!$C$10=0,0,MAX(0,Inputs!$B$19*Inputs!$B$22*$B$41-Inputs!$B$20)/Source_Data!$C$10) -> 22.5 | I49: =Source_Data!I$9+Source_Data!I$10*IF(Source_Data!$C$10=0,0,MAX(0,Inputs!$B$19*Inputs!$B$22*$B$41-Inputs!$B$20)/Source_Data!$C$10) -> 22.5 | J49: =Source_Data!J$9+Source_Data!J$10*IF(Source_Data!$C$10=0,0,MAX(0,Inputs!$B$19*Inputs!$B$22*$B$41-Inputs!$B$20)/Source_Data!$C$10) -> 22.5 | K49: =Source_Data!K$9+Source_Data!K$10*IF(Source_Data!$C$10=0,0,MAX(0,Inputs!$B$19*Inputs!$B$22*$B$41-Inputs!$B$20)/Source_Data!$C$10) -> 22.5 | ... BK49: =Source_Data!BK$9+Source_Data!BK$10*IF(Source_Data!$C$10=0,0,MAX(0,Inputs!$B$19*Inputs!$B$22*$B$41-Inputs!$B$20)/Source_Data!$C$10) -> 0
A50: Construction cost | D50: =Source_Data!D$11*$B$43 -> 0 | E50: =Source_Data!E$11*$B$43 -> 0 | F50: =Source_Data!F$11*$B$43 -> 0 | G50: =Source_Data!G$11*$B$43 -> 0 | H50: =Source_Data!H$11*$B$43 -> 20 | I50: =Source_Data!I$11*$B$43 -> 26.4 | J50: =Source_Data!J$11*$B$43 -> 40 | K50: =Source_Data!K$11*$B$43 -> 26.4 | ... BK50: =Source_Data!BK$11*$B$43 -> 0
A51: Sales commission | D51: =$B$41*IF(Source_Data!D$5-$B$42>=1,INDEX(Source_Data!$D$12:$BK$12,1,Source_Data!D$5-$B$42),0) -> 0 | E51: =$B$41*IF(Source_Data!E$5-$B$42>=1,INDEX(Source_Data!$D$12:$BK$12,1,Source_Data!E$5-$B$42),0) -> 0 | F51: =$B$41*IF(Source_Data!F$5-$B$42>=1,INDEX(Source_Data!$D$12:$BK$12,1,Source_Data!F$5-$B$42),0) -> 0 | G51: =$B$41*IF(Source_Data!G$5-$B$42>=1,INDEX(Source_Data!$D$12:$BK$12,1,Source_Data!G$5-$B$42),0) -> 0 | H51: =$B$41*IF(Source_Data!H$5-$B$42>=1,INDEX(Source_Data!$D$12:$BK$12,1,Source_Data!H$5-$B$42),0) -> 0 | I51: =$B$41*IF(Source_Data!I$5-$B$42>=1,INDEX(Source_Data!$D$12:$BK$12,1,Source_Data!I$5-$B$42),0) -> 0 | J51: =$B$41*IF(Source_Data!J$5-$B$42>=1,INDEX(Source_Data!$D$12:$BK$12,1,Source_Data!J$5-$B$42),0) -> 10.900251 | K51: =$B$41*IF(Source_Data!K$5-$B$42>=1,INDEX(Source_Data!$D$12:$BK$12,1,Source_Data!K$5-$B$42),0) -> 10.900251 | ... BK51: =$B$41*IF(Source_Data!BK$5-$B$42>=1,INDEX(Source_Data!$D$12:$BK$12,1,Source_Data!BK$5-$B$42),0) -> 0
A52: SG&A and others | D52: =Source_Data!D$13*$B$43 -> 0 | E52: =Source_Data!E$13*$B$43 -> 0 | F52: =Source_Data!F$13*$B$43 -> 0 | G52: =Source_Data!G$13*$B$43 -> 0 | H52: =Source_Data!H$13*$B$43 -> 3 | I52: =Source_Data!I$13*$B$43 -> 3.96 | J52: =Source_Data!J$13*$B$43 -> 6 | K52: =Source_Data!K$13*$B$43 -> 3.96 | ... BK52: =Source_Data!BK$13*$B$43 -> 0
A53: Net cash flow | D53: =D48-D49-D50-D51-D52 -> -91.25 | E53: =E48-E49-E50-E51-E52 -> -11.25 | F53: =F48-F49-F50-F51-F52 -> 2.3753138 | G53: =G48-G49-G50-G51-G52 -> 16.000628 | H53: =H48-H49-H50-H51-H52 -> -3.6391944 | I53: =I48-I49-I50-I51-I52 -> 3.6109837 | J53: =J48-J49-J50-J51-J52 -> -23.271121 | K53: =K48-K49-K50-K51-K52 -> -6.6340476 | ... BK53: =BK48-BK49-BK50-BK51-BK52 -> 0
A54: Cumulative net cash flow | D54: =D53 -> -91.25 | E54: =D54+E53 -> -102.5 | F54: =E54+F53 -> -100.12469 | G54: =F54+G53 -> -84.124059 | H54: =G54+H53 -> -87.763253 | I54: =H54+I53 -> -84.152269 | J54: =I54+J53 -> -107.42339 | K54: =J54+K53 -> -114.05744 | L54: =K54+L53 -> -114.44061 | ... BK54: =BJ54+BK53 -> 257.72937
A55: Option A investor cash flow | D55: =IF(Source_Data!D$6=Inputs!$B$12,-Inputs!$B$7,0)+IF(AND(Source_Data!D$6>=$B$46,Source_Data!D$6<$B$46+3*Inputs!$B$16,MOD(Source_Data!D$6-$B$46,3)=0),Inputs!$B$8*Inputs!$B$7*Inputs!$B$34*$B$41*(1-Inputs!$B$15)/Inputs!$B$16,0) -> -100 | E55: =IF(Source_Data!E$6=Inputs!$B$12,-Inputs!$B$7,0)+IF(AND(Source_Data!E$6>=$B$46,Source_Data!E$6<$B$46+3*Inputs!$B$16,MOD(Source_Data!E$6-$B$46,3)=0),Inputs!$B$8*Inputs!$B$7*Inputs!$B$34*$B$41*(1-Inputs!$B$15)/Inputs!$B$16,0) -> 0 | F55: =IF(Source_Data!F$6=Inputs!$B$12,-Inputs!$B$7,0)+IF(AND(Source_Data!F$6>=$B$46,Source_Data!F$6<$B$46+3*Inputs!$B$16,MOD(Source_Data!F$6-$B$46,3)=0),Inputs!$B$8*Inputs!$B$7*Inputs!$B$34*$B$41*(1-Inputs!$B$15)/Inputs!$B$16,0) -> 0 | G55: =IF(Source_Data!G$6=Inputs!$B$12,-Inputs!$B$7,0)+IF(AND(Source_Data!G$6>=$B$46,Source_Data!G$6<$B$46+3*Inputs!$B$16,MOD(Source_Data!G$6-$B$46,3)=0),Inputs!$B$8*Inputs!$B$7*Inputs!$B$34*$B$41*(1-Inputs!$B$15)/Inputs!$B$16,0) -> 0 | H55: =IF(Source_Data!H$6=Inputs!$B$12,-Inputs!$B$7,0)+IF(AND(Source_Data!H$6>=$B$46,Source_Data!H$6<$B$46+3*Inputs!$B$16,MOD(Source_Data!H$6-$B$46,3)=0),Inputs!$B$8*Inputs!$B$7*Inputs!$B$34*$B$41*(1-Inputs!$B$15)/Inputs!$B$16,0) -> 0 | I55: =IF(Source_Data!I$6=Inputs!$B$12,-Inputs!$B$7,0)+IF(AND(Source_Data!I$6>=$B$46,Source_Data!I$6<$B$46+3*Inputs!$B$16,MOD(Source_Data!I$6-$B$46,3)=0),Inputs!$B$8*Inputs!$B$7*Inputs!$B$34*$B$41*(1-Inputs!$B$15)/Inputs!$B$16,0) -> 0 | J55: =IF(Source_Data!J$6=Inputs!$B$12,-Inputs!$B$7,0)+IF(AND(Source_Data!J$6>=$B$46,Source_Data!J$6<$B$46+3*Inputs!$B$16,MOD(Source_Data!J$6-$B$46,3)=0),Inputs!$B$8*Inputs!$B$7*Inputs!$B$34*$B$41*(1-Inputs!$B$15)/Inputs!$B$16,0) -> 0 | K55: =IF(Source_Data!K$6=Inputs!$B$12,-Inputs!$B$7,0)+IF(AND(Source_Data!K$6>=$B$46,Source_Data!K$6<$B$46+3*Inputs!$B$16,MOD(Source_Data!K$6-$B$46,3)=0),Inputs!$B$8*Inputs!$B$7*Inputs!$B$34*$B$41*(1-Inputs!$B$15)/Inputs!$B$16,0) -> 0 | ... BK55: =IF(Source_Data!BK$6=Inputs!$B$12,-Inputs!$B$7,0)+IF(AND(Source_Data!BK$6>=$B$46,Source_Data!BK$6<$B$46+3*Inputs!$B$16,MOD(Source_Data!BK$6-$B$46,3)=0),Inputs!$B$8*Inputs!$B$7*Inputs!$B$34*$B$41*(1-Inputs!$B$15)/Inputs!$B$16,0) -> 0
A56: Option B payouts (fixed schedule) | D56: =IF(AND(Source_Data!D$6>=Inputs!$B$54,Source_Data!D$6<Inputs!$B$54+3*Inputs!$B$11),Inputs!$B$9*Inputs!$B$7/Inputs!$B$11,0) -> 0 | E56: =IF(AND(Source_Data!E$6>=Inputs!$B$54,Source_Data!E$6<Inputs!$B$54+3*Inputs!$B$11),Inputs!$B$9*Inputs!$B$7/Inputs!$B$11,0) -> 0 | F56: =IF(AND(Source_Data!F$6>=Inputs!$B$54,Source_Data!F$6<Inputs!$B$54+3*Inputs!$B$11),Inputs!$B$9*Inputs!$B$7/Inputs!$B$11,0) -> 0 | G56: =IF(AND(Source_Data!G$6>=Inputs!$B$54,Source_Data!G$6<Inputs!$B$54+3*Inputs!$B$11),Inputs!$B$9*Inputs!$B$7/Inputs!$B$11,0) -> 0 | H56: =IF(AND(Source_Data!H$6>=Inputs!$B$54,Source_Data!H$6<Inputs!$B$54+3*Inputs!$B$11),Inputs!$B$9*Inputs!$B$7/Inputs!$B$11,0) -> 0 | I56: =IF(AND(Source_Data!I$6>=Inputs!$B$54,Source_Data!I$6<Inputs!$B$54+3*Inputs!$B$11),Inputs!$B$9*Inputs!$B$7/Inputs!$B$11,0) -> 0 | J56: =IF(AND(Source_Data!J$6>=Inputs!$B$54,Source_Data!J$6<Inputs!$B$54+3*Inputs!$B$11),Inputs!$B$9*Inputs!$B$7/Inputs!$B$11,0) -> 0 | K56: =IF(AND(Source_Data!K$6>=Inputs!$B$54,Source_Data!K$6<Inputs!$B$54+3*Inputs!$B$11),Inputs!$B$9*Inputs!$B$7/Inputs!$B$11,0) -> 0 | ... BK56: =IF(AND(Source_Data!BK$6>=Inputs!$B$54,Source_Data!BK$6<Inputs!$B$54+3*Inputs!$B$11),Inputs!$B$9*Inputs!$B$7/Inputs!$B$11,0) -> 0
A57: Option B investor cash flow | D57: =IF(Source_Data!D$6=Inputs!$B$12,-Inputs!$B$7,0)+D56 -> -100 | E57: =IF(Source_Data!E$6=Inputs!$B$12,-Inputs!$B$7,0)+E56 -> 0 | F57: =IF(Source_Data!F$6=Inputs!$B$12,-Inputs!$B$7,0)+F56 -> 0 | G57: =IF(Source_Data!G$6=Inputs!$B$12,-Inputs!$B$7,0)+G56 -> 0 | H57: =IF(Source_Data!H$6=Inputs!$B$12,-Inputs!$B$7,0)+H56 -> 0 | I57: =IF(Source_Data!I$6=Inputs!$B$12,-Inputs!$B$7,0)+I56 -> 0 | J57: =IF(Source_Data!J$6=Inputs!$B$12,-Inputs!$B$7,0)+J56 -> 0 | K57: =IF(Source_Data!K$6=Inputs!$B$12,-Inputs!$B$7,0)+K56 -> 0 | ... BK57: =IF(Source_Data!BK$6=Inputs!$B$12,-Inputs!$B$7,0)+BK56 -> 0
A58: Pooled project cash after ticket and payouts | D58: =IF(Source_Data!D$6=Inputs!$B$12,Inputs!$B$7,0)+D53-D56 -> 8.75 | E58: =D58+IF(Source_Data!E$6=Inputs!$B$12,Inputs!$B$7,0)+E53-E56 -> -2.5 | F58: =E58+IF(Source_Data!F$6=Inputs!$B$12,Inputs!$B$7,0)+F53-F56 -> -0.12468625 | G58: =F58+IF(Source_Data!G$6=Inputs!$B$12,Inputs!$B$7,0)+G53-G56 -> 15.875941 | H58: =G58+IF(Source_Data!H$6=Inputs!$B$12,Inputs!$B$7,0)+H53-H56 -> 12.236747 | I58: =H58+IF(Source_Data!I$6=Inputs!$B$12,Inputs!$B$7,0)+I53-I56 -> 15.847731 | J58: =I58+IF(Source_Data!J$6=Inputs!$B$12,Inputs!$B$7,0)+J53-J56 -> -7.4233904 | K58: =J58+IF(Source_Data!K$6=Inputs!$B$12,Inputs!$B$7,0)+K53-K56 -> -14.057438 | L58: =K58+IF(Source_Data!L$6=Inputs!$B$12,Inputs!$B$7,0)+L53-L56 -> -14.440608 | ... BK58: =BJ58+IF(Source_Data!BK$6=Inputs!$B$12,Inputs!$B$7,0)+BK53-BK56 -> 127.72937
A59: Coverage: net cash flow / payout | D59: =IF(D56>0,D53/D56,"") | E59: =IF(E56>0,E53/E56,"") | F59: =IF(F56>0,F53/F56,"") | G59: =IF(G56>0,G53/G56,"") | H59: =IF(H56>0,H53/H56,"") | I59: =IF(I56>0,I53/I56,"") | J59: =IF(J56>0,J53/J56,"") | K59: =IF(K56>0,K53/K56,"") | ... BK59: =IF(BK56>0,BK53/BK56,"")
A60: Coverage: cash available / payout | D60: =IF(D56>0,(0+D53+IF(Source_Data!D$6=Inputs!$B$12,Inputs!$B$7,0))/D56,"") | E60: =IF(E56>0,(D58+E53+IF(Source_Data!E$6=Inputs!$B$12,Inputs!$B$7,0))/E56,"") | F60: =IF(F56>0,(E58+F53+IF(Source_Data!F$6=Inputs!$B$12,Inputs!$B$7,0))/F56,"") | G60: =IF(G56>0,(F58+G53+IF(Source_Data!G$6=Inputs!$B$12,Inputs!$B$7,0))/G56,"") | H60: =IF(H56>0,(G58+H53+IF(Source_Data!H$6=Inputs!$B$12,Inputs!$B$7,0))/H56,"") | I60: =IF(I56>0,(H58+I53+IF(Source_Data!I$6=Inputs!$B$12,Inputs!$B$7,0))/I56,"") | J60: =IF(J56>0,(I58+J53+IF(Source_Data!J$6=Inputs!$B$12,Inputs!$B$7,0))/J56,"") | K60: =IF(K56>0,(J58+K53+IF(Source_Data!K$6=Inputs!$B$12,Inputs!$B$7,0))/K56,"") | L60: =IF(L56>0,(K58+L53+IF(Source_Data!L$6=Inputs!$B$12,Inputs!$B$7,0))/L56,"") | ... BK60: =IF(BK56>0,(BJ58+BK53+IF(Source_Data!BK$6=Inputs!$B$12,Inputs!$B$7,0))/BK56,"")
A62: Net cash flow, nominal | B62: =SUM(D53:BK53) -> 257.72937
A63: NPV @ discount rate | B63: =SUMPRODUCT(D53:BK53,Project_CF!$D$15:$BK$15) -> 116.04119
A64: Peak cumulative cash shortage | B64: =MIN(D54:BK54) -> -114.44061
A65: Month of peak | B65: =INDEX(Project_CF!$D$6:$BK$6,MATCH(MIN(D54:BK54),D54:BK54,0)) -> 27
A66: Option A investor IRR | B66: =(1+IRR(D55:BK55,0.05))^4-1 -> 0.23383437
A67: Option A investor MOIC | B67: =SUMIF(D55:BK55,">0")/-SUMIF(D55:BK55,"<0") -> 2.5032258
A68: Option B investor IRR | B68: =(1+IRR(D57:BK57,0.05))^4-1 -> 0.26546399
A69: Option B lowest pooled cash (negative = sponsor support needed) | B69: =MIN(D58:BK58) -> -128.47395
A70: Option B lowest quarterly coverage (net cash flow / payout) | B70: =MIN(D59:BK59) -> -9.2742129
A71: Quarters below threshold (strict) | B71: =COUNTIF(D59:BK59,"<"&Inputs!$B$43) -> 9
A72: Option B lowest cash-available coverage | B72: =MIN(D60:BK60) -> -5.7029887
A73: Quarters below threshold (cash available) | B73: =COUNTIF(D60:BK60,"<"&Inputs!$B$43) -> 6
A76: price: 1.1
A77: Price factor | B77: 1.1
A78: Sales delay (quarters) | B78: 0
A79: Cost factor | B79: 1
A80: Collections slip (quarters) | B80: 0
A81: Delivery payments at handover (1 = yes) | B81: 0
A82: Resale start month (Option A) | B82: =Inputs!$B$13+3+3*$B$78 -> 51
A83: Collections before delay and price | D83: =Source_Data!D$7+IF($B$81=1,IF(Source_Data!D$6=Inputs!$B$13,Source_Data!$C$8,0),Source_Data!D$8) -> 0 | E83: =Source_Data!E$7+IF($B$81=1,IF(Source_Data!E$6=Inputs!$B$13,Source_Data!$C$8,0),Source_Data!E$8) -> 0 | F83: =Source_Data!F$7+IF($B$81=1,IF(Source_Data!F$6=Inputs!$B$13,Source_Data!$C$8,0),Source_Data!F$8) -> 15.139238 | G83: =Source_Data!G$7+IF($B$81=1,IF(Source_Data!G$6=Inputs!$B$13,Source_Data!$C$8,0),Source_Data!G$8) -> 30.278475 | H83: =Source_Data!H$7+IF($B$81=1,IF(Source_Data!H$6=Inputs!$B$13,Source_Data!$C$8,0),Source_Data!H$8) -> 46.512006 | I83: =Source_Data!I$7+IF($B$81=1,IF(Source_Data!I$6=Inputs!$B$13,Source_Data!$C$8,0),Source_Data!I$8) -> 62.745537 | J83: =Source_Data!J$7+IF($B$81=1,IF(Source_Data!J$6=Inputs!$B$13,Source_Data!$C$8,0),Source_Data!J$8) -> 62.3657 | K83: =Source_Data!K$7+IF($B$81=1,IF(Source_Data!K$6=Inputs!$B$13,Source_Data!$C$8,0),Source_Data!K$8) -> 63.473559 | ... BK83: =Source_Data!BK$7+IF($B$81=1,IF(Source_Data!BK$6=Inputs!$B$13,Source_Data!$C$8,0),Source_Data!BK$8) -> 0
A84: Collections | D84: =$B$77*IF(Source_Data!D$5-($B$78+$B$80)>=1,INDEX($D$83:$BK$83,1,Source_Data!D$5-($B$78+$B$80)),0) -> 0 | E84: =$B$77*IF(Source_Data!E$5-($B$78+$B$80)>=1,INDEX($D$83:$BK$83,1,Source_Data!E$5-($B$78+$B$80)),0) -> 0 | F84: =$B$77*IF(Source_Data!F$5-($B$78+$B$80)>=1,INDEX($D$83:$BK$83,1,Source_Data!F$5-($B$78+$B$80)),0) -> 16.653161 | G84: =$B$77*IF(Source_Data!G$5-($B$78+$B$80)>=1,INDEX($D$83:$BK$83,1,Source_Data!G$5-($B$78+$B$80)),0) -> 33.306323 | H84: =$B$77*IF(Source_Data!H$5-($B$78+$B$80)>=1,INDEX($D$83:$BK$83,1,Source_Data!H$5-($B$78+$B$80)),0) -> 51.163207 | I84: =$B$77*IF(Source_Data!I$5-($B$78+$B$80)>=1,INDEX($D$83:$BK$83,1,Source_Data!I$5-($B$78+$B$80)),0) -> 69.020091 | J84: =$B$77*IF(Source_Data!J$5-($B$78+$B$80)>=1,INDEX($D$83:$BK$83,1,Source_Data!J$5-($B$78+$B$80)),0) -> 68.60227 | K84: =$B$77*IF(Source_Data!K$5-($B$78+$B$80)>=1,INDEX($D$83:$BK$83,1,Source_Data!K$5-($B$78+$B$80)),0) -> 69.820915 | ... BK84: =$B$77*IF(Source_Data!BK$5-($B$78+$B$80)>=1,INDEX($D$83:$BK$83,1,Source_Data!BK$5-($B$78+$B$80)),0) -> 0
A85: Landlord payments | D85: =Source_Data!D$9+Source_Data!D$10*IF(Source_Data!$C$10=0,0,MAX(0,Inputs!$B$19*Inputs!$B$22*$B$77-Inputs!$B$20)/Source_Data!$C$10) -> 91.25 | E85: =Source_Data!E$9+Source_Data!E$10*IF(Source_Data!$C$10=0,0,MAX(0,Inputs!$B$19*Inputs!$B$22*$B$77-Inputs!$B$20)/Source_Data!$C$10) -> 11.25 | F85: =Source_Data!F$9+Source_Data!F$10*IF(Source_Data!$C$10=0,0,MAX(0,Inputs!$B$19*Inputs!$B$22*$B$77-Inputs!$B$20)/Source_Data!$C$10) -> 11.25 | G85: =Source_Data!G$9+Source_Data!G$10*IF(Source_Data!$C$10=0,0,MAX(0,Inputs!$B$19*Inputs!$B$22*$B$77-Inputs!$B$20)/Source_Data!$C$10) -> 11.25 | H85: =Source_Data!H$9+Source_Data!H$10*IF(Source_Data!$C$10=0,0,MAX(0,Inputs!$B$19*Inputs!$B$22*$B$77-Inputs!$B$20)/Source_Data!$C$10) -> 22.5 | I85: =Source_Data!I$9+Source_Data!I$10*IF(Source_Data!$C$10=0,0,MAX(0,Inputs!$B$19*Inputs!$B$22*$B$77-Inputs!$B$20)/Source_Data!$C$10) -> 22.5 | J85: =Source_Data!J$9+Source_Data!J$10*IF(Source_Data!$C$10=0,0,MAX(0,Inputs!$B$19*Inputs!$B$22*$B$77-Inputs!$B$20)/Source_Data!$C$10) -> 22.5 | K85: =Source_Data!K$9+Source_Data!K$10*IF(Source_Data!$C$10=0,0,MAX(0,Inputs!$B$19*Inputs!$B$22*$B$77-Inputs!$B$20)/Source_Data!$C$10) -> 22.5 | ... BK85: =Source_Data!BK$9+Source_Data!BK$10*IF(Source_Data!$C$10=0,0,MAX(0,Inputs!$B$19*Inputs!$B$22*$B$77-Inputs!$B$20)/Source_Data!$C$10) -> 0
A86: Construction cost | D86: =Source_Data!D$11*$B$79 -> 0 | E86: =Source_Data!E$11*$B$79 -> 0 | F86: =Source_Data!F$11*$B$79 -> 0 | G86: =Source_Data!G$11*$B$79 -> 0 | H86: =Source_Data!H$11*$B$79 -> 20 | I86: =Source_Data!I$11*$B$79 -> 26.4 | J86: =Source_Data!J$11*$B$79 -> 40 | K86: =Source_Data!K$11*$B$79 -> 26.4 | ... BK86: =Source_Data!BK$11*$B$79 -> 0
A87: Sales commission | D87: =$B$77*IF(Source_Data!D$5-$B$78>=1,INDEX(Source_Data!$D$12:$BK$12,1,Source_Data!D$5-$B$78),0) -> 0 | E87: =$B$77*IF(Source_Data!E$5-$B$78>=1,INDEX(Source_Data!$D$12:$BK$12,1,Source_Data!E$5-$B$78),0) -> 0 | F87: =$B$77*IF(Source_Data!F$5-$B$78>=1,INDEX(Source_Data!$D$12:$BK$12,1,Source_Data!F$5-$B$78),0) -> 0 | G87: =$B$77*IF(Source_Data!G$5-$B$78>=1,INDEX(Source_Data!$D$12:$BK$12,1,Source_Data!G$5-$B$78),0) -> 0 | H87: =$B$77*IF(Source_Data!H$5-$B$78>=1,INDEX(Source_Data!$D$12:$BK$12,1,Source_Data!H$5-$B$78),0) -> 0 | I87: =$B$77*IF(Source_Data!I$5-$B$78>=1,INDEX(Source_Data!$D$12:$BK$12,1,Source_Data!I$5-$B$78),0) -> 0 | J87: =$B$77*IF(Source_Data!J$5-$B$78>=1,INDEX(Source_Data!$D$12:$BK$12,1,Source_Data!J$5-$B$78),0) -> 13.322529 | K87: =$B$77*IF(Source_Data!K$5-$B$78>=1,INDEX(Source_Data!$D$12:$BK$12,1,Source_Data!K$5-$B$78),0) -> 13.322529 | ... BK87: =$B$77*IF(Source_Data!BK$5-$B$78>=1,INDEX(Source_Data!$D$12:$BK$12,1,Source_Data!BK$5-$B$78),0) -> 0
A88: SG&A and others | D88: =Source_Data!D$13*$B$79 -> 0 | E88: =Source_Data!E$13*$B$79 -> 0 | F88: =Source_Data!F$13*$B$79 -> 0 | G88: =Source_Data!G$13*$B$79 -> 0 | H88: =Source_Data!H$13*$B$79 -> 3 | I88: =Source_Data!I$13*$B$79 -> 3.96 | J88: =Source_Data!J$13*$B$79 -> 6 | K88: =Source_Data!K$13*$B$79 -> 3.96 | ... BK88: =Source_Data!BK$13*$B$79 -> 0
A89: Net cash flow | D89: =D84-D85-D86-D87-D88 -> -91.25 | E89: =E84-E85-E86-E87-E88 -> -11.25 | F89: =F84-F85-F86-F87-F88 -> 5.4031613 | G89: =G84-G85-G86-G87-G88 -> 22.056323 | H89: =H84-H85-H86-H87-H88 -> 5.6632069 | I89: =I84-I85-I86-I87-I88 -> 16.160091 | J89: =J84-J85-J86-J87-J88 -> -13.220259 | K89: =K84-K85-K86-K87-K88 -> 3.6383863 | ... BK89: =BK84-BK85-BK86-BK87-BK88 -> 0
A90: Cumulative net cash flow | D90: =D89 -> -91.25 | E90: =D90+E89 -> -102.5 | F90: =E90+F89 -> -97.096839 | G90: =F90+G89 -> -75.040516 | H90: =G90+H89 -> -69.377309 | I90: =H90+I89 -> -53.217218 | J90: =I90+J89 -> -66.437477 | K90: =J90+K89 -> -62.799091 | L90: =K90+L89 -> -49.020744 | ... BK90: =BJ90+BK89 -> 493.16568
A91: Option A investor cash flow | D91: =IF(Source_Data!D$6=Inputs!$B$12,-Inputs!$B$7,0)+IF(AND(Source_Data!D$6>=$B$82,Source_Data!D$6<$B$82+3*Inputs!$B$16,MOD(Source_Data!D$6-$B$82,3)=0),Inputs!$B$8*Inputs!$B$7*Inputs!$B$34*$B$77*(1-Inputs!$B$15)/Inputs!$B$16,0) -> -100 | E91: =IF(Source_Data!E$6=Inputs!$B$12,-Inputs!$B$7,0)+IF(AND(Source_Data!E$6>=$B$82,Source_Data!E$6<$B$82+3*Inputs!$B$16,MOD(Source_Data!E$6-$B$82,3)=0),Inputs!$B$8*Inputs!$B$7*Inputs!$B$34*$B$77*(1-Inputs!$B$15)/Inputs!$B$16,0) -> 0 | F91: =IF(Source_Data!F$6=Inputs!$B$12,-Inputs!$B$7,0)+IF(AND(Source_Data!F$6>=$B$82,Source_Data!F$6<$B$82+3*Inputs!$B$16,MOD(Source_Data!F$6-$B$82,3)=0),Inputs!$B$8*Inputs!$B$7*Inputs!$B$34*$B$77*(1-Inputs!$B$15)/Inputs!$B$16,0) -> 0 | G91: =IF(Source_Data!G$6=Inputs!$B$12,-Inputs!$B$7,0)+IF(AND(Source_Data!G$6>=$B$82,Source_Data!G$6<$B$82+3*Inputs!$B$16,MOD(Source_Data!G$6-$B$82,3)=0),Inputs!$B$8*Inputs!$B$7*Inputs!$B$34*$B$77*(1-Inputs!$B$15)/Inputs!$B$16,0) -> 0 | H91: =IF(Source_Data!H$6=Inputs!$B$12,-Inputs!$B$7,0)+IF(AND(Source_Data!H$6>=$B$82,Source_Data!H$6<$B$82+3*Inputs!$B$16,MOD(Source_Data!H$6-$B$82,3)=0),Inputs!$B$8*Inputs!$B$7*Inputs!$B$34*$B$77*(1-Inputs!$B$15)/Inputs!$B$16,0) -> 0 | I91: =IF(Source_Data!I$6=Inputs!$B$12,-Inputs!$B$7,0)+IF(AND(Source_Data!I$6>=$B$82,Source_Data!I$6<$B$82+3*Inputs!$B$16,MOD(Source_Data!I$6-$B$82,3)=0),Inputs!$B$8*Inputs!$B$7*Inputs!$B$34*$B$77*(1-Inputs!$B$15)/Inputs!$B$16,0) -> 0 | J91: =IF(Source_Data!J$6=Inputs!$B$12,-Inputs!$B$7,0)+IF(AND(Source_Data!J$6>=$B$82,Source_Data!J$6<$B$82+3*Inputs!$B$16,MOD(Source_Data!J$6-$B$82,3)=0),Inputs!$B$8*Inputs!$B$7*Inputs!$B$34*$B$77*(1-Inputs!$B$15)/Inputs!$B$16,0) -> 0 | K91: =IF(Source_Data!K$6=Inputs!$B$12,-Inputs!$B$7,0)+IF(AND(Source_Data!K$6>=$B$82,Source_Data!K$6<$B$82+3*Inputs!$B$16,MOD(Source_Data!K$6-$B$82,3)=0),Inputs!$B$8*Inputs!$B$7*Inputs!$B$34*$B$77*(1-Inputs!$B$15)/Inputs!$B$16,0) -> 0 | ... BK91: =IF(Source_Data!BK$6=Inputs!$B$12,-Inputs!$B$7,0)+IF(AND(Source_Data!BK$6>=$B$82,Source_Data!BK$6<$B$82+3*Inputs!$B$16,MOD(Source_Data!BK$6-$B$82,3)=0),Inputs!$B$8*Inputs!$B$7*Inputs!$B$34*$B$77*(1-Inputs!$B$15)/Inputs!$B$16,0) -> 0
A92: Option B payouts (fixed schedule) | D92: =IF(AND(Source_Data!D$6>=Inputs!$B$54,Source_Data!D$6<Inputs!$B$54+3*Inputs!$B$11),Inputs!$B$9*Inputs!$B$7/Inputs!$B$11,0) -> 0 | E92: =IF(AND(Source_Data!E$6>=Inputs!$B$54,Source_Data!E$6<Inputs!$B$54+3*Inputs!$B$11),Inputs!$B$9*Inputs!$B$7/Inputs!$B$11,0) -> 0 | F92: =IF(AND(Source_Data!F$6>=Inputs!$B$54,Source_Data!F$6<Inputs!$B$54+3*Inputs!$B$11),Inputs!$B$9*Inputs!$B$7/Inputs!$B$11,0) -> 0 | G92: =IF(AND(Source_Data!G$6>=Inputs!$B$54,Source_Data!G$6<Inputs!$B$54+3*Inputs!$B$11),Inputs!$B$9*Inputs!$B$7/Inputs!$B$11,0) -> 0 | H92: =IF(AND(Source_Data!H$6>=Inputs!$B$54,Source_Data!H$6<Inputs!$B$54+3*Inputs!$B$11),Inputs!$B$9*Inputs!$B$7/Inputs!$B$11,0) -> 0 | I92: =IF(AND(Source_Data!I$6>=Inputs!$B$54,Source_Data!I$6<Inputs!$B$54+3*Inputs!$B$11),Inputs!$B$9*Inputs!$B$7/Inputs!$B$11,0) -> 0 | J92: =IF(AND(Source_Data!J$6>=Inputs!$B$54,Source_Data!J$6<Inputs!$B$54+3*Inputs!$B$11),Inputs!$B$9*Inputs!$B$7/Inputs!$B$11,0) -> 0 | K92: =IF(AND(Source_Data!K$6>=Inputs!$B$54,Source_Data!K$6<Inputs!$B$54+3*Inputs!$B$11),Inputs!$B$9*Inputs!$B$7/Inputs!$B$11,0) -> 0 | ... BK92: =IF(AND(Source_Data!BK$6>=Inputs!$B$54,Source_Data!BK$6<Inputs!$B$54+3*Inputs!$B$11),Inputs!$B$9*Inputs!$B$7/Inputs!$B$11,0) -> 0
A93: Option B investor cash flow | D93: =IF(Source_Data!D$6=Inputs!$B$12,-Inputs!$B$7,0)+D92 -> -100 | E93: =IF(Source_Data!E$6=Inputs!$B$12,-Inputs!$B$7,0)+E92 -> 0 | F93: =IF(Source_Data!F$6=Inputs!$B$12,-Inputs!$B$7,0)+F92 -> 0 | G93: =IF(Source_Data!G$6=Inputs!$B$12,-Inputs!$B$7,0)+G92 -> 0 | H93: =IF(Source_Data!H$6=Inputs!$B$12,-Inputs!$B$7,0)+H92 -> 0 | I93: =IF(Source_Data!I$6=Inputs!$B$12,-Inputs!$B$7,0)+I92 -> 0 | J93: =IF(Source_Data!J$6=Inputs!$B$12,-Inputs!$B$7,0)+J92 -> 0 | K93: =IF(Source_Data!K$6=Inputs!$B$12,-Inputs!$B$7,0)+K92 -> 0 | ... BK93: =IF(Source_Data!BK$6=Inputs!$B$12,-Inputs!$B$7,0)+BK92 -> 0
A94: Pooled project cash after ticket and payouts | D94: =IF(Source_Data!D$6=Inputs!$B$12,Inputs!$B$7,0)+D89-D92 -> 8.75 | E94: =D94+IF(Source_Data!E$6=Inputs!$B$12,Inputs!$B$7,0)+E89-E92 -> -2.5 | F94: =E94+IF(Source_Data!F$6=Inputs!$B$12,Inputs!$B$7,0)+F89-F92 -> 2.9031613 | G94: =F94+IF(Source_Data!G$6=Inputs!$B$12,Inputs!$B$7,0)+G89-G92 -> 24.959484 | H94: =G94+IF(Source_Data!H$6=Inputs!$B$12,Inputs!$B$7,0)+H89-H92 -> 30.622691 | I94: =H94+IF(Source_Data!I$6=Inputs!$B$12,Inputs!$B$7,0)+I89-I92 -> 46.782782 | J94: =I94+IF(Source_Data!J$6=Inputs!$B$12,Inputs!$B$7,0)+J89-J92 -> 33.562523 | K94: =J94+IF(Source_Data!K$6=Inputs!$B$12,Inputs!$B$7,0)+K89-K92 -> 37.200909 | L94: =K94+IF(Source_Data!L$6=Inputs!$B$12,Inputs!$B$7,0)+L89-L92 -> 50.979256 | ... BK94: =BJ94+IF(Source_Data!BK$6=Inputs!$B$12,Inputs!$B$7,0)+BK89-BK92 -> 363.16568
A95: Coverage: net cash flow / payout | D95: =IF(D92>0,D89/D92,"") | E95: =IF(E92>0,E89/E92,"") | F95: =IF(F92>0,F89/F92,"") | G95: =IF(G92>0,G89/G92,"") | H95: =IF(H92>0,H89/H92,"") | I95: =IF(I92>0,I89/I92,"") | J95: =IF(J92>0,J89/J92,"") | K95: =IF(K92>0,K89/K92,"") | ... BK95: =IF(BK92>0,BK89/BK92,"")
A96: Coverage: cash available / payout | D96: =IF(D92>0,(0+D89+IF(Source_Data!D$6=Inputs!$B$12,Inputs!$B$7,0))/D92,"") | E96: =IF(E92>0,(D94+E89+IF(Source_Data!E$6=Inputs!$B$12,Inputs!$B$7,0))/E92,"") | F96: =IF(F92>0,(E94+F89+IF(Source_Data!F$6=Inputs!$B$12,Inputs!$B$7,0))/F92,"") | G96: =IF(G92>0,(F94+G89+IF(Source_Data!G$6=Inputs!$B$12,Inputs!$B$7,0))/G92,"") | H96: =IF(H92>0,(G94+H89+IF(Source_Data!H$6=Inputs!$B$12,Inputs!$B$7,0))/H92,"") | I96: =IF(I92>0,(H94+I89+IF(Source_Data!I$6=Inputs!$B$12,Inputs!$B$7,0))/I92,"") | J96: =IF(J92>0,(I94+J89+IF(Source_Data!J$6=Inputs!$B$12,Inputs!$B$7,0))/J92,"") | K96: =IF(K92>0,(J94+K89+IF(Source_Data!K$6=Inputs!$B$12,Inputs!$B$7,0))/K92,"") | L96: =IF(L92>0,(K94+L89+IF(Source_Data!L$6=Inputs!$B$12,Inputs!$B$7,0))/L92,"") | ... BK96: =IF(BK92>0,(BJ94+BK89+IF(Source_Data!BK$6=Inputs!$B$12,Inputs!$B$7,0))/BK92,"")
A98: Net cash flow, nominal | B98: =SUM(D89:BK89) -> 493.16568
A99: NPV @ discount rate | B99: =SUMPRODUCT(D89:BK89,Project_CF!$D$15:$BK$15) -> 314.58159
A100: Peak cumulative cash shortage | B100: =MIN(D90:BK90) -> -102.5
A101: Month of peak | B101: =INDEX(Project_CF!$D$6:$BK$6,MATCH(MIN(D90:BK90),D90:BK90,0)) -> 6
A102: Option A investor IRR | B102: =(1+IRR(D91:BK91,0.05))^4-1 -> 0.29199284
A103: Option A investor MOIC | B103: =SUMIF(D91:BK91,">0")/-SUMIF(D91:BK91,"<0") -> 3.0594982
A104: Option B investor IRR | B104: =(1+IRR(D93:BK93,0.05))^4-1 -> 0.26546399
A105: Option B lowest pooled cash (negative = sponsor support needed) | B105: =MIN(D94:BK94) -> -2.5
A106: Option B lowest quarterly coverage (net cash flow / payout) | B106: =MIN(D95:BK95) -> -8.6267434
A107: Quarters below threshold (strict) | B107: =COUNTIF(D95:BK95,"<"&Inputs!$B$43) -> 8
A108: Option B lowest cash-available coverage | B108: =MIN(D96:BK96) -> 11.619833
...

Sheet Reconciliation
A1: Green Square: reconciliation to the source model and independent recomputation (all checks must read zero)
A2: Differences are rounded to 5 decimals.
A4: Check | B4: This annex | C4: Reference | D4: Difference | E4: Reference basis
A5: Net cash flow, nominal | B5: =Project_CF!$B$18 -> 375.44753 | C5: =Inputs!$B$46 -> 375.44753 | D5: =ROUND(B5-C5,5) -> 0 | E5: Source model
A6: NPV with down payment | B6: =Project_CF!$B$19 -> 215.31139 | C6: =Inputs!$B$47 -> 215.31139 | D6: =ROUND(B6-C6,5) -> 0 | E6: Source model
A7: Peak cumulative shortage | B7: =Project_CF!$B$20 -> -102.5 | C7: =Inputs!$B$48 -> -102.5 | D7: =ROUND(B7-C7,5) -> 0 | E7: Source model
A8: Total collections | B8: =Project_CF!$C$8 -> 2252.979 | C8: =Inputs!$B$49 -> 2252.979 | D8: =ROUND(B8-C8,5) -> 0 | E8: Source model
A9: Total landlord payments | B9: =Project_CF!$C$9 -> 985.67831 | C9: =Inputs!$B$50 -> 985.67831 | D9: =ROUND(B9-C9,5) -> 0 | E9: Source model
A10: Construction, commission and SG&A | B10: =Project_CF!$C$10+Project_CF!$C$11+Project_CF!$C$12 -> 891.85316 | C10: =Inputs!$B$51 -> 891.85316 | D10: =ROUND(B10-C10,5) -> 0 | E10: Source model
A11: Scenario base block equals Project_CF (net) | B11: =Scenarios!$B$26 -> 375.44753 | C11: =Project_CF!$B$18 -> 375.44753 | D11: =ROUND(B11-C11,5) -> 0 | E11: Internal
A12: Scenario base block equals Project_CF (NPV) | B12: =Scenarios!$B$27 -> 215.31139 | C12: =Project_CF!$B$19 -> 215.31139 | D12: =ROUND(B12-C12,5) -> 0 | E12: Internal
A13: Option A investor total = face x appreciation x (1-friction) - ticket | B13: =Option_A!B17 -> 178.1362 | C13: =Option_A!B5*Inputs!$B$34*(1-Inputs!$B$15)-Inputs!$B$7 -> 178.1362 | D13: =ROUND(B13-C13,5) -> 0 | E13: Closed form
A14: Option B S1 total payouts = multiple x ticket | B14: =Option_B!B9 -> 230 | C14: =Inputs!$B$9*Inputs!$B$7 -> 230 | D14: =ROUND(B14-C14,5) -> 0 | E14: Closed form
A15: Total sources equal the larger of total uses and the ticket | B15: =Sources_Uses!B14 -> 112.9574 | C15: =MAX(Sources_Uses!B8,Sources_Uses!B12) -> 112.9574 | D15: =ROUND(B15-C15,5) -> 0 | E15: Internal
A16: Python recomputation: Option A investor IRR | B16: =Option_A!B26 -> 0.26402991 | C16: 0.26402991 | D16: =ROUND(B16-C16,5) -> 0 | E16: Independent Python (engine2.py)
A17: Python recomputation: Option A Jalour cost of capital | B17: =Option_A!B29 -> 0.20741957 | C17: 0.20741957 | D17: =ROUND(B17-C17,5) -> 0 | E17: Independent Python
A18: Python recomputation: Option B S1 investor IRR | B18: =Option_B!B34 -> 0.26546399 | C18: 0.26546399 | D18: =ROUND(B18-C18,5) -> 0 | E18: Independent Python
A19: Python recomputation: Option B S2 investor IRR | B19: =Option_B!C34 -> 0.29027663 | C19: 0.29027663 | D19: =ROUND(B19-C19,5) -> 0 | E19: Independent Python
A20: Python recomputation: Option B S3 investor IRR | B20: =Option_B!D34 -> 0.27835276 | C20: 0.27835276 | D20: =ROUND(B20-C20,5) -> 0 | E20: Independent Python
A21: Python recomputation: downside peak shortage | B21: =-Scenarios!$B$64 -> 441.19461 | C21: 441.19461 | D21: =ROUND(B21-C21,5) -> 0 | E21: Independent Python
A22: Python recomputation: Option B S1 lowest pooled cash | B22: =Option_B!B42 -> -2.5 | C22: -2.5 | D22: =ROUND(B22-C22,5) -> 0 | E22: Independent Python
A24: Sum of absolute differences | D24: =SUMPRODUCT(ABS(D5:D22)) -> 0
A25: Status | D25: =IF(D24=0,"ALL CHECKS ZERO","CHECK FAILED") -> ALL CHECKS ZERO
